Workbook

Sheet 00_Tổng hợp
A1: MCM — GIỐNG BÒ SỮA MỘC CHÂU · ĐỊNH GIÁ: DCF LÕI + TIỀN + DỰ ÁN, BỐN PHƯƠNG PHÁP ĐỐI CHIẾU
A2: Bản 13/10/2026 · giá phiên 08/10/2026 · giá trị = DCF lõi + tiền × (1 − k) + dự án · lợi suất yêu cầu Rf + β × ERP (β 0,72, ERP 9,2%) · hai dự án ở 06
A3: Chữ xanh dương nền xanh lá = đầu vào · chữ đen = công thức · chữ xanh lá = lấy từ sheet khác · nền vàng = kết quả · nền cam = cảnh báo. Đơn vị tỷ đồng trừ khi ghi khác.
A5: CHỈ SỐ CHÍNH | B5: Giá thị trường (đồng) | C5: Giá trị cơ sở (đồng) | D5: FAIR VALUE (đồng) | E5: Biên an toàn
B6: ='01_Số liệu gốc'!$B$11 -> 26450 | C6: =C16 -> 25471.705 | D6: =B21 -> 26818.698 | E6: =B22 -> 0.013747811
B7: ="Phiên "&'01_Số liệu gốc'!$B$12 -> Phiên 08/10/2026 | C7: ="DCF + tiền × "&TEXT((1-'02_Giả định'!$B$26)*100,"0")&"% + dự án" -> DCF + tiền × 90% + dự án | D7: Kỳ vọng ba kịch bản 25/50/25 | E7: (kỳ vọng − giá) ÷ kỳ vọng
A8: Tự kiểm số học (công thức, tổng, khớp DB) | B8: =IF(AND(OR(LEFT('01_Số liệu gốc'!$D$10,4)="KHỚP",LEFT('01_Số liệu gốc'!$D$10,3)="ĐẠT"),OR(LEFT('01_Số liệu gốc'!$I$36,4)="KHỚP",LEFT('01_Số liệu gốc'!$I$36,3)="ĐẠT"),OR(LEFT('01_Số liệu gốc'!$I$71,4)="KHỚP",LEFT('01_Số liệu gốc'!$I$71,3)="ĐẠT"),OR(LEFT('02_Giả định'!$C$24,4)="KHỚP",LEFT('02_Giả định'!$C$24,3)="ĐẠT"),OR(LEFT('02_Giả định'!$C$45,4)="KHỚP",LEFT('02_Giả định'!$C$45,3)="ĐẠT"),OR(LEFT('02_Giả định'!$C$74,4)="KHỚP",LEFT('02_Giả định'!$C$74,3)="ĐẠT"),OR(LEFT('03_Định giá'!$H$253,4)="KHỚP",LEFT('03_Định giá'!$H$253,3)="ĐẠT"),OR(LEFT('05_Đối chiếu'!$C$26,4)="KHỚP",LEFT('05_Đối chiếu'!$C$26,3)="ĐẠT"),OR(LEFT('05_Đối chiếu'!$C$27,4)="KHỚP",LEFT('05_Đối chiếu'!$C$27,3)="ĐẠT"),LEFT('06_Dự án'!$G$21,3)="ĐẠT"),"ĐẠT — 10 phép tự kiểm đều khớp","CÓ PHÉP KIỂM LỆCH — tìm ô báo LỆCH hoặc SAI ở từng sheet") -> ĐẠT — 10 phép tự kiểm đều khớp
A9: 1. KẾT QUẢ CHÍNH (đồng/cổ phiếu)
A10: Phương pháp | B10: Xấu | C10: Cơ sở | D10: Tốt | E10: Trọng số | F10: Ghi chú
A11: 1. P/E lợi nhuận lõi + tiền + dự án | B11: ='03_Định giá'!$B$215 -> 18179.513 | C11: ='03_Định giá'!$C$215 -> 25370.485 | D11: ='03_Định giá'!$D$215 -> 37132.35 | E11: ='02_Giả định'!$B$19 -> 0 | F11: Đối chiếu. Lõi × P/E (02), tiền × (1 − k), cộng giá trị ròng dự án (06)
A12: 2. DCF phần lõi + tiền + dự án | B12: ='03_Định giá'!$B$233 -> 17205.761 | C12: ='03_Định giá'!$C$233 -> 25471.705 | D12: ='03_Định giá'!$D$233 -> 39125.623 | E12: ='02_Giả định'!$B$20 -> 1 | F12: DÙNG LÀM GIÁ TRỊ. Dòng tiền phần lõi ở r (02 mục A), cộng tiền × (1 − k) và dự án
A13: 3. Chiết khấu cổ tức (DDM) | B13: ='03_Định giá'!$B$242 -> 9922.1708 | C13: ='03_Định giá'!$C$242 -> 22128.462 | D13: ='03_Định giá'!$D$242 -> 37180.273 | E13: ='02_Giả định'!$B$21 -> 0 | F13: Đối chiếu. Tạm ứng 2026 + cổ tức 2027–2031 theo chính sách, sau đó trả theo ROE
A14: 4. P/B theo ROE | B14: ='03_Định giá'!$B$224 -> 14239.967 | C14: ='03_Định giá'!$C$224 -> 18858.335 | D14: ='03_Định giá'!$D$224 -> 24631.295 | E14: ='02_Giả định'!$B$22 -> 0 | F14: Đối chiếu. ROE lịch sử, không qua động cơ lõi
A15: 5. EV/EBITDA lõi + tiền + dự án | B15: ='03_Định giá'!$B$220 -> 19704.207 | C15: ='03_Định giá'!$C$220 -> 25241.008 | D15: ='03_Định giá'!$D$220 -> 35335.969 | E15: ='02_Giả định'!$B$23 -> 0 | F15: Đối chiếu. EBITDA lõi × bội số (02), cộng tiền × (1 − k) và dự án
A16: GIÁ TRỊ TỪNG KỊCH BẢN (= phương pháp 2) | B16: ='03_Định giá'!$B$250 -> 17205.761 | C16: ='03_Định giá'!$C$250 -> 25471.705 | D16: ='03_Định giá'!$D$250 -> 39125.623
A17: So giá hiện tại | B17: =B16/'01_Số liệu gốc'!$B$11-1 -> -0.34949863 | C17: =C16/'01_Số liệu gốc'!$B$11-1 -> -0.03698659 | D17: =D16/'01_Số liệu gốc'!$B$11-1 -> 0.47922961
A18: Xác suất | B18: ='03_Định giá'!$B$254 -> 0.25 | C18: ='03_Định giá'!$C$254 -> 0.5 | D18: ='03_Định giá'!$D$254 -> 0.25 | F18: 25/50/25 mặc định, căn cứ ở 02 mục C
A20: Giá thị trường (đồng) | B20: ='01_Số liệu gốc'!$B$11 -> 26450 | F20: ="Phiên "&'01_Số liệu gốc'!$B$12 -> Phiên 08/10/2026
A21: FAIR VALUE = GIÁ TRỊ KỲ VỌNG (đồng/cổ phiếu) | B21: ='03_Định giá'!$B$257 -> 26818.698 | F21: Con số kết luận
A22: Biên an toàn = (kỳ vọng − giá) ÷ kỳ vọng | B22: ='03_Định giá'!$B$259 -> 0.013747811
A23: Tỷ lệ lời/lỗ = (kỳ vọng − giá) ÷ (giá − kịch bản xấu) | B23: ='03_Định giá'!$B$260 -> 0.039884128 | F23: Âm: giá đã trên kỳ vọng
A24: Độ phân tán năm phương pháp (cơ sở, cao ÷ thấp) | B24: ='03_Định giá'!$C$251 -> 1.3506868 | F24: Trên 1,5x: xem vì sao các phương pháp đối chiếu lệch xa DCF
A26: 2. BIỂU ĐỒ — giá trị từng phương pháp (kịch bản cơ sở) so với giá
A46: 3. NHỮNG CON SỐ PHẢI NHỚ TRƯỚC KHI NHÌN MCM
A47: Tiền ròng 30/06/2026 mỗi cổ phiếu (đồng) | B47: ='03_Định giá'!$C$210 -> 12713.973 | C47: Gần một nửa giá cổ phiếu là tiền gửi — câu hỏi là tiền này về cổ đông hay vào dự án · Tính vào giá trị 90% (k ở 02 ô B26)
A48: Giá trị ròng hai dự án, cơ sở (đồng/cp) | B48: ='03_Định giá'!$C$203 -> -3343.145 | C48: Âm: phần còn phải chi sinh lời dưới lợi suất dự án — chi tiết 06, giá × chi phí ở 04 bảng 2
A49: Tiền ròng thấp nhất 2027–2031, cơ sở (tỷ) | B49: ='03_Định giá'!$C$194 -> 321.41034 | C49: Cổ tức cơ sở và chi cả hai dự án. Âm = phải vay
A50: Lợi suất yêu cầu phần kinh doanh (r) | B50: ='02_Giả định'!$B$10 -> 0.11224 | C50: Rf 4,6% + β 0,72 × ERP 9,2% (02 mục A)
A51: Lợi suất ngầm định ở giá hiện tại (phần kinh doanh) | B51: ='05_Đối chiếu'!$B$23 -> 0.11645266 | C51: Thấp hơn r = thị trường trả đắt hơn lợi suất yêu cầu (05 mục B)
A52: Lợi suất kỳ vọng cả cổ phiếu nếu mua ở giá hiện tại | B52: ='05_Đối chiếu'!$B$24 -> 0.084702503 | C52: ="So lãi gửi tham chiếu "&TEXT('02_Giả định'!$B$17*100,"0.0")&"% (khoản lớn, thực nhận)" -> So lãi gửi tham chiếu 9.0% (khoản lớn, thực nhận)
A53: LNST Q3/2026 dự báo (tỷ) — mốc kiểm cuối tháng 10 | B53: ='02_Giả định'!$B$53 -> 48.16472 | C53: Ngoài dải ở 05 mục F thì xem lại B và chi phí bán hàng
A55: 4. TIỀN ĐI ĐÂU 2027–2031 — kịch bản cơ sở (tỷ đồng, 03 mục D)
A56: Khoản | B56: 2027 | C56: 2028 | D56: 2029 | E56: 2030 | F56: 2031
A57: Chi dự án | B57: ='03_Định giá'!$C$83 -> 704.679 | C57: ='03_Định giá'!$C$107 -> 355.9615 | D57: ='03_Định giá'!$C$131 -> 355.9615 | E57: ='03_Định giá'!$C$155 -> 0 | F57: ='03_Định giá'!$C$179 -> 0
A58: Cổ tức tiền mặt | B58: ='03_Định giá'!$C$93 -> 165 | C58: ='03_Định giá'!$C$117 -> 165 | D58: ='03_Định giá'!$C$141 -> 165 | E58: ='03_Định giá'!$C$165 -> 165 | F58: ='03_Định giá'!$C$189 -> 165
A59: LNST (cả lãi tiền gửi/vay) | B59: ='03_Định giá'!$C$92 -> 301.42239 | C59: ='03_Định giá'!$C$116 -> 307.57785 | D59: ='03_Định giá'!$C$140 -> 298.69947 | E59: ='03_Định giá'!$C$164 -> 334.47677 | F59: ='03_Định giá'!$C$188 -> 347.09733
A60: TIỀN RÒNG CUỐI NĂM | B60: ='03_Định giá'!$C$95 -> 798.3411 | C60: ='03_Định giá'!$C$119 -> 564.0857 | D60: ='03_Định giá'!$C$143 -> 321.41034 | E60: ='03_Định giá'!$C$167 -> 466.45375 | F60: ='03_Định giá'!$C$191 -> 622.4001
A61: Bắt đầu từ 1.398,5 tỷ ngày 30/06/2026. Cổ tức cơ sở và lãi tiền gửi theo 02 mục C.
A63: 5. CHƯA CÓ SỐ CÔNG BỐ — câu hỏi còn mở ở 06 mục F
A64: 1. Giá bán sữa nguyên liệu cho Vinamilk và giá thu mua nông hộ không công bố — mV 10% là ước của người viết (12/10/2026), giá sữa trang trại là tự đặt.
A65: 2. Chi phí mỗi lít ở trại tập trung; lãi du lịch; lãi tăng thêm của nhà máy — tự đặt (06).
A66: 3. Nhà máy: nội dung QĐ 2932/QĐ-UBND 19/11/2025; 18% mặt bằng còn vướng; tiền chi mới ~32 tỷ.
A67: 4. Trang trại: 1.120 tỷ gồm những gì sau khi thu nhỏ du lịch; nguồn bò; 40,9 tỷ mua của Lao-Jagro.
A68: 5. Doanh thu theo nhóm 6T/2026 không công bố: Creamery đóng góp bao nhiêu chưa đo được (ĐHĐCĐ: 5–6%).
A69: 6. BCTC Q3/2026 (cuối tháng 10): nhập LNST vào 05 mục F; xem dở dang trang trại, tiền thuê đất.
A71: 6. MỤC LỤC — bấm tên sheet để đi tới
A72: 01_Số liệu gốc | B72: Dữ kiện: cổ phiếu, kết quả năm và quý, cân đối, doanh thu theo nhóm và bán cho Vinamilk, ROE, dự án
A73: 02_Giả định | B73: Nhận định: lợi suất yêu cầu (β, ERP), động cơ lõi hiệu chỉnh trên 12 tháng, ba kịch bản, cổ tức
A74: 03_Định giá | B74: Lợi nhuận lõi, dòng tiền 2027–2031 (lõi, dự án, tiền), năm phương pháp × ba kịch bản, 16 cột phép thử
A75: 04_Độ nhạy | B75: B × chi phí bán hàng, giá × chi phí mỗi lít trang trại, ROE × r, mười chín phép thử một biến
A76: 05_Đối chiếu | B76: Bội số, giá đang ngầm định gì (cả lợi suất), hai đường tới ROE, nhóm so sánh, file QNS, mốc Q3
A77: 06_Dự án | B77: Hai dự án: giả định trang trại (bò sữa, du lịch), nhà máy; kết quả, hòa vốn, theo dõi quý, hỏi công ty
A79: 7. CHÚ GIẢI THUẬT NGỮ
A80: Lợi nhuận lõi (EBIT lõi) | B80: Lãi gộp − chi phí bán hàng − chi phí quản lý: không gồm lãi tiền gửi
A81: V | B81: Doanh thu bán cho Vinamilk: sữa nguyên liệu bán thô + gia công
A82: B | B82: Phần còn lại: sữa thương hiệu Mộc Châu, thức ăn chăn nuôi, khác — gánh toàn bộ khuyến mãi
A83: Năm chuẩn hoá | B83: Một năm 'bình thường' ~2027 trước khi dự án có lãi — không phải dự phóng năm cụ thể
A84: Giá trị ròng dự án | B84: Hiện giá dòng tiền dự án (2027–2031 + 20 năm đều) − hiện giá vốn CÒN phải chi, ở lợi suất dự án (phần đã chi là chi phí chìm)
A85: Lợi suất yêu cầu | B85: Rf + β × ERP (cách rút gọn của công ty chứng khoán); β đã bỏ phần tiền
A86: P/B hợp lý | B86: (ROE − g) ÷ (r − g): ROE thấp hơn r thì đáng giá dưới sổ sách
A87: DDM | B87: Chiết khấu cổ tức: giá trị = hiện giá cổ tức cổ đông thực nhận
A88: Biên an toàn | B88: (giá trị kỳ vọng − giá) ÷ giá trị kỳ vọng
A89: Fair value | B89: Giá trị kỳ vọng = 25% × xấu + 50% × cơ sở + 25% × tốt; mỗi kịch bản = DCF lõi + tiền ròng × (1 − k) + giá trị ròng dự án
A90: k | B90: Phần tiền ròng không tính vào giá trị: cổ đông thiểu số có thể không nhận đủ (Vinamilk 68% quyết chia). 10% (02 ô B26)
A188: Dữ liệu biểu đồ (đừng xoá)
A189: Phương pháp | B189: P/E lõi | C189: DCF | D189: Cổ tức | E189: P/B-ROE | F189: EV/EBITDA | G189: Bình quân | H189: Kỳ vọng
A190: Giá trị (cơ sở) | B190: =C11 -> 25370.485 | C190: =C12 -> 25471.705 | D190: =C13 -> 22128.462 | E190: =C14 -> 18858.335 | F190: =C15 -> 25241.008 | G190: =C16 -> 25471.705 | H190: =B21 -> 26818.698
A191: Giá thị trường | B191: =$B$20 -> 26450 | C191: =$B$20 -> 26450 | D191: =$B$20 -> 26450 | E191: =$B$20 -> 26450 | F191: =$B$20 -> 26450 | G191: =$B$20 -> 26450 | H191: =$B$20 -> 26450

Sheet 01_Số liệu gốc
A1: MCM — SỐ LIỆU GỐC
A2: Mọi số ở đây là DỮ KIỆN (báo cáo tài chính, thuyết minh, BCTN, giá). Nhận định nằm ở 02_Giả định. Nền xanh lá chữ xanh dương = số nhập tay; nền vàng = công thức. Đơn vị tỷ đồng trừ khi ghi khác. Số DB kéo ngày 12/10/2026. MCM không có công ty con: BCTC riêng là BCTC duy nhất. Bảng cân đối 30/06/2026 khớp BCTC bán niên soát xét (KPMG, 11/08/2026).
A4: A. CỔ PHIẾU VÀ GIÁ
A5: Chỉ tiêu | B5: Giá trị | C5: Đơn vị | D5: Nguồn / ghi chú
A6: Cổ phiếu đã phát hành | B6: 110 | C6: triệu cổ phiếu | D6: Thuyết minh 21 BCTC 2025: 110.000.000; không đổi đến 30/06/2026
A7: Cổ phiếu quỹ | B7: 0 | C7: triệu cổ phiếu | D7: BCTC 2025 TM 21: số đang lưu hành = số phát hành
A8: CỔ PHIẾU LƯU HÀNH | B8: =B6-B7 -> 110 | C8: triệu cổ phiếu
A9: Kiểm chéo: vốn góp trong DB (GEN_BS_097) 30/06/2026 | B9: 1100 | C9: tỷ đồng | D9: gen_balance_sheet quý 2/2026
A10: → số cổ phiếu suy từ vốn góp | B10: =B9/10 -> 110 | C10: triệu cổ phiếu | D10: =IF(ABS(B10-B6)<0.001,"KHỚP cổ phiếu đã phát hành","LỆCH") -> KHỚP cổ phiếu đã phát hành
A11: Giá cổ phiếu | B11: 26450 | C11: đồng | D11: daily_price, giá đóng cửa
A12: Ngày giá | B12: 08/10/2026
A13: Cao nhất 52 tuần (giá điều chỉnh cổ tức) | B13: 29400 | C13: đồng | D13: daily_price.adjusted_close
A14: Thấp nhất 52 tuần (giá điều chỉnh cổ tức) | B14: 23744 | C14: đồng | D14: daily_price.adjusted_close
A15: Giá trị giao dịch bình quân 30 phiên | B15: 433.6 | C15: triệu đồng/phiên | D15: daily_price (giá × khối lượng). RẤT THẤP: Vinamilk và Tổng Công ty Chăn nuôi nắm 68,15%
A16: Vốn hoá thị trường | B16: =B11*B8/1000 -> 2909.5 | C16: tỷ đồng | D16: giá × cổ phiếu lưu hành
A18: B. KẾT QUẢ KINH DOANH THEO NĂM (PostgreSQL, tỷ đồng)
A19: Khoản mục | B19: 2021 | C19: 2022 | D19: 2023 | E19: 2024 | F19: 2025 | I19: Mã khoản mục / ghi chú
A20: Doanh thu thuần | B20: 2925.664 | C20: 3133.099 | D20: 3135.423 | E20: 2916.958 | F20: 2834.874 | I20: GEN_IS_003
A21: Lãi gộp | B21: 898.503 | C21: 1017.789 | D21: 1008.618 | E21: 848.545 | F21: 796.98 | I21: GEN_IS_021
A22: Chi phí bán hàng | B22: 594.259 | C22: 688.742 | D22: 708.879 | E22: 657.046 | F22: 606.614 | I22: GEN_IS_011
A23: Chi phí quản lý doanh nghiệp | B23: 36.609 | C23: 39.603 | D23: 37.898 | E23: 37.145 | F23: 38.071 | I23: GEN_IS_012
A24: LỢI NHUẬN LÕI (EBIT lõi) = lãi gộp − bán hàng − quản lý | B24: =B21-B22-B23 -> 267.635 | C24: =C21-C22-C23 -> 289.444 | D24: =D21-D22-D23 -> 261.841 | E24: =E21-E22-E23 -> 154.354 | F24: =F21-F22-F23 -> 152.295 | I24: Không gồm lãi tiền gửi — phần đó cộng riêng bằng số dư tiền ở mọi phương pháp
A25: Doanh thu hoạt động tài chính (gần hết là lãi tiền gửi) | B25: 95.419 | C25: 103.156 | D25: 162.315 | E25: 101.252 | F25: 103.916 | I25: GEN_IS_004
A26: Chi phí tài chính | B26: 0.5 | C26: 0.996 | D26: 0.881 | E26: 1.898 | F26: 6.004 | I26: GEN_IS_014
A27: trong đó: chi phí lãi vay | B27: 0.163 | C27: 0.636 | D27: 0 | E27: 1.732 | F27: 5.706 | I27: GEN_IS_015
A28: Lợi nhuận khác (thu nhập khác − chi phí khác) | B28: -8.796 | C28: -10.917 | D28: 0.305 | E28: -1.652 | F28: -1.673 | I28: GEN_IS_005−017
A29: Lợi nhuận trước thuế | B29: 353.758 | C29: 380.687 | D29: 423.58 | E29: 252.057 | F29: 248.534 | I29: GEN_IS_027
A30: Thuế thu nhập doanh nghiệp | B30: 34.646 | C30: 34.138 | D30: 49.162 | E30: 32.136 | F30: 32.82 | I30: GEN_IS_006+007
A31: LỢI NHUẬN SAU THUẾ | B31: 319.112 | C31: 346.549 | D31: 374.417 | E31: 219.921 | F31: 215.714 | I31: GEN_IS_020
A32: Khấu hao tài sản cố định | B32: 49.922 | C32: 54.459 | D32: 62.041 | E32: 67.01 | F32: 68.763 | I32: GEN_CF_001
A33: Lưu chuyển tiền thuần từ hoạt động kinh doanh | B33: 230.26 | C33: 268.493 | D33: 287.49 | E33: 196.059 | F33: 180.854 | I33: GEN_CF_026
A34: Chi mua sắm, xây dựng tài sản cố định (âm = tiền ra) | B34: -151.349 | C34: -139.443 | D34: -246.393 | E34: -93.478 | F34: -174.152 | I34: GEN_CF_027
A35: Cổ tức tiền mặt đã trả (âm = tiền ra) | B35: -309.016 | C35: -274.948 | D35: -220.105 | E35: -220 | F35: -220 | I35: GEN_CF_040
A36: Kiểm: lõi + doanh thu tài chính − chi phí tài chính + khác − LNTT | B36: =B24+B25-B26+B28-B29 -> 0 | C36: =C24+C25-C26+C28-C29 -> 0 | D36: =D24+D25-D26+D28-D29 -> 0 | E36: =E24+E25-E26+E28-E29 -> -0.001 | F36: =F24+F25-F26+F28-F29 -> 0 | I36: =IF(MAX(ABS(B36),ABS(C36),ABS(D36),ABS(E36),ABS(F36))<0.5,"KHỚP (dung sai 0,5 tỷ — làm tròn DB)","LỆCH") -> KHỚP (dung sai 0,5 tỷ — làm tròn DB)
A37: Thuế suất thực tế = thuế ÷ lợi nhuận trước thuế | B37: =B30/B29 -> 0.097937008 | C37: =C30/C29 -> 0.08967472 | D37: =D30/D29 -> 0.11606308 | E37: =E30/E29 -> 0.12749497 | F37: =F30/F29 -> 0.13205437 | I37: Thuế suất phổ thông 20%. Thu nhập chăn nuôi, chế biến nông sản ở địa bàn đặc biệt khó khăn được miễn (TM 34 BCTC 2025, Nghị định 320/2025): 2025 miễn 18,0 tỷ tiền thuế
A38: Doanh thu tài chính ÷ lợi nhuận trước thuế | B38: =B25/B29 -> 0.26972959 | C38: =C25/C29 -> 0.27097327 | D38: =D25/D29 -> 0.38319798 | E38: =E25/E29 -> 0.40170279 | F38: =F25/F29 -> 0.41811583 | I38: Lãi tiền gửi từ 27% (2021) lên 42% LNTT (2025): lợi nhuận lõi giảm, tiền gửi đứng yên
A40: C. THEO QUÝ (PostgreSQL, tỷ đồng) — cột H = 12 tháng tới Q2/2026 = năm 2025 kiểm toán − 6T/2025 + 6T/2026
A41: Khoản mục | B41: Q1/2025 | C41: Q2/2025 | D41: Q3/2025 | E41: Q4/2025 | F41: Q1/2026 | G41: Q2/2026 | H41: 12 tháng | I41: Mã khoản mục / ghi chú
A42: Doanh thu thuần | B42: 591.151 | C42: 808.709 | D42: 716.234 | E42: 721.2 | F42: 741.55 | G42: 760.454 | H42: =F20-B42-C42+F42+G42 -> 2937.018 | I42: Từ 2026 áp dụng Thông tư 99: bán bò chuyển từ thu nhập khác sang doanh thu; số cùng kỳ 2025 trong BCTC 2026 đã trình bày lại (lệch DB ~1 tỷ/quý, không đổi LNTT)
A43: Lãi gộp | B43: 145.482 | C43: 236.99 | D43: 202.187 | E43: 209.543 | F43: 212.414 | G43: 235.899 | H43: =F21-B43-C43+F43+G43 -> 862.821 | I43: GEN_IS_021. Cột H lấy năm 2025 kiểm toán làm gốc: cộng thẳng bốn quý 2025 trong DB thiếu 2,8 tỷ lãi gộp so BCTC năm
A44: Chi phí bán hàng | B44: 102.323 | C44: 169.006 | D44: 182.058 | E44: 153.227 | F44: 138.014 | G44: 156.079 | H44: =F22-B44-C44+F44+G44 -> 629.378 | I44: Q3 thường là quý chi khuyến mãi nặng nhất (Q3/2025: 182 tỷ, LNST chỉ 28 tỷ)
A45: Chi phí quản lý doanh nghiệp | B45: 10.348 | C45: 8.972 | D45: 8.248 | E45: 10.503 | F45: 9.32 | G45: 9.662 | H45: =F23-B45-C45+F45+G45 -> 37.733 | I45: GEN_IS_012
A46: LỢI NHUẬN LÕI (EBIT lõi) | B46: =B43-B44-B45 -> 32.811 | C46: =C43-C44-C45 -> 59.012 | D46: =D43-D44-D45 -> 11.881 | E46: =E43-E44-E45 -> 45.813 | F46: =F43-F44-F45 -> 65.08 | G46: =G43-G44-G45 -> 70.158 | H46: =H43-H44-H45 -> 195.71
A47: Doanh thu hoạt động tài chính | B47: 24.493 | C47: 27.659 | D47: 25.932 | E47: 25.833 | F47: 25.326 | G47: 27.979 | H47: =F25-B47-C47+F47+G47 -> 105.069 | I47: GEN_IS_004
A48: Chi phí lãi vay | B48: 1.166 | C48: 1.981 | D48: 1.692 | E48: 0.868 | F48: 0.341 | G48: 0 | H48: =F27-B48-C48+F48+G48 -> 2.9 | I48: GEN_IS_015
A49: Lợi nhuận trước thuế | B49: 54.673 | C49: 86.523 | D49: 34.45 | E49: 72.887 | F49: 90.097 | G49: 98.145 | H49: =F29-B49-C49+F49+G49 -> 295.58 | I49: GEN_IS_027
A50: Thuế thu nhập doanh nghiệp | B50: 6.905 | C50: 10.781 | D50: 6.386 | E50: 8.748 | F50: 9.978 | G50: 9.638 | H50: =F30-B50-C50+F50+G50 -> 34.75 | I50: GEN_IS_006+007
A51: LỢI NHUẬN SAU THUẾ | B51: 47.768 | C51: 75.742 | D51: 28.064 | E51: 64.139 | F51: 80.119 | G51: 88.507 | H51: =F31-B51-C51+F51+G51 -> 260.83 | I51: GEN_IS_020
A52: Khấu hao tài sản cố định | B52: 16.928 | C52: 17.224 | D52: 17.335 | E52: 17.276 | F52: 17.744 | G52: 17.71 | H52: =F32-B52-C52+F52+G52 -> 70.065 | I52: GEN_CF_001
A53: Lưu chuyển tiền thuần từ hoạt động kinh doanh | B53: -9.669 | C53: 56.28 | D53: 136.873 | E53: -0.112 | F53: 1.69 | G53: 96.414 | H53: =F33-B53-C53+F53+G53 -> 232.347 | I53: GEN_CF_026
A54: Chi mua sắm, xây dựng tài sản cố định (âm = tiền ra) | B54: -55.521 | C54: -38.423 | D54: -62.847 | E54: -17.36 | F54: -67.533 | G54: -52.733 | H54: =F34-B54-C54+F54+G54 -> -200.474 | I54: GEN_CF_027
A56: D. BẢNG CÂN ĐỐI VÀ THUYẾT MINH (tỷ đồng)
A57: Khoản mục | B57: 31/12/2025 | C57: 30/06/2026 | I57: Nguồn / ghi chú
A58: Tiền và tương đương tiền | B58: 36.951 | C58: 68.747 | I58: GEN_BS_002
A59: Tiền gửi có kỳ hạn ngắn hạn (đầu tư giữ đến ngày đáo hạn) | B59: 1485.127 | C59: 1329.79 | I59: GEN_BS_005 — số 31/12/2025 là số ĐÃ PHÂN LOẠI LẠI theo Thông tư 99 (BCTC Q2/2026): gồm 54,1 tỷ lãi dự thu; BCTC 2025 gốc ghi 1.431,0
A60: Tiền gửi có kỳ hạn dài hạn | B60: 25 | C60: 0 | I60: GEN_BS_057 — TM 5 BCTC 2025: lãi suất 4,75%–8,2%/năm, không thấy cầm cố
A61: Vay ngắn hạn | B61: 67 | C61: 0 | I61: Vietcombank, VietinBank 4–6 tháng, không tài sản đảm bảo; trả hết 6T/2026
A62: Vay dài hạn | B62: 0 | C62: 0 | I62: GEN_BS_089
A63: TIỀN + TIỀN GỬI | B63: =B58+B59+B60 -> 1547.078 | C63: =C58+C59+C60 -> 1398.537 | I63: Gồm lãi dự thu (Thông tư 99). Khoản tiền còn lại của đợt phát hành 2021 dành cho hai dự án: 685,0 tỷ cuối 2025 (mục G)
A64: Tổng nợ vay | B64: =B61+B62 -> 67 | C64: =C61+C62 -> 0
A65: TIỀN RÒNG = tiền + tiền gửi − nợ vay | B65: =B63-B64 -> 1480.078 | C65: =C63-C64 -> 1398.537 | I65: Dùng 30/06/2026 ở mọi phương pháp. Cổ tức đợt 1/2026 (1.000đ/cp, thường chi tháng 11) chưa trừ — nằm trong lợi nhuận năm 2026
A66: VỐN CHỦ SỞ HỮU | B66: 2279.326 | C66: 2321.089 | I66: GEN_BS_095 — không có cổ đông thiểu số
A67: Xây dựng dở dang: tổ hợp trang trại bò sữa 4.000 con | B67: 311.599 | C67: 415.321 | I67: TM 15 BCTC bán niên soát xét 2026 (tổng 459,3 khớp bảng cân đối); cột 31/12/2025 = TM 12 BCTC 2025
A68: Xây dựng dở dang: nhà máy sữa công nghệ cao | B68: 31.077 | C68: 31.077 | I68: TM 15 BCTC bán niên soát xét 2026 (tổng 459,3 khớp bảng cân đối); cột 31/12/2025 = TM 12 BCTC 2025
A69: Xây dựng dở dang: máy móc, công trình khác | B69: 12.23 | C69: 12.919 | I69: TM 15 BCTC bán niên soát xét 2026 (tổng 459,3 khớp bảng cân đối); cột 31/12/2025 = TM 12 BCTC 2025
A70: Tổng xây dựng dở dang | B70: =SUM(B67:B69) -> 354.906 | C70: =SUM(C67:C69) -> 459.317
A71: Kiểm chéo: xây dựng dở dang trong DB (GEN_BS_051) | B71: 354.906 | C71: 459.317 | I71: =IF(AND(ABS(B71-B70)<0.01,ABS(C71-C70)<0.01),"KHỚP thuyết minh","LỆCH") -> KHỚP thuyết minh
A72: VỐN HOẠT ĐỘNG LÕI = vốn chủ − tiền ròng − xây dựng dở dang | B72: =B66-B65-B70 -> 444.342 | C72: =C66-C65-C70 -> 463.235 | I72: Phần vốn thực sự làm ra lợi nhuận lõi — chỉ ~460 tỷ vì nhà máy cũ đã khấu hao gần hết (610,7 tỷ nguyên giá khấu hao hết vẫn dùng, TM 10 BCTC 2025)
A73: GIÁ TRỊ SỔ SÁCH MỖI CỔ PHIẾU 30/06/2026 (đồng) | C73: =C66*1000/B8 -> 21100.809
A75: E. DOANH THU THEO NHÓM VÀ BÁN CHO VINAMILK (BCTN, thuyết minh bên liên quan — DB không có)
A76: Chỉ tiêu | B76: 2023 | C76: 2024 | D76: 2025 | E76: 6T/2025 | F76: 6T/2026 | I76: Nguồn / ghi chú
A77: Sữa thành phẩm (thương hiệu Mộc Châu) | B77: 2272.8 | C77: 1899.5 | D77: 1722.4
A78: Sữa nguyên liệu (bán thô) | B78: 425.3 | C78: 572.6 | D78: 615.1
A79: Thức ăn chăn nuôi và TMR | B79: 412.5 | C79: 418 | D79: 424.4
A80: Gia công (sữa thanh trùng hộp giấy cho Vinamilk) | B80: 0 | C80: 0 | D80: 48.1
A81: Nhóm khác | B81: 24.9 | C81: 26.8 | D81: 24.8
A82: Cộng theo nhóm (kiểm với doanh thu thuần) | B82: =SUM(B77:B81) -> 3135.5 | C82: =SUM(C77:C81) -> 2916.9 | D82: =SUM(D77:D81) -> 2834.8 | I82: BCTN 2025 tr.68; BCTN 2024 tr.59. Công ty không công bố số 6 tháng theo nhóm
A83: Doanh thu thuần (mục B, C) | B83: =D20 -> 3135.423 | C83: =E20 -> 2916.958 | D83: =F20 -> 2834.874 | E83: =B42+C42 -> 1399.86 | F83: =F42+G42 -> 1502.004
A84: V = Bán hàng cho Vinamilk (công ty mẹ cấp cao nhất) | B84: 425.3 | C84: 572.83 | D84: 668.088 | E84: 358.324 | F84: 327.441 | I84: TM bên liên quan: 2025 bán hàng hóa 668,08 tỷ (TM 36 BCTC 2025); 2024 572,62 + dịch vụ 0,21; 6T/2026 = 327,44 theo TM 39 BCTC bán niên SOÁT XÉT (bản Q2 tự lập ghi 327,41). ≈ sữa nguyên liệu + gia công. Q1/2025 168,2; Q1/2026 183,7 (BCTC quý 1)
A85: B = Phần còn lại = doanh thu − V (thương hiệu + thức ăn chăn nuôi + khác) | B85: =B83-B84 -> 2710.123 | C85: =C83-C84 -> 2344.128 | D85: =D83-D84 -> 2166.786 | E85: =E83-E84 -> 1041.536 | F85: =F83-F84 -> 1174.563 | I85: Gánh toàn bộ chi phí bán hàng (khuyến mãi, quảng cáo cho hàng thương hiệu)
A86: Lãi gộp | B86: =D21 -> 1008.618 | C86: =E21 -> 848.545 | D86: =F21 -> 796.98 | E86: =B43+C43 -> 382.472 | F86: =F43+G43 -> 448.313
A87: Chi phí bán hàng | B87: =D22 -> 708.879 | C87: =E22 -> 657.046 | D87: =F22 -> 606.614 | E87: =B44+C44 -> 271.329 | F87: =F44+G44 -> 294.093
A88: Tỷ trọng bán cho Vinamilk trong doanh thu | B88: =B84/B83 -> 0.13564358 | C88: =C84/C83 -> 0.19637924 | D88: =D84/D83 -> 0.23566762 | E88: =E84/E83 -> 0.25597131 | F88: =F84/F83 -> 0.21800275
A89: B 6T/2026 so 6T/2025 | F89: =F85/E85-1 -> 0.12772194 | I89: Sau hai năm giảm (sữa thành phẩm 2.273 → 1.722 tỷ), phần còn lại tăng lại từ Q1/2026
A91: F. LỊCH SỬ ROE 2018–2025 (ROE = LNST ÷ vốn chủ bình quân đầu và cuối năm)
A92: Năm | B92: Vốn chủ cuối năm | C92: LNST | D92: Vốn chủ bình quân | E92: ROE | I92: Ghi chú
A93: 2017 | B93: 766.782
A94: 2018 | B94: 767.852 | C94: 180.641 | D94: =(B93+B94)/2 -> 767.317 | E94: =C94/D94 -> 0.235419
A95: 2019 | B95: 726.74 | C95: 166.942 | D95: =(B94+B95)/2 -> 747.296 | E95: =C95/D95 -> 0.22339475
A96: 2020 | B96: 911.91 | C96: 280.735 | D96: =(B95+B96)/2 -> 819.325 | E96: =C96/D96 -> 0.34264181 | I96: Năm Vinamilk vào điều hành (mua lại qua Tổng Công ty Chăn nuôi)
A97: 2021 | B97: 2173.385 | C97: =B31 -> 319.112 | D97: =(B96+B97)/2 -> 1542.6475 | E97: =C97/D97 -> 0.20685996 | I97: Phát hành 43,2 triệu cổ phiếu thu 1.249,3 tỷ → vốn chủ gấp đôi, tiền gửi phình
A98: 2022 | B98: 2210.279 | C98: =C31 -> 346.549 | D98: =(B97+B98)/2 -> 2191.832 | E98: =C98/D98 -> 0.15810929
A99: 2023 | B99: 2327.255 | C99: =D31 -> 374.417 | D99: =(B98+B99)/2 -> 2268.767 | E99: =C99/D99 -> 0.16503105
A100: 2024 | B100: 2305.184 | C100: =E31 -> 219.921 | D100: =(B99+B100)/2 -> 2316.2195 | E100: =C100/D100 -> 0.094948255 | I100: LNST −41%: giá thu mua sữa tăng 7–8%, sức mua yếu (KBSV)
A101: 2025 | B101: 2279.326 | C101: =F31 -> 215.714 | D101: =(B100+B101)/2 -> 2292.255 | E101: =C101/D101 -> 0.094105586 | I101: Đáy: sữa thành phẩm −9,3%
A102: ROE 12 tháng tới Q2/2026 (vốn chủ bình quân 30/06/2025 và 30/06/2026) | E102: =H51/AVERAGE(2306.343,C66) -> 0.11273207
A103: ROE bình quân 2022–2025 (sau đợt phát hành, tiền gửi lớn) | E103: =AVERAGE(E98:E101) -> 0.12804855 | I103: Trước 2021 vốn chủ chỉ ~770 tỷ nên ROE 20%+; sau đợt phát hành ~43% tài sản là tiền gửi lãi 5–8% → ROE bị kéo về ~10–16%
A104: ROE bình quân 2018–2025 | E104: =AVERAGE(E94:E101) -> 0.19006371
A105: ROE trung vị 2018–2025 | E105: =MEDIAN(E94:E101) -> 0.1859455
A107: G. HAI DỰ ÁN VÀ NGUỒN TIỀN — dữ kiện (giả định dự án nằm ở 06_Dự án)
...

Sheet 02_Giả định
A1: MCM — GIẢ ĐỊNH (bản 12/10/2026)
A2: Ô nền xanh lá chữ xanh dương là NHẬN ĐỊNH — sửa là cả model chạy lại. Cột 'Mốc thực tế' lấy thẳng từ 01 để thấy giả định đặt ở đâu so với số thật. Giả định hai dự án nằm ở 06_Dự án.
A4: A. THAM SỐ CHUNG — lợi suất yêu cầu, thuế lãi tiền gửi, trọng số, chiết khấu tiền
A5: Tham số | B5: Giá trị | F5: Căn cứ
A6: Lợi suất phi rủi ro (Rf) | B6: 0.046 | F6: Khung chung của người viết. Trái phiếu Chính phủ 10 năm trúng thầu 4,43% đầu tháng 10/2026 — trong ngưỡng ±0,5 điểm, chưa đổi
A7: Phần bù rủi ro thị trường (ERP) — cách rút gọn của công ty chứng khoán | B7: 0.092 | F7: Chốt 12/10/2026: dùng như VNDirect, VDSC. VNDirect BSR 17/08/2026: 9,2% (Rf 4,3%); VDSC GDA 07/04/2026: 10% (mức cho doanh nghiệp chu kỳ → cận trên, phép thử T5); Kafi PVS 9,63%; MBS VCB 8,5%; KBSV MCM 8% (β 1 → 12%). Damodaran 07/2026 cho Việt Nam 7,92% (4,20% + rủi ro quốc gia 3,72%)
A8: β phần kinh doanh hiện tại (đã bỏ phần tiền) | B8: 0.72 | F8: Chốt 12/10/2026. VNM: Blume 0,644 (thô tuần 5 năm 0,469) ÷ (1 − tiền ròng bình quân 5 năm 11%) = 0,72. MCM tự tính, bỏ tiền TỪNG TUẦN (tiền bình quân 40% vốn hóa): 0,70 (tuần 5 năm, CI 0,50–0,91), 0,76 (tuần 2 năm); Dimson trễ 1 tuần −0,03 → ít giao dịch không làm méo. Phép thử T6 (0,85), T14 (0,65)
A9: β hai dự án mới | B9: 0.85 | F9: TỰ ĐẶT. Dự án làm chi phí cố định tăng (khấu hao trang trại ~40 tỷ + nhà máy ~37 tỷ/năm) và nghiêng hàng cao cấp (Creamery) — nhạy với chu kỳ hơn kinh doanh hiện tại. Rủi ro chậm, kẹt đất KHÔNG đưa vào đây (đã ở kịch bản xấu 06)
A10: LỢI SUẤT YÊU CẦU PHẦN KINH DOANH HIỆN TẠI (r) = Rf + β × ERP | B10: =B6+B8*B7 -> 0.11224 | F10: Không vay nên r cũng là chi phí vốn của DCF.
A11: LỢI SUẤT YÊU CẦU HAI DỰ ÁN = Rf + β dự án × ERP | B11: =B6+B9*B7 -> 0.1242 | F11: Chiết khấu dòng tiền dự án ở 06/03
A12: Tăng trưởng dài hạn (g) | B12: 0.03 | F12: Dùng cho P/B theo ROE, giá trị cuối kỳ DCF và cổ tức. Lạm phát 9T/2026 4,52% — phép thử g 4% không đặt sẵn
A13: Trích quỹ khen thưởng phúc lợi (% LNST) | B13: 0.1 | F13: 2024, 2025 đều đúng 10% (01 mục H). Tiền ra khỏi tay cổ đông trước cổ tức
A14: Thuế trên lãi tiền gửi | B14: 0.2 | F14: Thuế suất phổ thông; phần miễn thuế chỉ áp cho thu nhập chăn nuôi, chế biến nông sản (TM 34 BCTC 2025)
A15: Lãi suất vay khi tiền âm (chỉ dùng ở phương pháp 3) | B15: 0.075 | F15: TỰ ĐẶT. TM 17 BCTC 2025 chỉ ghi vay Vietcombank, VietinBank 4–6 tháng lãi cố định, KHÔNG ghi mức lãi
A16: Cổ tức tạm ứng đợt 1/2026 dự kiến (đồng/cp, khoảng tháng 11/2026) | B16: 1000 | F16: MCM tạm ứng 1.000đ vào tháng 11 các năm 2022–2025; đợt 2026 CHƯA công bố. Cộng vào phương pháp 3
A17: Lãi tiền gửi tham chiếu của nhà đầu tư (khoản lớn, thực nhận) | B17: 0.09 | F17: Niêm yết 6–7,5% (12 tháng, 10/2026); khoản trên 200 triệu thường được cộng thêm 2–2,5% ngoài biểu — không có số công khai. Dùng để so lợi suất kỳ vọng ở 05 mục B
A18: Trọng số phương pháp — Chốt 13/10/2026: chỉ DCF (phương pháp 2) làm giá trị, bốn phương pháp còn lại để đối chiếu (trước: 30/25/20/15/10)
A19: 1. P/E lợi nhuận lõi + tiền + dự án | B19: 0 | F19: Lợi nhuận lõi chuẩn hoá × P/E, cộng tiền theo mệnh giá, cộng giá trị ròng dự án · Từ 13/10/2026 chỉ đối chiếu (trước 30%)
A20: 2. DCF phần lõi + tiền + dự án | B20: 1 | F20: Dòng tiền phần lõi 2027–2031 ở r lõi; hai dự án cộng riêng (06) ở lợi suất dự án · Từ 13/10/2026 DÙNG LÀM GIÁ TRỊ: 100% (trước 25%)
A21: 3. Chiết khấu cổ tức (DDM) | B21: 0 | F21: Cổ đông thiểu số chỉ nhận cổ tức; Vinamilk kiểm soát 68% quyết định chia bao nhiêu · Từ 13/10/2026 chỉ đối chiếu (trước 20%): r phần kinh doanh áp cả lên tiền gửi nên định giá tiền thấp
A22: 4. P/B theo ROE | B22: 0 | F22: ROE lịch sử, độc lập với động cơ lõi; coi tiền gửi nằm lại công ty mãi · Từ 13/10/2026 chỉ đối chiếu (trước 15%): như phương pháp 3, mỗi đồng tiền chỉ được ~0,25 đồng
A23: 5. EV/EBITDA lõi + tiền + dự án | B23: 0 | F23: Gần như trùng phương pháp 1 (không vay) · Từ 13/10/2026 chỉ đối chiếu (trước 10%)
A24: Tổng trọng số (phải bằng 100%) | B24: =SUM(B19:B23) -> 1 | C24: =IF(ABS(B24-1)<0.000001,"ĐẠT","SAI — tổng khác 100%") -> ĐẠT
A26: Chiết khấu tiền ròng khi cộng vào giá trị (k) | B26: 0.1 | F26: Chốt 13/10/2026: giá trị = DCF phần lõi + tiền ròng × (1 − k) + giá trị ròng dự án. k là phần tiền cổ đông thiểu số có thể không nhận đủ: Vinamilk nắm 68% quyết định chia hay giữ, tiền nằm ở công ty chỉ lãi ~5% sau thuế và quỹ. Mỗi 10 điểm k ≈ 1.271 đ/cp. Áp cho phương pháp 1, 2, 5 (cùng cộng tiền); 04 bảng 4 có k = 0% và 20%.
A27: B. ĐỘNG CƠ LỢI NHUẬN LÕI — hiệu chỉnh trên 12 tháng tới Q2/2026 (dùng chung PP 1, 2, 3, 5)
A28: Tham số | B28: Giá trị | F28: Cách tính / căn cứ
A29: V 12 tháng = bán cho Vinamilk (2025 − 6T/2025 + 6T/2026) | B29: ='01_Số liệu gốc'!$D$84-'01_Số liệu gốc'!$E$84+'01_Số liệu gốc'!$F$84 -> 637.205 | F29: Thuyết minh bên liên quan, 01 mục E
A30: Doanh thu thuần 12 tháng | B30: ='01_Số liệu gốc'!$H$42 -> 2937.018
A31: B 12 tháng = doanh thu − V | B31: =B30-B29 -> 2299.813 | F31: Thương hiệu + thức ăn chăn nuôi + khác
A32: Lãi gộp 12 tháng | B32: ='01_Số liệu gốc'!$H$43 -> 862.821
A33: Chi phí bán hàng 12 tháng | B33: ='01_Số liệu gốc'!$H$44 -> 629.378
A34: Chi phí quản lý 12 tháng | B34: ='01_Số liệu gốc'!$H$45 -> 37.733
A35: EBIT lõi 12 tháng | B35: ='01_Số liệu gốc'!$H$46 -> 195.71
A36: Hồi quy lãi gộp 2023–2025 theo V và B (không hệ số chặn): biên của V | B36: =INDEX(LINEST('01_Số liệu gốc'!$B$86:$D$86,'01_Số liệu gốc'!$B$84:$D$85,FALSE,FALSE),1,2) -> -0.040691357 | F36: Ra số ÂM — vô lý: hồi quy 3 điểm lẫn cả việc giá thu mua sữa tăng 7–8% năm 2024 (KBSV). Chỉ cho biết biên của V THẤP, không đo được bao nhiêu
A37: Hồi quy như trên: biên của B | B37: =INDEX(LINEST('01_Số liệu gốc'!$B$86:$D$86,'01_Số liệu gốc'!$B$84:$D$85,FALSE,FALSE),1,1) -> 0.37696235
A38: BIÊN GỘP CỦA PHẦN BÁN CHO VINAMILK (mV) DÙNG TRONG MODEL | B38: 0.1 | F38: Ước của người viết (12/10/2026): khoảng 10% (bản trước dùng 5%, xem phép thử T15). Công ty không công bố giá bán cho Vinamilk; BCTC 2025 TM 25–26 chỉ tách thành phẩm/hàng hóa, sữa nguyên liệu nằm trong thành phẩm (biên 29,3%); CSDL gen_notes không có. Chỉ ảnh hưởng khi cơ cấu V/B đổi so 12 tháng (biên B hiệu chỉnh lại theo mV). Độ nhạy mV 0% / 5% / 10% / 15% → kỳ vọng 27.660 / 27.239 / 26.819 / 26.398 đ/cp (chạy lại 13/10/2026: du lịch 336, giá trị = DCF + tiền × 90%)
A39: Biên gộp của B 12 tháng = (lãi gộp − mV × V) ÷ B | B39: =(B32-B38*B29)/B31 -> 0.34746325
A40: Chi phí bán hàng ÷ B, 12 tháng | B40: =B33/B31 -> 0.27366486
A41: Cùng cách tính các kỳ trước: | B41: 2023 | C41: 2025 | D41: 6T/2025 | E41: 6T/2026
A42: biên gộp của B | B42: =('01_Số liệu gốc'!B86-$B$38*'01_Số liệu gốc'!B84)/'01_Số liệu gốc'!B85 -> 0.35647386 | C42: =('01_Số liệu gốc'!D86-$B$38*'01_Số liệu gốc'!D84)/'01_Số liệu gốc'!D85 -> 0.33698353 | D42: =('01_Số liệu gốc'!E86-$B$38*'01_Số liệu gốc'!E84)/'01_Số liệu gốc'!E85 -> 0.33281576 | E42: =('01_Số liệu gốc'!F86-$B$38*'01_Số liệu gốc'!F84)/'01_Số liệu gốc'!F85 -> 0.35380725
A43: chi phí bán hàng ÷ B | B43: ='01_Số liệu gốc'!B87/'01_Số liệu gốc'!B85 -> 0.26156709 | C43: ='01_Số liệu gốc'!D87/'01_Số liệu gốc'!D85 -> 0.27996027 | D43: ='01_Số liệu gốc'!E87/'01_Số liệu gốc'!E85 -> 0.26050852 | E43: ='01_Số liệu gốc'!F87/'01_Số liệu gốc'!F85 -> 0.25038504 | F43: 6T/2026 khuyến mãi giảm, biên gộp tăng — giải trình công ty: "thay đổi cơ cấu doanh thu"
A44: Lãi sau chi phí bán hàng trên 100 đồng doanh thu: B so với V | B44: =B39-B40 -> 0.073798391 | C44: =B38 -> 0.1 | F44: B: cột B · V: cột C, Trên 100 đồng doanh thu, hàng thương hiệu giữ ~7,4 đồng sau khuyến mãi, phần bán cho Vinamilk giữ 10 đồng (ước). So theo doanh thu, không theo lít sữa: một lít làm thành hàng thương hiệu cho doanh thu cao hơn bán thô. Đòn bẩy thật là biên gộp B và tỷ lệ khuyến mãi
A45: Kiểm: mV × V + (biên B − CPBH/B) × B − quản lý = EBIT lõi 12 tháng | B45: =B38*B29+(B39-B40)*B31-B34 -> 195.71 | C45: =IF(ABS(B45-B35)<0.001,"KHỚP","LỆCH") -> KHỚP
A46: Chi phí quản lý năm chuẩn hoá (tỷ) | B46: 39 | F46: 12 tháng 37,7 tỷ; 2025 38,1 tỷ; cộng lạm phát
A47: Khấu hao năm chuẩn hoá = 6 tháng 2026 × 2 (chỉ dùng cho EBITDA) | B47: =('01_Số liệu gốc'!$F$52+'01_Số liệu gốc'!$G$52)*2 -> 70.908
A48: Thuế suất trên lợi nhuận lõi, 12 tháng (lãi tài chính ròng chịu 20%) | B48: =('01_Số liệu gốc'!$H$50-B14*('01_Số liệu gốc'!$H$47-'01_Số liệu gốc'!$H$48))/('01_Số liệu gốc'!$H$49-('01_Số liệu gốc'!$H$47-'01_Số liệu gốc'!$H$48)) -> 0.074019575
A49: cùng cách tính cho năm 2025 | B49: =('01_Số liệu gốc'!$F$30-B14*('01_Số liệu gốc'!$F$25-'01_Số liệu gốc'!$F$26))/('01_Số liệu gốc'!$F$29-('01_Số liệu gốc'!$F$25-'01_Số liệu gốc'!$F$26)) -> 0.087886232 | F49: Giả định lãi tiền gửi chịu đủ 20%, phần miễn thuế rơi hết vào lợi nhuận lõi
A50: Vốn hoạt động lõi 30/06/2026 (01 mục D) | B50: ='01_Số liệu gốc'!$C$72 -> 463.235
A51: ROIC lõi 12 tháng = EBIT lõi × (1 − thuế lõi) ÷ vốn hoạt động lõi | B51: =B35*(1-B48)/B50 -> 0.39121316 | F51: Rất cao vì nhà máy cũ đã khấu hao gần hết — chính là lý do phải xây nhà máy mới
A52: EBIT lõi tăng thêm mỗi quý: (6T/2026 − 6T/2025) ÷ 2 | B52: =(('01_Số liệu gốc'!$F$46+'01_Số liệu gốc'!$G$46)-('01_Số liệu gốc'!$B$46+'01_Số liệu gốc'!$C$46))/2 -> 21.7075
A53: MỐC KIỂM: LNST Q3/2026 = Q3/2025 + mức tăng × (1 − thuế) (tỷ) | B53: ='01_Số liệu gốc'!$D$51+1*B52*(1-B48) -> 48.16472 | C53: ='01_Số liệu gốc'!$D$51+0.5*B52*(1-B48) -> 38.11436 | D53: ='01_Số liệu gốc'!$D$51+1.5*B52*(1-B48) -> 58.21508 | F53: B = giữ đúng đà 6 tháng · C = còn một nửa · D = mạnh gấp rưỡi. Q3/2025 là quý xấu nhất 2025 (LNST 28 tỷ, khuyến mãi 182 tỷ). BCTC Q3 ra cuối tháng 10/2026
A55: C. BA KỊCH BẢN (năm chuẩn hoá ~2027, trước khi dự án có lãi — không phải dự phóng một năm)
A56: Tham số | B56: Xấu | C56: Cơ sở | D56: Tốt | E56: Mốc thực tế | F56: Căn cứ
A57: ĐỘNG CƠ LÕI (phương pháp 1, 2, 3, 5)
A58: B — doanh thu phần còn lại (tỷ) | B58: 2200 | C58: 2450 | D58: 2700 | E58: =B31 -> 2299.813 | F58: Mốc = 12 tháng. 6T/2026 +12,8% so cùng kỳ; 2026 chạy đà ~2.390. Xấu = mức 2025 (2.167) nếu Creamery không cất cánh; Tốt = mức 2023 (2.710). Kế hoạch 2026 doanh thu 3.126 tỷ ≈ B 2.470
A59: V — bán cho Vinamilk (tỷ) | B59: 700 | C59: 640 | D59: 600 | E59: =B29 -> 637.205 | F59: Bò vẫn cho sữa mỗi ngày: hàng thương hiệu bán chậm thì sữa dư dồn sang V. 2025: 668; 6T/2026 −8,6%
A60: Biên gộp của B: chênh so 12 tháng (điểm %) | B60: -0.015 | C60: 0 | D60: 0.01 | E60: =E42-B39 -> 0.0063439955 | F60: Mốc = 6T/2026 − 12 tháng. Giá thu mua sữa, thức ăn (ngô, khô đậu +21–25% so cùng kỳ tháng 9/2026) và cơ cấu sản phẩm
A61: Chi phí bán hàng ÷ B | B61: 0.28 | C61: 0.27 | D61: 0.26 | E61: =B40 -> 0.27366486 | F61: 2024–2025 28%; 6T/2026 25%; 12 tháng 27,3%. Đẩy Creamery vào miền Nam tốn khuyến mãi
A62: Thuế suất trên lợi nhuận lõi | B62: 0.11 | C62: 0.09 | D62: 0.08 | E62: =B48 -> 0.074019575 | F62: Mốc = 12 tháng. 2025: xem 02 mục B. Ưu đãi Nghị định 320/2025 có điều kiện (nguyên liệu nông sản ≥ 30% giá thành)
A63: Tăng trưởng B mỗi năm 2027–2031 (PP 2, 3) | B63: 0 | C63: 0.03 | D63: 0.05 | F63: Ngành sữa tăng thấp (−1% đến 3%/năm theo KBSV); Creamery là biến số
A64: BỘI SỐ (phương pháp 1, 5) — dùng chung ba kịch bản
A65: P/E trên lợi nhuận lõi sau thuế và quỹ | B65: 10.8 | C65: 10.8 | D65: 10.8 | E65: ='01_Số liệu gốc'!$B$138 -> 13.89 | F65: Dùng chung: lợi nhuận đã khác nhau theo kịch bản, hạ bội số nữa là phạt hai lần. Mốc = P/E trung vị cả công ty (gồm lãi tiền gửi). 10,8x = bội số Vinasoy file QNS (9x EBIT) quy về lợi nhuận lõi sau thuế, quỹ; ≈ P/E cơ bản ở r mới (05 mục A). Phép thử T11 (10x)
A66: EV/EBITDA lõi | B66: 6.6 | C66: 6.6 | D66: 6.6 | F66: Bội số Vinasoy quy ra ~6,6x; ≈ EV/EBITDA cơ bản ở r mới (05 mục A). Vietcap ghi 10,8x nhưng KHÔNG trừ tiền gửi có kỳ hạn — không so thẳng
A67: PHƯƠNG PHÁP 4 — P/B theo ROE (không qua động cơ lõi)
A68: ROE chu kỳ, trước trích quỹ | B68: 0.095 | C68: 0.115 | D68: 0.14 | E68: ='01_Số liệu gốc'!$E$103 -> 0.12804855 | F68: Mốc = bình quân 2022–2025 (sau đợt phát hành). 2024–2025 9,4–9,5%; 12 tháng 11,3%. Tính trên vốn chủ GỒM tiền gửi — coi tiền nằm lại công ty mãi, nên khắt khe hơn PP 1
A69: CỔ TỨC VÀ TIỀN (phương pháp 3) — hai dự án: xem 06_Dự án
A70: Cổ tức tiền mặt 2027–2031 (đồng/cổ phiếu) | B70: 1000 | C70: 1500 | D70: 2000 | E70: ='01_Số liệu gốc'!$B$129 -> 2000 | F70: Chính sách 2026: tối thiểu 50% LNST (ĐHĐCĐ 20/04/2026) ≈ 1.000đ ở kế hoạch 241 tỷ → Xấu. 2022–2025 trả 2.000đ → Tốt. Cơ sở 1.500đ = 165 tỷ/năm — TỰ ĐẶT. Tiền âm thì phải vay (lãi suất ở mục A)
A71: Lãi suất tiền gửi | B71: 0.065 | C71: 0.07 | D71: 0.075 | E71: ='01_Số liệu gốc'!$B$137 -> 0.063826955 | F71: Mốc = lãi tiền gửi 2025 ÷ số dư bình quân. Lãi 12 tháng niêm yết 10/2026: 6–7,5%; khoản lớn được cộng thêm → cơ sở 7%
A72: XÁC SUẤT
A73: Xác suất | B73: 0.25 | C73: 0.5 | D73: 0.25 | F73: Mặc định đối xứng — chưa có lý do nghiêng
A74: Tổng xác suất (phải bằng 100%) | B74: =SUM(B73:D73) -> 1 | C74: =IF(ABS(B74-1)<0.000001,"ĐẠT","SAI — tổng khác 100%") -> ĐẠT

Sheet 03_Định giá
A1: MCM — ĐỊNH GIÁ: DCF LÕI + TIỀN + DỰ ÁN (BỐN PHƯƠNG PHÁP ĐỐI CHIẾU), BA KỊCH BẢN, MƯỜI SÁU CỘT PHÉP THỬ (bản 12/10/2026, sửa 13/10)
A2: Toàn bộ là công thức đọc từ 01 và 02 — không nhập số ở sheet này, TRỪ ô đổi tham số ở cột phép thử (nền xanh lá). Mỗi cột H–W là một bản tính lại đầy đủ: lấy đúng tham số cột Cơ sở, đổi đúng một ô (T15 đổi thêm biên gộp B 12 tháng đi kèm để EBIT 12 tháng vẫn khớp).
H3: Đối chứng: không đổi gì (phải ra đúng cơ sở) | I3: Không xây nhà máy trong 5 năm — MỨC TRẦN (coi nhà máy cũ chạy mãi không tốn thêm) | J3: Nhà máy chạy từ 2028 (lịch công ty: xong Q4/2027) | K3: Sữa trang trại bán thô 13.000 đ/lít | L3: Chi phí nuôi 11.500 đ/lít | M3: ERP 10% (VDSC, cận trên) | N3: β phần kinh doanh 0,85 (bằng dự án) | O3: Cổ tức 1.000đ/cp (tối thiểu 50% LNST) | P3: B về mức 2025 (Creamery không cất cánh) | Q3: B về mức 2023 | R3: Chi phí bán hàng ÷ B = mức 12 tháng | S3: P/E lõi 10x | T3: P/E lõi = P/E trung vị lịch sử MCM | U3: Biên gộp B giữ mức 6T/2026 | V3: β phần kinh doanh 0,65 | W3: Biên gộp bán cho Vinamilk 5% thay cho 10% (cơ sở). Biên gộp B 12 tháng tính lại theo ô này để EBIT 12 tháng vẫn khớp
A4: Chỉ tiêu (tỷ đồng) | B4: Xấu | C4: Cơ sở | D4: Tốt | E4: Trọng số | F4: Cách tính | H4: T0 | I4: T1 | J4: T2 | K4: T3 | L4: T4 | M4: T5 | N4: T6 | O4: T7 | P4: T8 | Q4: T9 | R4: T10 | S4: T11 | T4: T12 | U4: T13 | V4: T14 | W4: T15
A5: P. THAM SỐ — cột Xấu/Cơ sở/Tốt lấy từ 02 và 06; cột phép thử = Cơ sở, trừ một ô nền xanh
A6: B — doanh thu phần còn lại | B6: ='02_Giả định'!B58 -> 2200 | C6: ='02_Giả định'!C58 -> 2450 | D6: ='02_Giả định'!D58 -> 2700 | H6: =$C6 -> 2450 | I6: =$C6 -> 2450 | J6: =$C6 -> 2450 | K6: =$C6 -> 2450 | L6: =$C6 -> 2450 | M6: =$C6 -> 2450 | N6: =$C6 -> 2450 | O6: =$C6 -> 2450 | P6: ='01_Số liệu gốc'!$D$85 -> 2166.786 | Q6: ='01_Số liệu gốc'!$B$85 -> 2710.123 | R6: =$C6 -> 2450 | S6: =$C6 -> 2450 | T6: =$C6 -> 2450 | U6: =$C6 -> 2450 | V6: =$C6 -> 2450 | W6: =$C6 -> 2450
A7: V — bán cho Vinamilk | B7: ='02_Giả định'!B59 -> 700 | C7: ='02_Giả định'!C59 -> 640 | D7: ='02_Giả định'!D59 -> 600 | H7: =$C7 -> 640 | I7: =$C7 -> 640 | J7: =$C7 -> 640 | K7: =$C7 -> 640 | L7: =$C7 -> 640 | M7: =$C7 -> 640 | N7: =$C7 -> 640 | O7: =$C7 -> 640 | ... W7: =$C7 -> 640
A8: Biên gộp B: chênh so 12 tháng | B8: ='02_Giả định'!B60 -> -0.015 | C8: ='02_Giả định'!C60 -> 0 | D8: ='02_Giả định'!D60 -> 0.01 | H8: =$C8 -> 0 | I8: =$C8 -> 0 | J8: =$C8 -> 0 | K8: =$C8 -> 0 | L8: =$C8 -> 0 | M8: =$C8 -> 0 | N8: =$C8 -> 0 | O8: =$C8 -> 0 | ... T8: =$C8 -> 0 | U8: ='02_Giả định'!$E$42-'02_Giả định'!$B$39 -> 0.0063439955 | V8: =$C8 -> 0 | W8: =$C8 -> 0
A9: Chi phí bán hàng ÷ B | B9: ='02_Giả định'!B61 -> 0.28 | C9: ='02_Giả định'!C61 -> 0.27 | D9: ='02_Giả định'!D61 -> 0.26 | H9: =$C9 -> 0.27 | I9: =$C9 -> 0.27 | J9: =$C9 -> 0.27 | K9: =$C9 -> 0.27 | L9: =$C9 -> 0.27 | M9: =$C9 -> 0.27 | N9: =$C9 -> 0.27 | O9: =$C9 -> 0.27 | ... Q9: =$C9 -> 0.27 | R9: ='02_Giả định'!$B$40 -> 0.27366486 | S9: =$C9 -> 0.27 | T9: =$C9 -> 0.27 | U9: =$C9 -> 0.27 | V9: =$C9 -> 0.27 | W9: =$C9 -> 0.27
A10: Thuế suất lõi | B10: ='02_Giả định'!B62 -> 0.11 | C10: ='02_Giả định'!C62 -> 0.09 | D10: ='02_Giả định'!D62 -> 0.08 | H10: =$C10 -> 0.09 | I10: =$C10 -> 0.09 | J10: =$C10 -> 0.09 | K10: =$C10 -> 0.09 | L10: =$C10 -> 0.09 | M10: =$C10 -> 0.09 | N10: =$C10 -> 0.09 | O10: =$C10 -> 0.09 | ... W10: =$C10 -> 0.09
A11: Tăng trưởng B 2027–2031 | B11: ='02_Giả định'!B63 -> 0 | C11: ='02_Giả định'!C63 -> 0.03 | D11: ='02_Giả định'!D63 -> 0.05 | H11: =$C11 -> 0.03 | I11: =$C11 -> 0.03 | J11: =$C11 -> 0.03 | K11: =$C11 -> 0.03 | L11: =$C11 -> 0.03 | M11: =$C11 -> 0.03 | N11: =$C11 -> 0.03 | O11: =$C11 -> 0.03 | ... W11: =$C11 -> 0.03
A12: P/E lõi | B12: ='02_Giả định'!B65 -> 10.8 | C12: ='02_Giả định'!C65 -> 10.8 | D12: ='02_Giả định'!D65 -> 10.8 | H12: =$C12 -> 10.8 | I12: =$C12 -> 10.8 | J12: =$C12 -> 10.8 | K12: =$C12 -> 10.8 | L12: =$C12 -> 10.8 | M12: =$C12 -> 10.8 | N12: =$C12 -> 10.8 | O12: =$C12 -> 10.8 | ... R12: =$C12 -> 10.8 | S12: 10 | T12: ='01_Số liệu gốc'!$B$138 -> 13.89 | U12: =$C12 -> 10.8 | V12: =$C12 -> 10.8 | W12: =$C12 -> 10.8
A13: EV/EBITDA lõi | B13: ='02_Giả định'!B66 -> 6.6 | C13: ='02_Giả định'!C66 -> 6.6 | D13: ='02_Giả định'!D66 -> 6.6 | H13: =$C13 -> 6.6 | I13: =$C13 -> 6.6 | J13: =$C13 -> 6.6 | K13: =$C13 -> 6.6 | L13: =$C13 -> 6.6 | M13: =$C13 -> 6.6 | N13: =$C13 -> 6.6 | O13: =$C13 -> 6.6 | ... W13: =$C13 -> 6.6
A14: ROE chu kỳ | B14: ='02_Giả định'!B68 -> 0.095 | C14: ='02_Giả định'!C68 -> 0.115 | D14: ='02_Giả định'!D68 -> 0.14 | H14: =$C14 -> 0.115 | I14: =$C14 -> 0.115 | J14: =$C14 -> 0.115 | K14: =$C14 -> 0.115 | L14: =$C14 -> 0.115 | M14: =$C14 -> 0.115 | N14: =$C14 -> 0.115 | O14: =$C14 -> 0.115 | ... W14: =$C14 -> 0.115
A15: Cổ tức 2027–2031 (đồng/cp) | B15: ='02_Giả định'!B70 -> 1000 | C15: ='02_Giả định'!C70 -> 1500 | D15: ='02_Giả định'!D70 -> 2000 | H15: =$C15 -> 1500 | I15: =$C15 -> 1500 | J15: =$C15 -> 1500 | K15: =$C15 -> 1500 | L15: =$C15 -> 1500 | M15: =$C15 -> 1500 | N15: =$C15 -> 1500 | O15: 1000 | P15: =$C15 -> 1500 | Q15: =$C15 -> 1500 | R15: =$C15 -> 1500 | S15: =$C15 -> 1500 | T15: =$C15 -> 1500 | U15: =$C15 -> 1500 | V15: =$C15 -> 1500 | W15: =$C15 -> 1500
A16: Lãi suất tiền gửi | B16: ='02_Giả định'!B71 -> 0.065 | C16: ='02_Giả định'!C71 -> 0.07 | D16: ='02_Giả định'!D71 -> 0.075 | H16: =$C16 -> 0.07 | I16: =$C16 -> 0.07 | J16: =$C16 -> 0.07 | K16: =$C16 -> 0.07 | L16: =$C16 -> 0.07 | M16: =$C16 -> 0.07 | N16: =$C16 -> 0.07 | O16: =$C16 -> 0.07 | ... W16: =$C16 -> 0.07
A17: Trang trại: vốn phần bò sữa | B17: ='06_Dự án'!B6 -> 860 | C17: ='06_Dự án'!C6 -> 784 | D17: ='06_Dự án'!D6 -> 784 | H17: =$C17 -> 784 | I17: =$C17 -> 784 | J17: =$C17 -> 784 | K17: =$C17 -> 784 | L17: =$C17 -> 784 | M17: =$C17 -> 784 | N17: =$C17 -> 784 | O17: =$C17 -> 784 | ... W17: =$C17 -> 784
A18: Trang trại: vốn phần du lịch | B18: ='06_Dự án'!B7 -> 336 | C18: ='06_Dự án'!C7 -> 336 | D18: ='06_Dự án'!D7 -> 336 | H18: =$C18 -> 336 | I18: =$C18 -> 336 | J18: =$C18 -> 336 | K18: =$C18 -> 336 | L18: =$C18 -> 336 | M18: =$C18 -> 336 | N18: =$C18 -> 336 | O18: =$C18 -> 336 | ... W18: =$C18 -> 336
A19: Trang trại: triệu lít/năm khi đủ đàn | B19: ='06_Dự án'!B8 -> 18 | C19: ='06_Dự án'!C8 -> 20 | D19: ='06_Dự án'!D8 -> 22 | H19: =$C19 -> 20 | I19: =$C19 -> 20 | J19: =$C19 -> 20 | K19: =$C19 -> 20 | L19: =$C19 -> 20 | M19: =$C19 -> 20 | N19: =$C19 -> 20 | O19: =$C19 -> 20 | ... W19: =$C19 -> 20
A20: Trang trại: sản lượng 2027 | B20: ='06_Dự án'!B9 -> 0.3 | C20: ='06_Dự án'!C9 -> 0.5 | D20: ='06_Dự án'!D9 -> 0.6 | H20: =$C20 -> 0.5 | I20: =$C20 -> 0.5 | J20: =$C20 -> 0.5 | K20: =$C20 -> 0.5 | L20: =$C20 -> 0.5 | M20: =$C20 -> 0.5 | N20: =$C20 -> 0.5 | O20: =$C20 -> 0.5 | ... W20: =$C20 -> 0.5
A21: Trang trại: giá bán (đ/lít) | B21: ='06_Dự án'!B10 -> 13000 | C21: ='06_Dự án'!C10 -> 14500 | D21: ='06_Dự án'!D10 -> 16000 | H21: =$C21 -> 14500 | I21: =$C21 -> 14500 | J21: =$C21 -> 14500 | K21: 13000 | L21: =$C21 -> 14500 | M21: =$C21 -> 14500 | N21: =$C21 -> 14500 | O21: =$C21 -> 14500 | P21: =$C21 -> 14500 | Q21: =$C21 -> 14500 | R21: =$C21 -> 14500 | S21: =$C21 -> 14500 | ... W21: =$C21 -> 14500
A22: Trang trại: chi phí tiền mặt (đ/lít) | B22: ='06_Dự án'!B11 -> 11500 | C22: ='06_Dự án'!C11 -> 10500 | D22: ='06_Dự án'!D11 -> 9500 | H22: =$C22 -> 10500 | I22: =$C22 -> 10500 | J22: =$C22 -> 10500 | K22: =$C22 -> 10500 | L22: 11500 | M22: =$C22 -> 10500 | N22: =$C22 -> 10500 | O22: =$C22 -> 10500 | P22: =$C22 -> 10500 | Q22: =$C22 -> 10500 | R22: =$C22 -> 10500 | S22: =$C22 -> 10500 | T22: =$C22 -> 10500 | ... W22: =$C22 -> 10500
A23: Trang trại: thu thêm bê, bò loại | B23: ='06_Dự án'!B12 -> 0.05 | C23: ='06_Dự án'!C12 -> 0.05 | D23: ='06_Dự án'!D12 -> 0.05 | H23: =$C23 -> 0.05 | I23: =$C23 -> 0.05 | J23: =$C23 -> 0.05 | K23: =$C23 -> 0.05 | L23: =$C23 -> 0.05 | M23: =$C23 -> 0.05 | N23: =$C23 -> 0.05 | O23: =$C23 -> 0.05 | ... W23: =$C23 -> 0.05
A24: Trang trại: chi duy trì | B24: ='06_Dự án'!B13 -> 15 | C24: ='06_Dự án'!C13 -> 15 | D24: ='06_Dự án'!D13 -> 15 | H24: =$C24 -> 15 | I24: =$C24 -> 15 | J24: =$C24 -> 15 | K24: =$C24 -> 15 | L24: =$C24 -> 15 | M24: =$C24 -> 15 | N24: =$C24 -> 15 | O24: =$C24 -> 15 | ... W24: =$C24 -> 15
A25: Trang trại: năm khấu hao | B25: ='06_Dự án'!B14 -> 20 | C25: ='06_Dự án'!C14 -> 20 | D25: ='06_Dự án'!D14 -> 20 | H25: =$C25 -> 20 | I25: =$C25 -> 20 | J25: =$C25 -> 20 | K25: =$C25 -> 20 | L25: =$C25 -> 20 | M25: =$C25 -> 20 | N25: =$C25 -> 20 | O25: =$C25 -> 20 | ... W25: =$C25 -> 20
A26: Du lịch: lãi trước thuế từ 2028 | B26: ='06_Dự án'!B15 -> 0 | C26: ='06_Dự án'!C15 -> 10 | D26: ='06_Dự án'!D15 -> 25 | H26: =$C26 -> 10 | I26: =$C26 -> 10 | J26: =$C26 -> 10 | K26: =$C26 -> 10 | L26: =$C26 -> 10 | M26: =$C26 -> 10 | N26: =$C26 -> 10 | O26: =$C26 -> 10 | ... W26: =$C26 -> 10
A27: Nhà máy: có xây trong 5 năm | B27: ='06_Dự án'!B19 -> 0 | C27: ='06_Dự án'!C19 -> 1 | D27: ='06_Dự án'!D19 -> 1 | H27: =$C27 -> 1 | I27: 0 | J27: =$C27 -> 1 | K27: =$C27 -> 1 | L27: =$C27 -> 1 | M27: =$C27 -> 1 | N27: =$C27 -> 1 | O27: =$C27 -> 1 | P27: =$C27 -> 1 | Q27: =$C27 -> 1 | ... W27: =$C27 -> 1
A28: Nhà máy: vốn giai đoạn 1 | B28: ='06_Dự án'!B20 -> 850 | C28: ='06_Dự án'!C20 -> 743 | D28: ='06_Dự án'!D20 -> 743 | H28: =$C28 -> 743 | I28: =$C28 -> 743 | J28: =$C28 -> 743 | K28: =$C28 -> 743 | L28: =$C28 -> 743 | M28: =$C28 -> 743 | N28: =$C28 -> 743 | O28: =$C28 -> 743 | ... W28: =$C28 -> 743
A29: Nhà máy: năm bắt đầu có lãi | B29: ='06_Dự án'!B21 -> 2031 | C29: ='06_Dự án'!C21 -> 2030 | D29: ='06_Dự án'!D21 -> 2028 | H29: =$C29 -> 2030 | I29: =$C29 -> 2030 | J29: 2028 | K29: =$C29 -> 2030 | L29: =$C29 -> 2030 | M29: =$C29 -> 2030 | N29: =$C29 -> 2030 | O29: =$C29 -> 2030 | P29: =$C29 -> 2030 | Q29: =$C29 -> 2030 | R29: =$C29 -> 2030 | ... W29: =$C29 -> 2030
A30: Nhà máy: lãi tăng thêm sau thuế | B30: ='06_Dự án'!B22 -> 20 | C30: ='06_Dự án'!C22 -> 45 | D30: ='06_Dự án'!D22 -> 75 | H30: =$C30 -> 45 | I30: =$C30 -> 45 | J30: =$C30 -> 45 | K30: =$C30 -> 45 | L30: =$C30 -> 45 | M30: =$C30 -> 45 | N30: =$C30 -> 45 | O30: =$C30 -> 45 | ... W30: =$C30 -> 45
A31: Lợi suất phi rủi ro | B31: ='02_Giả định'!$B$6 -> 0.046 | C31: ='02_Giả định'!$B$6 -> 0.046 | D31: ='02_Giả định'!$B$6 -> 0.046 | H31: =$C31 -> 0.046 | I31: =$C31 -> 0.046 | J31: =$C31 -> 0.046 | K31: =$C31 -> 0.046 | L31: =$C31 -> 0.046 | M31: =$C31 -> 0.046 | N31: =$C31 -> 0.046 | O31: =$C31 -> 0.046 | ... W31: =$C31 -> 0.046
A32: Phần bù rủi ro thị trường | B32: ='02_Giả định'!$B$7 -> 0.092 | C32: ='02_Giả định'!$B$7 -> 0.092 | D32: ='02_Giả định'!$B$7 -> 0.092 | H32: =$C32 -> 0.092 | I32: =$C32 -> 0.092 | J32: =$C32 -> 0.092 | K32: =$C32 -> 0.092 | L32: =$C32 -> 0.092 | M32: 0.1 | N32: =$C32 -> 0.092 | O32: =$C32 -> 0.092 | P32: =$C32 -> 0.092 | Q32: =$C32 -> 0.092 | R32: =$C32 -> 0.092 | S32: =$C32 -> 0.092 | T32: =$C32 -> 0.092 | U32: =$C32 -> 0.092 | ... W32: =$C32 -> 0.092
A33: β phần kinh doanh hiện tại | B33: ='02_Giả định'!$B$8 -> 0.72 | C33: ='02_Giả định'!$B$8 -> 0.72 | D33: ='02_Giả định'!$B$8 -> 0.72 | H33: =$C33 -> 0.72 | I33: =$C33 -> 0.72 | J33: =$C33 -> 0.72 | K33: =$C33 -> 0.72 | L33: =$C33 -> 0.72 | M33: =$C33 -> 0.72 | N33: 0.85 | O33: =$C33 -> 0.72 | P33: =$C33 -> 0.72 | Q33: =$C33 -> 0.72 | R33: =$C33 -> 0.72 | S33: =$C33 -> 0.72 | T33: =$C33 -> 0.72 | U33: =$C33 -> 0.72 | V33: 0.65 | W33: =$C33 -> 0.72
A34: β hai dự án | B34: ='02_Giả định'!$B$9 -> 0.85 | C34: ='02_Giả định'!$B$9 -> 0.85 | D34: ='02_Giả định'!$B$9 -> 0.85 | H34: =$C34 -> 0.85 | I34: =$C34 -> 0.85 | J34: =$C34 -> 0.85 | K34: =$C34 -> 0.85 | L34: =$C34 -> 0.85 | M34: =$C34 -> 0.85 | N34: =$C34 -> 0.85 | O34: =$C34 -> 0.85 | ... W34: =$C34 -> 0.85
A35: Tăng trưởng dài hạn g | B35: ='02_Giả định'!$B$12 -> 0.03 | C35: ='02_Giả định'!$B$12 -> 0.03 | D35: ='02_Giả định'!$B$12 -> 0.03 | H35: =$C35 -> 0.03 | I35: =$C35 -> 0.03 | J35: =$C35 -> 0.03 | K35: =$C35 -> 0.03 | L35: =$C35 -> 0.03 | M35: =$C35 -> 0.03 | N35: =$C35 -> 0.03 | O35: =$C35 -> 0.03 | ... W35: =$C35 -> 0.03
A36: Trích quỹ khen thưởng phúc lợi | B36: ='02_Giả định'!$B$13 -> 0.1 | C36: ='02_Giả định'!$B$13 -> 0.1 | D36: ='02_Giả định'!$B$13 -> 0.1 | H36: =$C36 -> 0.1 | I36: =$C36 -> 0.1 | J36: =$C36 -> 0.1 | K36: =$C36 -> 0.1 | L36: =$C36 -> 0.1 | M36: =$C36 -> 0.1 | N36: =$C36 -> 0.1 | O36: =$C36 -> 0.1 | ... W36: =$C36 -> 0.1
A37: Thuế trên lãi tiền gửi | B37: ='02_Giả định'!$B$14 -> 0.2 | C37: ='02_Giả định'!$B$14 -> 0.2 | D37: ='02_Giả định'!$B$14 -> 0.2 | H37: =$C37 -> 0.2 | I37: =$C37 -> 0.2 | J37: =$C37 -> 0.2 | K37: =$C37 -> 0.2 | L37: =$C37 -> 0.2 | M37: =$C37 -> 0.2 | N37: =$C37 -> 0.2 | O37: =$C37 -> 0.2 | ... W37: =$C37 -> 0.2
A38: Lãi suất vay khi tiền âm | B38: ='02_Giả định'!$B$15 -> 0.075 | C38: ='02_Giả định'!$B$15 -> 0.075 | D38: ='02_Giả định'!$B$15 -> 0.075 | H38: =$C38 -> 0.075 | I38: =$C38 -> 0.075 | J38: =$C38 -> 0.075 | K38: =$C38 -> 0.075 | L38: =$C38 -> 0.075 | M38: =$C38 -> 0.075 | N38: =$C38 -> 0.075 | O38: =$C38 -> 0.075 | ... W38: =$C38 -> 0.075
A39: Cổ tức tạm ứng đợt 1/2026 (đồng/cp) | B39: ='02_Giả định'!$B$16 -> 1000 | C39: ='02_Giả định'!$B$16 -> 1000 | D39: ='02_Giả định'!$B$16 -> 1000 | H39: =$C39 -> 1000 | I39: =$C39 -> 1000 | J39: =$C39 -> 1000 | K39: =$C39 -> 1000 | L39: =$C39 -> 1000 | M39: =$C39 -> 1000 | N39: =$C39 -> 1000 | O39: =$C39 -> 1000 | ... W39: =$C39 -> 1000
A40: Biên gộp phần bán cho Vinamilk | B40: ='02_Giả định'!$B$38 -> 0.1 | C40: ='02_Giả định'!$B$38 -> 0.1 | D40: ='02_Giả định'!$B$38 -> 0.1 | H40: =$C40 -> 0.1 | I40: =$C40 -> 0.1 | J40: =$C40 -> 0.1 | K40: =$C40 -> 0.1 | L40: =$C40 -> 0.1 | M40: =$C40 -> 0.1 | N40: =$C40 -> 0.1 | O40: =$C40 -> 0.1 | ... V40: =$C40 -> 0.1 | W40: 0.05
A41: Biên gộp B 12 tháng | B41: ='02_Giả định'!$B$39 -> 0.34746325 | C41: ='02_Giả định'!$B$39 -> 0.34746325 | D41: ='02_Giả định'!$B$39 -> 0.34746325 | H41: =$C41 -> 0.34746325 | I41: =$C41 -> 0.34746325 | J41: =$C41 -> 0.34746325 | K41: =$C41 -> 0.34746325 | L41: =$C41 -> 0.34746325 | M41: =$C41 -> 0.34746325 | N41: =$C41 -> 0.34746325 | O41: =$C41 -> 0.34746325 | ... V41: =$C41 -> 0.34746325 | W41: =('02_Giả định'!$B$32-W40*'02_Giả định'!$B$29)/'02_Giả định'!$B$31 -> 0.36131666
A42: Chi phí quản lý chuẩn hoá | B42: ='02_Giả định'!$B$46 -> 39 | C42: ='02_Giả định'!$B$46 -> 39 | D42: ='02_Giả định'!$B$46 -> 39 | H42: =$C42 -> 39 | I42: =$C42 -> 39 | J42: =$C42 -> 39 | K42: =$C42 -> 39 | L42: =$C42 -> 39 | M42: =$C42 -> 39 | N42: =$C42 -> 39 | O42: =$C42 -> 39 | ... W42: =$C42 -> 39
A43: Khấu hao chuẩn hoá | B43: ='02_Giả định'!$B$47 -> 70.908 | C43: ='02_Giả định'!$B$47 -> 70.908 | D43: ='02_Giả định'!$B$47 -> 70.908 | H43: =$C43 -> 70.908 | I43: =$C43 -> 70.908 | J43: =$C43 -> 70.908 | K43: =$C43 -> 70.908 | L43: =$C43 -> 70.908 | M43: =$C43 -> 70.908 | N43: =$C43 -> 70.908 | O43: =$C43 -> 70.908 | ... W43: =$C43 -> 70.908
A44: LỢI SUẤT YÊU CẦU PHẦN LÕI r = Rf + β × ERP | B44: =B31+B33*B32 -> 0.11224 | C44: =C31+C33*C32 -> 0.11224 | D44: =D31+D33*D32 -> 0.11224 | H44: =H31+H33*H32 -> 0.11224 | I44: =I31+I33*I32 -> 0.11224 | J44: =J31+J33*J32 -> 0.11224 | K44: =K31+K33*K32 -> 0.11224 | L44: =L31+L33*L32 -> 0.11224 | M44: =M31+M33*M32 -> 0.118 | N44: =N31+N33*N32 -> 0.1242 | O44: =O31+O33*O32 -> 0.11224 | ... W44: =W31+W33*W32 -> 0.11224
A45: LỢI SUẤT YÊU CẦU HAI DỰ ÁN = Rf + β dự án × ERP | B45: =B31+B34*B32 -> 0.1242 | C45: =C31+C34*C32 -> 0.1242 | D45: =D31+D34*D32 -> 0.1242 | H45: =H31+H34*H32 -> 0.1242 | I45: =I31+I34*I32 -> 0.1242 | J45: =J31+J34*J32 -> 0.1242 | K45: =K31+K34*K32 -> 0.1242 | L45: =L31+L34*L32 -> 0.1242 | M45: =M31+M34*M32 -> 0.131 | N45: =N31+N34*N32 -> 0.1242 | O45: =O31+O34*O32 -> 0.1242 | ... W45: =W31+W34*W32 -> 0.1242
A47: A. LỢI NHUẬN LÕI CHUẨN HOÁ — tách bán cho Vinamilk (V) khỏi phần còn lại (B)
A48: Biên gộp của B = 12 tháng + chênh | B48: =B41+B8 -> 0.33246325 | C48: =C41+C8 -> 0.34746325 | D48: =D41+D8 -> 0.35746325 | H48: =H41+H8 -> 0.34746325 | I48: =I41+I8 -> 0.34746325 | J48: =J41+J8 -> 0.34746325 | K48: =K41+K8 -> 0.34746325 | L48: =L41+L8 -> 0.34746325 | M48: =M41+M8 -> 0.34746325 | N48: =N41+N8 -> 0.34746325 | O48: =O41+O8 -> 0.34746325 | ... W48: =W41+W8 -> 0.36131666
A49: Lãi gộp = mV × V + biên B × B | B49: =B40*B7+B48*B6 -> 801.41915 | C49: =C40*C7+C48*C6 -> 915.28496 | D49: =D40*D7+D48*D6 -> 1025.1508 | H49: =H40*H7+H48*H6 -> 915.28496 | I49: =I40*I7+I48*I6 -> 915.28496 | J49: =J40*J7+J48*J6 -> 915.28496 | K49: =K40*K7+K48*K6 -> 915.28496 | L49: =L40*L7+L48*L6 -> 915.28496 | M49: =M40*M7+M48*M6 -> 915.28496 | N49: =N40*N7+N48*N6 -> 915.28496 | O49: =O40*O7+O48*O6 -> 915.28496 | ... W49: =W40*W7+W48*W6 -> 917.22582
A50: Chi phí bán hàng = CPBH/B × B | B50: =B9*B6 -> 616 | C50: =C9*C6 -> 661.5 | D50: =D9*D6 -> 702 | F50: Hàng bán cho Vinamilk không tốn khuyến mãi | H50: =H9*H6 -> 661.5 | I50: =I9*I6 -> 661.5 | J50: =J9*J6 -> 661.5 | K50: =K9*K6 -> 661.5 | L50: =L9*L6 -> 661.5 | M50: =M9*M6 -> 661.5 | N50: =N9*N6 -> 661.5 | O50: =O9*O6 -> 661.5 | ... W50: =W9*W6 -> 661.5
A51: EBIT LÕI = lãi gộp − bán hàng − quản lý | B51: =B49-B50-B42 -> 146.41915 | C51: =C49-C50-C42 -> 214.78496 | D51: =D49-D50-D42 -> 284.15078 | F51: 12 tháng tới Q2/2026 (02 mục B, theo năm 2025 kiểm toán); 2023: 261,8; 2025: 152,3 | H51: =H49-H50-H42 -> 214.78496 | I51: =I49-I50-I42 -> 214.78496 | J51: =J49-J50-J42 -> 214.78496 | K51: =K49-K50-K42 -> 214.78496 | L51: =L49-L50-L42 -> 214.78496 | M51: =M49-M50-M42 -> 214.78496 | N51: =N49-N50-N42 -> 214.78496 | O51: =O49-O50-O42 -> 214.78496 | ... W51: =W49-W50-W42 -> 216.72582
A52: Lợi nhuận lõi sau thuế | B52: =B51*(1-B10) -> 130.31304 | C52: =C51*(1-C10) -> 195.45432 | D52: =D51*(1-D10) -> 261.41871 | H52: =H51*(1-H10) -> 195.45432 | I52: =I51*(1-I10) -> 195.45432 | J52: =J51*(1-J10) -> 195.45432 | K52: =K51*(1-K10) -> 195.45432 | L52: =L51*(1-L10) -> 195.45432 | M52: =M51*(1-M10) -> 195.45432 | N52: =N51*(1-N10) -> 195.45432 | O52: =O51*(1-O10) -> 195.45432 | ... W52: =W51*(1-W10) -> 197.22049
A53: LỢI NHUẬN LÕI THUỘC CỔ ĐÔNG (sau quỹ khen thưởng phúc lợi) | B53: =B52*(1-B36) -> 117.28174 | C53: =C52*(1-C36) -> 175.90888 | D53: =D52*(1-D36) -> 235.27684 | H53: =H52*(1-H36) -> 175.90888 | I53: =I52*(1-I36) -> 175.90888 | J53: =J52*(1-J36) -> 175.90888 | K53: =K52*(1-K36) -> 175.90888 | L53: =L52*(1-L36) -> 175.90888 | M53: =M52*(1-M36) -> 175.90888 | N53: =N52*(1-N36) -> 175.90888 | O53: =O52*(1-O36) -> 175.90888 | ... W53: =W52*(1-W36) -> 177.49844
A54: mỗi cổ phiếu (đồng) | B54: =B53*1000/'01_Số liệu gốc'!$B$8 -> 1066.1976 | C54: =C53*1000/'01_Số liệu gốc'!$B$8 -> 1599.1717 | D54: =D53*1000/'01_Số liệu gốc'!$B$8 -> 2138.8804 | H54: =H53*1000/'01_Số liệu gốc'!$B$8 -> 1599.1717 | I54: =I53*1000/'01_Số liệu gốc'!$B$8 -> 1599.1717 | J54: =J53*1000/'01_Số liệu gốc'!$B$8 -> 1599.1717 | K54: =K53*1000/'01_Số liệu gốc'!$B$8 -> 1599.1717 | L54: =L53*1000/'01_Số liệu gốc'!$B$8 -> 1599.1717 | M54: =M53*1000/'01_Số liệu gốc'!$B$8 -> 1599.1717 | N54: =N53*1000/'01_Số liệu gốc'!$B$8 -> 1599.1717 | O54: =O53*1000/'01_Số liệu gốc'!$B$8 -> 1599.1717 | ... W54: =W53*1000/'01_Số liệu gốc'!$B$8 -> 1613.6222
A55: EBITDA lõi = EBIT lõi + khấu hao | B55: =B51+B43 -> 217.32715 | C55: =C51+C43 -> 285.69296 | D55: =D51+D43 -> 355.05878 | H55: =H51+H43 -> 285.69296 | I55: =I51+I43 -> 285.69296 | J55: =J51+J43 -> 285.69296 | K55: =K51+K43 -> 285.69296 | L55: =L51+L43 -> 285.69296 | M55: =M51+M43 -> 285.69296 | N55: =N51+N43 -> 285.69296 | O55: =O51+O43 -> 285.69296 | ... W55: =W51+W43 -> 287.63382
A56: Vốn hoạt động lõi 30/06/2026 | B56: ='01_Số liệu gốc'!$C$72 -> 463.235 | C56: ='01_Số liệu gốc'!$C$72 -> 463.235 | D56: ='01_Số liệu gốc'!$C$72 -> 463.235 | H56: ='01_Số liệu gốc'!$C$72 -> 463.235 | I56: ='01_Số liệu gốc'!$C$72 -> 463.235 | J56: ='01_Số liệu gốc'!$C$72 -> 463.235 | K56: ='01_Số liệu gốc'!$C$72 -> 463.235 | L56: ='01_Số liệu gốc'!$C$72 -> 463.235 | M56: ='01_Số liệu gốc'!$C$72 -> 463.235 | N56: ='01_Số liệu gốc'!$C$72 -> 463.235 | O56: ='01_Số liệu gốc'!$C$72 -> 463.235 | ... W56: ='01_Số liệu gốc'!$C$72 -> 463.235
A57: ROIC lõi | B57: =B52/B56 -> 0.28131088 | C57: =C52/C56 -> 0.4219334 | D57: =D52/D56 -> 0.56433282 | H57: =H52/H56 -> 0.4219334 | I57: =I52/I56 -> 0.4219334 | J57: =J52/J56 -> 0.4219334 | K57: =K52/K56 -> 0.4219334 | L57: =L52/L56 -> 0.4219334 | M57: =M52/M56 -> 0.4219334 | N57: =N52/N56 -> 0.4219334 | O57: =O52/O56 -> 0.4219334 | ... W57: =W52/W56 -> 0.42574609
A59: B. HAI DỰ ÁN — năm đủ công suất (giả định ở 06_Dự án; dòng tiền từng năm ở mục D, giá trị ở mục B2)
A60: Trang trại: tổng vốn theo kịch bản = phần bò sữa + phần du lịch | B60: =B17+B18 -> 1196 | C60: =C17+C18 -> 1120 | D60: =D17+D18 -> 1120 | H60: =H17+H18 -> 1120 | I60: =I17+I18 -> 1120 | J60: =J17+J18 -> 1120 | K60: =K17+K18 -> 1120 | L60: =L17+L18 -> 1120 | M60: =M17+M18 -> 1120 | N60: =N17+N18 -> 1120 | O60: =O17+O18 -> 1120 | ... W60: =W17+W18 -> 1120
A61: Trang trại: còn phải chi sau 30/06/2026 (dồn vào 2027) | B61: =MAX(0,B60-'01_Số liệu gốc'!$C$67) -> 780.679 | C61: =MAX(0,C60-'01_Số liệu gốc'!$C$67) -> 704.679 | D61: =MAX(0,D60-'01_Số liệu gốc'!$C$67) -> 704.679 | F61: Phần đã ghi sổ là chi phí chìm | H61: =MAX(0,H60-'01_Số liệu gốc'!$C$67) -> 704.679 | I61: =MAX(0,I60-'01_Số liệu gốc'!$C$67) -> 704.679 | J61: =MAX(0,J60-'01_Số liệu gốc'!$C$67) -> 704.679 | K61: =MAX(0,K60-'01_Số liệu gốc'!$C$67) -> 704.679 | L61: =MAX(0,L60-'01_Số liệu gốc'!$C$67) -> 704.679 | M61: =MAX(0,M60-'01_Số liệu gốc'!$C$67) -> 704.679 | N61: =MAX(0,N60-'01_Số liệu gốc'!$C$67) -> 704.679 | O61: =MAX(0,O60-'01_Số liệu gốc'!$C$67) -> 704.679 | ... W61: =MAX(0,W60-'01_Số liệu gốc'!$C$67) -> 704.679
A62: Trang trại: doanh thu khi đủ đàn = triệu lít × giá × (1 + thu thêm) ÷ 1.000 | B62: =B19*B21*(1+B23)/1000 -> 245.7 | C62: =C19*C21*(1+C23)/1000 -> 304.5 | D62: =D19*D21*(1+D23)/1000 -> 369.6 | H62: =H19*H21*(1+H23)/1000 -> 304.5 | I62: =I19*I21*(1+I23)/1000 -> 304.5 | J62: =J19*J21*(1+J23)/1000 -> 304.5 | K62: =K19*K21*(1+K23)/1000 -> 273 | L62: =L19*L21*(1+L23)/1000 -> 304.5 | M62: =M19*M21*(1+M23)/1000 -> 304.5 | N62: =N19*N21*(1+N23)/1000 -> 304.5 | O62: =O19*O21*(1+O23)/1000 -> 304.5 | ... W62: =W19*W21*(1+W23)/1000 -> 304.5
A63: lãi trước khấu hao = doanh thu − triệu lít × chi phí ÷ 1.000 | B63: =B62-B19*B22/1000 -> 38.7 | C63: =C62-C19*C22/1000 -> 94.5 | D63: =D62-D19*D22/1000 -> 160.6 | H63: =H62-H19*H22/1000 -> 94.5 | I63: =I62-I19*I22/1000 -> 94.5 | J63: =J62-J19*J22/1000 -> 94.5 | K63: =K62-K19*K22/1000 -> 63 | L63: =L62-L19*L22/1000 -> 74.5 | M63: =M62-M19*M22/1000 -> 94.5 | N63: =N62-N19*N22/1000 -> 94.5 | O63: =O62-O19*O22/1000 -> 94.5 | ... W63: =W62-W19*W22/1000 -> 94.5
A64: khấu hao phần bò sữa | B64: =B17/B25 -> 43 | C64: =C17/C25 -> 39.2 | D64: =D17/D25 -> 39.2 | H64: =H17/H25 -> 39.2 | I64: =I17/I25 -> 39.2 | J64: =J17/J25 -> 39.2 | K64: =K17/K25 -> 39.2 | L64: =L17/L25 -> 39.2 | M64: =M17/M25 -> 39.2 | N64: =N17/N25 -> 39.2 | O64: =O17/O25 -> 39.2 | ... W64: =W17/W25 -> 39.2
A65: lãi kế toán (thu nhập chăn nuôi miễn thuế) | B65: =B63-B64 -> -4.3 | C65: =C63-C64 -> 55.3 | D65: =D63-D64 -> 121.4 | H65: =H63-H64 -> 55.3 | I65: =I63-I64 -> 55.3 | J65: =J63-J64 -> 55.3 | K65: =K63-K64 -> 23.8 | L65: =L63-L64 -> 35.3 | M65: =M63-M64 -> 55.3 | N65: =N63-N64 -> 55.3 | O65: =O63-O64 -> 55.3 | ... W65: =W63-W64 -> 55.3
A66: tiền thu về = lãi trước khấu hao − chi duy trì | B66: =B63-B24 -> 23.7 | C66: =C63-C24 -> 79.5 | D66: =D63-D24 -> 145.6 | H66: =H63-H24 -> 79.5 | I66: =I63-I24 -> 79.5 | J66: =J63-J24 -> 79.5 | K66: =K63-K24 -> 48 | L66: =L63-L24 -> 59.5 | M66: =M63-M24 -> 79.5 | N66: =N63-N24 -> 79.5 | O66: =O63-O24 -> 79.5 | ... W66: =W63-W24 -> 79.5
A67: lãi trên vốn phần bò sữa | B67: =B65/B17 -> -0.005 | C67: =C65/C17 -> 0.070535714 | D67: =D65/D17 -> 0.15484694 | H67: =H65/H17 -> 0.070535714 | I67: =I65/I17 -> 0.070535714 | J67: =J65/J17 -> 0.070535714 | K67: =K65/K17 -> 0.030357143 | L67: =L65/L17 -> 0.04502551 | M67: =M65/M17 -> 0.070535714 | N67: =N65/N17 -> 0.070535714 | O67: =O65/O17 -> 0.070535714 | ... W67: =W65/W17 -> 0.070535714
A68: Du lịch: lãi sau thuế 20% từ 2028 | B68: =B26*(1-B37) -> 0 | C68: =C26*(1-C37) -> 8 | D68: =D26*(1-D37) -> 20 | H68: =H26*(1-H37) -> 8 | I68: =I26*(1-I37) -> 8 | J68: =J26*(1-J37) -> 8 | K68: =K26*(1-K37) -> 8 | L68: =L26*(1-L37) -> 8 | M68: =M26*(1-M37) -> 8 | N68: =N26*(1-N37) -> 8 | O68: =O26*(1-O37) -> 8 | ... W68: =W26*(1-W37) -> 8
A69: Nhà máy: vốn còn phải chi | B69: =B27*MAX(0,B28-'01_Số liệu gốc'!$C$68) -> 0 | C69: =C27*MAX(0,C28-'01_Số liệu gốc'!$C$68) -> 711.923 | D69: =D27*MAX(0,D28-'01_Số liệu gốc'!$C$68) -> 711.923 | F69: Không xây thì 31 tỷ dở dang mất trắng (đã là chi phí chìm) | H69: =H27*MAX(0,H28-'01_Số liệu gốc'!$C$68) -> 711.923 | I69: =I27*MAX(0,I28-'01_Số liệu gốc'!$C$68) -> 0 | J69: =J27*MAX(0,J28-'01_Số liệu gốc'!$C$68) -> 711.923 | K69: =K27*MAX(0,K28-'01_Số liệu gốc'!$C$68) -> 711.923 | L69: =L27*MAX(0,L28-'01_Số liệu gốc'!$C$68) -> 711.923 | M69: =M27*MAX(0,M28-'01_Số liệu gốc'!$C$68) -> 711.923 | N69: =N27*MAX(0,N28-'01_Số liệu gốc'!$C$68) -> 711.923 | O69: =O27*MAX(0,O28-'01_Số liệu gốc'!$C$68) -> 711.923 | ... W69: =W27*MAX(0,W28-'01_Số liệu gốc'!$C$68) -> 711.923
A70: lãi tăng thêm ÷ vốn | B70: =IF(B27=0,0,B30/B28) -> 0 | C70: =IF(C27=0,0,C30/C28) -> 0.060565276 | D70: =IF(D27=0,0,D30/D28) -> 0.10094213 | H70: =IF(H27=0,0,H30/H28) -> 0.060565276 | I70: =IF(I27=0,0,I30/I28) -> 0 | J70: =IF(J27=0,0,J30/J28) -> 0.060565276 | K70: =IF(K27=0,0,K30/K28) -> 0.060565276 | L70: =IF(L27=0,0,L30/L28) -> 0.060565276 | M70: =IF(M27=0,0,M30/M28) -> 0.060565276 | N70: =IF(N27=0,0,N30/N28) -> 0.060565276 | O70: =IF(O27=0,0,O30/O28) -> 0.060565276 | ... W70: =IF(W27=0,0,W30/W28) -> 0.060565276
A71: Hệ số dòng tiền đều 20 năm sau 2031 ở lợi suất dự án | B71: =(1-(1+B45)^-20)/B45 -> 7.2770559 | C71: =(1-(1+C45)^-20)/C45 -> 7.2770559 | D71: =(1-(1+D45)^-20)/D45 -> 7.2770559 | H71: =(1-(1+H45)^-20)/H45 -> 7.2770559 | I71: =(1-(1+I45)^-20)/I45 -> 7.2770559 | J71: =(1-(1+J45)^-20)/J45 -> 7.2770559 | K71: =(1-(1+K45)^-20)/K45 -> 7.2770559 | L71: =(1-(1+L45)^-20)/L45 -> 7.2770559 | M71: =(1-(1+M45)^-20)/M45 -> 6.9827442 | N71: =(1-(1+N45)^-20)/N45 -> 7.2770559 | O71: =(1-(1+O45)^-20)/O45 -> 7.2770559 | ... W71: =(1-(1+W45)^-20)/W45 -> 7.2770559
A73: D. DÒNG TIỀN 2027–2031 — lõi (phương pháp 2), hai dự án (B2), tiền ròng và cổ tức (phương pháp 3)
A74: Năm 1 — 2027
A75: B | B75: =B6*(1+B11)^0 -> 2200 | C75: =C6*(1+C11)^0 -> 2450 | D75: =D6*(1+D11)^0 -> 2700 | H75: =H6*(1+H11)^0 -> 2450 | I75: =I6*(1+I11)^0 -> 2450 | J75: =J6*(1+J11)^0 -> 2450 | K75: =K6*(1+K11)^0 -> 2450 | L75: =L6*(1+L11)^0 -> 2450 | M75: =M6*(1+M11)^0 -> 2450 | N75: =N6*(1+N11)^0 -> 2450 | O75: =O6*(1+O11)^0 -> 2450 | ... W75: =W6*(1+W11)^0 -> 2450
A76: EBIT lõi | B76: =B40*B7+(B48-B9)*B75-B42*(1+B35)^0 -> 146.41915 | C76: =C40*C7+(C48-C9)*C75-C42*(1+C35)^0 -> 214.78496 | D76: =D40*D7+(D48-D9)*D75-D42*(1+D35)^0 -> 284.15078 | H76: =H40*H7+(H48-H9)*H75-H42*(1+H35)^0 -> 214.78496 | I76: =I40*I7+(I48-I9)*I75-I42*(1+I35)^0 -> 214.78496 | J76: =J40*J7+(J48-J9)*J75-J42*(1+J35)^0 -> 214.78496 | K76: =K40*K7+(K48-K9)*K75-K42*(1+K35)^0 -> 214.78496 | L76: =L40*L7+(L48-L9)*L75-L42*(1+L35)^0 -> 214.78496 | M76: =M40*M7+(M48-M9)*M75-M42*(1+M35)^0 -> 214.78496 | N76: =N40*N7+(N48-N9)*N75-N42*(1+N35)^0 -> 214.78496 | O76: =O40*O7+(O48-O9)*O75-O42*(1+O35)^0 -> 214.78496 | ... W76: =W40*W7+(W48-W9)*W75-W42*(1+W35)^0 -> 216.72582
A77: lợi nhuận lõi sau thuế | B77: =B76*(1-B10) -> 130.31304 | C77: =C76*(1-C10) -> 195.45432 | D77: =D76*(1-D10) -> 261.41871 | H77: =H76*(1-H10) -> 195.45432 | I77: =I76*(1-I10) -> 195.45432 | J77: =J76*(1-J10) -> 195.45432 | K77: =K76*(1-K10) -> 195.45432 | L77: =L76*(1-L10) -> 195.45432 | M77: =M76*(1-M10) -> 195.45432 | N77: =N76*(1-N10) -> 195.45432 | O77: =O76*(1-O10) -> 195.45432 | ... W77: =W76*(1-W10) -> 197.22049
A78: tái đầu tư lõi = tăng trưởng B × vốn hoạt động | B78: =B11*B56*(1+B11)^0 -> 0 | C78: =C11*C56*(1+C11)^0 -> 13.89705 | D78: =D11*D56*(1+D11)^0 -> 23.16175 | H78: =H11*H56*(1+H11)^0 -> 13.89705 | I78: =I11*I56*(1+I11)^0 -> 13.89705 | J78: =J11*J56*(1+J11)^0 -> 13.89705 | K78: =K11*K56*(1+K11)^0 -> 13.89705 | L78: =L11*L56*(1+L11)^0 -> 13.89705 | M78: =M11*M56*(1+M11)^0 -> 13.89705 | N78: =N11*N56*(1+N11)^0 -> 13.89705 | O78: =O11*O56*(1+O11)^0 -> 13.89705 | ... W78: =W11*W56*(1+W11)^0 -> 13.89705
A79: dòng tiền tự do phần lõi = lõi × (1 − quỹ) − tái đầu tư | B79: =B77*(1-B36)-B78 -> 117.28174 | C79: =C77*(1-C36)-C78 -> 162.01183 | D79: =D77*(1-D36)-D78 -> 212.11509 | H79: =H77*(1-H36)-H78 -> 162.01183 | I79: =I77*(1-I36)-I78 -> 162.01183 | J79: =J77*(1-J36)-J78 -> 162.01183 | K79: =K77*(1-K36)-K78 -> 162.01183 | L79: =L77*(1-L36)-L78 -> 162.01183 | M79: =M77*(1-M36)-M78 -> 162.01183 | N79: =N77*(1-N36)-N78 -> 162.01183 | O79: =O77*(1-O36)-O78 -> 162.01183 | ... W79: =W77*(1-W36)-W78 -> 163.60139
A80: hiện giá dòng tiền phần lõi ở r | B80: =B79/(1+B44)^1 -> 105.44643 | C80: =C79/(1+C44)^1 -> 145.66266 | D80: =D79/(1+D44)^1 -> 190.70982 | H80: =H79/(1+H44)^1 -> 145.66266 | I80: =I79/(1+I44)^1 -> 145.66266 | J80: =J79/(1+J44)^1 -> 145.66266 | K80: =K79/(1+K44)^1 -> 145.66266 | L80: =L79/(1+L44)^1 -> 145.66266 | M80: =M79/(1+M44)^1 -> 144.9122 | N80: =N79/(1+N44)^1 -> 144.113 | O80: =O79/(1+O44)^1 -> 145.66266 | ... W80: =W79/(1+W44)^1 -> 147.09181
A81: chi trang trại | B81: =B61 -> 780.679 | C81: =C61 -> 704.679 | D81: =D61 -> 704.679 | H81: =H61 -> 704.679 | I81: =I61 -> 704.679 | J81: =J61 -> 704.679 | K81: =K61 -> 704.679 | L81: =L61 -> 704.679 | M81: =M61 -> 704.679 | N81: =N61 -> 704.679 | O81: =O61 -> 704.679 | ... W81: =W61 -> 704.679
A82: chi nhà máy (50% hai năm trước năm có lãi; có lãi 2028 thì dồn vào 2027) | B82: =B69*(IF(B29-2027=1,0.5,0)+IF(B29-2027=2,0.5,0)+IF(AND(B29=2028,2027=2027),0.5,0)) -> 0 | C82: =C69*(IF(C29-2027=1,0.5,0)+IF(C29-2027=2,0.5,0)+IF(AND(C29=2028,2027=2027),0.5,0)) -> 0 | D82: =D69*(IF(D29-2027=1,0.5,0)+IF(D29-2027=2,0.5,0)+IF(AND(D29=2028,2027=2027),0.5,0)) -> 711.923 | H82: =H69*(IF(H29-2027=1,0.5,0)+IF(H29-2027=2,0.5,0)+IF(AND(H29=2028,2027=2027),0.5,0)) -> 0 | I82: =I69*(IF(I29-2027=1,0.5,0)+IF(I29-2027=2,0.5,0)+IF(AND(I29=2028,2027=2027),0.5,0)) -> 0 | J82: =J69*(IF(J29-2027=1,0.5,0)+IF(J29-2027=2,0.5,0)+IF(AND(J29=2028,2027=2027),0.5,0)) -> 711.923 | K82: =K69*(IF(K29-2027=1,0.5,0)+IF(K29-2027=2,0.5,0)+IF(AND(K29=2028,2027=2027),0.5,0)) -> 0 | L82: =L69*(IF(L29-2027=1,0.5,0)+IF(L29-2027=2,0.5,0)+IF(AND(L29=2028,2027=2027),0.5,0)) -> 0 | M82: =M69*(IF(M29-2027=1,0.5,0)+IF(M29-2027=2,0.5,0)+IF(AND(M29=2028,2027=2027),0.5,0)) -> 0 | N82: =N69*(IF(N29-2027=1,0.5,0)+IF(N29-2027=2,0.5,0)+IF(AND(N29=2028,2027=2027),0.5,0)) -> 0 | O82: =O69*(IF(O29-2027=1,0.5,0)+IF(O29-2027=2,0.5,0)+IF(AND(O29=2028,2027=2027),0.5,0)) -> 0 | ... W82: =W69*(IF(W29-2027=1,0.5,0)+IF(W29-2027=2,0.5,0)+IF(AND(W29=2028,2027=2027),0.5,0)) -> 0
A83: chi hai dự án | B83: =B81+B82 -> 780.679 | C83: =C81+C82 -> 704.679 | D83: =D81+D82 -> 1416.602 | H83: =H81+H82 -> 704.679 | I83: =I81+I82 -> 704.679 | J83: =J81+J82 -> 1416.602 | K83: =K81+K82 -> 704.679 | L83: =L81+L82 -> 704.679 | M83: =M81+M82 -> 704.679 | N83: =N81+N82 -> 704.679 | O83: =O81+O82 -> 704.679 | ... W83: =W81+W82 -> 704.679
A84: lãi kế toán trang trại + du lịch | B84: =B65*B20 -> -1.29 | C84: =C65*C20 -> 27.65 | D84: =D65*D20 -> 72.84 | H84: =H65*H20 -> 27.65 | I84: =I65*I20 -> 27.65 | J84: =J65*J20 -> 27.65 | K84: =K65*K20 -> 11.9 | L84: =L65*L20 -> 17.65 | M84: =M65*M20 -> 27.65 | N84: =N65*N20 -> 27.65 | O84: =O65*O20 -> 27.65 | ... W84: =W65*W20 -> 27.65
A85: lãi tăng thêm nhà máy | B85: =B27*B30*IF(2027>=B29,1,0) -> 0 | C85: =C27*C30*IF(2027>=C29,1,0) -> 0 | D85: =D27*D30*IF(2027>=D29,1,0) -> 0 | H85: =H27*H30*IF(2027>=H29,1,0) -> 0 | I85: =I27*I30*IF(2027>=I29,1,0) -> 0 | J85: =J27*J30*IF(2027>=J29,1,0) -> 0 | K85: =K27*K30*IF(2027>=K29,1,0) -> 0 | L85: =L27*L30*IF(2027>=L29,1,0) -> 0 | M85: =M27*M30*IF(2027>=M29,1,0) -> 0 | N85: =N27*N30*IF(2027>=N29,1,0) -> 0 | O85: =O27*O30*IF(2027>=O29,1,0) -> 0 | ... W85: =W27*W30*IF(2027>=W29,1,0) -> 0
A86: lãi kế toán hai dự án | B86: =B84+B85 -> -1.29 | C86: =C84+C85 -> 27.65 | D86: =D84+D85 -> 72.84 | H86: =H84+H85 -> 27.65 | I86: =I84+I85 -> 27.65 | J86: =J84+J85 -> 27.65 | K86: =K84+K85 -> 11.9 | L86: =L84+L85 -> 17.65 | M86: =M84+M85 -> 27.65 | N86: =N84+N85 -> 27.65 | O86: =O84+O85 -> 27.65 | ... W86: =W84+W85 -> 27.65
A87: dòng tiền trang trại + du lịch = tiền thu − quỹ × lãi − chi | B87: =B66*B20-B36*B84-B81 -> -773.44 | C87: =C66*C20-C36*C84-C81 -> -667.694 | D87: =D66*D20-D36*D84-D81 -> -624.603 | H87: =H66*H20-H36*H84-H81 -> -667.694 | I87: =I66*I20-I36*I84-I81 -> -667.694 | J87: =J66*J20-J36*J84-J81 -> -667.694 | K87: =K66*K20-K36*K84-K81 -> -681.869 | L87: =L66*L20-L36*L84-L81 -> -676.694 | M87: =M66*M20-M36*M84-M81 -> -667.694 | N87: =N66*N20-N36*N84-N81 -> -667.694 | O87: =O66*O20-O36*O84-O81 -> -667.694 | ... W87: =W66*W20-W36*W84-W81 -> -667.694
A88: dòng tiền nhà máy = lãi × (1 − quỹ) − chi | B88: =B85*(1-B36)-B82 -> 0 | C88: =C85*(1-C36)-C82 -> 0 | D88: =D85*(1-D36)-D82 -> -711.923 | H88: =H85*(1-H36)-H82 -> 0 | I88: =I85*(1-I36)-I82 -> 0 | J88: =J85*(1-J36)-J82 -> -711.923 | K88: =K85*(1-K36)-K82 -> 0 | L88: =L85*(1-L36)-L82 -> 0 | M88: =M85*(1-M36)-M82 -> 0 | N88: =N85*(1-N36)-N82 -> 0 | O88: =O85*(1-O36)-O82 -> 0 | ... W88: =W85*(1-W36)-W82 -> 0
A89: hiện giá dòng tiền trang trại ở lợi suất dự án | B89: =B87/(1+B45)^1 -> -687.99146 | C89: =C87/(1+C45)^1 -> -593.92813 | D89: =D87/(1+D45)^1 -> -555.59776 | H89: =H87/(1+H45)^1 -> -593.92813 | I89: =I87/(1+I45)^1 -> -593.92813 | J89: =J87/(1+J45)^1 -> -593.92813 | K89: =K87/(1+K45)^1 -> -606.53709 | L89: =L87/(1+L45)^1 -> -601.93382 | M89: =M87/(1+M45)^1 -> -590.35721 | N89: =N87/(1+N45)^1 -> -593.92813 | O89: =O87/(1+O45)^1 -> -593.92813 | ... W89: =W87/(1+W45)^1 -> -593.92813
A90: hiện giá dòng tiền nhà máy ở lợi suất dự án | B90: =B88/(1+B45)^1 -> 0 | C90: =C88/(1+C45)^1 -> 0 | D90: =D88/(1+D45)^1 -> -633.27077 | H90: =H88/(1+H45)^1 -> 0 | I90: =I88/(1+I45)^1 -> 0 | J90: =J88/(1+J45)^1 -> -633.27077 | K90: =K88/(1+K45)^1 -> 0 | L90: =L88/(1+L45)^1 -> 0 | M90: =M88/(1+M45)^1 -> 0 | N90: =N88/(1+N45)^1 -> 0 | O90: =O88/(1+O45)^1 -> 0 | ... W90: =W88/(1+W45)^1 -> 0
A91: lãi tiền gửi (âm = lãi vay) trên số dư đầu năm | B91: =IF('01_Số liệu gốc'!$C$65>0,B16,B38)*'01_Số liệu gốc'!$C$65 -> 90.904905 | C91: =IF('01_Số liệu gốc'!$C$65>0,C16,C38)*'01_Số liệu gốc'!$C$65 -> 97.89759 | D91: =IF('01_Số liệu gốc'!$C$65>0,D16,D38)*'01_Số liệu gốc'!$C$65 -> 104.89028 | H91: =IF('01_Số liệu gốc'!$C$65>0,H16,H38)*'01_Số liệu gốc'!$C$65 -> 97.89759 | I91: =IF('01_Số liệu gốc'!$C$65>0,I16,I38)*'01_Số liệu gốc'!$C$65 -> 97.89759 | J91: =IF('01_Số liệu gốc'!$C$65>0,J16,J38)*'01_Số liệu gốc'!$C$65 -> 97.89759 | K91: =IF('01_Số liệu gốc'!$C$65>0,K16,K38)*'01_Số liệu gốc'!$C$65 -> 97.89759 | L91: =IF('01_Số liệu gốc'!$C$65>0,L16,L38)*'01_Số liệu gốc'!$C$65 -> 97.89759 | M91: =IF('01_Số liệu gốc'!$C$65>0,M16,M38)*'01_Số liệu gốc'!$C$65 -> 97.89759 | N91: =IF('01_Số liệu gốc'!$C$65>0,N16,N38)*'01_Số liệu gốc'!$C$65 -> 97.89759 | O91: =IF('01_Số liệu gốc'!$C$65>0,O16,O38)*'01_Số liệu gốc'!$C$65 -> 97.89759 | ... W91: =IF('01_Số liệu gốc'!$C$65>0,W16,W38)*'01_Số liệu gốc'!$C$65 -> 97.89759
A92: LNST = lõi + dự án + lãi × (1 − 20%) | B92: =B77+B86+B91*(1-B37) -> 201.74697 | C92: =C77+C86+C91*(1-C37) -> 301.42239 | D92: =D77+D86+D91*(1-D37) -> 418.17093 | H92: =H77+H86+H91*(1-H37) -> 301.42239 | I92: =I77+I86+I91*(1-I37) -> 301.42239 | J92: =J77+J86+J91*(1-J37) -> 301.42239 | K92: =K77+K86+K91*(1-K37) -> 285.67239 | L92: =L77+L86+L91*(1-L37) -> 291.42239 | M92: =M77+M86+M91*(1-M37) -> 301.42239 | N92: =N77+N86+N91*(1-N37) -> 301.42239 | O92: =O77+O86+O91*(1-O37) -> 301.42239 | ... W92: =W77+W86+W91*(1-W37) -> 303.18856
A93: cổ tức tiền mặt | B93: =B15*'01_Số liệu gốc'!$B$8/1000 -> 110 | C93: =C15*'01_Số liệu gốc'!$B$8/1000 -> 165 | D93: =D15*'01_Số liệu gốc'!$B$8/1000 -> 220 | H93: =H15*'01_Số liệu gốc'!$B$8/1000 -> 165 | I93: =I15*'01_Số liệu gốc'!$B$8/1000 -> 165 | J93: =J15*'01_Số liệu gốc'!$B$8/1000 -> 165 | K93: =K15*'01_Số liệu gốc'!$B$8/1000 -> 165 | L93: =L15*'01_Số liệu gốc'!$B$8/1000 -> 165 | M93: =M15*'01_Số liệu gốc'!$B$8/1000 -> 165 | N93: =N15*'01_Số liệu gốc'!$B$8/1000 -> 165 | O93: =O15*'01_Số liệu gốc'!$B$8/1000 -> 110 | ... W93: =W15*'01_Số liệu gốc'!$B$8/1000 -> 165
A94: cộng lại khấu hao trang trại − chi duy trì (không ra tiền) | B94: =(B64-B24)*B20 -> 8.4 | C94: =(C64-C24)*C20 -> 12.1 | D94: =(D64-D24)*D20 -> 14.52 | H94: =(H64-H24)*H20 -> 12.1 | I94: =(I64-I24)*I20 -> 12.1 | J94: =(J64-J24)*J20 -> 12.1 | K94: =(K64-K24)*K20 -> 12.1 | L94: =(L64-L24)*L20 -> 12.1 | M94: =(M64-M24)*M20 -> 12.1 | N94: =(N64-N24)*N20 -> 12.1 | O94: =(O64-O24)*O20 -> 12.1 | ... W94: =(W64-W24)*W20 -> 12.1
A95: TIỀN RÒNG CUỐI NĂM (âm = phải vay) | B95: ='01_Số liệu gốc'!$C$65+B92*(1-B36)-B93-B83-B78+B94 -> 697.83027 | C95: ='01_Số liệu gốc'!$C$65+C92*(1-C36)-C93-C83-C78+C94 -> 798.3411 | D95: ='01_Số liệu gốc'!$C$65+D92*(1-D36)-D93-D83-D78+D94 -> 129.64709 | H95: ='01_Số liệu gốc'!$C$65+H92*(1-H36)-H93-H83-H78+H94 -> 798.3411 | I95: ='01_Số liệu gốc'!$C$65+I92*(1-I36)-I93-I83-I78+I94 -> 798.3411 | J95: ='01_Số liệu gốc'!$C$65+J92*(1-J36)-J93-J83-J78+J94 -> 86.4181 | K95: ='01_Số liệu gốc'!$C$65+K92*(1-K36)-K93-K83-K78+K94 -> 784.1661 | L95: ='01_Số liệu gốc'!$C$65+L92*(1-L36)-L93-L83-L78+L94 -> 789.3411 | M95: ='01_Số liệu gốc'!$C$65+M92*(1-M36)-M93-M83-M78+M94 -> 798.3411 | N95: ='01_Số liệu gốc'!$C$65+N92*(1-N36)-N93-N83-N78+N94 -> 798.3411 | O95: ='01_Số liệu gốc'!$C$65+O92*(1-O36)-O93-O83-O78+O94 -> 853.3411 | ... W95: ='01_Số liệu gốc'!$C$65+W92*(1-W36)-W93-W83-W78+W94 -> 799.93066
A96: vốn chủ cuối năm | B96: ='01_Số liệu gốc'!$C$66+B92*(1-B36)-B93 -> 2392.6613 | C96: ='01_Số liệu gốc'!$C$66+C92*(1-C36)-C93 -> 2427.3691 | D96: ='01_Số liệu gốc'!$C$66+D92*(1-D36)-D93 -> 2477.4428 | H96: ='01_Số liệu gốc'!$C$66+H92*(1-H36)-H93 -> 2427.3691 | I96: ='01_Số liệu gốc'!$C$66+I92*(1-I36)-I93 -> 2427.3691 | J96: ='01_Số liệu gốc'!$C$66+J92*(1-J36)-J93 -> 2427.3691 | K96: ='01_Số liệu gốc'!$C$66+K92*(1-K36)-K93 -> 2413.1941 | L96: ='01_Số liệu gốc'!$C$66+L92*(1-L36)-L93 -> 2418.3691 | M96: ='01_Số liệu gốc'!$C$66+M92*(1-M36)-M93 -> 2427.3691 | N96: ='01_Số liệu gốc'!$C$66+N92*(1-N36)-N93 -> 2427.3691 | O96: ='01_Số liệu gốc'!$C$66+O92*(1-O36)-O93 -> 2482.3691 | ... W96: ='01_Số liệu gốc'!$C$66+W92*(1-W36)-W93 -> 2428.9587
A97: hiện giá cổ tức | B97: =B93/(1+B44)^1 -> 98.899518 | C97: =C93/(1+C44)^1 -> 148.34928 | D97: =D93/(1+D44)^1 -> 197.79904 | H97: =H93/(1+H44)^1 -> 148.34928 | I97: =I93/(1+I44)^1 -> 148.34928 | J97: =J93/(1+J44)^1 -> 148.34928 | K97: =K93/(1+K44)^1 -> 148.34928 | L97: =L93/(1+L44)^1 -> 148.34928 | M97: =M93/(1+M44)^1 -> 147.58497 | N97: =N93/(1+N44)^1 -> 146.77104 | O97: =O93/(1+O44)^1 -> 98.899518 | ... W97: =W93/(1+W44)^1 -> 148.34928
A98: Năm 2 — 2028
A99: B | B99: =B6*(1+B11)^1 -> 2200 | C99: =C6*(1+C11)^1 -> 2523.5 | D99: =D6*(1+D11)^1 -> 2835 | H99: =H6*(1+H11)^1 -> 2523.5 | I99: =I6*(1+I11)^1 -> 2523.5 | J99: =J6*(1+J11)^1 -> 2523.5 | K99: =K6*(1+K11)^1 -> 2523.5 | L99: =L6*(1+L11)^1 -> 2523.5 | M99: =M6*(1+M11)^1 -> 2523.5 | N99: =N6*(1+N11)^1 -> 2523.5 | O99: =O6*(1+O11)^1 -> 2523.5 | ... W99: =W6*(1+W11)^1 -> 2523.5
A100: EBIT lõi | B100: =B40*B7+(B48-B9)*B99-B42*(1+B35)^1 -> 145.24915 | C100: =C40*C7+(C48-C9)*C99-C42*(1+C35)^1 -> 219.30851 | D100: =D40*D7+(D48-D9)*D99-D42*(1+D35)^1 -> 296.13831 | H100: =H40*H7+(H48-H9)*H99-H42*(1+H35)^1 -> 219.30851 | I100: =I40*I7+(I48-I9)*I99-I42*(1+I35)^1 -> 219.30851 | J100: =J40*J7+(J48-J9)*J99-J42*(1+J35)^1 -> 219.30851 | K100: =K40*K7+(K48-K9)*K99-K42*(1+K35)^1 -> 219.30851 | L100: =L40*L7+(L48-L9)*L99-L42*(1+L35)^1 -> 219.30851 | M100: =M40*M7+(M48-M9)*M99-M42*(1+M35)^1 -> 219.30851 | N100: =N40*N7+(N48-N9)*N99-N42*(1+N35)^1 -> 219.30851 | O100: =O40*O7+(O48-O9)*O99-O42*(1+O35)^1 -> 219.30851 | ... W100: =W40*W7+(W48-W9)*W99-W42*(1+W35)^1 -> 222.26759
A101: lợi nhuận lõi sau thuế | B101: =B100*(1-B10) -> 129.27174 | C101: =C100*(1-C10) -> 199.57075 | D101: =D100*(1-D10) -> 272.44725 | H101: =H100*(1-H10) -> 199.57075 | I101: =I100*(1-I10) -> 199.57075 | J101: =J100*(1-J10) -> 199.57075 | K101: =K100*(1-K10) -> 199.57075 | L101: =L100*(1-L10) -> 199.57075 | M101: =M100*(1-M10) -> 199.57075 | N101: =N100*(1-N10) -> 199.57075 | O101: =O100*(1-O10) -> 199.57075 | ... W101: =W100*(1-W10) -> 202.26351
A102: tái đầu tư lõi = tăng trưởng B × vốn hoạt động | B102: =B11*B56*(1+B11)^1 -> 0 | C102: =C11*C56*(1+C11)^1 -> 14.313961 | D102: =D11*D56*(1+D11)^1 -> 24.319837 | H102: =H11*H56*(1+H11)^1 -> 14.313961 | I102: =I11*I56*(1+I11)^1 -> 14.313961 | J102: =J11*J56*(1+J11)^1 -> 14.313961 | K102: =K11*K56*(1+K11)^1 -> 14.313961 | L102: =L11*L56*(1+L11)^1 -> 14.313961 | M102: =M11*M56*(1+M11)^1 -> 14.313961 | N102: =N11*N56*(1+N11)^1 -> 14.313961 | O102: =O11*O56*(1+O11)^1 -> 14.313961 | ... W102: =W11*W56*(1+W11)^1 -> 14.313961
A103: dòng tiền tự do phần lõi = lõi × (1 − quỹ) − tái đầu tư | B103: =B101*(1-B36)-B102 -> 116.34457 | C103: =C101*(1-C36)-C102 -> 165.29971 | D103: =D101*(1-D36)-D102 -> 220.88269 | H103: =H101*(1-H36)-H102 -> 165.29971 | I103: =I101*(1-I36)-I102 -> 165.29971 | J103: =J101*(1-J36)-J102 -> 165.29971 | K103: =K101*(1-K36)-K102 -> 165.29971 | L103: =L101*(1-L36)-L102 -> 165.29971 | M103: =M101*(1-M36)-M102 -> 165.29971 | N103: =N101*(1-N36)-N102 -> 165.29971 | O103: =O101*(1-O36)-O102 -> 165.29971 | ... W103: =W101*(1-W36)-W102 -> 167.72319
...

Sheet 04_Độ nhạy
A1: MCM — ĐỘ NHẠY (đồng/cổ phiếu)
A2: Quanh kịch bản CƠ SỞ. Ô nền vàng = cơ sở; nền cam = thấp hơn giá hiện tại (bảng 2: âm). Bảng 1–3 là công thức dạng đóng của riêng một phương pháp; bảng 4 đọc từ các cột phép thử ở 03 — mỗi dòng là một bản tính lại đầy đủ cả năm phương pháp.
A4: BẢNG 1 — RIÊNG PHƯƠNG PHÁP 1: B, doanh thu phần còn lại (hàng, tỷ) × CHI PHÍ BÁN HÀNG ÷ B (cột) — tiền × (1 − k) như phương pháp 1
A5: hàng \ cột | B5: ='03_Định giá'!$C$9-0.02 -> 0.25 | C5: ='03_Định giá'!$C$9-0.01 -> 0.26 | D5: ='03_Định giá'!$C$9+0 -> 0.27 | E5: ='03_Định giá'!$C$9+0.01 -> 0.28 | F5: ='03_Định giá'!$C$9+0.02 -> 0.29
A6: ='03_Định giá'!$C$6-300 -> 2150 | B6: =MAX(0,(('03_Định giá'!$C$40*'03_Định giá'!$C$7+('03_Định giá'!$C$48-(B$5))*($A6)-'03_Định giá'!$C$42)*(1-'03_Định giá'!$C$10)*(1-'03_Định giá'!$C$36)*'03_Định giá'!$C$12+'03_Định giá'!$C$209*(1-'02_Giả định'!$B$26)+'03_Định giá'!$C$202)*1000/'01_Số liệu gốc'!$B$8) -> 26959.487 | C6: =MAX(0,(('03_Định giá'!$C$40*'03_Định giá'!$C$7+('03_Định giá'!$C$48-(C$5))*($A6)-'03_Định giá'!$C$42)*(1-'03_Định giá'!$C$10)*(1-'03_Định giá'!$C$36)*'03_Định giá'!$C$12+'03_Định giá'!$C$209*(1-'02_Giả định'!$B$26)+'03_Định giá'!$C$202)*1000/'01_Số liệu gốc'!$B$8) -> 25230.652 | D6: =MAX(0,(('03_Định giá'!$C$40*'03_Định giá'!$C$7+('03_Định giá'!$C$48-(D$5))*($A6)-'03_Định giá'!$C$42)*(1-'03_Định giá'!$C$10)*(1-'03_Định giá'!$C$36)*'03_Định giá'!$C$12+'03_Định giá'!$C$209*(1-'02_Giả định'!$B$26)+'03_Định giá'!$C$202)*1000/'01_Số liệu gốc'!$B$8) -> 23501.817 | E6: =MAX(0,(('03_Định giá'!$C$40*'03_Định giá'!$C$7+('03_Định giá'!$C$48-(E$5))*($A6)-'03_Định giá'!$C$42)*(1-'03_Định giá'!$C$10)*(1-'03_Định giá'!$C$36)*'03_Định giá'!$C$12+'03_Định giá'!$C$209*(1-'02_Giả định'!$B$26)+'03_Định giá'!$C$202)*1000/'01_Số liệu gốc'!$B$8) -> 21772.983 | F6: =MAX(0,(('03_Định giá'!$C$40*'03_Định giá'!$C$7+('03_Định giá'!$C$48-(F$5))*($A6)-'03_Định giá'!$C$42)*(1-'03_Định giá'!$C$10)*(1-'03_Định giá'!$C$36)*'03_Định giá'!$C$12+'03_Định giá'!$C$209*(1-'02_Giả định'!$B$26)+'03_Định giá'!$C$202)*1000/'01_Số liệu gốc'!$B$8) -> 20044.148
A7: ='03_Định giá'!$C$6-150 -> 2300 | B7: =MAX(0,(('03_Định giá'!$C$40*'03_Định giá'!$C$7+('03_Định giá'!$C$48-(B$5))*($A7)-'03_Định giá'!$C$42)*(1-'03_Định giá'!$C$10)*(1-'03_Định giá'!$C$36)*'03_Định giá'!$C$12+'03_Định giá'!$C$209*(1-'02_Giả định'!$B$26)+'03_Định giá'!$C$202)*1000/'01_Số liệu gốc'!$B$8) -> 28135.053 | C7: =MAX(0,(('03_Định giá'!$C$40*'03_Định giá'!$C$7+('03_Định giá'!$C$48-(C$5))*($A7)-'03_Định giá'!$C$42)*(1-'03_Định giá'!$C$10)*(1-'03_Định giá'!$C$36)*'03_Định giá'!$C$12+'03_Định giá'!$C$209*(1-'02_Giả định'!$B$26)+'03_Định giá'!$C$202)*1000/'01_Số liệu gốc'!$B$8) -> 26285.602 | D7: =MAX(0,(('03_Định giá'!$C$40*'03_Định giá'!$C$7+('03_Định giá'!$C$48-(D$5))*($A7)-'03_Định giá'!$C$42)*(1-'03_Định giá'!$C$10)*(1-'03_Định giá'!$C$36)*'03_Định giá'!$C$12+'03_Định giá'!$C$209*(1-'02_Giả định'!$B$26)+'03_Định giá'!$C$202)*1000/'01_Số liệu gốc'!$B$8) -> 24436.151 | E7: =MAX(0,(('03_Định giá'!$C$40*'03_Định giá'!$C$7+('03_Định giá'!$C$48-(E$5))*($A7)-'03_Định giá'!$C$42)*(1-'03_Định giá'!$C$10)*(1-'03_Định giá'!$C$36)*'03_Định giá'!$C$12+'03_Định giá'!$C$209*(1-'02_Giả định'!$B$26)+'03_Định giá'!$C$202)*1000/'01_Số liệu gốc'!$B$8) -> 22586.7 | F7: =MAX(0,(('03_Định giá'!$C$40*'03_Định giá'!$C$7+('03_Định giá'!$C$48-(F$5))*($A7)-'03_Định giá'!$C$42)*(1-'03_Định giá'!$C$10)*(1-'03_Định giá'!$C$36)*'03_Định giá'!$C$12+'03_Định giá'!$C$209*(1-'02_Giả định'!$B$26)+'03_Định giá'!$C$202)*1000/'01_Số liệu gốc'!$B$8) -> 20737.249
A8: ='03_Định giá'!$C$6+0 -> 2450 | B8: =MAX(0,(('03_Định giá'!$C$40*'03_Định giá'!$C$7+('03_Định giá'!$C$48-(B$5))*($A8)-'03_Định giá'!$C$42)*(1-'03_Định giá'!$C$10)*(1-'03_Định giá'!$C$36)*'03_Định giá'!$C$12+'03_Định giá'!$C$209*(1-'02_Giả định'!$B$26)+'03_Định giá'!$C$202)*1000/'01_Số liệu gốc'!$B$8) -> 29310.619 | C8: =MAX(0,(('03_Định giá'!$C$40*'03_Định giá'!$C$7+('03_Định giá'!$C$48-(C$5))*($A8)-'03_Định giá'!$C$42)*(1-'03_Định giá'!$C$10)*(1-'03_Định giá'!$C$36)*'03_Định giá'!$C$12+'03_Định giá'!$C$209*(1-'02_Giả định'!$B$26)+'03_Định giá'!$C$202)*1000/'01_Số liệu gốc'!$B$8) -> 27340.552 | D8: =MAX(0,(('03_Định giá'!$C$40*'03_Định giá'!$C$7+('03_Định giá'!$C$48-(D$5))*($A8)-'03_Định giá'!$C$42)*(1-'03_Định giá'!$C$10)*(1-'03_Định giá'!$C$36)*'03_Định giá'!$C$12+'03_Định giá'!$C$209*(1-'02_Giả định'!$B$26)+'03_Định giá'!$C$202)*1000/'01_Số liệu gốc'!$B$8) -> 25370.485 | E8: =MAX(0,(('03_Định giá'!$C$40*'03_Định giá'!$C$7+('03_Định giá'!$C$48-(E$5))*($A8)-'03_Định giá'!$C$42)*(1-'03_Định giá'!$C$10)*(1-'03_Định giá'!$C$36)*'03_Định giá'!$C$12+'03_Định giá'!$C$209*(1-'02_Giả định'!$B$26)+'03_Định giá'!$C$202)*1000/'01_Số liệu gốc'!$B$8) -> 23400.417 | F8: =MAX(0,(('03_Định giá'!$C$40*'03_Định giá'!$C$7+('03_Định giá'!$C$48-(F$5))*($A8)-'03_Định giá'!$C$42)*(1-'03_Định giá'!$C$10)*(1-'03_Định giá'!$C$36)*'03_Định giá'!$C$12+'03_Định giá'!$C$209*(1-'02_Giả định'!$B$26)+'03_Định giá'!$C$202)*1000/'01_Số liệu gốc'!$B$8) -> 21430.35
A9: ='03_Định giá'!$C$6+150 -> 2600 | B9: =MAX(0,(('03_Định giá'!$C$40*'03_Định giá'!$C$7+('03_Định giá'!$C$48-(B$5))*($A9)-'03_Định giá'!$C$42)*(1-'03_Định giá'!$C$10)*(1-'03_Định giá'!$C$36)*'03_Định giá'!$C$12+'03_Định giá'!$C$209*(1-'02_Giả định'!$B$26)+'03_Định giá'!$C$202)*1000/'01_Số liệu gốc'!$B$8) -> 30486.185 | C9: =MAX(0,(('03_Định giá'!$C$40*'03_Định giá'!$C$7+('03_Định giá'!$C$48-(C$5))*($A9)-'03_Định giá'!$C$42)*(1-'03_Định giá'!$C$10)*(1-'03_Định giá'!$C$36)*'03_Định giá'!$C$12+'03_Định giá'!$C$209*(1-'02_Giả định'!$B$26)+'03_Định giá'!$C$202)*1000/'01_Số liệu gốc'!$B$8) -> 28395.502 | D9: =MAX(0,(('03_Định giá'!$C$40*'03_Định giá'!$C$7+('03_Định giá'!$C$48-(D$5))*($A9)-'03_Định giá'!$C$42)*(1-'03_Định giá'!$C$10)*(1-'03_Định giá'!$C$36)*'03_Định giá'!$C$12+'03_Định giá'!$C$209*(1-'02_Giả định'!$B$26)+'03_Định giá'!$C$202)*1000/'01_Số liệu gốc'!$B$8) -> 26304.818 | E9: =MAX(0,(('03_Định giá'!$C$40*'03_Định giá'!$C$7+('03_Định giá'!$C$48-(E$5))*($A9)-'03_Định giá'!$C$42)*(1-'03_Định giá'!$C$10)*(1-'03_Định giá'!$C$36)*'03_Định giá'!$C$12+'03_Định giá'!$C$209*(1-'02_Giả định'!$B$26)+'03_Định giá'!$C$202)*1000/'01_Số liệu gốc'!$B$8) -> 24214.134 | F9: =MAX(0,(('03_Định giá'!$C$40*'03_Định giá'!$C$7+('03_Định giá'!$C$48-(F$5))*($A9)-'03_Định giá'!$C$42)*(1-'03_Định giá'!$C$10)*(1-'03_Định giá'!$C$36)*'03_Định giá'!$C$12+'03_Định giá'!$C$209*(1-'02_Giả định'!$B$26)+'03_Định giá'!$C$202)*1000/'01_Số liệu gốc'!$B$8) -> 22123.451
A10: ='03_Định giá'!$C$6+300 -> 2750 | B10: =MAX(0,(('03_Định giá'!$C$40*'03_Định giá'!$C$7+('03_Định giá'!$C$48-(B$5))*($A10)-'03_Định giá'!$C$42)*(1-'03_Định giá'!$C$10)*(1-'03_Định giá'!$C$36)*'03_Định giá'!$C$12+'03_Định giá'!$C$209*(1-'02_Giả định'!$B$26)+'03_Định giá'!$C$202)*1000/'01_Số liệu gốc'!$B$8) -> 31661.752 | C10: =MAX(0,(('03_Định giá'!$C$40*'03_Định giá'!$C$7+('03_Định giá'!$C$48-(C$5))*($A10)-'03_Định giá'!$C$42)*(1-'03_Định giá'!$C$10)*(1-'03_Định giá'!$C$36)*'03_Định giá'!$C$12+'03_Định giá'!$C$209*(1-'02_Giả định'!$B$26)+'03_Định giá'!$C$202)*1000/'01_Số liệu gốc'!$B$8) -> 29450.452 | D10: =MAX(0,(('03_Định giá'!$C$40*'03_Định giá'!$C$7+('03_Định giá'!$C$48-(D$5))*($A10)-'03_Định giá'!$C$42)*(1-'03_Định giá'!$C$10)*(1-'03_Định giá'!$C$36)*'03_Định giá'!$C$12+'03_Định giá'!$C$209*(1-'02_Giả định'!$B$26)+'03_Định giá'!$C$202)*1000/'01_Số liệu gốc'!$B$8) -> 27239.152 | E10: =MAX(0,(('03_Định giá'!$C$40*'03_Định giá'!$C$7+('03_Định giá'!$C$48-(E$5))*($A10)-'03_Định giá'!$C$42)*(1-'03_Định giá'!$C$10)*(1-'03_Định giá'!$C$36)*'03_Định giá'!$C$12+'03_Định giá'!$C$209*(1-'02_Giả định'!$B$26)+'03_Định giá'!$C$202)*1000/'01_Số liệu gốc'!$B$8) -> 25027.852 | F10: =MAX(0,(('03_Định giá'!$C$40*'03_Định giá'!$C$7+('03_Định giá'!$C$48-(F$5))*($A10)-'03_Định giá'!$C$42)*(1-'03_Định giá'!$C$10)*(1-'03_Định giá'!$C$36)*'03_Định giá'!$C$12+'03_Định giá'!$C$209*(1-'02_Giả định'!$B$26)+'03_Định giá'!$C$202)*1000/'01_Số liệu gốc'!$B$8) -> 22816.552
A11: Mỗi 1 điểm % chi phí bán hàng trên ~2.450 tỷ doanh thu = ~24,5 tỷ EBIT — gần bằng 150 tỷ doanh thu. Khuyến mãi quyết định lợi nhuận nhiều như doanh thu.
A13: BẢNG 2 — GIÁ TRỊ RÒNG HAI DỰ ÁN (đồng/cp): GIÁ BÁN SỮA TRANG TRẠI (hàng, đ/lít) × CHI PHÍ TIỀN MẶT MỖI LÍT (cột)
A14: hàng \ cột | B14: ='03_Định giá'!$C$22-1000 -> 9500 | C14: ='03_Định giá'!$C$22-500 -> 10000 | D14: ='03_Định giá'!$C$22+0 -> 10500 | E14: ='03_Định giá'!$C$22+500 -> 11000 | F14: ='03_Định giá'!$C$22+1000 -> 11500
A15: ='03_Định giá'!$C$21-2000 -> 12500 | B15: =('03_Định giá'!$C$202+'03_Định giá'!$C$19*((($A15)-'03_Định giá'!$C$21)*(1+'03_Định giá'!$C$23)-((B$14)-'03_Định giá'!$C$22))/1000*'03_Định giá'!$C$204)*1000/'01_Số liệu gốc'!$B$8 -> -4634.7278 | C15: =('03_Định giá'!$C$202+'03_Định giá'!$C$19*((($A15)-'03_Định giá'!$C$21)*(1+'03_Định giá'!$C$23)-((C$14)-'03_Định giá'!$C$22))/1000*'03_Định giá'!$C$204)*1000/'01_Số liệu gốc'!$B$8 -> -5221.8108 | D15: =('03_Định giá'!$C$202+'03_Định giá'!$C$19*((($A15)-'03_Định giá'!$C$21)*(1+'03_Định giá'!$C$23)-((D$14)-'03_Định giá'!$C$22))/1000*'03_Định giá'!$C$204)*1000/'01_Số liệu gốc'!$B$8 -> -5808.8939 | E15: =('03_Định giá'!$C$202+'03_Định giá'!$C$19*((($A15)-'03_Định giá'!$C$21)*(1+'03_Định giá'!$C$23)-((E$14)-'03_Định giá'!$C$22))/1000*'03_Định giá'!$C$204)*1000/'01_Số liệu gốc'!$B$8 -> -6395.977 | F15: =('03_Định giá'!$C$202+'03_Định giá'!$C$19*((($A15)-'03_Định giá'!$C$21)*(1+'03_Định giá'!$C$23)-((F$14)-'03_Định giá'!$C$22))/1000*'03_Định giá'!$C$204)*1000/'01_Số liệu gốc'!$B$8 -> -6983.06
A16: ='03_Định giá'!$C$21-1000 -> 13500 | B16: =('03_Định giá'!$C$202+'03_Định giá'!$C$19*((($A16)-'03_Định giá'!$C$21)*(1+'03_Định giá'!$C$23)-((B$14)-'03_Định giá'!$C$22))/1000*'03_Định giá'!$C$204)*1000/'01_Số liệu gốc'!$B$8 -> -3401.8533 | C16: =('03_Định giá'!$C$202+'03_Định giá'!$C$19*((($A16)-'03_Định giá'!$C$21)*(1+'03_Định giá'!$C$23)-((C$14)-'03_Định giá'!$C$22))/1000*'03_Định giá'!$C$204)*1000/'01_Số liệu gốc'!$B$8 -> -3988.9364 | D16: =('03_Định giá'!$C$202+'03_Định giá'!$C$19*((($A16)-'03_Định giá'!$C$21)*(1+'03_Định giá'!$C$23)-((D$14)-'03_Định giá'!$C$22))/1000*'03_Định giá'!$C$204)*1000/'01_Số liệu gốc'!$B$8 -> -4576.0195 | E16: =('03_Định giá'!$C$202+'03_Định giá'!$C$19*((($A16)-'03_Định giá'!$C$21)*(1+'03_Định giá'!$C$23)-((E$14)-'03_Định giá'!$C$22))/1000*'03_Định giá'!$C$204)*1000/'01_Số liệu gốc'!$B$8 -> -5163.1025 | F16: =('03_Định giá'!$C$202+'03_Định giá'!$C$19*((($A16)-'03_Định giá'!$C$21)*(1+'03_Định giá'!$C$23)-((F$14)-'03_Định giá'!$C$22))/1000*'03_Định giá'!$C$204)*1000/'01_Số liệu gốc'!$B$8 -> -5750.1856
A17: ='03_Định giá'!$C$21+0 -> 14500 | B17: =('03_Định giá'!$C$202+'03_Định giá'!$C$19*((($A17)-'03_Định giá'!$C$21)*(1+'03_Định giá'!$C$23)-((B$14)-'03_Định giá'!$C$22))/1000*'03_Định giá'!$C$204)*1000/'01_Số liệu gốc'!$B$8 -> -2168.9789 | C17: =('03_Định giá'!$C$202+'03_Định giá'!$C$19*((($A17)-'03_Định giá'!$C$21)*(1+'03_Định giá'!$C$23)-((C$14)-'03_Định giá'!$C$22))/1000*'03_Định giá'!$C$204)*1000/'01_Số liệu gốc'!$B$8 -> -2756.062 | D17: =('03_Định giá'!$C$202+'03_Định giá'!$C$19*((($A17)-'03_Định giá'!$C$21)*(1+'03_Định giá'!$C$23)-((D$14)-'03_Định giá'!$C$22))/1000*'03_Định giá'!$C$204)*1000/'01_Số liệu gốc'!$B$8 -> -3343.145 | E17: =('03_Định giá'!$C$202+'03_Định giá'!$C$19*((($A17)-'03_Định giá'!$C$21)*(1+'03_Định giá'!$C$23)-((E$14)-'03_Định giá'!$C$22))/1000*'03_Định giá'!$C$204)*1000/'01_Số liệu gốc'!$B$8 -> -3930.2281 | F17: =('03_Định giá'!$C$202+'03_Định giá'!$C$19*((($A17)-'03_Định giá'!$C$21)*(1+'03_Định giá'!$C$23)-((F$14)-'03_Định giá'!$C$22))/1000*'03_Định giá'!$C$204)*1000/'01_Số liệu gốc'!$B$8 -> -4517.3112
A18: ='03_Định giá'!$C$21+1000 -> 15500 | B18: =('03_Định giá'!$C$202+'03_Định giá'!$C$19*((($A18)-'03_Định giá'!$C$21)*(1+'03_Định giá'!$C$23)-((B$14)-'03_Định giá'!$C$22))/1000*'03_Định giá'!$C$204)*1000/'01_Số liệu gốc'!$B$8 -> -936.10445 | C18: =('03_Định giá'!$C$202+'03_Định giá'!$C$19*((($A18)-'03_Định giá'!$C$21)*(1+'03_Định giá'!$C$23)-((C$14)-'03_Định giá'!$C$22))/1000*'03_Định giá'!$C$204)*1000/'01_Số liệu gốc'!$B$8 -> -1523.1875 | D18: =('03_Định giá'!$C$202+'03_Định giá'!$C$19*((($A18)-'03_Định giá'!$C$21)*(1+'03_Định giá'!$C$23)-((D$14)-'03_Định giá'!$C$22))/1000*'03_Định giá'!$C$204)*1000/'01_Số liệu gốc'!$B$8 -> -2110.2706 | E18: =('03_Định giá'!$C$202+'03_Định giá'!$C$19*((($A18)-'03_Định giá'!$C$21)*(1+'03_Định giá'!$C$23)-((E$14)-'03_Định giá'!$C$22))/1000*'03_Định giá'!$C$204)*1000/'01_Số liệu gốc'!$B$8 -> -2697.3537 | F18: =('03_Định giá'!$C$202+'03_Định giá'!$C$19*((($A18)-'03_Định giá'!$C$21)*(1+'03_Định giá'!$C$23)-((F$14)-'03_Định giá'!$C$22))/1000*'03_Định giá'!$C$204)*1000/'01_Số liệu gốc'!$B$8 -> -3284.4367
A19: ='03_Định giá'!$C$21+2000 -> 16500 | B19: =('03_Định giá'!$C$202+'03_Định giá'!$C$19*((($A19)-'03_Định giá'!$C$21)*(1+'03_Định giá'!$C$23)-((B$14)-'03_Định giá'!$C$22))/1000*'03_Định giá'!$C$204)*1000/'01_Số liệu gốc'!$B$8 -> 296.76999 | C19: =('03_Định giá'!$C$202+'03_Định giá'!$C$19*((($A19)-'03_Định giá'!$C$21)*(1+'03_Định giá'!$C$23)-((C$14)-'03_Định giá'!$C$22))/1000*'03_Định giá'!$C$204)*1000/'01_Số liệu gốc'!$B$8 -> -290.31307 | D19: =('03_Định giá'!$C$202+'03_Định giá'!$C$19*((($A19)-'03_Định giá'!$C$21)*(1+'03_Định giá'!$C$23)-((D$14)-'03_Định giá'!$C$22))/1000*'03_Định giá'!$C$204)*1000/'01_Số liệu gốc'!$B$8 -> -877.39614 | E19: =('03_Định giá'!$C$202+'03_Định giá'!$C$19*((($A19)-'03_Định giá'!$C$21)*(1+'03_Định giá'!$C$23)-((E$14)-'03_Định giá'!$C$22))/1000*'03_Định giá'!$C$204)*1000/'01_Số liệu gốc'!$B$8 -> -1464.4792 | F19: =('03_Định giá'!$C$202+'03_Định giá'!$C$19*((($A19)-'03_Định giá'!$C$21)*(1+'03_Định giá'!$C$23)-((F$14)-'03_Định giá'!$C$22))/1000*'03_Định giá'!$C$204)*1000/'01_Số liệu gốc'!$B$8 -> -2051.5623
A20: Nhà máy giữ nguyên cơ sở. Mỗi 1.000 đ/lít ≈ 20 tỷ lãi trước khấu hao/năm. Cộng thẳng vào cả năm phương pháp (trừ P/B theo ROE). Mức hòa vốn từng kịch bản ở 06 mục C.
A22: BẢNG 3 — RIÊNG PHƯƠNG PHÁP 4: ROE CHU KỲ (hàng) × LỢI SUẤT YÊU CẦU r (cột)
A23: hàng \ cột | B23: ='03_Định giá'!$C$44-0.02 -> 0.09224 | C23: ='03_Định giá'!$C$44-0.01 -> 0.10224 | D23: ='03_Định giá'!$C$44+0 -> 0.11224 | E23: ='03_Định giá'!$C$44+0.01 -> 0.12224 | F23: ='03_Định giá'!$C$44+0.02 -> 0.13224
A24: ='03_Định giá'!$C$14-0.03 -> 0.085 | B24: =MAX(0,(($A24)*(1-'03_Định giá'!$C$36)-'03_Định giá'!$C$35)/((B$23)-'03_Định giá'!$C$35)*'01_Số liệu gốc'!$C$73) -> 15764.583 | C24: =MAX(0,(($A24)*(1-'03_Định giá'!$C$36)-'03_Định giá'!$C$35)/((C$23)-'03_Định giá'!$C$35)*'01_Số liệu gốc'!$C$73) -> 13582.331 | D24: =MAX(0,(($A24)*(1-'03_Định giá'!$C$36)-'03_Định giá'!$C$35)/((D$23)-'03_Định giá'!$C$35)*'01_Số liệu gốc'!$C$73) -> 11930.783 | E24: =MAX(0,(($A24)*(1-'03_Định giá'!$C$36)-'03_Định giá'!$C$35)/((E$23)-'03_Định giá'!$C$35)*'01_Số liệu gốc'!$C$73) -> 10637.333 | F24: =MAX(0,(($A24)*(1-'03_Định giá'!$C$36)-'03_Định giá'!$C$35)/((F$23)-'03_Định giá'!$C$35)*'01_Số liệu gốc'!$C$73) -> 9596.9055
A25: ='03_Định giá'!$C$14-0.015 -> 0.1 | B25: =MAX(0,(($A25)*(1-'03_Định giá'!$C$36)-'03_Định giá'!$C$35)/((B$23)-'03_Định giá'!$C$35)*'01_Số liệu gốc'!$C$73) -> 20341.397 | C25: =MAX(0,(($A25)*(1-'03_Định giá'!$C$36)-'03_Định giá'!$C$35)/((C$23)-'03_Định giá'!$C$35)*'01_Số liệu gốc'!$C$73) -> 17525.589 | D25: =MAX(0,(($A25)*(1-'03_Định giá'!$C$36)-'03_Định giá'!$C$35)/((D$23)-'03_Định giá'!$C$35)*'01_Số liệu gốc'!$C$73) -> 15394.559 | E25: =MAX(0,(($A25)*(1-'03_Định giá'!$C$36)-'03_Định giá'!$C$35)/((E$23)-'03_Định giá'!$C$35)*'01_Số liệu gốc'!$C$73) -> 13725.591 | F25: =MAX(0,(($A25)*(1-'03_Định giá'!$C$36)-'03_Định giá'!$C$35)/((F$23)-'03_Định giá'!$C$35)*'01_Số liệu gốc'!$C$73) -> 12383.104
A26: ='03_Định giá'!$C$14+0 -> 0.115 | B26: =MAX(0,(($A26)*(1-'03_Định giá'!$C$36)-'03_Định giá'!$C$35)/((B$23)-'03_Định giá'!$C$35)*'01_Số liệu gốc'!$C$73) -> 24918.211 | C26: =MAX(0,(($A26)*(1-'03_Định giá'!$C$36)-'03_Định giá'!$C$35)/((C$23)-'03_Định giá'!$C$35)*'01_Số liệu gốc'!$C$73) -> 21468.846 | D26: =MAX(0,(($A26)*(1-'03_Định giá'!$C$36)-'03_Định giá'!$C$35)/((D$23)-'03_Định giá'!$C$35)*'01_Số liệu gốc'!$C$73) -> 18858.335 | E26: =MAX(0,(($A26)*(1-'03_Định giá'!$C$36)-'03_Định giá'!$C$35)/((E$23)-'03_Định giá'!$C$35)*'01_Số liệu gốc'!$C$73) -> 16813.849 | F26: =MAX(0,(($A26)*(1-'03_Định giá'!$C$36)-'03_Định giá'!$C$35)/((F$23)-'03_Định giá'!$C$35)*'01_Số liệu gốc'!$C$73) -> 15169.302
A27: ='03_Định giá'!$C$14+0.015 -> 0.13 | B27: =MAX(0,(($A27)*(1-'03_Định giá'!$C$36)-'03_Định giá'!$C$35)/((B$23)-'03_Định giá'!$C$35)*'01_Số liệu gốc'!$C$73) -> 29495.026 | C27: =MAX(0,(($A27)*(1-'03_Định giá'!$C$36)-'03_Định giá'!$C$35)/((C$23)-'03_Định giá'!$C$35)*'01_Số liệu gốc'!$C$73) -> 25412.104 | D27: =MAX(0,(($A27)*(1-'03_Định giá'!$C$36)-'03_Định giá'!$C$35)/((D$23)-'03_Định giá'!$C$35)*'01_Số liệu gốc'!$C$73) -> 22322.111 | E27: =MAX(0,(($A27)*(1-'03_Định giá'!$C$36)-'03_Định giá'!$C$35)/((E$23)-'03_Định giá'!$C$35)*'01_Số liệu gốc'!$C$73) -> 19902.107 | F27: =MAX(0,(($A27)*(1-'03_Định giá'!$C$36)-'03_Định giá'!$C$35)/((F$23)-'03_Định giá'!$C$35)*'01_Số liệu gốc'!$C$73) -> 17955.501
A28: ='03_Định giá'!$C$14+0.03 -> 0.145 | B28: =MAX(0,(($A28)*(1-'03_Định giá'!$C$36)-'03_Định giá'!$C$35)/((B$23)-'03_Định giá'!$C$35)*'01_Số liệu gốc'!$C$73) -> 34071.84 | C28: =MAX(0,(($A28)*(1-'03_Định giá'!$C$36)-'03_Định giá'!$C$35)/((C$23)-'03_Định giá'!$C$35)*'01_Số liệu gốc'!$C$73) -> 29355.361 | D28: =MAX(0,(($A28)*(1-'03_Định giá'!$C$36)-'03_Định giá'!$C$35)/((D$23)-'03_Định giá'!$C$35)*'01_Số liệu gốc'!$C$73) -> 25785.887 | E28: =MAX(0,(($A28)*(1-'03_Định giá'!$C$36)-'03_Định giá'!$C$35)/((E$23)-'03_Định giá'!$C$35)*'01_Số liệu gốc'!$C$73) -> 22990.365 | F28: =MAX(0,(($A28)*(1-'03_Định giá'!$C$36)-'03_Định giá'!$C$35)/((F$23)-'03_Định giá'!$C$35)*'01_Số liệu gốc'!$C$73) -> 20741.699
A29: r ± 1 điểm ≈ β ± 0,11 ở ERP 9,2%. Phép thử β 0,65 / 0,85 và ERP 10% tính đủ cả năm phương pháp ở bảng 4 (T5, T6, T14).
A31: BẢNG 4 — PHÉP THỬ MỘT BIẾN trên GIÁ TRỊ CƠ SỞ = DCF + tiền × (1 − k) + dự án (tính lại đầy đủ ở 03 cột H–W)
A32: Phép thử | B32: Giá trị thử | C32: Giá trị cơ sở | D32: Chênh (đồng) | E32: Chênh % | F32: Cột ở 03 | G32: Đọc thế nào
A33: T0 · Đối chứng: không đổi gì (phải ra đúng cơ sở) | C33: ='03_Định giá'!$H$250 -> 25471.705 | D33: =C33-'03_Định giá'!$C$250 -> 0 | E33: =C33/'03_Định giá'!$C$250-1 -> 0 | F33: H | G33: Phải bằng 0 — kiểm đường ống phép thử
A34: T1 · Không xây nhà máy trong 5 năm — MỨC TRẦN (coi nhà máy cũ chạy mãi không tốn thêm) | B34: ='03_Định giá'!$I$27 -> 0 | C34: ='03_Định giá'!$I$250 -> 28382.147 | D34: =C34-'03_Định giá'!$C$250 -> 2910.4424 | E34: =C34/'03_Định giá'!$C$250-1 -> 0.11426178 | F34: I | G34: MỨC TRẦN: không tính chi phí giữ nhà máy cũ (hết đất, xuống cấp) hay Creamery bị chặn công suất
A35: T2 · Nhà máy chạy từ 2028 (lịch công ty: xong Q4/2027) | B35: ='03_Định giá'!$J$29 -> 2028 | C35: ='03_Định giá'!$J$250 -> 25103.261 | D35: =C35-'03_Định giá'!$C$250 -> -368.44361 | E35: =C35/'03_Định giá'!$C$250-1 -> -0.01446482 | F35: J | G35: Chi sớm hơn nhưng có lãi sớm hơn
A36: T3 · Sữa trang trại bán thô 13.000 đ/lít | B36: ='03_Định giá'!$K$21 -> 13000 | C36: ='03_Định giá'!$K$250 -> 23622.393 | D36: =C36-'03_Định giá'!$C$250 -> -1849.3117 | E36: =C36/'03_Định giá'!$C$250-1 -> -0.072602587 | F36: K | G36: Creamery không hút được sữa trại mới — bán thô cho Vinamilk
A37: T4 · Chi phí nuôi 11.500 đ/lít | B37: ='03_Định giá'!$L$22 -> 11500 | C37: ='03_Định giá'!$L$250 -> 24297.539 | D37: =C37-'03_Định giá'!$C$250 -> -1174.1661 | E37: =C37/'03_Định giá'!$C$250-1 -> -0.046096881 | F37: L
A38: T5 · ERP 10% (VDSC, cận trên) | B38: ='03_Định giá'!$M$32 -> 0.1 | C38: ='03_Định giá'!$M$250 -> 24084.529 | D38: =C38-'03_Định giá'!$C$250 -> -1387.1761 | E38: =C38/'03_Định giá'!$C$250-1 -> -0.054459491 | F38: M | G38: Mức VDSC dùng cho doanh nghiệp chu kỳ
A39: T6 · β phần kinh doanh 0,85 (bằng dự án) | B39: ='03_Định giá'!$N$33 -> 0.85 | C39: ='03_Định giá'!$N$250 -> 23277.736 | D39: =C39-'03_Định giá'!$C$250 -> -2193.9683 | E39: =C39/'03_Định giá'!$C$250-1 -> -0.086133547 | F39: N | G39: Coi kinh doanh hiện tại rủi ro như dự án
A40: T7 · Cổ tức 1.000đ/cp (tối thiểu 50% LNST) | B40: ='03_Định giá'!$O$15 -> 1000 | C40: ='03_Định giá'!$O$250 -> 25471.705 | D40: =C40-'03_Định giá'!$C$250 -> 0 | E40: =C40/'03_Định giá'!$C$250-1 -> 0 | F40: O | G40: Ít tiền về cổ đông sớm, ít phải vay · Từ 13/10/2026 chênh 0: chỉ đổi phương pháp đối chiếu
A41: T8 · B về mức 2025 (Creamery không cất cánh) | B41: ='03_Định giá'!$P$6 -> 2166.786 | C41: ='03_Định giá'!$P$250 -> 23485.525 | D41: =C41-'03_Định giá'!$C$250 -> -1986.1797 | E41: =C41/'03_Định giá'!$C$250-1 -> -0.077975925 | F41: P | G41: Creamery không bù được sữa thương hiệu đang giảm
A42: T9 · B về mức 2023 | B42: ='03_Định giá'!$Q$6 -> 2710.123 | C42: ='03_Định giá'!$Q$250 -> 27295.947 | D42: =C42-'03_Định giá'!$C$250 -> 1824.2426 | E42: =C42/'03_Định giá'!$C$250-1 -> 0.071618393 | F42: Q | G42: Hàng thương hiệu trở lại thời trước 2024
A43: T10 · Chi phí bán hàng ÷ B = mức 12 tháng | B43: ='03_Định giá'!$R$9 -> 0.27366486 | C43: ='03_Định giá'!$R$250 -> 24658.815 | D43: =C43-'03_Định giá'!$C$250 -> -812.88938 | E43: =C43/'03_Định giá'!$C$250-1 -> -0.031913427 | F43: R
A44: T11 · P/E lõi 10x | B44: ='03_Định giá'!$S$12 -> 10 | C44: ='03_Định giá'!$S$250 -> 25471.705 | D44: =C44-'03_Định giá'!$C$250 -> 0 | E44: =C44/'03_Định giá'!$C$250-1 -> 0 | F44: S | G44: Mức bội số tròn để so · Từ 13/10/2026 chênh 0: chỉ đổi phương pháp đối chiếu
A45: T12 · P/E lõi = P/E trung vị lịch sử MCM | B45: ='03_Định giá'!$T$12 -> 13.89 | C45: ='03_Định giá'!$T$250 -> 25471.705 | D45: =C45-'03_Định giá'!$C$250 -> 0 | E45: =C45/'03_Định giá'!$C$250-1 -> 0 | F45: T | G45: Bội số thị trường từng trả cho CẢ công ty (gồm lãi tiền gửi) — quá rộng tay cho phần lõi · Từ 13/10/2026 chênh 0: chỉ đổi phương pháp đối chiếu
A46: T13 · Biên gộp B giữ mức 6T/2026 | B46: ='03_Định giá'!$U$8 -> 0.0063439955 | C46: ='03_Định giá'!$U$250 -> 26878.844 | D46: =C46-'03_Định giá'!$C$250 -> 1407.1392 | E46: =C46/'03_Định giá'!$C$250-1 -> 0.055243229 | F46: U | G46: Biên gộp nửa đầu 2026 là mức bền
A47: T14 · β phần kinh doanh 0,65 | B47: ='03_Định giá'!$V$33 -> 0.65 | C47: ='03_Định giá'!$V$250 -> 26939.587 | D47: =C47-'03_Định giá'!$C$250 -> 1467.8827 | E47: =C47/'03_Định giá'!$C$250-1 -> 0.057627975 | F47: V | G47: Đầu dưới dải β (MCM tự tính 0,70)
A48: T15 · Biên gộp bán cho Vinamilk 5% | B48: ='03_Định giá'!$W$40 -> 0.05 | C48: ='03_Định giá'!$W$250 -> 25915.771 | D48: =C48-'03_Định giá'!$C$250 -> 444.06662 | E48: =C48/'03_Định giá'!$C$250-1 -> 0.017433722 | F48: W | G48: Cơ sở dùng 10%. Fair value ba kịch bản ở 5%: 27.239 đ/cp (chạy lại toàn bộ 13/10/2026, giá trị = DCF + tiền × 90%; không tự cập nhật)
A49: Trọng số bằng nhau (20% mỗi phương pháp) | C49: =AVERAGE('03_Định giá'!$C$215,'03_Định giá'!$C$233,'03_Định giá'!$C$242,'03_Định giá'!$C$224,'03_Định giá'!$C$220) -> 23413.999 | D49: =C49-'03_Định giá'!$C$250 -> -2057.7058 | E49: =C49/'03_Định giá'!$C$250-1 -> -0.080783984
A50: Chỉ phương pháp 1 (P/E lõi + tiền + dự án) | C50: ='03_Định giá'!$C$215 -> 25370.485 | D50: =C50-'03_Định giá'!$C$250 -> -101.22011 | E50: =C50/'03_Định giá'!$C$250-1 -> -0.0039738254 | G50: Cách thị trường hay nhìn MCM
A51: Chỉ phương pháp 3 (cổ tức) | C51: ='03_Định giá'!$C$242 -> 22128.462 | D51: =C51-'03_Định giá'!$C$250 -> -3343.2426 | E51: =C51/'03_Định giá'!$C$250-1 -> -0.13125319 | G51: Góc nhìn của cổ đông thiểu số
A52: Cách tính trước 13/10: bình quân năm phương pháp 30/25/20/15/10, tiền tính đủ | C52: =0.3*'03_Định giá'!$C$215+0.25*'03_Định giá'!$C$233+0.2*'03_Định giá'!$C$242+0.15*'03_Định giá'!$C$224+0.1*'03_Định giá'!$C$220+(0.3+0.25+0.1)*'02_Giả định'!$B$26*'03_Định giá'!$C$210 -> 24584.023 | D52: =C52-'03_Định giá'!$C$250 -> -887.68143 | E52: =C52/'03_Định giá'!$C$250-1 -> -0.034849706 | G52: Để so với bản trước: cơ sở 24.584 sau khi đổi du lịch 336 (sáng 13/10/2026)
A53: k = 0% (tiền ròng tính đủ mệnh giá) | C53: ='03_Định giá'!$C$233+'02_Giả định'!$B$26*'03_Định giá'!$C$210 -> 26743.102 | D53: =C53-'03_Định giá'!$C$250 -> 1271.3973 | E53: =C53/'03_Định giá'!$C$250-1 -> 0.049914102 | G53: Mỗi 10 điểm k ≈ 1.271 đ/cp
A54: k = 20% | C54: ='03_Định giá'!$C$233-(0.2-'02_Giả định'!$B$26)*'03_Định giá'!$C$210 -> 24200.307 | D54: =C54-'03_Định giá'!$C$250 -> -1271.3973 | E54: =C54/'03_Định giá'!$C$250-1 -> -0.049914102 | G54: Vinamilk giữ tiền lâu hoặc dồn vào dự án mới

Sheet 05_Đối chiếu
A1: MCM — ĐỐI CHIẾU CHÉO
A3: A. BỘI SỐ TẠI GIÁ THỊ TRƯỜNG, TẠI KỲ VỌNG, TẠI BÌNH QUÂN CƠ SỞ
A4: Chỉ tiêu | B4: Tại giá thị trường | C4: Tại giá trị kỳ vọng | D4: Tại bình quân cơ sở | F4: Ghi chú
A5: Vốn hoá (tỷ đồng) | B5: ='01_Số liệu gốc'!$B$11*'01_Số liệu gốc'!$B$8/1000 -> 2909.5 | C5: ='03_Định giá'!$B$257*'01_Số liệu gốc'!$B$8/1000 -> 2950.0568 | D5: ='03_Định giá'!$C$250*'01_Số liệu gốc'!$B$8/1000 -> 2801.8875
A6: Giá trị phần lõi + dự án = vốn hoá − tiền ròng (tỷ đồng) | B6: =B5-'01_Số liệu gốc'!$C$65 -> 1510.963 | C6: =C5-'01_Số liệu gốc'!$C$65 -> 1551.5198 | D6: =D5-'01_Số liệu gốc'!$C$65 -> 1403.3505 | F6: Thị trường trả cho kinh doanh lõi CỘNG hai dự án bao nhiêu sau khi trừ tiền
A7: P/E 12 tháng (cả lãi tiền gửi) | B7: =B5/'01_Số liệu gốc'!$H$51 -> 11.154775 | C7: =C5/'01_Số liệu gốc'!$H$51 -> 11.310267 | D7: =D5/'01_Số liệu gốc'!$H$51 -> 10.742198 | F7: Cách thị trường và Vietcap đọc
A8: P/E lõi 12 tháng = (vốn hoá − tiền) ÷ lợi nhuận lõi sau thuế, sau quỹ | B8: =B6/('02_Giả định'!$B$35*(1-'02_Giả định'!$B$48)*(1-'02_Giả định'!$B$13)) -> 9.2639563 | C8: =C6/('02_Giả định'!$B$35*(1-'02_Giả định'!$B$48)*(1-'02_Giả định'!$B$13)) -> 9.5126167 | D8: =D6/('02_Giả định'!$B$35*(1-'02_Giả định'!$B$48)*(1-'02_Giả định'!$B$13)) -> 8.6041669 | F8: Coi dự án hòa vốn
A9: P/E lõi chuẩn hoá cơ sở | B9: =B6/'03_Định giá'!$C$53 -> 8.5894638 | C9: =C6/'03_Định giá'!$C$53 -> 8.8200197 | D9: =D6/'03_Định giá'!$C$53 -> 7.9777125 | F9: So P/E đặt ở 02 (10,8x) — chưa trừ giá trị ròng dự án
A10: P/B (sổ sách 30/06/2026) | B10: ='01_Số liệu gốc'!$B$11/'01_Số liệu gốc'!$C$73 -> 1.2535064 | C10: ='03_Định giá'!$B$257/'01_Số liệu gốc'!$C$73 -> 1.2709796 | D10: ='03_Định giá'!$C$250/'01_Số liệu gốc'!$C$73 -> 1.2071435
A11: EV/EBITDA lõi 12 tháng (EV = vốn hoá − tiền) | B11: =B6/('02_Giả định'!$B$35+'01_Số liệu gốc'!$H$52) -> 5.6851209 | C11: =C6/('02_Giả định'!$B$35+'01_Số liệu gốc'!$H$52) -> 5.8377192 | D11: =D6/('02_Giả định'!$B$35+'01_Số liệu gốc'!$H$52) -> 5.2802202
A12: Tỷ suất cổ tức (2.000đ/cp như 2022–2025) | B12: ='01_Số liệu gốc'!$B$129/'01_Số liệu gốc'!$B$11 -> 0.075614367 | C12: ='01_Số liệu gốc'!$B$129/'03_Định giá'!$B$257 -> 0.074574835 | D12: ='01_Số liệu gốc'!$B$129/'03_Định giá'!$C$250 -> 0.078518498 | F12: Cổ tức 2025 cao hơn LNST sau quỹ — chính sách 2026 hạ về tối thiểu 50% LNST
A13: P/E lõi cơ bản = (1 − quỹ − g ÷ ROIC) ÷ ((1 − quỹ) × (r − g)), ROIC lõi 12 tháng | B13: =(1-'02_Giả định'!$B$13-'02_Giả định'!$B$12/'02_Giả định'!$B$51)/((1-'02_Giả định'!$B$13)*('02_Giả định'!$B$10-'02_Giả định'!$B$12)) -> 11.12348 | F13: Bội số mà ROIC lõi và r (02 mục A) biện minh được. Đặt ở 02: 10,8x
A14: EV/EBITDA lõi cơ bản = (1 − thuế)(1 − quỹ − g ÷ ROIC) × EBIT/EBITDA ÷ (r − g) | B14: =(1-'02_Giả định'!$B$48)*(1-'02_Giả định'!$B$13-'02_Giả định'!$B$12/'02_Giả định'!$B$51)*('02_Giả định'!$B$35/('02_Giả định'!$B$35+'01_Số liệu gốc'!$H$52))/('02_Giả định'!$B$10-'02_Giả định'!$B$12) -> 6.8262764 | F14: Đặt ở 02: 6,6x
A16: B. GIÁ ĐANG NGẦM ĐỊNH ĐIỀU GÌ — giải ngược dạng đóng
A17: (a) ROE thuộc cổ đông ngầm định (công thức phương pháp 4) | B17: ='02_Giả định'!$B$12+'01_Số liệu gốc'!$B$11/'01_Số liệu gốc'!$C$73*('02_Giả định'!$B$10-'02_Giả định'!$B$12) -> 0.13308837
A18: quy về ROE trước trích quỹ | B18: =B17/(1-'02_Giả định'!$B$13) -> 0.14787597 | F18: So ROE 2022–2025 bình quân và 12 tháng (01 mục F)
A19: (b) P/E lõi ngầm định nếu hai dự án hòa vốn | B19: =(('01_Số liệu gốc'!$B$11*'01_Số liệu gốc'!$B$8/1000)-'01_Số liệu gốc'!$C$65)/'03_Định giá'!$C$53 -> 8.5894638 | F19: Trên lợi nhuận lõi chuẩn hoá cơ sở
A20: (c) P/E lõi ngầm định với giá trị ròng dự án cơ sở | B20: =(('01_Số liệu gốc'!$B$11*'01_Số liệu gốc'!$B$8/1000)-'01_Số liệu gốc'!$C$65-'03_Định giá'!$C$202)/'03_Định giá'!$C$53 -> 10.680012 | F20: Cao hơn P/E đặt ở 02 nghĩa là giá đang trả trước cho dự án tốt hơn cơ sở
A21: (d) B (doanh thu phần còn lại) ngầm định ở P/E đặt ở 02 và dự án cơ sở (tỷ) | B21: =((('01_Số liệu gốc'!$B$11*'01_Số liệu gốc'!$B$8/1000)-'01_Số liệu gốc'!$C$65-'03_Định giá'!$C$202)/'03_Định giá'!$C$12/((1-'03_Định giá'!$C$10)*(1-'03_Định giá'!$C$36))+'03_Định giá'!$C$42-'03_Định giá'!$C$40*'03_Định giá'!$C$7)/('03_Định giá'!$C$48-'03_Định giá'!$C$9) -> 2419.1949 | F21: So B cơ sở 2.450; 12 tháng 2.302; đỉnh 2023 2.710
A22: (e) Giá trị ròng dự án ngầm định ở P/E đặt ở 02 và lõi cơ sở (tỷ) | B22: =('01_Số liệu gốc'!$B$11*'01_Số liệu gốc'!$B$8/1000)-'01_Số liệu gốc'!$C$65-'03_Định giá'!$C$213 -> -388.85296 | F22: So giá trị ròng dự án cơ sở ở 06 mục C
A23: (f) LỢI SUẤT YÊU CẦU PHẦN KINH DOANH NGẦM ĐỊNH Ở GIÁ HIỆN TẠI | B23: ='02_Giả định'!$B$12+'03_Định giá'!$C$53*(1-'02_Giả định'!$B$12/'02_Giả định'!$B$51)/(('01_Số liệu gốc'!$B$11*'01_Số liệu gốc'!$B$8/1000)-'01_Số liệu gốc'!$C$65-'03_Định giá'!$C$202) -> 0.11645266 | F23: Bằng g + lợi nhuận lõi × (1 − g ÷ ROIC) ÷ (vốn hoá − tiền − dự án). So r ở 02 mục A: thấp hơn r = giá đắt
A24: (g) LỢI SUẤT KỲ VỌNG CẢ CỔ PHIẾU NẾU MUA Ở GIÁ HIỆN TẠI | B24: =((('01_Số liệu gốc'!$B$11*'01_Số liệu gốc'!$B$8/1000)-'01_Số liệu gốc'!$C$65)*B23+'01_Số liệu gốc'!$C$65*'03_Định giá'!$C$16*(1-'02_Giả định'!$B$14)*(1-'02_Giả định'!$B$13))/('01_Số liệu gốc'!$B$11*'01_Số liệu gốc'!$B$8/1000) -> 0.084702503 | F24: Bình quân: phần kinh doanh ở (f), phần tiền gửi ở lãi tiền gửi sau thuế, sau quỹ — tiền là ~nửa giá trị
A25: (h) Chênh so lãi tiền gửi tham chiếu của nhà đầu tư (điểm %) | B25: =(B24-'02_Giả định'!$B$17)*100 -> -0.52974975 | F25: Âm = thấp hơn lãi gửi tham chiếu (02 mục A)
A26: Tự kiểm: thế (a) ngược vào công thức phương pháp 4 ra đúng giá thị trường | B26: =(B17-'02_Giả định'!$B$12)/('02_Giả định'!$B$10-'02_Giả định'!$B$12)*'01_Số liệu gốc'!$C$73 -> 26450 | C26: =IF(ABS(B26-'01_Số liệu gốc'!$B$11)<0.01,"KHỚP","LỆCH") -> KHỚP
A27: Tự kiểm: thế (d) vào phương pháp 1 cơ sở ra đúng giá thị trường | B27: =(('03_Định giá'!$C$40*'03_Định giá'!$C$7+('03_Định giá'!$C$48-'03_Định giá'!$C$9)*B21-'03_Định giá'!$C$42)*(1-'03_Định giá'!$C$10)*(1-'03_Định giá'!$C$36)*'03_Định giá'!$C$12+'01_Số liệu gốc'!$C$65+'03_Định giá'!$C$202)*1000/'01_Số liệu gốc'!$B$8 -> 26450 | C27: =IF(ABS(B27-'01_Số liệu gốc'!$B$11)<0.01,"KHỚP","LỆCH") -> KHỚP
A29: C. HAI ĐƯỜNG TỚI ROE — lịch sử (phương pháp 4) và động cơ lõi + lãi tiền gửi
A30: Chỉ tiêu | B30: Xấu | C30: Cơ sở | D30: Tốt | F30: Đọc thế nào
A31: ROE chu kỳ lịch sử đặt ở 02 (trước trích quỹ) | B31: ='02_Giả định'!B68 -> 0.095 | C31: ='02_Giả định'!C68 -> 0.115 | D31: ='02_Giả định'!D68 -> 0.14
A32: ROE theo động cơ = (lợi nhuận lõi + lãi tiền gửi × 80%) ÷ vốn chủ 30/06/2026, trước dự án | B32: =('03_Định giá'!B52+'03_Định giá'!B16*'03_Định giá'!B209*(1-'03_Định giá'!B37))/'01_Số liệu gốc'!$C$66 -> 0.087474874 | C32: =('03_Định giá'!C52+'03_Định giá'!C16*'03_Định giá'!C209*(1-'03_Định giá'!C37))/'01_Số liệu gốc'!$C$66 -> 0.11794997 | D32: =('03_Định giá'!D52+'03_Định giá'!D16*'03_Định giá'!D209*(1-'03_Định giá'!D37))/'01_Số liệu gốc'!$C$66 -> 0.1487797
A33: Chênh (điểm %) | B33: =(B32-B31)*100 -> -0.75251259 | C33: =(C32-C31)*100 -> 0.29499746 | D33: =(D32-D31)*100 -> 0.87797037 | F33: Gần 0 = hai cách độc lập kể cùng câu chuyện. Khi tiền gửi đổ vào dự án ROIC thấp, ROE không tăng dù tiền nhàn rỗi giảm
A35: D. NHÓM SO SÁNH (số cứng — cập nhật tay)
A36: Mã | B36: P/E | C36: P/B | D36: EV/EBITDA 12 tháng | F36: Ghi chú
A37: VNM | B37: 11.06 | C37: 3.8 | D37: 9.29 | F37: Vinamilk — công ty mẹ cấp cao nhất của MCM
A38: IDP | B38: 27.55 | C38: 5.36 | D38: 17.76 | F38: Sữa Quốc tế (Kun) — tăng trưởng, ít tiền gửi
A39: QNS | B39: 9.97 | C39: 1.81 | D39: 8.66 | F39: Đường Quảng Ngãi — Vinasoy (sữa đậu nành) + đường
A40: SAB | B40: 11.51 | C40: 2.81 | D40: 10.38 | F40: Bia — hàng tiêu dùng, nhiều tiền gửi như MCM
A41: MCM | B41: 11.18 | C41: 1.26 | D41: 10.82 | F41: Hệ thống (Vietcap) — để so. EV KHÔNG trừ tiền gửi có kỳ hạn → không so thẳng với mục A
A42: Trung vị VNM, IDP, QNS, SAB | B42: =MEDIAN(B37:B40) -> 11.285 | C42: =MEDIAN(C37:C40) -> 3.305 | D42: =MEDIAN(D37:D40) -> 9.835
A43: P/E, P/B: daily_valuation phiên 07/10/2026. EV/EBITDA: gen_ratios_vietcap RATIO_TTM Q2/2026. Không mã nào cùng mô hình nửa trại sữa nửa thương hiệu, lại bị công ty mẹ mua sữa — chỉ để định vị.
A45: E. ĐỐI CHIẾU VỚI FILE QNS — nếu định giá phần lõi như Vinasoy (9 lần EBIT, dùng chung)
A46: Chỉ tiêu | B46: Xấu | C46: Cơ sở | D46: Tốt | F46: Ghi chú
A47: Bội số Vinasoy trong file QNS (lần EBIT) | B47: 9 | F47: QNS_SOTP_2026-09-30.xlsx, 02_Giả định dòng 25 — đọc trên bản sao 09/10/2026
A48: Giá trị = (EBIT lõi × 9 + tiền ròng + giá trị ròng dự án) ÷ cổ phiếu (đồng) | B48: =MAX(0,('03_Định giá'!B51*$B$47+'03_Định giá'!B209+'03_Định giá'!B202)*1000/'01_Số liệu gốc'!$B$8) -> 19915.724 | C48: =MAX(0,('03_Định giá'!C51*$B$47+'03_Định giá'!C209+'03_Định giá'!C202)*1000/'01_Số liệu gốc'!$B$8) -> 26944.143 | D48: =MAX(0,('03_Định giá'!D51*$B$47+'03_Định giá'!D209+'03_Định giá'!D202)*1000/'01_Số liệu gốc'!$B$8) -> 38552.539 | F48: Không trừ quỹ khen thưởng phúc lợi, không trừ thuế — cách đọc của file QNS. Dùng để thấy chênh giữa hai file, không đưa vào bình quân
A50: F. MỐC KIỂM QUÝ 3/2026 — đà cải thiện lợi nhuận lõi 6 tháng có giữ được không
A51: Chỉ tiêu | B51: Dự báo (giữ đà) | C51: Cận dưới | D51: Cận trên | E51: Thực tế | F51: Trạng thái
A52: LNST Q3/2026 (tỷ đồng) | B52: ='02_Giả định'!$B$53 -> 48.16472 | C52: ='02_Giả định'!$C$53 -> 38.11436 | D52: ='02_Giả định'!$D$53 -> 58.21508 | F52: =IF(E52="","CHỜ BCTC Q3 (cuối tháng 10/2026) — nhập LNST vào cột E",IF(E52<C52,"DƯỚI DẢI — đà 6 tháng không giữ được: xem lại B và chi phí bán hàng ở 02",IF(E52>D52,"TRÊN DẢI — xem có khoản bất thường không","TRONG DẢI"))) -> CHỜ BCTC Q3 (cuối tháng 10/2026) — nhập LNST vào cột E
A53: Cận dưới/trên = còn một nửa / mạnh gấp rưỡi mức EBIT lõi tăng thêm mỗi quý của 6T/2026. Kèm theo: xây dựng dở dang nhà máy có nhích khỏi 31 tỷ không (san lấp Q3/2026 theo kế hoạch).
A55: G. GIỚI HẠN MÔ HÌNH
A56: 1. Biên gộp của phần bán cho Vinamilk (mV) 10% là ước của người viết (12/10/2026), không có nguồn công bố (bản trước dùng 5%; hồi quy 3 năm cho số âm). Đổi mV chỉ dịch biên của B; EBIT 12 tháng vẫn khớp. mV 5–15% → kỳ vọng 27.239–26.398 đ/cp.
A57: 2. Phương pháp 1, 2, 3, 5 cùng đi từ một con số lợi nhuận lõi chuẩn hoá — B và chi phí bán hàng sai thì bốn phương pháp sai cùng chiều. Chỉ phương pháp 4 (ROE lịch sử) độc lập.
A58: 3. Giá bán, chi phí mỗi lít của trang trại và lãi du lịch, lãi tăng thêm của nhà máy là TỰ ĐẶT: công ty không công bố (06 mục F). Trang trại chi nốt dồn vào 2027; sau 2031 dòng tiền dự án đều thêm 20 năm rồi dừng.
A59: 4. Lợi nhuận lõi coi nhà máy cũ chạy mãi; phần nhà máy mới thay nhà máy cũ nằm trong lãi tăng thêm thấp, không mô hình riêng chi phí sửa chữa nhà máy cũ. Sữa trại mới có giành chỗ sữa nông hộ (đang dư) hay không — không mô hình.
A60: 5. Lợi suất yêu cầu theo cách rút gọn của công ty chứng khoán (Rf + β × ERP); cách Damodaran đầy đủ (cộng riêng rủi ro quốc gia, Rf quy từ USD) cho MCM ~13,3%. Thuế: lãi tiền gửi chịu đủ 20%, phần miễn thuế dồn hết vào lợi nhuận lõi.
A61: 6. Dòng tiền bắt đầu từ 30/06/2026, bỏ qua lợi nhuận nửa cuối 2026 (~100 tỷ); tạm ứng cổ tức đợt 1/2026 cộng ở phương pháp 3 coi như chi từ khoản đó.
A62: 7. Thanh khoản rất thấp (~0,4 tỷ/phiên): giá thị trường có thể lệch xa giá trị lâu; Vinamilk có thể mua nốt hoặc không bao giờ — không mô hình.

Sheet 06_Dự án
A1: MCM — HAI DỰ ÁN MỚI: TRANG TRẠI 4.000 CON (CÓ DU LỊCH) VÀ NHÀ MÁY SỮA (bản 12/10/2026)
A2: Dữ kiện dự án ở 01 mục G. Sheet này: giả định theo ba kịch bản (nền xanh lá), kết quả đọc từ 03 (tính lại đủ ở mọi cột phép thử), mức hòa vốn, việc theo dõi mỗi quý và những gì phải hỏi công ty. Giá trị dự án = dòng tiền 2027–2031 + 20 năm đều sau đó, chiết khấu ở lợi suất dự án (02 mục A). Phần đã chi là chi phí chìm.
A4: A. TRANG TRẠI 4.000 CON — tách phần bò sữa (lít × giá − chi phí) và phần du lịch
A5: Tham số | B5: Xấu | C5: Cơ sở | D5: Tốt | E5: Mốc / nguồn số | F5: Căn cứ
A6: Vốn phần trang trại bò sữa (tỷ) | B6: 860 | C6: 784 | D6: 784 | E6: ='01_Số liệu gốc'!$B$109*'01_Số liệu gốc'!$B$110/('01_Số liệu gốc'!$B$110+'01_Số liệu gốc'!$B$111) -> 784 | F6: Mốc = 1.120 × 70% (tỷ lệ 700/1.000 lúc khởi công). Xấu: vượt dự toán ~10% — đang lắp máy, nhập gian vắt sữa. Vinamilk Quảng Ngãi 4.000 con: 700 tỷ
A7: Vốn phần du lịch, cảnh quan thực làm (tỷ) | B7: 336 | C7: 336 | D7: 336 | E7: ='01_Số liệu gốc'!$B$109*(1-'01_Số liệu gốc'!$B$110/('01_Số liệu gốc'!$B$110+'01_Số liệu gốc'!$B$111)) -> 336 | F7: Chốt 13/10/2026: giữ 336 tỷ cả ba kịch bản = 1.120 × 30% như phương án 2022 — chưa có nghị quyết thu nhỏ du lịch. Bản trước: cơ sở 150, tốt 100 (tự đặt theo lời chủ tịch ĐHĐCĐ 20/04/2026). Lãi du lịch B15:D15 giữ nguyên.
A8: Sản lượng khi đủ đàn (triệu lít/năm) | B8: 18 | C8: 20 | D8: 22 | E8: ='01_Số liệu gốc'!$B$112 -> 20 | F8: Thiết kế 20; trại 2.000 con hiện có làm ra 11 triệu lít → 4.000 con ≈ 22. Năng suất đàn MCM 26 lít/con/ngày (BCTN 2025), KBSV kỳ vọng trại mới 30–32
A9: Sản lượng năm 2027 so với khi đủ đàn | B9: 0.3 | C9: 0.5 | D9: 0.6 | F9: Chính thức Q2/2027, đủ đàn 2028 (KBSV). Xấu: lên đàn chậm (nguồn bò chưa công bố)
A10: Giá bán sữa của trang trại (đồng/lít) | B10: 13000 | C10: 14500 | D10: 16000 | F10: Giá tại trại cả nước 13.000–14.500 đ/kg (2024), 14.000–15.000 (2025) — Người Chăn Nuôi 17/03/2026; Ba Vì 12.000–14.000 (09/2025). MCM: giá mua, giá bán cho Vinamilk 2026 "giữ nguyên 2025", không công bố số. Tốt = sữa vào Creamery (giá nội bộ cao hơn) — TỰ ĐẶT
A11: Chi phí tiền mặt mỗi lít: thức ăn, nhân công, thú y (đồng/lít) | B11: 11500 | C11: 10500 | D11: 9500 | F11: TỰ ĐẶT — công ty không công bố. Mốc duy nhất: chi phí sản xuất sữa Việt Nam 9.500–10.000 đ/lít (IPSARD 2019, cũ). Ngô, khô đậu +21–25% so cùng kỳ (09/2026). Trại công nghệ cao năng suất cao thì thấp hơn nông hộ
A12: Thu thêm từ bê đực, bò loại (% doanh thu sữa) | B12: 0.05 | C12: 0.05 | D12: 0.05 | F12: TỰ ĐẶT
A13: Chi duy trì chuồng trại, thiết bị (tỷ/năm) | B13: 15 | C13: 15 | D13: 15 | F13: TỰ ĐẶT
A14: Khấu hao phần bò sữa (năm) | B14: 20 | C14: 20 | D14: 20 | F14: Nhà cửa 5–33 năm, máy móc 5–24 năm (chính sách kế toán BCTC 2025)
A15: Du lịch: lãi trước thuế mỗi năm từ 2028 (tỷ) | B15: 0 | C15: 10 | D15: 25 | F15: TỰ ĐẶT — không có số khách, giá vé. Mộc Châu 2,5 triệu lượt khách (2023), quy hoạch 5 triệu (2030); bán sữa tại chỗ chỉ tiêu được vài % sản lượng. Thuế 20% (không phải thu nhập chăn nuôi)
A17: B. NHÀ MÁY SỮA MỚI — giai đoạn 1 (giai đoạn 2 1.257 tỷ ngoài 5 năm, không tính)
A18: Tham số | B18: Xấu | C18: Cơ sở | D18: Tốt | E18: Mốc / nguồn số | F18: Căn cứ
A19: Có xây trong 5 năm (1 = có, 0 = không) | B19: 0 | C19: 1 | D19: 1 | F19: Xấu: mặt bằng tiếp tục kẹt (82%, hộ nhà kiên cố chưa chịu đền bù), không xây trong 5 năm → sữa dư bán thô (giá Xấu ở mục A)
A20: Vốn giai đoạn 1 (tỷ) | B20: 850 | C20: 743 | D20: 743 | E20: ='01_Số liệu gốc'!$B$116 -> 743 | F20: Báo Sơn La 09/09/2025. QĐ 2932/QĐ-UBND 19/11/2025 điều chỉnh chủ trương — chưa có toàn văn. Xấu chỉ để tham khảo (không xây)
A21: Năm bắt đầu có lãi (chi 50%/50% trong hai năm trước đó) | B21: 2031 | C21: 2030 | D21: 2028 | F21: Chốt 12/10/2026: cơ sở 3 năm nữa, chạy đầu 2030 — theo lời chủ tịch ĐHĐCĐ 20/04/2026 ("2,3 năm tới vẫn đáp ứng") và tiến độ thực (tiền chi cho nhà máy 6 tháng chỉ +0,5 tỷ). Tốt: Q4/2027 theo bản tin NĐT (chi dồn vào 2027). Dùng năm 2028–2032 | G21: =IF(AND(MIN(B21:D21)>=2028,MAX(B21:D21)<=2032),"ĐẠT — năm có lãi trong 2028–2032","SAI — năm có lãi phải trong 2028–2032: năm khác làm 03 dòng 82 tính sai vốn nhà máy") -> ĐẠT — năm có lãi trong 2028–2032
A22: Lãi tăng thêm sau thuế mỗi năm khi chạy (tỷ) | B22: 20 | C22: 45 | D22: 75 | F22: TỰ ĐẶT. Phần lớn là THAY nhà máy cũ (200 tấn/ngày, hết đất, xuống cấp); lãi thêm chỉ có khi Creamery cần thêm công suất (chủ tịch: xây khi công suất cũ chạm 70%). Gồm chi phí sửa chữa nhà máy cũ tránh được. Tương ứng ~6% vốn ở cơ sở
A24: C. KẾT QUẢ BA KỊCH BẢN (đọc từ 03 — đổi giả định ở trên là chạy lại)
A25: Chỉ tiêu | B25: Xấu | C25: Cơ sở | D25: Tốt | F25: Đọc thế nào
A26: Trang trại: tổng vốn theo kịch bản (bò sữa + du lịch, tỷ) | B26: ='03_Định giá'!$B$60 -> 1196 | C26: ='03_Định giá'!$C$60 -> 1120 | D26: ='03_Định giá'!$D$60 -> 1120
A27: còn phải chi sau 30/06/2026 (tỷ) | B27: ='03_Định giá'!$B$61 -> 780.679 | C27: ='03_Định giá'!$C$61 -> 704.679 | D27: ='03_Định giá'!$D$61 -> 704.679 | F27: Đã ghi sổ 415,3 tỷ (01 mục D) là chi phí chìm
A28: Trang trại: doanh thu khi đủ đàn (tỷ/năm) | B28: ='03_Định giá'!$B$62 -> 245.7 | C28: ='03_Định giá'!$C$62 -> 304.5 | D28: ='03_Định giá'!$D$62 -> 369.6 | F28: lít × giá × (1 + thu thêm)
A29: lãi trước khấu hao (tỷ/năm) | B29: ='03_Định giá'!$B$63 -> 38.7 | C29: ='03_Định giá'!$C$63 -> 94.5 | D29: ='03_Định giá'!$D$63 -> 160.6 | F29: Mỗi 1.000 đ/lít giá hoặc chi phí ≈ 20 tỷ/năm
A30: lãi sau khấu hao, miễn thuế (tỷ/năm) | B30: ='03_Định giá'!$B$65 -> -4.3 | C30: ='03_Định giá'!$C$65 -> 55.3 | D30: ='03_Định giá'!$D$65 -> 121.4
A31: LÃI TRÊN VỐN PHẦN BÒ SỮA | B31: ='03_Định giá'!$B$67 -> -0.005 | C31: ='03_Định giá'!$C$67 -> 0.070535714 | D31: ='03_Định giá'!$D$67 -> 0.15484694 | F31: So lợi suất dự án 12,4% và lãi gửi ngân hàng
A32: Du lịch: lãi sau thuế (tỷ/năm) | B32: ='03_Định giá'!$B$68 -> 0 | C32: ='03_Định giá'!$C$68 -> 8 | D32: ='03_Định giá'!$D$68 -> 20 | F32: Cần ~20 tỷ/năm mới bằng gửi tiết kiệm trên 150–336 tỷ vốn
A33: Nhà máy: vốn còn phải chi (tỷ) | B33: ='03_Định giá'!$B$69 -> 0 | C33: ='03_Định giá'!$C$69 -> 711.923 | D33: ='03_Định giá'!$D$69 -> 711.923
A34: lãi tăng thêm ÷ vốn | B34: ='03_Định giá'!$B$70 -> 0 | C34: ='03_Định giá'!$C$70 -> 0.060565276 | D34: ='03_Định giá'!$D$70 -> 0.10094213
A35: GIÁ TRỊ RÒNG TRANG TRẠI, gồm du lịch (tỷ) | B35: ='03_Định giá'!$B$200 -> -525.57969 | C35: ='03_Định giá'!$C$200 -> -47.597289 | D35: ='03_Định giá'!$D$200 -> 463.83391 | F35: Âm = phần còn phải chi sinh lời dưới 12,4%
A36: GIÁ TRỊ RÒNG NHÀ MÁY (tỷ) | B36: ='03_Định giá'!$B$201 -> 0 | C36: ='03_Định giá'!$C$201 -> -320.14866 | D36: ='03_Định giá'!$D$201 -> -178.94859
A37: GIÁ TRỊ RÒNG HAI DỰ ÁN (tỷ) | B37: ='03_Định giá'!$B$202 -> -525.57969 | C37: ='03_Định giá'!$C$202 -> -367.74595 | D37: ='03_Định giá'!$D$202 -> 284.88532 | F37: Cộng vào cả năm phương pháp (PP4 qua ROE lịch sử)
A38: quy ra đồng/cổ phiếu | B38: ='03_Định giá'!$B$203 -> -4777.9972 | C38: ='03_Định giá'!$C$203 -> -3343.145 | D38: ='03_Định giá'!$D$203 -> 2589.8666
A39: HÒA VỐN: giá bán sữa trang trại để giá trị ròng trang trại = 0 (đ/lít) | B39: ='03_Định giá'!$B$205 -> 17415.582 | C39: ='03_Định giá'!$C$205 -> 14850.971 | D39: ='03_Định giá'!$D$205 -> 12928.804 | F39: Giữ chi phí ở kịch bản đó
A40: HÒA VỐN: lãi tăng thêm nhà máy để giá trị ròng nhà máy = 0 (tỷ/năm) | B40: ='03_Định giá'!$B$207 -> 0 | C40: ='03_Định giá'!$C$207 -> 112.94245 | D40: ='03_Định giá'!$D$207 -> 104.54103
A41: tương ứng lãi trên vốn nhà máy | B41: ='03_Định giá'!$B$208 -> 0 | C41: ='03_Định giá'!$C$208 -> 0.15200868 | D41: ='03_Định giá'!$D$208 -> 0.14070125
A43: D. DÒNG TIỀN HAI DỰ ÁN, KỊCH BẢN CƠ SỞ (tỷ đồng, 03 mục D)
A44: Khoản | B44: 2027 | C44: 2028 | D44: 2029 | E44: 2030 | F44: 2031
A45: Chi trang trại | B45: ='03_Định giá'!$C$81 -> 704.679 | C45: ='03_Định giá'!$C$105 -> 0 | D45: ='03_Định giá'!$C$129 -> 0 | E45: ='03_Định giá'!$C$153 -> 0 | F45: ='03_Định giá'!$C$177 -> 0
A46: Chi nhà máy | B46: ='03_Định giá'!$C$82 -> 0 | C46: ='03_Định giá'!$C$106 -> 355.9615 | D46: ='03_Định giá'!$C$130 -> 355.9615 | E46: ='03_Định giá'!$C$154 -> 0 | F46: ='03_Định giá'!$C$178 -> 0
A47: Lãi kế toán hai dự án | B47: ='03_Định giá'!$C$86 -> 27.65 | C47: ='03_Định giá'!$C$110 -> 63.3 | D47: ='03_Định giá'!$C$134 -> 63.3 | E47: ='03_Định giá'!$C$158 -> 108.3 | F47: ='03_Định giá'!$C$182 -> 108.3
A48: Dòng tiền trang trại + du lịch sau quỹ | B48: ='03_Định giá'!$C$87 -> -667.694 | C48: ='03_Định giá'!$C$111 -> 81.17 | D48: ='03_Định giá'!$C$135 -> 81.17 | E48: ='03_Định giá'!$C$159 -> 81.17 | F48: ='03_Định giá'!$C$183 -> 81.17
A49: Dòng tiền nhà máy sau quỹ | B49: ='03_Định giá'!$C$88 -> 0 | C49: ='03_Định giá'!$C$112 -> -355.9615 | D49: ='03_Định giá'!$C$136 -> -355.9615 | E49: ='03_Định giá'!$C$160 -> 40.5 | F49: ='03_Định giá'!$C$184 -> 40.5
A50: Sau 2031: dòng tiền đều thêm 20 năm (không tăng, không vĩnh viễn) — 03 mục B2
A52: E. THEO DÕI MỖI QUÝ — dự án đi đúng hay lệch
A53: Chỉ tiêu | B53: Xem ở đâu | E53: Tốt | F53: Xấu
A54: Xây dựng dở dang trang trại | B54: Thuyết minh xây dựng dở dang | E54: Chuyển sang tài sản cố định ~Q2/2027 | F54: Kéo dài, hoặc tổng vốn vượt 1.120 tỷ
A55: Tiền phát hành chi cho nhà máy | B55: Báo cáo sử dụng vốn (6 tháng/lần) | E55: Tăng — đã san lấp, xây hàng rào | F55: Đứng ở ~32 tỷ
A56: Tiền ròng | B56: Bảng cân đối | E56: Giảm đúng nhịp chi dự án | F56: Giảm nhanh hơn, hoặc bắt đầu vay
A57: Cổ tức | B57: Nghị quyết HĐQT, ĐHĐCĐ | E57: ≥ 50% LNST mà không phải vay | F57: Vay để trả cổ tức
A58: Bán cho Vinamilk | B58: Thuyết minh bên liên quan | E58: Ổn định | F58: Tiếp tục giảm (6T/2026 −8,6%)
A59: Đàn bò | B59: Thuyết minh tài sản sinh học | E59: Tăng mạnh 2026–2027 | F59: Đứng yên
A60: Biên lãi gộp | B60: Kết quả kinh doanh | E60: Tăng khi sữa trại mới vào Creamery (2027–2028) | F60: Sản lượng tăng mà biên không tăng
A61: Tiền thuê đất | B61: Thuyết minh thuế, phải nộp | E61: Rõ phần của dự án | F61: Tiếp tục tăng mạnh (6T/2026: 19,1 tỷ)
A62: Doanh thu du lịch hoặc "khác" | B62: Thuyết minh doanh thu | E62: Xuất hiện từ 2027 | F62: Không có
A64: F. CÒN THIẾU — chỉ công ty trả lời được
A65: 1. Giá MCM bán sữa tươi nguyên liệu cho Vinamilk và giá thu mua của nông hộ (đ/kg) — ĐHĐCĐ 2026 hỏi thẳng, công ty không nêu số.
A66: 2. Chi phí ra 1 lít sữa ở trại tập trung 2.000 con hiện có.
A67: 3. Toàn văn QĐ 2932/QĐ-UBND ngày 19/11/2025: vốn, giai đoạn, tiến độ nhà máy sau điều chỉnh.
A68: 4. 1.120 tỷ hiện gồm những gì; phần du lịch còn bao nhiêu; đã gồm tiền mua bò chưa.
A69: 5. Bò cho trại mới lấy từ đâu; 40,9 tỷ mua của Lao-Jagro là tài sản gì.
A70: 6. Sản lượng sữa nguyên liệu từng năm, chia trại tự có / nông hộ, bán Vinamilk / chế biến.
A71: 7. Tiền thuê 138 ha (QĐ 2126/QĐ-UBND 19/10/2023): đơn giá, trả hằng năm hay một lần.
