Workbook

Sheet 00_Tổng hợp
A1: MCM — GIỐNG BÒ SỮA MỘC CHÂU · ĐỊNH GIÁ: DCF LÕI + TIỀN + DỰ ÁN, BA KỊCH BẢN (KHÔNG XÁC SUẤT), BỐN PHƯƠNG PHÁP ĐỐI CHIẾU
A2: Bản 15/10/2026 · giá phiên 13/10/2026 · mỗi kịch bản = DCF lõi + (tiền − quỹ) × (1 − k) + dự án · không gán xác suất, giá trị hợp lý = kịch bản cơ sở
A3: Chữ xanh dương nền xanh lá = đầu vào · chữ đen = công thức · chữ xanh lá = lấy từ sheet khác · nền vàng = kết quả · nền cam = cảnh báo. Đơn vị tỷ đồng trừ khi ghi khác.
A5: CHỈ SỐ CHÍNH | B5: Giá thị trường (đồng) | C5: Giá trị cơ sở (đồng) | E5: Biên an toàn
B6: ='01_Số liệu gốc'!$B$11 -> 26600 | C6: =C16 -> 26693.757 | E6: ='03_Định giá'!$B$265 -> 0.0060694119
B7: ="Phiên "&'01_Số liệu gốc'!$B$12 -> Phiên 13/10/2026 | C7: ="DCF + (tiền − quỹ) × "&TEXT((1-'02_Giả định'!$B$26)*100,"0")&"% + dự án" -> DCF + (tiền − quỹ) × 90% + dự án | E7: (cơ sở − giá) ÷ (cơ sở − tiền)
A8: Tự kiểm số học (công thức, tổng, khớp DB) | B8: =IF(AND(OR(LEFT('01_Số liệu gốc'!$D$10,4)="KHỚP",LEFT('01_Số liệu gốc'!$D$10,3)="ĐẠT"),OR(LEFT('01_Số liệu gốc'!$I$36,4)="KHỚP",LEFT('01_Số liệu gốc'!$I$36,3)="ĐẠT"),OR(LEFT('01_Số liệu gốc'!$I$72,4)="KHỚP",LEFT('01_Số liệu gốc'!$I$72,3)="ĐẠT"),OR(LEFT('02_Giả định'!$C$24,4)="KHỚP",LEFT('02_Giả định'!$C$24,3)="ĐẠT"),OR(LEFT('02_Giả định'!$C$45,4)="KHỚP",LEFT('02_Giả định'!$C$45,3)="ĐẠT"),OR(LEFT('03_Định giá'!$H$259,4)="KHỚP",LEFT('03_Định giá'!$H$259,3)="ĐẠT"),OR(LEFT('05_Đối chiếu'!$C$26,4)="KHỚP",LEFT('05_Đối chiếu'!$C$26,3)="ĐẠT"),OR(LEFT('05_Đối chiếu'!$C$27,4)="KHỚP",LEFT('05_Đối chiếu'!$C$27,3)="ĐẠT"),LEFT('06_Dự án'!$G$21,3)="ĐẠT",LEFT('04_Độ nhạy'!$B$65,3)="ĐẠT"),"ĐẠT — 10 phép tự kiểm đều khớp","CÓ PHÉP KIỂM LỆCH — tìm ô báo LỆCH hoặc SAI ở từng sheet") -> ĐẠT — 10 phép tự kiểm đều khớp
A9: 1. KẾT QUẢ CHÍNH (đồng/cổ phiếu)
A10: Phương pháp | B10: Xấu | C10: Cơ sở | D10: Tốt | E10: Trọng số | F10: Ghi chú
A11: 1. P/E lợi nhuận lõi + tiền + dự án | B11: ='03_Định giá'!$B$221 -> 15602.83 | C11: ='03_Định giá'!$C$221 -> 27130.765 | D11: ='03_Định giá'!$D$221 -> 35934.576 | E11: ='02_Giả định'!$B$19 -> 0 | F11: Đối chiếu. Lõi × P/E (02), (tiền − quỹ) × (1 − k), cộng giá trị ròng dự án (06)
A12: 2. DCF phần lõi + tiền + dự án | B12: ='03_Định giá'!$B$239 -> 14575.268 | C12: ='03_Định giá'!$C$239 -> 26693.757 | D12: ='03_Định giá'!$D$239 -> 36657.749 | E12: ='02_Giả định'!$B$20 -> 1 | F12: DÙNG LÀM GIÁ TRỊ. Dòng tiền phần lõi ở r (02 mục A), cộng (tiền − quỹ) × (1 − k) và dự án
A13: 3. Chiết khấu cổ tức (DDM) | B13: ='03_Định giá'!$B$248 -> 8764.0522 | C13: ='03_Định giá'!$C$248 -> 22496.248 | D13: ='03_Định giá'!$D$248 -> 32689.631 | E13: ='02_Giả định'!$B$21 -> 0 | F13: Đối chiếu. Tạm ứng 2026 + cổ tức 2027–2031 theo chính sách, sau đó trả theo ROE
A14: 4. P/B theo ROE | B14: ='03_Định giá'!$B$230 -> 14239.967 | C14: ='03_Định giá'!$C$230 -> 18858.335 | D14: ='03_Định giá'!$D$230 -> 24631.295 | E14: ='02_Giả định'!$B$22 -> 0 | F14: Đối chiếu. ROE lịch sử, không qua động cơ lõi
A15: 5. EV/EBITDA lõi + tiền + dự án | B15: ='03_Định giá'!$B$226 -> 16868.762 | C15: ='03_Định giá'!$C$226 -> 27001.289 | D15: ='03_Định giá'!$D$226 -> 34389.28 | E15: ='02_Giả định'!$B$23 -> 0 | F15: Đối chiếu. EBITDA lõi × bội số (02), cộng (tiền − quỹ) × (1 − k) và dự án
A16: GIÁ TRỊ TỪNG KỊCH BẢN (= phương pháp 2) | B16: ='03_Định giá'!$B$256 -> 14575.268 | C16: ='03_Định giá'!$C$256 -> 26693.757 | D16: ='03_Định giá'!$D$256 -> 36657.749
A17: So giá hiện tại | B17: =B16/'01_Số liệu gốc'!$B$11-1 -> -0.45205758 | C17: =C16/'01_Số liệu gốc'!$B$11-1 -> 0.0035246887 | D17: =D16/'01_Số liệu gốc'!$B$11-1 -> 0.37811087
A18: Phần ngoài tiền (lõi + hai dự án) | B18: ='03_Định giá'!B261 -> 3328.9255 | C18: ='03_Định giá'!C261 -> 15447.414 | D18: ='03_Định giá'!D261 -> 25411.406 | F18: ="Tiền trừ quỹ, sau chiết khấu: "&TEXT('03_Định giá'!$B$260,"#,##0")&" đ/cp — như nhau ở ba kịch bản" -> Tiền trừ quỹ, sau chiết khấu: 11,246 đ/cp — như nhau ở ba kịch bản
A20: Giá thị trường (đồng) | B20: ='01_Số liệu gốc'!$B$11 -> 26600 | F20: ="Phiên "&'01_Số liệu gốc'!$B$12 -> Phiên 13/10/2026
A21: GIÁ TRỊ CƠ SỞ (đồng/cổ phiếu) | B21: ='03_Định giá'!$C$256 -> 26693.757 | F21: Con số trung tâm, không gán xác suất
A22: Biên an toàn trên phần ngoài tiền = (cơ sở − giá) ÷ (cơ sở − tiền) | B22: ='03_Định giá'!$B$265 -> 0.0060694119
A23: Tỷ lệ lên/xuống = (tốt − giá) ÷ (giá − xấu) | B23: ='03_Định giá'!$B$266 -> 0.83642191 | F23: Dưới 1: phần có thể mất lớn hơn phần có thể được
A24: Độ phân tán năm phương pháp (cơ sở, cao ÷ thấp) | B24: ='03_Định giá'!$C$257 -> 1.4386618 | F24: Trên 1,5x: xem vì sao các phương pháp đối chiếu lệch xa DCF
A26: 2. BIỂU ĐỒ — giá trị từng phương pháp (kịch bản cơ sở) so với giá
A46: 3. NHỮNG CON SỐ PHẢI NHỚ TRƯỚC KHI NHÌN MCM
A47: Tiền ròng 30/06/2026 mỗi cổ phiếu (đồng) | B47: ='03_Định giá'!$C$215 -> 12713.973 | C47: Gần một nửa giá cổ phiếu là tiền gửi — câu hỏi là tiền này về cổ đông hay vào dự án · Tính vào giá trị: (tiền − quỹ khen thưởng phúc lợi) × 90%, xem 03 dòng tiền trừ quỹ
A48: Giá trị ròng hai dự án, cơ sở (đồng/cp) | B48: ='03_Định giá'!$C$208 -> -1386.6315 | C48: Âm: phần còn phải chi sinh lời dưới lợi suất dự án — chi tiết 06, giá × chi phí ở 04 bảng 2
A49: Tiền ròng thấp nhất 2027–2031, cơ sở (tỷ) | B49: ='03_Định giá'!$C$199 -> 323.73986 | C49: Cổ tức cơ sở và chi cả hai dự án. Âm = phải vay
A50: Lợi suất yêu cầu phần kinh doanh (r) | B50: ='02_Giả định'!$B$10 -> 0.11224 | C50: Rf 4,6% + β 0,72 × ERP 9,2% (02 mục A)
A51: Lợi suất ngầm định ở giá hiện tại (phần kinh doanh) | B51: ='05_Đối chiếu'!$B$23 -> 0.11633829 | C51: Thấp hơn r = thị trường trả đắt hơn lợi suất yêu cầu (05 mục B)
A52: Lợi suất kỳ vọng cả cổ phiếu nếu mua ở giá hiện tại | B52: ='05_Đối chiếu'!$B$24 -> 0.084821838 | C52: ="So lãi gửi tham chiếu "&TEXT('02_Giả định'!$B$17*100,"0.0")&"% (khoản lớn, thực nhận)" -> So lãi gửi tham chiếu 9.0% (khoản lớn, thực nhận)
A53: LNST Q3/2026 dự báo (tỷ) — mốc kiểm cuối tháng 10 | B53: ='02_Giả định'!$B$56 -> 48.16472 | C53: Ngoài dải ở 05 mục F thì xem lại B và chi phí bán hàng
A55: 4. TIỀN ĐI ĐÂU 2027–2031 — kịch bản cơ sở (tỷ đồng, 03 mục D)
A56: Khoản | B56: 2027 | C56: 2028 | D56: 2029 | E56: 2030 | F56: 2031
A57: Chi dự án | B57: ='03_Định giá'!$C$88 -> 704.679 | C57: ='03_Định giá'!$C$112 -> 355.9615 | D57: ='03_Định giá'!$C$136 -> 355.9615 | E57: ='03_Định giá'!$C$160 -> 0 | F57: ='03_Định giá'!$C$184 -> 0
A58: Cổ tức tiền mặt | B58: ='03_Định giá'!$C$98 -> 165 | C58: ='03_Định giá'!$C$122 -> 165 | D58: ='03_Định giá'!$C$146 -> 165 | E58: ='03_Định giá'!$C$170 -> 165 | F58: ='03_Định giá'!$C$194 -> 165
A59: LNST (cả lãi tiền gửi/vay) | B59: ='03_Định giá'!$C$97 -> 301.42239 | C59: ='03_Định giá'!$C$121 -> 307.49428 | D59: ='03_Định giá'!$C$145 -> 298.71716 | E59: ='03_Định giá'!$C$169 -> 334.60722 | F59: ='03_Định giá'!$C$193 -> 352.9778
A60: TIỀN RÒNG CUỐI NĂM | B60: ='03_Định giá'!$C$100 -> 796.84887 | C60: ='03_Định giá'!$C$124 -> 564.40172 | D60: ='03_Định giá'!$C$148 -> 323.73986 | E60: ='03_Định giá'!$C$172 -> 471.01577 | F60: ='03_Định giá'!$C$196 -> 634.49068
A61: Bắt đầu từ 1.398,5 tỷ ngày 30/06/2026. Cổ tức cơ sở và lãi tiền gửi theo 02 mục C.
A63: 5. CHƯA CÓ SỐ CÔNG BỐ — câu hỏi còn mở ở 06 mục F
A64: 1. Giá bán sữa nguyên liệu cho Vinamilk và giá thu mua nông hộ không công bố — mV 10% là ước của người viết (12/10/2026), giá sữa trang trại là tự đặt.
A65: 2. Chi phí mỗi lít ở trại tập trung (10.500 cả ba kịch bản, 04 bảng 5); lãi du lịch; lãi tăng thêm của nhà máy (tăng dần 45 → 90 tỷ, đầy công suất 2038) — tự đặt (06).
A66: 3. Nhà máy: nội dung QĐ 2932/QĐ-UBND 19/11/2025; 18% mặt bằng còn vướng; tiền chi mới ~32 tỷ.
A67: 4. Trang trại: 1.120 tỷ gồm những gì sau khi thu nhỏ du lịch; nguồn bò; 40,9 tỷ mua của Lao-Jagro.
A68: 5. Doanh thu theo nhóm 6T/2026 không công bố: Creamery đóng góp bao nhiêu chưa đo được (ĐHĐCĐ: 5–6%).
A69: 6. BCTC Q3/2026 (cuối tháng 10): nhập LNST vào 05 mục F; xem dở dang trang trại, tiền thuê đất.
A71: 6. MỤC LỤC — bấm tên sheet để đi tới
A72: 01_Số liệu gốc | B72: Dữ kiện: cổ phiếu, kết quả năm và quý, cân đối, doanh thu theo nhóm và bán cho Vinamilk, ROE, dự án
A73: 02_Giả định | B73: Nhận định: lợi suất yêu cầu (β, ERP), động cơ lõi hiệu chỉnh trên 12 tháng, ba kịch bản, cổ tức
A74: 03_Định giá | B74: Lợi nhuận lõi, dòng tiền 2027–2031 (lõi, dự án, tiền), năm phương pháp × ba kịch bản, 16 cột phép thử
A75: 04_Độ nhạy | B75: B × chi phí bán hàng, giá × chi phí mỗi lít trang trại, ROE × r, mười chín phép thử một biến
A76: 05_Đối chiếu | B76: Bội số, giá đang ngầm định gì (cả lợi suất), hai đường tới ROE, nhóm so sánh, file QNS, mốc Q3
A77: 06_Dự án | B77: Hai dự án: giả định trang trại (bò sữa, du lịch), nhà máy; kết quả, hòa vốn, theo dõi quý, hỏi công ty
A79: 7. CHÚ GIẢI THUẬT NGỮ
A80: Lợi nhuận lõi (EBIT lõi) | B80: Lãi gộp − chi phí bán hàng − chi phí quản lý: không gồm lãi tiền gửi
A81: V | B81: Doanh thu bán cho Vinamilk: sữa nguyên liệu bán thô + gia công
A82: B | B82: Phần còn lại: sữa thương hiệu Mộc Châu, thức ăn chăn nuôi, khác — gánh toàn bộ khuyến mãi
A83: Năm chuẩn hoá | B83: Một năm 'bình thường' ~2027 trước khi dự án có lãi — không phải dự phóng năm cụ thể
A84: Giá trị ròng dự án | B84: Hiện giá dòng tiền dự án (2027–2031 + đuôi: trang trại 20 năm đều, nhà máy tăng dần tới năm đầy công suất rồi vĩnh viễn) − hiện giá vốn CÒN phải chi, ở lợi suất dự án (phần đã chi là chi phí chìm)
A85: Lợi suất yêu cầu | B85: Rf + β × ERP (cách rút gọn của công ty chứng khoán); β đã bỏ phần tiền
A86: P/B hợp lý | B86: (ROE − g) ÷ (r − g): ROE thấp hơn r thì đáng giá dưới sổ sách
A87: DDM | B87: Chiết khấu cổ tức: giá trị = hiện giá cổ tức cổ đông thực nhận
A88: Biên an toàn | B88: (giá trị cơ sở − giá) ÷ (giá trị cơ sở − tiền): chỉ đo trên phần kinh doanh và dự án
A89: Giá trị kịch bản | B89: Mỗi kịch bản = DCF lõi + (tiền ròng − quỹ) × (1 − k) + giá trị ròng dự án. Không gán xác suất
A90: k | B90: Phần tiền ròng không tính vào giá trị: cổ đông thiểu số có thể không nhận đủ (Vinamilk 68% quyết chia). 10% (02 ô B26)
A91: ROIC trạng thái dừng | B91: Lợi nhuận trên vốn giữ được mãi sau năm 5 — quyết định phần lợi nhuận phải giữ lại để tăng trưởng g (= g ÷ ROIC). 17,1% (02 mục B)
A188: Dữ liệu biểu đồ (đừng xoá)
A189: Phương pháp | B189: P/E lõi | C189: DCF | D189: Cổ tức | E189: P/B-ROE | F189: EV/EBITDA | G189: Giá trị cơ sở
A190: Giá trị (cơ sở) | B190: =C11 -> 27130.765 | C190: =C12 -> 26693.757 | D190: =C13 -> 22496.248 | E190: =C14 -> 18858.335 | F190: =C15 -> 27001.289 | G190: =C16 -> 26693.757
A191: Giá thị trường | B191: =$B$20 -> 26600 | C191: =$B$20 -> 26600 | D191: =$B$20 -> 26600 | E191: =$B$20 -> 26600 | F191: =$B$20 -> 26600 | G191: =$B$20 -> 26600

Sheet 01_Số liệu gốc
A1: MCM — SỐ LIỆU GỐC
A2: Mọi số ở đây là DỮ KIỆN (báo cáo tài chính, thuyết minh, BCTN, giá). Nhận định nằm ở 02_Giả định. Nền xanh lá chữ xanh dương = số nhập tay; nền vàng = công thức. Đơn vị tỷ đồng trừ khi ghi khác. Số DB kéo ngày 12/10/2026. MCM không có công ty con: BCTC riêng là BCTC duy nhất. Bảng cân đối 30/06/2026 khớp BCTC bán niên soát xét (KPMG, 11/08/2026).
A4: A. CỔ PHIẾU VÀ GIÁ
A5: Chỉ tiêu | B5: Giá trị | C5: Đơn vị | D5: Nguồn / ghi chú
A6: Cổ phiếu đã phát hành | B6: 110 | C6: triệu cổ phiếu | D6: Thuyết minh 21 BCTC 2025: 110.000.000; không đổi đến 30/06/2026
A7: Cổ phiếu quỹ | B7: 0 | C7: triệu cổ phiếu | D7: BCTC 2025 TM 21: số đang lưu hành = số phát hành
A8: CỔ PHIẾU LƯU HÀNH | B8: =B6-B7 -> 110 | C8: triệu cổ phiếu
A9: Kiểm chéo: vốn góp trong DB (GEN_BS_097) 30/06/2026 | B9: 1100 | C9: tỷ đồng | D9: gen_balance_sheet quý 2/2026
A10: → số cổ phiếu suy từ vốn góp | B10: =B9/10 -> 110 | C10: triệu cổ phiếu | D10: =IF(ABS(B10-B6)<0.001,"KHỚP cổ phiếu đã phát hành","LỆCH") -> KHỚP cổ phiếu đã phát hành
A11: Giá cổ phiếu | B11: 26600 | C11: đồng | D11: daily_price, giá đóng cửa
A12: Ngày giá | B12: 13/10/2026
A13: Cao nhất 52 tuần (giá điều chỉnh cổ tức) | B13: 29400 | C13: đồng | D13: daily_price.adjusted_close
A14: Thấp nhất 52 tuần (giá điều chỉnh cổ tức) | B14: 23744 | C14: đồng | D14: daily_price.adjusted_close
A15: Giá trị giao dịch bình quân 30 phiên | B15: 520.4 | C15: triệu đồng/phiên | D15: daily_price (giá × khối lượng). RẤT THẤP: Vinamilk và Tổng Công ty Chăn nuôi nắm 68,15%
A16: Vốn hoá thị trường | B16: =B11*B8/1000 -> 2926 | C16: tỷ đồng | D16: giá × cổ phiếu lưu hành
A18: B. KẾT QUẢ KINH DOANH THEO NĂM (PostgreSQL, tỷ đồng)
A19: Khoản mục | B19: 2021 | C19: 2022 | D19: 2023 | E19: 2024 | F19: 2025 | I19: Mã khoản mục / ghi chú
A20: Doanh thu thuần | B20: 2925.664 | C20: 3133.099 | D20: 3135.423 | E20: 2916.958 | F20: 2834.874 | I20: GEN_IS_003
A21: Lãi gộp | B21: 898.503 | C21: 1017.789 | D21: 1008.618 | E21: 848.545 | F21: 796.98 | I21: GEN_IS_021
A22: Chi phí bán hàng | B22: 594.259 | C22: 688.742 | D22: 708.879 | E22: 657.046 | F22: 606.614 | I22: GEN_IS_011
A23: Chi phí quản lý doanh nghiệp | B23: 36.609 | C23: 39.603 | D23: 37.898 | E23: 37.145 | F23: 38.071 | I23: GEN_IS_012
A24: LỢI NHUẬN LÕI (EBIT lõi) = lãi gộp − bán hàng − quản lý | B24: =B21-B22-B23 -> 267.635 | C24: =C21-C22-C23 -> 289.444 | D24: =D21-D22-D23 -> 261.841 | E24: =E21-E22-E23 -> 154.354 | F24: =F21-F22-F23 -> 152.295 | I24: Không gồm lãi tiền gửi — phần đó cộng riêng bằng số dư tiền ở mọi phương pháp
A25: Doanh thu hoạt động tài chính (gần hết là lãi tiền gửi) | B25: 95.419 | C25: 103.156 | D25: 162.315 | E25: 101.252 | F25: 103.916 | I25: GEN_IS_004
A26: Chi phí tài chính | B26: 0.5 | C26: 0.996 | D26: 0.881 | E26: 1.898 | F26: 6.004 | I26: GEN_IS_014
A27: trong đó: chi phí lãi vay | B27: 0.163 | C27: 0.636 | D27: 0 | E27: 1.732 | F27: 5.706 | I27: GEN_IS_015
A28: Lợi nhuận khác (thu nhập khác − chi phí khác) | B28: -8.796 | C28: -10.917 | D28: 0.305 | E28: -1.652 | F28: -1.673 | I28: GEN_IS_005−017
A29: Lợi nhuận trước thuế | B29: 353.758 | C29: 380.687 | D29: 423.58 | E29: 252.057 | F29: 248.534 | I29: GEN_IS_027
A30: Thuế thu nhập doanh nghiệp | B30: 34.646 | C30: 34.138 | D30: 49.162 | E30: 32.136 | F30: 32.82 | I30: GEN_IS_006+007
A31: LỢI NHUẬN SAU THUẾ | B31: 319.112 | C31: 346.549 | D31: 374.417 | E31: 219.921 | F31: 215.714 | I31: GEN_IS_020
A32: Khấu hao tài sản cố định | B32: 49.922 | C32: 54.459 | D32: 62.041 | E32: 67.01 | F32: 68.763 | I32: GEN_CF_001
A33: Lưu chuyển tiền thuần từ hoạt động kinh doanh | B33: 230.26 | C33: 268.493 | D33: 287.49 | E33: 196.059 | F33: 180.854 | I33: GEN_CF_026
A34: Chi mua sắm, xây dựng tài sản cố định (âm = tiền ra) | B34: -151.349 | C34: -139.443 | D34: -246.393 | E34: -93.478 | F34: -174.152 | I34: GEN_CF_027
A35: Cổ tức tiền mặt đã trả (âm = tiền ra) | B35: -309.016 | C35: -274.948 | D35: -220.105 | E35: -220 | F35: -220 | I35: GEN_CF_040
A36: Kiểm: lõi + doanh thu tài chính − chi phí tài chính + khác − LNTT | B36: =B24+B25-B26+B28-B29 -> 0 | C36: =C24+C25-C26+C28-C29 -> 0 | D36: =D24+D25-D26+D28-D29 -> 0 | E36: =E24+E25-E26+E28-E29 -> -0.001 | F36: =F24+F25-F26+F28-F29 -> 0 | I36: =IF(MAX(ABS(B36),ABS(C36),ABS(D36),ABS(E36),ABS(F36))<0.5,"KHỚP (dung sai 0,5 tỷ — làm tròn DB)","LỆCH") -> KHỚP (dung sai 0,5 tỷ — làm tròn DB)
A37: Thuế suất thực tế = thuế ÷ lợi nhuận trước thuế | B37: =B30/B29 -> 0.097937008 | C37: =C30/C29 -> 0.08967472 | D37: =D30/D29 -> 0.11606308 | E37: =E30/E29 -> 0.12749497 | F37: =F30/F29 -> 0.13205437 | I37: Thuế suất phổ thông 20%. Thu nhập chăn nuôi, chế biến nông sản ở địa bàn đặc biệt khó khăn được miễn (TM 34 BCTC 2025, Nghị định 320/2025): 2025 miễn 18,0 tỷ tiền thuế
A38: Doanh thu tài chính ÷ lợi nhuận trước thuế | B38: =B25/B29 -> 0.26972959 | C38: =C25/C29 -> 0.27097327 | D38: =D25/D29 -> 0.38319798 | E38: =E25/E29 -> 0.40170279 | F38: =F25/F29 -> 0.41811583 | I38: Lãi tiền gửi từ 27% (2021) lên 42% LNTT (2025): lợi nhuận lõi giảm, tiền gửi đứng yên
A40: C. THEO QUÝ (PostgreSQL, tỷ đồng) — cột H = 12 tháng tới Q2/2026 = năm 2025 kiểm toán − 6T/2025 + 6T/2026
A41: Khoản mục | B41: Q1/2025 | C41: Q2/2025 | D41: Q3/2025 | E41: Q4/2025 | F41: Q1/2026 | G41: Q2/2026 | H41: 12 tháng | I41: Mã khoản mục / ghi chú
A42: Doanh thu thuần | B42: 591.151 | C42: 808.709 | D42: 716.234 | E42: 721.2 | F42: 741.55 | G42: 760.454 | H42: =F20-B42-C42+F42+G42 -> 2937.018 | I42: Từ 2026 áp dụng Thông tư 99: bán bò chuyển từ thu nhập khác sang doanh thu; số cùng kỳ 2025 trong BCTC 2026 đã trình bày lại (lệch DB ~1 tỷ/quý, không đổi LNTT)
A43: Lãi gộp | B43: 145.482 | C43: 236.99 | D43: 202.187 | E43: 209.543 | F43: 212.414 | G43: 235.899 | H43: =F21-B43-C43+F43+G43 -> 862.821 | I43: GEN_IS_021. Cột H lấy năm 2025 kiểm toán làm gốc: cộng thẳng bốn quý 2025 trong DB thiếu 2,8 tỷ lãi gộp so BCTC năm
A44: Chi phí bán hàng | B44: 102.323 | C44: 169.006 | D44: 182.058 | E44: 153.227 | F44: 138.014 | G44: 156.079 | H44: =F22-B44-C44+F44+G44 -> 629.378 | I44: Q3 thường là quý chi khuyến mãi nặng nhất (Q3/2025: 182 tỷ, LNST chỉ 28 tỷ)
A45: Chi phí quản lý doanh nghiệp | B45: 10.348 | C45: 8.972 | D45: 8.248 | E45: 10.503 | F45: 9.32 | G45: 9.662 | H45: =F23-B45-C45+F45+G45 -> 37.733 | I45: GEN_IS_012
A46: LỢI NHUẬN LÕI (EBIT lõi) | B46: =B43-B44-B45 -> 32.811 | C46: =C43-C44-C45 -> 59.012 | D46: =D43-D44-D45 -> 11.881 | E46: =E43-E44-E45 -> 45.813 | F46: =F43-F44-F45 -> 65.08 | G46: =G43-G44-G45 -> 70.158 | H46: =H43-H44-H45 -> 195.71
A47: Doanh thu hoạt động tài chính | B47: 24.493 | C47: 27.659 | D47: 25.932 | E47: 25.833 | F47: 25.326 | G47: 27.979 | H47: =F25-B47-C47+F47+G47 -> 105.069 | I47: GEN_IS_004
A48: Chi phí lãi vay | B48: 1.166 | C48: 1.981 | D48: 1.692 | E48: 0.868 | F48: 0.341 | G48: 0 | H48: =F27-B48-C48+F48+G48 -> 2.9 | I48: GEN_IS_015
A49: Lợi nhuận trước thuế | B49: 54.673 | C49: 86.523 | D49: 34.45 | E49: 72.887 | F49: 90.097 | G49: 98.145 | H49: =F29-B49-C49+F49+G49 -> 295.58 | I49: GEN_IS_027
A50: Thuế thu nhập doanh nghiệp | B50: 6.905 | C50: 10.781 | D50: 6.386 | E50: 8.748 | F50: 9.978 | G50: 9.638 | H50: =F30-B50-C50+F50+G50 -> 34.75 | I50: GEN_IS_006+007
A51: LỢI NHUẬN SAU THUẾ | B51: 47.768 | C51: 75.742 | D51: 28.064 | E51: 64.139 | F51: 80.119 | G51: 88.507 | H51: =F31-B51-C51+F51+G51 -> 260.83 | I51: GEN_IS_020
A52: Khấu hao tài sản cố định | B52: 16.928 | C52: 17.224 | D52: 17.335 | E52: 17.276 | F52: 17.744 | G52: 17.71 | H52: =F32-B52-C52+F52+G52 -> 70.065 | I52: GEN_CF_001
A53: Lưu chuyển tiền thuần từ hoạt động kinh doanh | B53: -9.669 | C53: 56.28 | D53: 136.873 | E53: -0.112 | F53: 1.69 | G53: 96.414 | H53: =F33-B53-C53+F53+G53 -> 232.347 | I53: GEN_CF_026
A54: Chi mua sắm, xây dựng tài sản cố định (âm = tiền ra) | B54: -55.521 | C54: -38.423 | D54: -62.847 | E54: -17.36 | F54: -67.533 | G54: -52.733 | H54: =F34-B54-C54+F54+G54 -> -200.474 | I54: GEN_CF_027
A56: D. BẢNG CÂN ĐỐI VÀ THUYẾT MINH (tỷ đồng)
A57: Khoản mục | B57: 31/12/2025 | C57: 30/06/2026 | I57: Nguồn / ghi chú
A58: Tiền và tương đương tiền | B58: 36.951 | C58: 68.747 | I58: GEN_BS_002
A59: Tiền gửi có kỳ hạn ngắn hạn (đầu tư giữ đến ngày đáo hạn) | B59: 1485.127 | C59: 1329.79 | I59: GEN_BS_005 — số 31/12/2025 là số ĐÃ PHÂN LOẠI LẠI theo Thông tư 99 (BCTC Q2/2026): gồm 54,1 tỷ lãi dự thu; BCTC 2025 gốc ghi 1.431,0
A60: Tiền gửi có kỳ hạn dài hạn | B60: 25 | C60: 0 | I60: GEN_BS_057 — TM 5 BCTC 2025: lãi suất 4,75%–8,2%/năm, không thấy cầm cố
A61: Vay ngắn hạn | B61: 67 | C61: 0 | I61: Vietcombank, VietinBank 4–6 tháng, không tài sản đảm bảo; trả hết 6T/2026
A62: Vay dài hạn | B62: 0 | C62: 0 | I62: GEN_BS_089
A63: TIỀN + TIỀN GỬI | B63: =B58+B59+B60 -> 1547.078 | C63: =C58+C59+C60 -> 1398.537 | I63: Gồm lãi dự thu (Thông tư 99). Khoản tiền còn lại của đợt phát hành 2021 dành cho hai dự án: 685,0 tỷ cuối 2025 (mục G)
A64: Tổng nợ vay | B64: =B61+B62 -> 67 | C64: =C61+C62 -> 0
A65: TIỀN RÒNG = tiền + tiền gửi − nợ vay | B65: =B63-B64 -> 1480.078 | C65: =C63-C64 -> 1398.537 | I65: Dùng 30/06/2026 ở mọi phương pháp. Cổ tức đợt 1/2026 (1.000đ/cp, thường chi tháng 11) chưa trừ — nằm trong lợi nhuận năm 2026
A66: Quỹ khen thưởng, phúc lợi (nợ phải trả) | B66: 23.951 | C66: 23.984 | I66: GEN_BS_118 (DB). Tiền đã trích cho người lao động, không thuộc cổ đông — trừ khỏi tiền ròng khi định giá, cùng chịu chiết khấu k (02 mục A). Thêm 14/10/2026
A67: VỐN CHỦ SỞ HỮU | B67: 2279.326 | C67: 2321.089 | I67: GEN_BS_095 — không có cổ đông thiểu số
A68: Xây dựng dở dang: tổ hợp trang trại bò sữa 4.000 con | B68: 311.599 | C68: 415.321 | I68: TM 15 BCTC bán niên soát xét 2026 (tổng 459,3 khớp bảng cân đối); cột 31/12/2025 = TM 12 BCTC 2025
A69: Xây dựng dở dang: nhà máy sữa công nghệ cao | B69: 31.077 | C69: 31.077 | I69: TM 15 BCTC bán niên soát xét 2026 (tổng 459,3 khớp bảng cân đối); cột 31/12/2025 = TM 12 BCTC 2025
A70: Xây dựng dở dang: máy móc, công trình khác | B70: 12.23 | C70: 12.919 | I70: TM 15 BCTC bán niên soát xét 2026 (tổng 459,3 khớp bảng cân đối); cột 31/12/2025 = TM 12 BCTC 2025
A71: Tổng xây dựng dở dang | B71: =SUM(B68:B70) -> 354.906 | C71: =SUM(C68:C70) -> 459.317
A72: Kiểm chéo: xây dựng dở dang trong DB (GEN_BS_051) | B72: 354.906 | C72: 459.317 | I72: =IF(AND(ABS(B72-B71)<0.01,ABS(C72-C71)<0.01),"KHỚP thuyết minh","LỆCH") -> KHỚP thuyết minh
A73: VỐN HOẠT ĐỘNG LÕI = vốn chủ − tiền ròng − xây dựng dở dang | B73: =B67-B65-B71 -> 444.342 | C73: =C67-C65-C71 -> 463.235 | I73: Phần vốn thực sự làm ra lợi nhuận lõi — chỉ ~460 tỷ vì nhà máy cũ đã khấu hao gần hết (610,7 tỷ nguyên giá khấu hao hết vẫn dùng, TM 10 BCTC 2025)
A74: GIÁ TRỊ SỔ SÁCH MỖI CỔ PHIẾU 30/06/2026 (đồng) | C74: =C67*1000/B8 -> 21100.809
A76: E. DOANH THU THEO NHÓM VÀ BÁN CHO VINAMILK (BCTN, thuyết minh bên liên quan — DB không có)
A77: Chỉ tiêu | B77: 2023 | C77: 2024 | D77: 2025 | E77: 6T/2025 | F77: 6T/2026 | I77: Nguồn / ghi chú
A78: Sữa thành phẩm (thương hiệu Mộc Châu) | B78: 2272.8 | C78: 1899.5 | D78: 1722.4
A79: Sữa nguyên liệu (bán thô) | B79: 425.3 | C79: 572.6 | D79: 615.1
A80: Thức ăn chăn nuôi và TMR | B80: 412.5 | C80: 418 | D80: 424.4
A81: Gia công (sữa thanh trùng hộp giấy cho Vinamilk) | B81: 0 | C81: 0 | D81: 48.1
A82: Nhóm khác | B82: 24.9 | C82: 26.8 | D82: 24.8
A83: Cộng theo nhóm (kiểm với doanh thu thuần) | B83: =SUM(B78:B82) -> 3135.5 | C83: =SUM(C78:C82) -> 2916.9 | D83: =SUM(D78:D82) -> 2834.8 | I83: BCTN 2025 tr.68; BCTN 2024 tr.59. Công ty không công bố số 6 tháng theo nhóm
A84: Doanh thu thuần (mục B, C) | B84: =D20 -> 3135.423 | C84: =E20 -> 2916.958 | D84: =F20 -> 2834.874 | E84: =B42+C42 -> 1399.86 | F84: =F42+G42 -> 1502.004
A85: V = Bán hàng cho Vinamilk (công ty mẹ cấp cao nhất) | B85: 425.3 | C85: 572.83 | D85: 668.088 | E85: 358.324 | F85: 327.441 | I85: TM bên liên quan: 2025 bán hàng hóa 668,08 tỷ (TM 36 BCTC 2025); 2024 572,62 + dịch vụ 0,21; 6T/2026 = 327,44 theo TM 39 BCTC bán niên SOÁT XÉT (bản Q2 tự lập ghi 327,41). ≈ sữa nguyên liệu + gia công. Q1/2025 168,2; Q1/2026 183,7 (BCTC quý 1)
A86: B = Phần còn lại = doanh thu − V (thương hiệu + thức ăn chăn nuôi + khác) | B86: =B84-B85 -> 2710.123 | C86: =C84-C85 -> 2344.128 | D86: =D84-D85 -> 2166.786 | E86: =E84-E85 -> 1041.536 | F86: =F84-F85 -> 1174.563 | I86: Gánh toàn bộ chi phí bán hàng (khuyến mãi, quảng cáo cho hàng thương hiệu)
A87: Lãi gộp | B87: =D21 -> 1008.618 | C87: =E21 -> 848.545 | D87: =F21 -> 796.98 | E87: =B43+C43 -> 382.472 | F87: =F43+G43 -> 448.313
A88: Chi phí bán hàng | B88: =D22 -> 708.879 | C88: =E22 -> 657.046 | D88: =F22 -> 606.614 | E88: =B44+C44 -> 271.329 | F88: =F44+G44 -> 294.093
A89: Tỷ trọng bán cho Vinamilk trong doanh thu | B89: =B85/B84 -> 0.13564358 | C89: =C85/C84 -> 0.19637924 | D89: =D85/D84 -> 0.23566762 | E89: =E85/E84 -> 0.25597131 | F89: =F85/F84 -> 0.21800275
A90: B 6T/2026 so 6T/2025 | F90: =F86/E86-1 -> 0.12772194 | I90: Sau hai năm giảm (sữa thành phẩm 2.273 → 1.722 tỷ), phần còn lại tăng lại từ Q1/2026
A92: F. LỊCH SỬ ROE 2018–2025 (ROE = LNST ÷ vốn chủ bình quân đầu và cuối năm)
A93: Năm | B93: Vốn chủ cuối năm | C93: LNST | D93: Vốn chủ bình quân | E93: ROE | I93: Ghi chú
A94: 2017 | B94: 766.782
A95: 2018 | B95: 767.852 | C95: 180.641 | D95: =(B94+B95)/2 -> 767.317 | E95: =C95/D95 -> 0.235419
A96: 2019 | B96: 726.74 | C96: 166.942 | D96: =(B95+B96)/2 -> 747.296 | E96: =C96/D96 -> 0.22339475
A97: 2020 | B97: 911.91 | C97: 280.735 | D97: =(B96+B97)/2 -> 819.325 | E97: =C97/D97 -> 0.34264181 | I97: Năm Vinamilk vào điều hành (mua lại qua Tổng Công ty Chăn nuôi)
A98: 2021 | B98: 2173.385 | C98: =B31 -> 319.112 | D98: =(B97+B98)/2 -> 1542.6475 | E98: =C98/D98 -> 0.20685996 | I98: Phát hành 43,2 triệu cổ phiếu thu 1.249,3 tỷ → vốn chủ gấp đôi, tiền gửi phình
A99: 2022 | B99: 2210.279 | C99: =C31 -> 346.549 | D99: =(B98+B99)/2 -> 2191.832 | E99: =C99/D99 -> 0.15810929
A100: 2023 | B100: 2327.255 | C100: =D31 -> 374.417 | D100: =(B99+B100)/2 -> 2268.767 | E100: =C100/D100 -> 0.16503105
A101: 2024 | B101: 2305.184 | C101: =E31 -> 219.921 | D101: =(B100+B101)/2 -> 2316.2195 | E101: =C101/D101 -> 0.094948255 | I101: LNST −41%: giá thu mua sữa tăng 7–8%, sức mua yếu (KBSV)
A102: 2025 | B102: 2279.326 | C102: =F31 -> 215.714 | D102: =(B101+B102)/2 -> 2292.255 | E102: =C102/D102 -> 0.094105586 | I102: Đáy: sữa thành phẩm −9,3%
A103: ROE 12 tháng tới Q2/2026 (vốn chủ bình quân 30/06/2025 và 30/06/2026) | E103: =H51/AVERAGE(2306.343,C67) -> 0.11273207
A104: ROE bình quân 2022–2025 (sau đợt phát hành, tiền gửi lớn) | E104: =AVERAGE(E99:E102) -> 0.12804855 | I104: Trước 2021 vốn chủ chỉ ~770 tỷ nên ROE 20%+; sau đợt phát hành ~43% tài sản là tiền gửi lãi 5–8% → ROE bị kéo về ~10–16%
A105: ROE bình quân 2018–2025 | E105: =AVERAGE(E95:E102) -> 0.19006371
A106: ROE trung vị 2018–2025 | E106: =MEDIAN(E95:E102) -> 0.1859455
...

Sheet 02_Giả định
A1: MCM — GIẢ ĐỊNH (bản 15/10/2026: ba kịch bản, không xác suất)
A2: Ô nền xanh lá chữ xanh dương là NHẬN ĐỊNH — sửa là cả model chạy lại. Cột 'Mốc thực tế' lấy thẳng từ 01 để thấy giả định đặt ở đâu so với số thật. Giả định hai dự án nằm ở 06_Dự án.
A4: A. THAM SỐ CHUNG — lợi suất yêu cầu, thuế lãi tiền gửi, trọng số, chiết khấu tiền
A5: Tham số | B5: Giá trị | F5: Căn cứ
A6: Lợi suất phi rủi ro (Rf) | B6: 0.046 | F6: Khung chung của người viết. Trái phiếu Chính phủ 10 năm trúng thầu 4,43% đầu tháng 10/2026 — trong ngưỡng ±0,5 điểm, chưa đổi
A7: Phần bù rủi ro thị trường (ERP) — cách rút gọn của công ty chứng khoán | B7: 0.092 | F7: Chốt 12/10/2026: dùng như VNDirect, VDSC. VNDirect BSR 17/08/2026: 9,2% (Rf 4,3%); VDSC GDA 07/04/2026: 10% (mức cho doanh nghiệp chu kỳ → cận trên, phép thử T5); Kafi PVS 9,63%; MBS VCB 8,5%; KBSV MCM 8% (β 1 → 12%). Damodaran 07/2026 cho Việt Nam 7,92% (4,20% + rủi ro quốc gia 3,72%)
A8: β phần kinh doanh hiện tại (đã bỏ phần tiền) | B8: 0.72 | F8: Chốt 12/10/2026. VNM: Blume 0,644 (thô tuần 5 năm 0,469) ÷ (1 − tiền ròng bình quân 5 năm 11%) = 0,72. MCM tự tính, bỏ tiền TỪNG TUẦN (tiền bình quân 40% vốn hóa): 0,70 (tuần 5 năm, CI 0,50–0,91), 0,76 (tuần 2 năm); Dimson trễ 1 tuần −0,03 → ít giao dịch không làm méo. Phép thử T6 (0,85), T14 (0,65)
A9: β hai dự án mới | B9: 0.85 | F9: TỰ ĐẶT. Dự án làm chi phí cố định tăng (khấu hao trang trại ~40 tỷ + nhà máy ~37 tỷ/năm) và nghiêng hàng cao cấp (Creamery) — nhạy với chu kỳ hơn kinh doanh hiện tại. Rủi ro chậm, kẹt đất KHÔNG đưa vào đây (đã ở kịch bản xấu 06)
A10: LỢI SUẤT YÊU CẦU PHẦN KINH DOANH HIỆN TẠI (r) = Rf + β × ERP | B10: =B6+B8*B7 -> 0.11224 | F10: Không vay nên r cũng là chi phí vốn của DCF.
A11: LỢI SUẤT YÊU CẦU HAI DỰ ÁN = Rf + β dự án × ERP | B11: =B6+B9*B7 -> 0.1242 | F11: Chiết khấu dòng tiền dự án ở 06/03
A12: Tăng trưởng dài hạn (g) | B12: 0.03 | F12: Dùng cho P/B theo ROE, giá trị cuối kỳ DCF và cổ tức. Lạm phát 9T/2026 4,52% — phép thử g 4% không đặt sẵn
A13: Trích quỹ khen thưởng phúc lợi (% LNST) | B13: 0.1 | F13: 2024, 2025 đều đúng 10% (01 mục H). Tiền ra khỏi tay cổ đông trước cổ tức
A14: Thuế trên lãi tiền gửi | B14: 0.2 | F14: Thuế suất phổ thông; phần miễn thuế chỉ áp cho thu nhập chăn nuôi, chế biến nông sản (TM 34 BCTC 2025)
A15: Lãi suất vay khi tiền âm (chỉ dùng ở phương pháp 3) | B15: 0.075 | F15: TỰ ĐẶT. TM 17 BCTC 2025 chỉ ghi vay Vietcombank, VietinBank 4–6 tháng lãi cố định, KHÔNG ghi mức lãi
A16: Cổ tức tạm ứng đợt 1/2026 dự kiến (đồng/cp, khoảng tháng 11/2026) | B16: 1000 | F16: MCM tạm ứng 1.000đ vào tháng 11 các năm 2022–2025; đợt 2026 CHƯA công bố. Cộng vào phương pháp 3
A17: Lãi tiền gửi tham chiếu của nhà đầu tư (khoản lớn, thực nhận) | B17: 0.09 | F17: Niêm yết 6–7,5% (12 tháng, 10/2026); khoản trên 200 triệu thường được cộng thêm 2–2,5% ngoài biểu — không có số công khai. Dùng để so lợi suất kỳ vọng ở 05 mục B
A18: Trọng số phương pháp — Chốt 13/10/2026: chỉ DCF (phương pháp 2) làm giá trị, bốn phương pháp còn lại để đối chiếu (trước: 30/25/20/15/10)
A19: 1. P/E lợi nhuận lõi + tiền + dự án | B19: 0 | F19: Lợi nhuận lõi chuẩn hoá × P/E, cộng tiền theo mệnh giá, cộng giá trị ròng dự án · Từ 13/10/2026 chỉ đối chiếu (trước 30%)
A20: 2. DCF phần lõi + tiền + dự án | B20: 1 | F20: Dòng tiền phần lõi 2027–2031 ở r lõi; hai dự án cộng riêng (06) ở lợi suất dự án · Từ 13/10/2026 DÙNG LÀM GIÁ TRỊ: 100% (trước 25%)
A21: 3. Chiết khấu cổ tức (DDM) | B21: 0 | F21: Cổ đông thiểu số chỉ nhận cổ tức; Vinamilk kiểm soát 68% quyết định chia bao nhiêu · Từ 13/10/2026 chỉ đối chiếu (trước 20%): r phần kinh doanh áp cả lên tiền gửi nên định giá tiền thấp
A22: 4. P/B theo ROE | B22: 0 | F22: ROE lịch sử, độc lập với động cơ lõi; coi tiền gửi nằm lại công ty mãi · Từ 13/10/2026 chỉ đối chiếu (trước 15%): như phương pháp 3, mỗi đồng tiền chỉ được ~0,25 đồng
A23: 5. EV/EBITDA lõi + tiền + dự án | B23: 0 | F23: Gần như trùng phương pháp 1 (không vay) · Từ 13/10/2026 chỉ đối chiếu (trước 10%)
A24: Tổng trọng số (phải bằng 100%) | B24: =SUM(B19:B23) -> 1 | C24: =IF(ABS(B24-1)<0.000001,"ĐẠT","SAI — tổng khác 100%") -> ĐẠT
A26: Chiết khấu tiền ròng khi cộng vào giá trị (k) | B26: 0.1 | F26: Chốt 13/10/2026: giá trị = DCF phần lõi + (tiền ròng − quỹ khen thưởng phúc lợi) × (1 − k) + giá trị ròng dự án. k là phần tiền cổ đông thiểu số có thể không nhận đủ: Vinamilk nắm 68% quyết định chia hay giữ, tiền nằm ở công ty chỉ lãi ~5% sau thuế và quỹ. Mỗi 10 điểm k ≈ 1.250 đ/cp. Áp cho phương pháp 1, 2, 5 (cùng cộng tiền); 04 bảng 4 có k = 0% và 20%. Trừ quỹ từ 14/10/2026: tiền đã trích cho người lao động, không thuộc cổ đông (01 mục D).
A27: B. ĐỘNG CƠ LỢI NHUẬN LÕI — hiệu chỉnh trên 12 tháng tới Q2/2026 (dùng chung PP 1, 2, 3, 5)
A28: Tham số | B28: Giá trị | F28: Cách tính / căn cứ
A29: V 12 tháng = bán cho Vinamilk (2025 − 6T/2025 + 6T/2026) | B29: ='01_Số liệu gốc'!$D$85-'01_Số liệu gốc'!$E$85+'01_Số liệu gốc'!$F$85 -> 637.205 | F29: Thuyết minh bên liên quan, 01 mục E
A30: Doanh thu thuần 12 tháng | B30: ='01_Số liệu gốc'!$H$42 -> 2937.018
A31: B 12 tháng = doanh thu − V | B31: =B30-B29 -> 2299.813 | F31: Thương hiệu + thức ăn chăn nuôi + khác
A32: Lãi gộp 12 tháng | B32: ='01_Số liệu gốc'!$H$43 -> 862.821
A33: Chi phí bán hàng 12 tháng | B33: ='01_Số liệu gốc'!$H$44 -> 629.378
A34: Chi phí quản lý 12 tháng | B34: ='01_Số liệu gốc'!$H$45 -> 37.733
A35: EBIT lõi 12 tháng | B35: ='01_Số liệu gốc'!$H$46 -> 195.71
A36: Hồi quy lãi gộp 2023–2025 theo V và B (không hệ số chặn): biên của V | B36: =INDEX(LINEST('01_Số liệu gốc'!$B$87:$D$87,'01_Số liệu gốc'!$B$85:$D$86,FALSE,FALSE),1,2) -> -0.040691357 | F36: Ra số ÂM — vô lý: hồi quy 3 điểm lẫn cả việc giá thu mua sữa tăng 7–8% năm 2024 (KBSV). Chỉ cho biết biên của V THẤP, không đo được bao nhiêu
A37: Hồi quy như trên: biên của B | B37: =INDEX(LINEST('01_Số liệu gốc'!$B$87:$D$87,'01_Số liệu gốc'!$B$85:$D$86,FALSE,FALSE),1,1) -> 0.37696235
A38: BIÊN GỘP CỦA PHẦN BÁN CHO VINAMILK (mV) DÙNG TRONG MODEL | B38: 0.1 | F38: Ước của người viết (12/10/2026): khoảng 10% (bản trước dùng 5%, xem phép thử T15). Công ty không công bố giá bán cho Vinamilk; BCTC 2025 TM 25–26 chỉ tách thành phẩm/hàng hóa, sữa nguyên liệu nằm trong thành phẩm (biên 29,3%); CSDL gen_notes không có. Chỉ ảnh hưởng khi cơ cấu V/B đổi so 12 tháng (biên B hiệu chỉnh lại theo mV). Độ nhạy: 04 bảng 4 dòng T15 (mV 5%).
A39: Biên gộp của B 12 tháng = (lãi gộp − mV × V) ÷ B | B39: =(B32-B38*B29)/B31 -> 0.34746325
A40: Chi phí bán hàng ÷ B, 12 tháng | B40: =B33/B31 -> 0.27366486
A41: Cùng cách tính các kỳ trước: | B41: 2023 | C41: 2025 | D41: 6T/2025 | E41: 6T/2026
A42: biên gộp của B | B42: =('01_Số liệu gốc'!B87-$B$38*'01_Số liệu gốc'!B85)/'01_Số liệu gốc'!B86 -> 0.35647386 | C42: =('01_Số liệu gốc'!D87-$B$38*'01_Số liệu gốc'!D85)/'01_Số liệu gốc'!D86 -> 0.33698353 | D42: =('01_Số liệu gốc'!E87-$B$38*'01_Số liệu gốc'!E85)/'01_Số liệu gốc'!E86 -> 0.33281576 | E42: =('01_Số liệu gốc'!F87-$B$38*'01_Số liệu gốc'!F85)/'01_Số liệu gốc'!F86 -> 0.35380725
A43: chi phí bán hàng ÷ B | B43: ='01_Số liệu gốc'!B88/'01_Số liệu gốc'!B86 -> 0.26156709 | C43: ='01_Số liệu gốc'!D88/'01_Số liệu gốc'!D86 -> 0.27996027 | D43: ='01_Số liệu gốc'!E88/'01_Số liệu gốc'!E86 -> 0.26050852 | E43: ='01_Số liệu gốc'!F88/'01_Số liệu gốc'!F86 -> 0.25038504 | F43: 6T/2026 khuyến mãi giảm, biên gộp tăng — giải trình công ty: "thay đổi cơ cấu doanh thu"
A44: Lãi sau chi phí bán hàng trên 100 đồng doanh thu: B so với V | B44: =B39-B40 -> 0.073798391 | C44: =B38 -> 0.1 | F44: B: cột B · V: cột C, Trên 100 đồng doanh thu, hàng thương hiệu giữ ~7,4 đồng sau khuyến mãi, phần bán cho Vinamilk giữ 10 đồng (ước). So theo doanh thu, không theo lít sữa: một lít làm thành hàng thương hiệu cho doanh thu cao hơn bán thô. Đòn bẩy thật là biên gộp B và tỷ lệ khuyến mãi
A45: Kiểm: mV × V + (biên B − CPBH/B) × B − quản lý = EBIT lõi 12 tháng | B45: =B38*B29+(B39-B40)*B31-B34 -> 195.71 | C45: =IF(ABS(B45-B35)<0.001,"KHỚP","LỆCH") -> KHỚP
A46: Chi phí quản lý năm chuẩn hoá (tỷ) | B46: 39 | F46: 12 tháng 37,7 tỷ; 2025 38,1 tỷ; cộng lạm phát
A47: Khấu hao năm chuẩn hoá = 6 tháng 2026 × 2 (chỉ dùng cho EBITDA) | B47: =('01_Số liệu gốc'!$F$52+'01_Số liệu gốc'!$G$52)*2 -> 70.908
A48: Thuế suất trên lợi nhuận lõi, 12 tháng (lãi tài chính ròng chịu 20%) | B48: =('01_Số liệu gốc'!$H$50-B14*('01_Số liệu gốc'!$H$47-'01_Số liệu gốc'!$H$48))/('01_Số liệu gốc'!$H$49-('01_Số liệu gốc'!$H$47-'01_Số liệu gốc'!$H$48)) -> 0.074019575
A49: cùng cách tính cho năm 2025 | B49: =('01_Số liệu gốc'!$F$30-B14*('01_Số liệu gốc'!$F$25-'01_Số liệu gốc'!$F$26))/('01_Số liệu gốc'!$F$29-('01_Số liệu gốc'!$F$25-'01_Số liệu gốc'!$F$26)) -> 0.087886232 | F49: Giả định lãi tiền gửi chịu đủ 20%, phần miễn thuế rơi hết vào lợi nhuận lõi
A50: Vốn hoạt động lõi 30/06/2026 (01 mục D) | B50: ='01_Số liệu gốc'!$C$73 -> 463.235
A51: ROIC lõi 12 tháng = EBIT lõi × (1 − thuế lõi) ÷ vốn hoạt động lõi | B51: =B35*(1-B48)/B50 -> 0.39121316 | F51: Rất cao vì nhà máy cũ đã khấu hao gần hết — chính là lý do phải xây nhà máy mới
A52: ROIC lõi trung tâm = trung vị 2021–2025 (EBIT sạch; vốn bỏ xây dựng dở dang) | B52: 0.307 | F52: Engine đo 13/10/2026: 53,9 · 45,2 · 30,7 · 21,7 · 26,7% (2021–2025). Cửa sổ có hai năm đỉnh (2021–22) và hai năm đáy (2024–25) — trung vị rơi đúng 2023
A53: Hệ số bền vững (luật ROIC trạng thái dừng) | B53: 0.3 | F53: Đầu trên dải CHU KỲ 0,15–0,30 (quy trình): ROIC 5 năm trải 32 điểm, biên EBIT 5,3–9,2%, không kiểm soát giá sữa thu mua và thức ăn. Hệ số 0,15 / 0,45 → −550 / +380 đ/cp (quy trình)
A54: ROIC TRẠNG THÁI DỪNG = r + hệ số × (trung tâm − r), làm tròn 0,1 điểm | B54: =ROUND(B10+B53*(B52-B10),3) -> 0.171 | F54: Dùng cho giá trị cuối kỳ cả ba kịch bản (14/10/2026). Bản 12/10 ngầm định ROIC 28 / 41 / 54% vì chỉ trừ g × vốn hoạt động sổ sách ~460 tỷ — nhỏ do nhà máy cũ đã khấu hao gần hết. Theo giá thay thế: vốn lõi sau nhà máy mới ~1.200 tỷ, lợi nhuận lõi ~200–240 tỷ → 17–20%
A55: EBIT lõi tăng thêm mỗi quý: (6T/2026 − 6T/2025) ÷ 2 | B55: =(('01_Số liệu gốc'!$F$46+'01_Số liệu gốc'!$G$46)-('01_Số liệu gốc'!$B$46+'01_Số liệu gốc'!$C$46))/2 -> 21.7075
A56: MỐC KIỂM: LNST Q3/2026 = Q3/2025 + mức tăng × (1 − thuế) (tỷ) | B56: ='01_Số liệu gốc'!$D$51+1*B55*(1-B48) -> 48.16472 | C56: ='01_Số liệu gốc'!$D$51+0.5*B55*(1-B48) -> 38.11436 | D56: ='01_Số liệu gốc'!$D$51+1.5*B55*(1-B48) -> 58.21508 | F56: B = giữ đúng đà 6 tháng · C = còn một nửa · D = mạnh gấp rưỡi. Q3/2025 là quý xấu nhất 2025 (LNST 28 tỷ, khuyến mãi 182 tỷ). BCTC Q3 ra cuối tháng 10/2026
A58: C. BA KỊCH BẢN (năm chuẩn hoá ~2027, trước khi dự án có lãi — không phải dự phóng một năm)
A59: Tham số | B59: Xấu | C59: Cơ sở | D59: Tốt | E59: Mốc thực tế | F59: Căn cứ
A60: ĐỘNG CƠ LÕI (phương pháp 1, 2, 3, 5)
A61: B — doanh thu phần còn lại (tỷ) | B61: 2200 | C61: 2450 | D61: 2700 | E61: =B31 -> 2299.813 | F61: Mốc = 12 tháng. 6T/2026 +12,8% so cùng kỳ; 2026 chạy đà ~2.390. Xấu = mức 2025 (2.167) nếu Creamery không cất cánh; Tốt = mức 2023 (2.710). Kế hoạch 2026 doanh thu 3.126 tỷ ≈ B 2.470
A62: V — bán cho Vinamilk (tỷ) | B62: 700 | C62: 640 | D62: 600 | E62: =B29 -> 637.205 | F62: Bò vẫn cho sữa mỗi ngày: hàng thương hiệu bán chậm thì sữa dư dồn sang V. 2025: 668; 6T/2026 −8,6%
A63: Biên gộp của B: chênh so 12 tháng (điểm %) | B63: -0.015 | C63: 0 | D63: 0.01 | E63: =E42-B39 -> 0.0063439955 | F63: Mốc = 6T/2026 − 12 tháng. Giá thu mua sữa, thức ăn (ngô, khô đậu +21–25% so cùng kỳ tháng 9/2026) và cơ cấu sản phẩm
A64: Chi phí bán hàng ÷ B | B64: 0.28 | C64: 0.27 | D64: 0.26 | E64: =B40 -> 0.27366486 | F64: 2024–2025 28%; 6T/2026 25%; 12 tháng 27,3%. Đẩy Creamery vào miền Nam tốn khuyến mãi
A65: Thuế suất trên lợi nhuận lõi | B65: 0.09 | C65: 0.09 | D65: 0.09 | E65: =B48 -> 0.074019575 | F65: 9% CẢ BA kịch bản (14/10/2026, theo quy trình; bản 12/10: 11 / 9 / 8%). Ưu đãi miễn thuế theo NGÀNH và ĐỊA BÀN (Nghị định 320/2025), không theo chu kỳ kinh doanh — năm xấu không làm thuế suất tăng; kịch bản xấu dồn sữa sang bán thô (thu nhập chăn nuôi miễn thuế). Mốc = 12 tháng; 2025: 8,8%. Mất ưu đãi để ở độ nhạy: thuế 20% → −2.092 đ/cp (quy trình)
A66: Tăng trưởng B mỗi năm 2027–2031 (PP 2, 3) | B66: 0 | C66: 0.03 | D66: 0.05 | F66: Ngành sữa tăng thấp (−1% đến 3%/năm theo KBSV); Creamery là biến số
A67: Chi đầu tư lõi (% doanh thu) (PP 2, 3) | B67: 0.023 | C67: 0.026 | D67: 0.028 | F67: Theo quy trình (14/10/2026). Xấu = khấu hao vì không tăng trưởng; tốt cao hơn vì tăng nhanh. THẤP hơn lịch sử: chi ngoài xây dựng dở dang 2021–2025 ~90 tỷ/năm, khấu hao ~60 tỷ → độ nhạy chi duy trì 48 / 80 / 90 tỷ: +1.189 / 0 / −355 đ/cp (quy trình)
A68: Khấu hao lõi (% doanh thu) | B68: 0.023 | C68: 0.023 | D68: 0.023 | E68: =$B$47/$B$30 -> 0.024142855 | F68: Khấu hao chuẩn hoá (mục B, 6 tháng 2026 × 2) ÷ doanh thu năm 1 ~3.090 tỷ. Mốc = ÷ doanh thu 12 tháng
A69: Vốn lưu động lõi (% doanh thu) | B69: 0.04 | C69: 0.04 | D69: 0.04 | F69: Vốn lưu động lõi 30/06/2026 ≈ 120 tỷ ≈ 4,1% doanh thu 12 tháng. Tái đầu tư = (chi đầu tư − khấu hao) × doanh thu + vốn lưu động × tăng doanh thu (thay cách cũ: tăng trưởng B × vốn hoạt động sổ sách)
A70: Hệ số giải phóng vốn lưu động khi doanh thu giảm | B70: 0 | C70: 1 | D70: 1 | F70: Xấu = 0: doanh thu co nhẹ năm 1 không được thưởng tiền giải phóng vốn lưu động (luật quy trình — tránh biến kịch bản xấu thành phần thưởng)
A71: BỘI SỐ (phương pháp 1, 5) — dùng chung ba kịch bản
A72: P/E trên lợi nhuận lõi sau thuế và quỹ | B72: 10.8 | C72: 10.8 | D72: 10.8 | E72: ='01_Số liệu gốc'!$B$144 -> 13.89 | F72: Dùng chung: lợi nhuận đã khác nhau theo kịch bản, hạ bội số nữa là phạt hai lần. Mốc = P/E trung vị cả công ty (gồm lãi tiền gửi). 10,8x = bội số Vinasoy file QNS (9x EBIT) quy về lợi nhuận lõi sau thuế, quỹ; ≈ P/E cơ bản ở r mới (05 mục A). Phép thử T11 (10x)
A73: EV/EBITDA lõi | B73: 6.6 | C73: 6.6 | D73: 6.6 | F73: Bội số Vinasoy quy ra ~6,6x; ≈ EV/EBITDA cơ bản ở r mới (05 mục A). Vietcap ghi 10,8x nhưng KHÔNG trừ tiền gửi có kỳ hạn — không so thẳng
A74: PHƯƠNG PHÁP 4 — P/B theo ROE (không qua động cơ lõi)
A75: ROE chu kỳ, trước trích quỹ | B75: 0.095 | C75: 0.115 | D75: 0.14 | E75: ='01_Số liệu gốc'!$E$104 -> 0.12804855 | F75: Mốc = bình quân 2022–2025 (sau đợt phát hành). 2024–2025 9,4–9,5%; 12 tháng 11,3%. Tính trên vốn chủ GỒM tiền gửi — coi tiền nằm lại công ty mãi, nên khắt khe hơn PP 1
A76: CỔ TỨC VÀ TIỀN (phương pháp 3) — hai dự án: xem 06_Dự án
A77: Cổ tức tiền mặt 2027–2031 (đồng/cổ phiếu) | B77: 1000 | C77: 1500 | D77: 2000 | E77: ='01_Số liệu gốc'!$B$135 -> 2000 | F77: Chính sách 2026: tối thiểu 50% LNST (ĐHĐCĐ 20/04/2026) ≈ 1.000đ ở kế hoạch 241 tỷ → Xấu. 2022–2025 trả 2.000đ → Tốt. Cơ sở 1.500đ = 165 tỷ/năm — TỰ ĐẶT. Tiền âm thì phải vay (lãi suất ở mục A)
A78: Lãi suất tiền gửi | B78: 0.065 | C78: 0.07 | D78: 0.075 | E78: ='01_Số liệu gốc'!$B$143 -> 0.063826955 | F78: Mốc = lãi tiền gửi 2025 ÷ số dư bình quân. Lãi 12 tháng niêm yết 10/2026: 6–7,5%; khoản lớn được cộng thêm → cơ sở 7%
A79: XÁC SUẤT — KHÔNG DÙNG
A80: Không gán xác suất cho ba kịch bản. Kịch bản cơ sở là con số trung tâm; xấu và tốt là ranh giới khi mọi giả định cùng lệch về một phía. Vùng hành động neo kịch bản cơ sở (00 mục 2).

Sheet 03_Định giá
A1: MCM — ĐỊNH GIÁ: DCF LÕI + TIỀN + DỰ ÁN (BỐN PHƯƠNG PHÁP ĐỐI CHIẾU), BA KỊCH BẢN, MƯỜI SÁU CỘT PHÉP THỬ (bản 15/10/2026)
A2: Toàn bộ là công thức đọc từ 01 và 02 — không nhập số ở sheet này, TRỪ ô đổi tham số ở cột phép thử (nền xanh lá). Mỗi cột H–W là một bản tính lại đầy đủ: lấy đúng tham số cột Cơ sở, đổi đúng một ô (T15 đổi thêm biên gộp B 12 tháng đi kèm để EBIT 12 tháng vẫn khớp).
H3: Đối chứng: không đổi gì (phải ra đúng cơ sở) | I3: Không xây nhà máy trong 5 năm — MỨC TRẦN (coi nhà máy cũ chạy mãi không tốn thêm) | J3: Nhà máy chạy từ 2028 (lịch công ty: xong Q4/2027) | K3: Sữa trang trại bán thô 13.000 đ/lít | L3: Chi phí nuôi 11.500 đ/lít | M3: ERP 10% (VDSC, cận trên) | N3: β phần kinh doanh 0,85 (bằng dự án) | O3: Cổ tức 1.000đ/cp (tối thiểu 50% LNST) | P3: B về mức 2025 (Creamery không cất cánh) | Q3: B về mức 2023 | R3: Chi phí bán hàng ÷ B = mức 12 tháng | S3: P/E lõi 10x (như bản 09/10) | T3: P/E lõi = P/E trung vị lịch sử MCM | U3: Biên gộp B giữ mức 6T/2026 | V3: β phần kinh doanh 0,65 | W3: Biên gộp bán cho Vinamilk 5% thay cho 10% (cơ sở). Biên gộp B 12 tháng tính lại theo ô này để EBIT 12 tháng vẫn khớp
A4: Chỉ tiêu (tỷ đồng) | B4: Xấu | C4: Cơ sở | D4: Tốt | E4: Trọng số | F4: Cách tính | H4: T0 | I4: T1 | J4: T2 | K4: T3 | L4: T4 | M4: T5 | N4: T6 | O4: T7 | P4: T8 | Q4: T9 | R4: T10 | S4: T11 | T4: T12 | U4: T13 | V4: T14 | W4: T15
A5: P. THAM SỐ — cột Xấu/Cơ sở/Tốt lấy từ 02 và 06; cột phép thử = Cơ sở, trừ một ô nền xanh
A6: B — doanh thu phần còn lại | B6: ='02_Giả định'!B61 -> 2200 | C6: ='02_Giả định'!C61 -> 2450 | D6: ='02_Giả định'!D61 -> 2700 | H6: =$C6 -> 2450 | I6: =$C6 -> 2450 | J6: =$C6 -> 2450 | K6: =$C6 -> 2450 | L6: =$C6 -> 2450 | M6: =$C6 -> 2450 | N6: =$C6 -> 2450 | O6: =$C6 -> 2450 | P6: ='01_Số liệu gốc'!$D$86 -> 2166.786 | Q6: ='01_Số liệu gốc'!$B$86 -> 2710.123 | R6: =$C6 -> 2450 | S6: =$C6 -> 2450 | T6: =$C6 -> 2450 | U6: =$C6 -> 2450 | V6: =$C6 -> 2450 | W6: =$C6 -> 2450
A7: V — bán cho Vinamilk | B7: ='02_Giả định'!B62 -> 700 | C7: ='02_Giả định'!C62 -> 640 | D7: ='02_Giả định'!D62 -> 600 | H7: =$C7 -> 640 | I7: =$C7 -> 640 | J7: =$C7 -> 640 | K7: =$C7 -> 640 | L7: =$C7 -> 640 | M7: =$C7 -> 640 | N7: =$C7 -> 640 | O7: =$C7 -> 640 | ... W7: =$C7 -> 640
A8: Biên gộp B: chênh so 12 tháng | B8: ='02_Giả định'!B63 -> -0.015 | C8: ='02_Giả định'!C63 -> 0 | D8: ='02_Giả định'!D63 -> 0.01 | H8: =$C8 -> 0 | I8: =$C8 -> 0 | J8: =$C8 -> 0 | K8: =$C8 -> 0 | L8: =$C8 -> 0 | M8: =$C8 -> 0 | N8: =$C8 -> 0 | O8: =$C8 -> 0 | ... T8: =$C8 -> 0 | U8: ='02_Giả định'!$E$42-'02_Giả định'!$B$39 -> 0.0063439955 | V8: =$C8 -> 0 | W8: =$C8 -> 0
A9: Chi phí bán hàng ÷ B | B9: ='02_Giả định'!B64 -> 0.28 | C9: ='02_Giả định'!C64 -> 0.27 | D9: ='02_Giả định'!D64 -> 0.26 | H9: =$C9 -> 0.27 | I9: =$C9 -> 0.27 | J9: =$C9 -> 0.27 | K9: =$C9 -> 0.27 | L9: =$C9 -> 0.27 | M9: =$C9 -> 0.27 | N9: =$C9 -> 0.27 | O9: =$C9 -> 0.27 | ... Q9: =$C9 -> 0.27 | R9: ='02_Giả định'!$B$40 -> 0.27366486 | S9: =$C9 -> 0.27 | T9: =$C9 -> 0.27 | U9: =$C9 -> 0.27 | V9: =$C9 -> 0.27 | W9: =$C9 -> 0.27
A10: Thuế suất lõi | B10: ='02_Giả định'!B65 -> 0.09 | C10: ='02_Giả định'!C65 -> 0.09 | D10: ='02_Giả định'!D65 -> 0.09 | H10: =$C10 -> 0.09 | I10: =$C10 -> 0.09 | J10: =$C10 -> 0.09 | K10: =$C10 -> 0.09 | L10: =$C10 -> 0.09 | M10: =$C10 -> 0.09 | N10: =$C10 -> 0.09 | O10: =$C10 -> 0.09 | ... W10: =$C10 -> 0.09
A11: Tăng trưởng B 2027–2031 | B11: ='02_Giả định'!B66 -> 0 | C11: ='02_Giả định'!C66 -> 0.03 | D11: ='02_Giả định'!D66 -> 0.05 | H11: =$C11 -> 0.03 | I11: =$C11 -> 0.03 | J11: =$C11 -> 0.03 | K11: =$C11 -> 0.03 | L11: =$C11 -> 0.03 | M11: =$C11 -> 0.03 | N11: =$C11 -> 0.03 | O11: =$C11 -> 0.03 | ... W11: =$C11 -> 0.03
A12: P/E lõi | B12: ='02_Giả định'!B72 -> 10.8 | C12: ='02_Giả định'!C72 -> 10.8 | D12: ='02_Giả định'!D72 -> 10.8 | H12: =$C12 -> 10.8 | I12: =$C12 -> 10.8 | J12: =$C12 -> 10.8 | K12: =$C12 -> 10.8 | L12: =$C12 -> 10.8 | M12: =$C12 -> 10.8 | N12: =$C12 -> 10.8 | O12: =$C12 -> 10.8 | ... R12: =$C12 -> 10.8 | S12: 10 | T12: ='01_Số liệu gốc'!$B$144 -> 13.89 | U12: =$C12 -> 10.8 | V12: =$C12 -> 10.8 | W12: =$C12 -> 10.8
A13: EV/EBITDA lõi | B13: ='02_Giả định'!B73 -> 6.6 | C13: ='02_Giả định'!C73 -> 6.6 | D13: ='02_Giả định'!D73 -> 6.6 | H13: =$C13 -> 6.6 | I13: =$C13 -> 6.6 | J13: =$C13 -> 6.6 | K13: =$C13 -> 6.6 | L13: =$C13 -> 6.6 | M13: =$C13 -> 6.6 | N13: =$C13 -> 6.6 | O13: =$C13 -> 6.6 | ... W13: =$C13 -> 6.6
A14: ROE chu kỳ | B14: ='02_Giả định'!B75 -> 0.095 | C14: ='02_Giả định'!C75 -> 0.115 | D14: ='02_Giả định'!D75 -> 0.14 | H14: =$C14 -> 0.115 | I14: =$C14 -> 0.115 | J14: =$C14 -> 0.115 | K14: =$C14 -> 0.115 | L14: =$C14 -> 0.115 | M14: =$C14 -> 0.115 | N14: =$C14 -> 0.115 | O14: =$C14 -> 0.115 | ... W14: =$C14 -> 0.115
A15: Cổ tức 2027–2031 (đồng/cp) | B15: ='02_Giả định'!B77 -> 1000 | C15: ='02_Giả định'!C77 -> 1500 | D15: ='02_Giả định'!D77 -> 2000 | H15: =$C15 -> 1500 | I15: =$C15 -> 1500 | J15: =$C15 -> 1500 | K15: =$C15 -> 1500 | L15: =$C15 -> 1500 | M15: =$C15 -> 1500 | N15: =$C15 -> 1500 | O15: 1000 | P15: =$C15 -> 1500 | Q15: =$C15 -> 1500 | R15: =$C15 -> 1500 | S15: =$C15 -> 1500 | T15: =$C15 -> 1500 | U15: =$C15 -> 1500 | V15: =$C15 -> 1500 | W15: =$C15 -> 1500
A16: Lãi suất tiền gửi | B16: ='02_Giả định'!B78 -> 0.065 | C16: ='02_Giả định'!C78 -> 0.07 | D16: ='02_Giả định'!D78 -> 0.075 | H16: =$C16 -> 0.07 | I16: =$C16 -> 0.07 | J16: =$C16 -> 0.07 | K16: =$C16 -> 0.07 | L16: =$C16 -> 0.07 | M16: =$C16 -> 0.07 | N16: =$C16 -> 0.07 | O16: =$C16 -> 0.07 | ... W16: =$C16 -> 0.07
A17: Trang trại: vốn phần bò sữa | B17: ='06_Dự án'!B6 -> 860 | C17: ='06_Dự án'!C6 -> 784 | D17: ='06_Dự án'!D6 -> 784 | H17: =$C17 -> 784 | I17: =$C17 -> 784 | J17: =$C17 -> 784 | K17: =$C17 -> 784 | L17: =$C17 -> 784 | M17: =$C17 -> 784 | N17: =$C17 -> 784 | O17: =$C17 -> 784 | ... W17: =$C17 -> 784
A18: Trang trại: vốn phần du lịch | B18: ='06_Dự án'!B7 -> 336 | C18: ='06_Dự án'!C7 -> 336 | D18: ='06_Dự án'!D7 -> 336 | H18: =$C18 -> 336 | I18: =$C18 -> 336 | J18: =$C18 -> 336 | K18: =$C18 -> 336 | L18: =$C18 -> 336 | M18: =$C18 -> 336 | N18: =$C18 -> 336 | O18: =$C18 -> 336 | ... W18: =$C18 -> 336
A19: Trang trại: triệu lít/năm khi đủ đàn | B19: ='06_Dự án'!B8 -> 18 | C19: ='06_Dự án'!C8 -> 20 | D19: ='06_Dự án'!D8 -> 22 | H19: =$C19 -> 20 | I19: =$C19 -> 20 | J19: =$C19 -> 20 | K19: =$C19 -> 20 | L19: =$C19 -> 20 | M19: =$C19 -> 20 | N19: =$C19 -> 20 | O19: =$C19 -> 20 | ... W19: =$C19 -> 20
A20: Trang trại: sản lượng 2027 | B20: ='06_Dự án'!B9 -> 0.3 | C20: ='06_Dự án'!C9 -> 0.5 | D20: ='06_Dự án'!D9 -> 0.6 | H20: =$C20 -> 0.5 | I20: =$C20 -> 0.5 | J20: =$C20 -> 0.5 | K20: =$C20 -> 0.5 | L20: =$C20 -> 0.5 | M20: =$C20 -> 0.5 | N20: =$C20 -> 0.5 | O20: =$C20 -> 0.5 | ... W20: =$C20 -> 0.5
A21: Trang trại: giá bán (đ/lít) | B21: ='06_Dự án'!B10 -> 13000 | C21: ='06_Dự án'!C10 -> 14500 | D21: ='06_Dự án'!D10 -> 15000 | H21: =$C21 -> 14500 | I21: =$C21 -> 14500 | J21: =$C21 -> 14500 | K21: 13000 | L21: =$C21 -> 14500 | M21: =$C21 -> 14500 | N21: =$C21 -> 14500 | O21: =$C21 -> 14500 | P21: =$C21 -> 14500 | Q21: =$C21 -> 14500 | R21: =$C21 -> 14500 | S21: =$C21 -> 14500 | ... W21: =$C21 -> 14500
A22: Trang trại: chi phí tiền mặt (đ/lít) | B22: ='06_Dự án'!B11 -> 10500 | C22: ='06_Dự án'!C11 -> 10500 | D22: ='06_Dự án'!D11 -> 10500 | H22: =$C22 -> 10500 | I22: =$C22 -> 10500 | J22: =$C22 -> 10500 | K22: =$C22 -> 10500 | L22: 11500 | M22: =$C22 -> 10500 | N22: =$C22 -> 10500 | O22: =$C22 -> 10500 | P22: =$C22 -> 10500 | Q22: =$C22 -> 10500 | R22: =$C22 -> 10500 | S22: =$C22 -> 10500 | T22: =$C22 -> 10500 | ... W22: =$C22 -> 10500
A23: Trang trại: thu thêm bê, bò loại | B23: ='06_Dự án'!B12 -> 0.05 | C23: ='06_Dự án'!C12 -> 0.05 | D23: ='06_Dự án'!D12 -> 0.05 | H23: =$C23 -> 0.05 | I23: =$C23 -> 0.05 | J23: =$C23 -> 0.05 | K23: =$C23 -> 0.05 | L23: =$C23 -> 0.05 | M23: =$C23 -> 0.05 | N23: =$C23 -> 0.05 | O23: =$C23 -> 0.05 | ... W23: =$C23 -> 0.05
A24: Trang trại: chi duy trì | B24: ='06_Dự án'!B13 -> 15 | C24: ='06_Dự án'!C13 -> 15 | D24: ='06_Dự án'!D13 -> 15 | H24: =$C24 -> 15 | I24: =$C24 -> 15 | J24: =$C24 -> 15 | K24: =$C24 -> 15 | L24: =$C24 -> 15 | M24: =$C24 -> 15 | N24: =$C24 -> 15 | O24: =$C24 -> 15 | ... W24: =$C24 -> 15
A25: Trang trại: năm khấu hao | B25: ='06_Dự án'!B14 -> 20 | C25: ='06_Dự án'!C14 -> 20 | D25: ='06_Dự án'!D14 -> 20 | H25: =$C25 -> 20 | I25: =$C25 -> 20 | J25: =$C25 -> 20 | K25: =$C25 -> 20 | L25: =$C25 -> 20 | M25: =$C25 -> 20 | N25: =$C25 -> 20 | O25: =$C25 -> 20 | ... W25: =$C25 -> 20
A26: Du lịch: lãi trước thuế từ 2028 | B26: ='06_Dự án'!B15 -> 0 | C26: ='06_Dự án'!C15 -> 10 | D26: ='06_Dự án'!D15 -> 25 | H26: =$C26 -> 10 | I26: =$C26 -> 10 | J26: =$C26 -> 10 | K26: =$C26 -> 10 | L26: =$C26 -> 10 | M26: =$C26 -> 10 | N26: =$C26 -> 10 | O26: =$C26 -> 10 | ... W26: =$C26 -> 10
A27: Nhà máy: có xây trong 5 năm | B27: ='06_Dự án'!B19 -> 1 | C27: ='06_Dự án'!C19 -> 1 | D27: ='06_Dự án'!D19 -> 1 | H27: =$C27 -> 1 | I27: 0 | J27: =$C27 -> 1 | K27: =$C27 -> 1 | L27: =$C27 -> 1 | M27: =$C27 -> 1 | N27: =$C27 -> 1 | O27: =$C27 -> 1 | P27: =$C27 -> 1 | Q27: =$C27 -> 1 | ... W27: =$C27 -> 1
A28: Nhà máy: vốn giai đoạn 1 | B28: ='06_Dự án'!B20 -> 850 | C28: ='06_Dự án'!C20 -> 743 | D28: ='06_Dự án'!D20 -> 743 | H28: =$C28 -> 743 | I28: =$C28 -> 743 | J28: =$C28 -> 743 | K28: =$C28 -> 743 | L28: =$C28 -> 743 | M28: =$C28 -> 743 | N28: =$C28 -> 743 | O28: =$C28 -> 743 | ... W28: =$C28 -> 743
A29: Nhà máy: năm bắt đầu có lãi | B29: ='06_Dự án'!B21 -> 2032 | C29: ='06_Dự án'!C21 -> 2030 | D29: ='06_Dự án'!D21 -> 2030 | H29: =$C29 -> 2030 | I29: =$C29 -> 2030 | J29: 2028 | K29: =$C29 -> 2030 | L29: =$C29 -> 2030 | M29: =$C29 -> 2030 | N29: =$C29 -> 2030 | O29: =$C29 -> 2030 | P29: =$C29 -> 2030 | Q29: =$C29 -> 2030 | R29: =$C29 -> 2030 | ... W29: =$C29 -> 2030
A30: Nhà máy: lãi tăng thêm sau thuế năm đầu chạy | B30: ='06_Dự án'!B22 -> 20 | C30: ='06_Dự án'!C22 -> 45 | D30: ='06_Dự án'!D22 -> 45 | H30: =$C30 -> 45 | I30: =$C30 -> 45 | J30: =$C30 -> 45 | K30: =$C30 -> 45 | L30: =$C30 -> 45 | M30: =$C30 -> 45 | N30: =$C30 -> 45 | O30: =$C30 -> 45 | ... W30: =$C30 -> 45
A31: Lợi suất phi rủi ro | B31: ='02_Giả định'!$B$6 -> 0.046 | C31: ='02_Giả định'!$B$6 -> 0.046 | D31: ='02_Giả định'!$B$6 -> 0.046 | H31: =$C31 -> 0.046 | I31: =$C31 -> 0.046 | J31: =$C31 -> 0.046 | K31: =$C31 -> 0.046 | L31: =$C31 -> 0.046 | M31: =$C31 -> 0.046 | N31: =$C31 -> 0.046 | O31: =$C31 -> 0.046 | ... W31: =$C31 -> 0.046
A32: Phần bù rủi ro thị trường | B32: ='02_Giả định'!$B$7 -> 0.092 | C32: ='02_Giả định'!$B$7 -> 0.092 | D32: ='02_Giả định'!$B$7 -> 0.092 | H32: =$C32 -> 0.092 | I32: =$C32 -> 0.092 | J32: =$C32 -> 0.092 | K32: =$C32 -> 0.092 | L32: =$C32 -> 0.092 | M32: 0.1 | N32: =$C32 -> 0.092 | O32: =$C32 -> 0.092 | P32: =$C32 -> 0.092 | Q32: =$C32 -> 0.092 | R32: =$C32 -> 0.092 | S32: =$C32 -> 0.092 | T32: =$C32 -> 0.092 | U32: =$C32 -> 0.092 | ... W32: =$C32 -> 0.092
A33: β phần kinh doanh hiện tại | B33: ='02_Giả định'!$B$8 -> 0.72 | C33: ='02_Giả định'!$B$8 -> 0.72 | D33: ='02_Giả định'!$B$8 -> 0.72 | H33: =$C33 -> 0.72 | I33: =$C33 -> 0.72 | J33: =$C33 -> 0.72 | K33: =$C33 -> 0.72 | L33: =$C33 -> 0.72 | M33: =$C33 -> 0.72 | N33: 0.85 | O33: =$C33 -> 0.72 | P33: =$C33 -> 0.72 | Q33: =$C33 -> 0.72 | R33: =$C33 -> 0.72 | S33: =$C33 -> 0.72 | T33: =$C33 -> 0.72 | U33: =$C33 -> 0.72 | V33: 0.65 | W33: =$C33 -> 0.72
A34: β hai dự án | B34: ='02_Giả định'!$B$9 -> 0.85 | C34: ='02_Giả định'!$B$9 -> 0.85 | D34: ='02_Giả định'!$B$9 -> 0.85 | H34: =$C34 -> 0.85 | I34: =$C34 -> 0.85 | J34: =$C34 -> 0.85 | K34: =$C34 -> 0.85 | L34: =$C34 -> 0.85 | M34: =$C34 -> 0.85 | N34: =$C34 -> 0.85 | O34: =$C34 -> 0.85 | ... W34: =$C34 -> 0.85
A35: Tăng trưởng dài hạn g | B35: ='02_Giả định'!$B$12 -> 0.03 | C35: ='02_Giả định'!$B$12 -> 0.03 | D35: ='02_Giả định'!$B$12 -> 0.03 | H35: =$C35 -> 0.03 | I35: =$C35 -> 0.03 | J35: =$C35 -> 0.03 | K35: =$C35 -> 0.03 | L35: =$C35 -> 0.03 | M35: =$C35 -> 0.03 | N35: =$C35 -> 0.03 | O35: =$C35 -> 0.03 | ... W35: =$C35 -> 0.03
A36: Trích quỹ khen thưởng phúc lợi | B36: ='02_Giả định'!$B$13 -> 0.1 | C36: ='02_Giả định'!$B$13 -> 0.1 | D36: ='02_Giả định'!$B$13 -> 0.1 | H36: =$C36 -> 0.1 | I36: =$C36 -> 0.1 | J36: =$C36 -> 0.1 | K36: =$C36 -> 0.1 | L36: =$C36 -> 0.1 | M36: =$C36 -> 0.1 | N36: =$C36 -> 0.1 | O36: =$C36 -> 0.1 | ... W36: =$C36 -> 0.1
A37: Thuế trên lãi tiền gửi | B37: ='02_Giả định'!$B$14 -> 0.2 | C37: ='02_Giả định'!$B$14 -> 0.2 | D37: ='02_Giả định'!$B$14 -> 0.2 | H37: =$C37 -> 0.2 | I37: =$C37 -> 0.2 | J37: =$C37 -> 0.2 | K37: =$C37 -> 0.2 | L37: =$C37 -> 0.2 | M37: =$C37 -> 0.2 | N37: =$C37 -> 0.2 | O37: =$C37 -> 0.2 | ... W37: =$C37 -> 0.2
A38: Lãi suất vay khi tiền âm | B38: ='02_Giả định'!$B$15 -> 0.075 | C38: ='02_Giả định'!$B$15 -> 0.075 | D38: ='02_Giả định'!$B$15 -> 0.075 | H38: =$C38 -> 0.075 | I38: =$C38 -> 0.075 | J38: =$C38 -> 0.075 | K38: =$C38 -> 0.075 | L38: =$C38 -> 0.075 | M38: =$C38 -> 0.075 | N38: =$C38 -> 0.075 | O38: =$C38 -> 0.075 | ... W38: =$C38 -> 0.075
A39: Cổ tức tạm ứng đợt 1/2026 (đồng/cp) | B39: ='02_Giả định'!$B$16 -> 1000 | C39: ='02_Giả định'!$B$16 -> 1000 | D39: ='02_Giả định'!$B$16 -> 1000 | H39: =$C39 -> 1000 | I39: =$C39 -> 1000 | J39: =$C39 -> 1000 | K39: =$C39 -> 1000 | L39: =$C39 -> 1000 | M39: =$C39 -> 1000 | N39: =$C39 -> 1000 | O39: =$C39 -> 1000 | ... W39: =$C39 -> 1000
A40: Biên gộp phần bán cho Vinamilk | B40: ='02_Giả định'!$B$38 -> 0.1 | C40: ='02_Giả định'!$B$38 -> 0.1 | D40: ='02_Giả định'!$B$38 -> 0.1 | H40: =$C40 -> 0.1 | I40: =$C40 -> 0.1 | J40: =$C40 -> 0.1 | K40: =$C40 -> 0.1 | L40: =$C40 -> 0.1 | M40: =$C40 -> 0.1 | N40: =$C40 -> 0.1 | O40: =$C40 -> 0.1 | ... V40: =$C40 -> 0.1 | W40: 0.05
A41: Biên gộp B 12 tháng | B41: ='02_Giả định'!$B$39 -> 0.34746325 | C41: ='02_Giả định'!$B$39 -> 0.34746325 | D41: ='02_Giả định'!$B$39 -> 0.34746325 | H41: =$C41 -> 0.34746325 | I41: =$C41 -> 0.34746325 | J41: =$C41 -> 0.34746325 | K41: =$C41 -> 0.34746325 | L41: =$C41 -> 0.34746325 | M41: =$C41 -> 0.34746325 | N41: =$C41 -> 0.34746325 | O41: =$C41 -> 0.34746325 | ... V41: =$C41 -> 0.34746325 | W41: =('02_Giả định'!$B$32-W40*'02_Giả định'!$B$29)/'02_Giả định'!$B$31 -> 0.36131666
A42: Chi phí quản lý chuẩn hoá | B42: ='02_Giả định'!$B$46 -> 39 | C42: ='02_Giả định'!$B$46 -> 39 | D42: ='02_Giả định'!$B$46 -> 39 | H42: =$C42 -> 39 | I42: =$C42 -> 39 | J42: =$C42 -> 39 | K42: =$C42 -> 39 | L42: =$C42 -> 39 | M42: =$C42 -> 39 | N42: =$C42 -> 39 | O42: =$C42 -> 39 | ... W42: =$C42 -> 39
A43: Khấu hao chuẩn hoá | B43: ='02_Giả định'!$B$47 -> 70.908 | C43: ='02_Giả định'!$B$47 -> 70.908 | D43: ='02_Giả định'!$B$47 -> 70.908 | H43: =$C43 -> 70.908 | I43: =$C43 -> 70.908 | J43: =$C43 -> 70.908 | K43: =$C43 -> 70.908 | L43: =$C43 -> 70.908 | M43: =$C43 -> 70.908 | N43: =$C43 -> 70.908 | O43: =$C43 -> 70.908 | ... W43: =$C43 -> 70.908
A44: LỢI SUẤT YÊU CẦU PHẦN LÕI r = Rf + β × ERP | B44: =B31+B33*B32 -> 0.11224 | C44: =C31+C33*C32 -> 0.11224 | D44: =D31+D33*D32 -> 0.11224 | H44: =H31+H33*H32 -> 0.11224 | I44: =I31+I33*I32 -> 0.11224 | J44: =J31+J33*J32 -> 0.11224 | K44: =K31+K33*K32 -> 0.11224 | L44: =L31+L33*L32 -> 0.11224 | M44: =M31+M33*M32 -> 0.118 | N44: =N31+N33*N32 -> 0.1242 | O44: =O31+O33*O32 -> 0.11224 | ... W44: =W31+W33*W32 -> 0.11224
A45: LỢI SUẤT YÊU CẦU HAI DỰ ÁN = Rf + β dự án × ERP | B45: =B31+B34*B32 -> 0.1242 | C45: =C31+C34*C32 -> 0.1242 | D45: =D31+D34*D32 -> 0.1242 | H45: =H31+H34*H32 -> 0.1242 | I45: =I31+I34*I32 -> 0.1242 | J45: =J31+J34*J32 -> 0.1242 | K45: =K31+K34*K32 -> 0.1242 | L45: =L31+L34*L32 -> 0.1242 | M45: =M31+M34*M32 -> 0.131 | N45: =N31+N34*N32 -> 0.1242 | O45: =O31+O34*O32 -> 0.1242 | ... W45: =W31+W34*W32 -> 0.1242
A46: Chi đầu tư lõi (% doanh thu) | B46: ='02_Giả định'!B67 -> 0.023 | C46: ='02_Giả định'!C67 -> 0.026 | D46: ='02_Giả định'!D67 -> 0.028 | H46: =$C46 -> 0.026 | I46: =$C46 -> 0.026 | J46: =$C46 -> 0.026 | K46: =$C46 -> 0.026 | L46: =$C46 -> 0.026 | M46: =$C46 -> 0.026 | N46: =$C46 -> 0.026 | O46: =$C46 -> 0.026 | ... W46: =$C46 -> 0.026
A47: Khấu hao lõi (% doanh thu) | B47: ='02_Giả định'!B68 -> 0.023 | C47: ='02_Giả định'!C68 -> 0.023 | D47: ='02_Giả định'!D68 -> 0.023 | H47: =$C47 -> 0.023 | I47: =$C47 -> 0.023 | J47: =$C47 -> 0.023 | K47: =$C47 -> 0.023 | L47: =$C47 -> 0.023 | M47: =$C47 -> 0.023 | N47: =$C47 -> 0.023 | O47: =$C47 -> 0.023 | ... W47: =$C47 -> 0.023
A48: Vốn lưu động lõi (% doanh thu) | B48: ='02_Giả định'!B69 -> 0.04 | C48: ='02_Giả định'!C69 -> 0.04 | D48: ='02_Giả định'!D69 -> 0.04 | H48: =$C48 -> 0.04 | I48: =$C48 -> 0.04 | J48: =$C48 -> 0.04 | K48: =$C48 -> 0.04 | L48: =$C48 -> 0.04 | M48: =$C48 -> 0.04 | N48: =$C48 -> 0.04 | O48: =$C48 -> 0.04 | ... W48: =$C48 -> 0.04
A49: Hệ số giải phóng vốn lưu động | B49: ='02_Giả định'!B70 -> 0 | C49: ='02_Giả định'!C70 -> 1 | D49: ='02_Giả định'!D70 -> 1 | H49: =$C49 -> 1 | I49: =$C49 -> 1 | J49: =$C49 -> 1 | K49: =$C49 -> 1 | L49: =$C49 -> 1 | M49: =$C49 -> 1 | N49: =$C49 -> 1 | O49: =$C49 -> 1 | ... W49: =$C49 -> 1
A50: ROIC trạng thái dừng (dùng chung ba kịch bản) | B50: ='02_Giả định'!$B$54 -> 0.171 | C50: ='02_Giả định'!$B$54 -> 0.171 | D50: ='02_Giả định'!$B$54 -> 0.171 | H50: =$C50 -> 0.171 | I50: =$C50 -> 0.171 | J50: =$C50 -> 0.171 | K50: =$C50 -> 0.171 | L50: =$C50 -> 0.171 | M50: =$C50 -> 0.171 | N50: =$C50 -> 0.171 | O50: =$C50 -> 0.171 | ... W50: =$C50 -> 0.171
A52: A. LỢI NHUẬN LÕI CHUẨN HOÁ — tách bán cho Vinamilk (V) khỏi phần còn lại (B)
A53: Biên gộp của B = 12 tháng + chênh | B53: =B41+B8 -> 0.33246325 | C53: =C41+C8 -> 0.34746325 | D53: =D41+D8 -> 0.35746325 | H53: =H41+H8 -> 0.34746325 | I53: =I41+I8 -> 0.34746325 | J53: =J41+J8 -> 0.34746325 | K53: =K41+K8 -> 0.34746325 | L53: =L41+L8 -> 0.34746325 | M53: =M41+M8 -> 0.34746325 | N53: =N41+N8 -> 0.34746325 | O53: =O41+O8 -> 0.34746325 | ... W53: =W41+W8 -> 0.36131666
A54: Lãi gộp = mV × V + biên B × B | B54: =B40*B7+B53*B6 -> 801.41915 | C54: =C40*C7+C53*C6 -> 915.28496 | D54: =D40*D7+D53*D6 -> 1025.1508 | H54: =H40*H7+H53*H6 -> 915.28496 | I54: =I40*I7+I53*I6 -> 915.28496 | J54: =J40*J7+J53*J6 -> 915.28496 | K54: =K40*K7+K53*K6 -> 915.28496 | L54: =L40*L7+L53*L6 -> 915.28496 | M54: =M40*M7+M53*M6 -> 915.28496 | N54: =N40*N7+N53*N6 -> 915.28496 | O54: =O40*O7+O53*O6 -> 915.28496 | ... W54: =W40*W7+W53*W6 -> 917.22582
A55: Chi phí bán hàng = CPBH/B × B | B55: =B9*B6 -> 616 | C55: =C9*C6 -> 661.5 | D55: =D9*D6 -> 702 | F55: Hàng bán cho Vinamilk không tốn khuyến mãi | H55: =H9*H6 -> 661.5 | I55: =I9*I6 -> 661.5 | J55: =J9*J6 -> 661.5 | K55: =K9*K6 -> 661.5 | L55: =L9*L6 -> 661.5 | M55: =M9*M6 -> 661.5 | N55: =N9*N6 -> 661.5 | O55: =O9*O6 -> 661.5 | ... W55: =W9*W6 -> 661.5
A56: EBIT LÕI = lãi gộp − bán hàng − quản lý | B56: =B54-B55-B42 -> 146.41915 | C56: =C54-C55-C42 -> 214.78496 | D56: =D54-D55-D42 -> 284.15078 | F56: 12 tháng tới Q2/2026 (02 mục B, theo năm 2025 kiểm toán); 2023: 261,8; 2025: 152,3 | H56: =H54-H55-H42 -> 214.78496 | I56: =I54-I55-I42 -> 214.78496 | J56: =J54-J55-J42 -> 214.78496 | K56: =K54-K55-K42 -> 214.78496 | L56: =L54-L55-L42 -> 214.78496 | M56: =M54-M55-M42 -> 214.78496 | N56: =N54-N55-N42 -> 214.78496 | O56: =O54-O55-O42 -> 214.78496 | ... W56: =W54-W55-W42 -> 216.72582
A57: Lợi nhuận lõi sau thuế | B57: =B56*(1-B10) -> 133.24143 | C57: =C56*(1-C10) -> 195.45432 | D57: =D56*(1-D10) -> 258.57721 | H57: =H56*(1-H10) -> 195.45432 | I57: =I56*(1-I10) -> 195.45432 | J57: =J56*(1-J10) -> 195.45432 | K57: =K56*(1-K10) -> 195.45432 | L57: =L56*(1-L10) -> 195.45432 | M57: =M56*(1-M10) -> 195.45432 | N57: =N56*(1-N10) -> 195.45432 | O57: =O56*(1-O10) -> 195.45432 | ... W57: =W56*(1-W10) -> 197.22049
A58: LỢI NHUẬN LÕI THUỘC CỔ ĐÔNG (sau quỹ khen thưởng phúc lợi) | B58: =B57*(1-B36) -> 119.91728 | C58: =C57*(1-C36) -> 175.90888 | D58: =D57*(1-D36) -> 232.71949 | H58: =H57*(1-H36) -> 175.90888 | I58: =I57*(1-I36) -> 175.90888 | J58: =J57*(1-J36) -> 175.90888 | K58: =K57*(1-K36) -> 175.90888 | L58: =L57*(1-L36) -> 175.90888 | M58: =M57*(1-M36) -> 175.90888 | N58: =N57*(1-N36) -> 175.90888 | O58: =O57*(1-O36) -> 175.90888 | ... W58: =W57*(1-W36) -> 177.49844
A59: mỗi cổ phiếu (đồng) | B59: =B58*1000/'01_Số liệu gốc'!$B$8 -> 1090.1571 | C59: =C58*1000/'01_Số liệu gốc'!$B$8 -> 1599.1717 | D59: =D58*1000/'01_Số liệu gốc'!$B$8 -> 2115.6317 | H59: =H58*1000/'01_Số liệu gốc'!$B$8 -> 1599.1717 | I59: =I58*1000/'01_Số liệu gốc'!$B$8 -> 1599.1717 | J59: =J58*1000/'01_Số liệu gốc'!$B$8 -> 1599.1717 | K59: =K58*1000/'01_Số liệu gốc'!$B$8 -> 1599.1717 | L59: =L58*1000/'01_Số liệu gốc'!$B$8 -> 1599.1717 | M59: =M58*1000/'01_Số liệu gốc'!$B$8 -> 1599.1717 | N59: =N58*1000/'01_Số liệu gốc'!$B$8 -> 1599.1717 | O59: =O58*1000/'01_Số liệu gốc'!$B$8 -> 1599.1717 | ... W59: =W58*1000/'01_Số liệu gốc'!$B$8 -> 1613.6222
A60: EBITDA lõi = EBIT lõi + khấu hao | B60: =B56+B43 -> 217.32715 | C60: =C56+C43 -> 285.69296 | D60: =D56+D43 -> 355.05878 | H60: =H56+H43 -> 285.69296 | I60: =I56+I43 -> 285.69296 | J60: =J56+J43 -> 285.69296 | K60: =K56+K43 -> 285.69296 | L60: =L56+L43 -> 285.69296 | M60: =M56+M43 -> 285.69296 | N60: =N56+N43 -> 285.69296 | O60: =O56+O43 -> 285.69296 | ... W60: =W56+W43 -> 287.63382
A61: Vốn hoạt động lõi 30/06/2026 | B61: ='01_Số liệu gốc'!$C$73 -> 463.235 | C61: ='01_Số liệu gốc'!$C$73 -> 463.235 | D61: ='01_Số liệu gốc'!$C$73 -> 463.235 | H61: ='01_Số liệu gốc'!$C$73 -> 463.235 | I61: ='01_Số liệu gốc'!$C$73 -> 463.235 | J61: ='01_Số liệu gốc'!$C$73 -> 463.235 | K61: ='01_Số liệu gốc'!$C$73 -> 463.235 | L61: ='01_Số liệu gốc'!$C$73 -> 463.235 | M61: ='01_Số liệu gốc'!$C$73 -> 463.235 | N61: ='01_Số liệu gốc'!$C$73 -> 463.235 | O61: ='01_Số liệu gốc'!$C$73 -> 463.235 | ... W61: ='01_Số liệu gốc'!$C$73 -> 463.235
A62: ROIC lõi | B62: =B57/B61 -> 0.28763247 | C62: =C57/C61 -> 0.4219334 | D62: =D57/D61 -> 0.55819877 | H62: =H57/H61 -> 0.4219334 | I62: =I57/I61 -> 0.4219334 | J62: =J57/J61 -> 0.4219334 | K62: =K57/K61 -> 0.4219334 | L62: =L57/L61 -> 0.4219334 | M62: =M57/M61 -> 0.4219334 | N62: =N57/N61 -> 0.4219334 | O62: =O57/O61 -> 0.4219334 | ... W62: =W57/W61 -> 0.42574609
A64: B. HAI DỰ ÁN — năm đủ công suất (giả định ở 06_Dự án; dòng tiền từng năm ở mục D, giá trị ở mục B2)
A65: Trang trại: tổng vốn theo kịch bản = phần bò sữa + phần du lịch | B65: =B17+B18 -> 1196 | C65: =C17+C18 -> 1120 | D65: =D17+D18 -> 1120 | H65: =H17+H18 -> 1120 | I65: =I17+I18 -> 1120 | J65: =J17+J18 -> 1120 | K65: =K17+K18 -> 1120 | L65: =L17+L18 -> 1120 | M65: =M17+M18 -> 1120 | N65: =N17+N18 -> 1120 | O65: =O17+O18 -> 1120 | ... W65: =W17+W18 -> 1120
A66: Trang trại: còn phải chi sau 30/06/2026 (dồn vào 2027) | B66: =MAX(0,B65-'01_Số liệu gốc'!$C$68) -> 780.679 | C66: =MAX(0,C65-'01_Số liệu gốc'!$C$68) -> 704.679 | D66: =MAX(0,D65-'01_Số liệu gốc'!$C$68) -> 704.679 | F66: Phần đã ghi sổ là chi phí chìm | H66: =MAX(0,H65-'01_Số liệu gốc'!$C$68) -> 704.679 | I66: =MAX(0,I65-'01_Số liệu gốc'!$C$68) -> 704.679 | J66: =MAX(0,J65-'01_Số liệu gốc'!$C$68) -> 704.679 | K66: =MAX(0,K65-'01_Số liệu gốc'!$C$68) -> 704.679 | L66: =MAX(0,L65-'01_Số liệu gốc'!$C$68) -> 704.679 | M66: =MAX(0,M65-'01_Số liệu gốc'!$C$68) -> 704.679 | N66: =MAX(0,N65-'01_Số liệu gốc'!$C$68) -> 704.679 | O66: =MAX(0,O65-'01_Số liệu gốc'!$C$68) -> 704.679 | ... W66: =MAX(0,W65-'01_Số liệu gốc'!$C$68) -> 704.679
A67: Trang trại: doanh thu khi đủ đàn = triệu lít × giá × (1 + thu thêm) ÷ 1.000 | B67: =B19*B21*(1+B23)/1000 -> 245.7 | C67: =C19*C21*(1+C23)/1000 -> 304.5 | D67: =D19*D21*(1+D23)/1000 -> 346.5 | H67: =H19*H21*(1+H23)/1000 -> 304.5 | I67: =I19*I21*(1+I23)/1000 -> 304.5 | J67: =J19*J21*(1+J23)/1000 -> 304.5 | K67: =K19*K21*(1+K23)/1000 -> 273 | L67: =L19*L21*(1+L23)/1000 -> 304.5 | M67: =M19*M21*(1+M23)/1000 -> 304.5 | N67: =N19*N21*(1+N23)/1000 -> 304.5 | O67: =O19*O21*(1+O23)/1000 -> 304.5 | ... W67: =W19*W21*(1+W23)/1000 -> 304.5
A68: lãi trước khấu hao = doanh thu − triệu lít × chi phí ÷ 1.000 | B68: =B67-B19*B22/1000 -> 56.7 | C68: =C67-C19*C22/1000 -> 94.5 | D68: =D67-D19*D22/1000 -> 115.5 | H68: =H67-H19*H22/1000 -> 94.5 | I68: =I67-I19*I22/1000 -> 94.5 | J68: =J67-J19*J22/1000 -> 94.5 | K68: =K67-K19*K22/1000 -> 63 | L68: =L67-L19*L22/1000 -> 74.5 | M68: =M67-M19*M22/1000 -> 94.5 | N68: =N67-N19*N22/1000 -> 94.5 | O68: =O67-O19*O22/1000 -> 94.5 | ... W68: =W67-W19*W22/1000 -> 94.5
A69: khấu hao phần bò sữa | B69: =B17/B25 -> 43 | C69: =C17/C25 -> 39.2 | D69: =D17/D25 -> 39.2 | H69: =H17/H25 -> 39.2 | I69: =I17/I25 -> 39.2 | J69: =J17/J25 -> 39.2 | K69: =K17/K25 -> 39.2 | L69: =L17/L25 -> 39.2 | M69: =M17/M25 -> 39.2 | N69: =N17/N25 -> 39.2 | O69: =O17/O25 -> 39.2 | ... W69: =W17/W25 -> 39.2
A70: lãi kế toán (thu nhập chăn nuôi miễn thuế) | B70: =B68-B69 -> 13.7 | C70: =C68-C69 -> 55.3 | D70: =D68-D69 -> 76.3 | H70: =H68-H69 -> 55.3 | I70: =I68-I69 -> 55.3 | J70: =J68-J69 -> 55.3 | K70: =K68-K69 -> 23.8 | L70: =L68-L69 -> 35.3 | M70: =M68-M69 -> 55.3 | N70: =N68-N69 -> 55.3 | O70: =O68-O69 -> 55.3 | ... W70: =W68-W69 -> 55.3
A71: tiền thu về = lãi trước khấu hao − chi duy trì | B71: =B68-B24 -> 41.7 | C71: =C68-C24 -> 79.5 | D71: =D68-D24 -> 100.5 | H71: =H68-H24 -> 79.5 | I71: =I68-I24 -> 79.5 | J71: =J68-J24 -> 79.5 | K71: =K68-K24 -> 48 | L71: =L68-L24 -> 59.5 | M71: =M68-M24 -> 79.5 | N71: =N68-N24 -> 79.5 | O71: =O68-O24 -> 79.5 | ... W71: =W68-W24 -> 79.5
A72: lãi trên vốn phần bò sữa | B72: =B70/B17 -> 0.015930233 | C72: =C70/C17 -> 0.070535714 | D72: =D70/D17 -> 0.097321429 | H72: =H70/H17 -> 0.070535714 | I72: =I70/I17 -> 0.070535714 | J72: =J70/J17 -> 0.070535714 | K72: =K70/K17 -> 0.030357143 | L72: =L70/L17 -> 0.04502551 | M72: =M70/M17 -> 0.070535714 | N72: =N70/N17 -> 0.070535714 | O72: =O70/O17 -> 0.070535714 | ... W72: =W70/W17 -> 0.070535714
A73: Du lịch: lãi sau thuế 20% từ 2028 | B73: =B26*(1-B37) -> 0 | C73: =C26*(1-C37) -> 8 | D73: =D26*(1-D37) -> 20 | H73: =H26*(1-H37) -> 8 | I73: =I26*(1-I37) -> 8 | J73: =J26*(1-J37) -> 8 | K73: =K26*(1-K37) -> 8 | L73: =L26*(1-L37) -> 8 | M73: =M26*(1-M37) -> 8 | N73: =N26*(1-N37) -> 8 | O73: =O26*(1-O37) -> 8 | ... W73: =W26*(1-W37) -> 8
A74: Nhà máy: vốn còn phải chi | B74: =B27*MAX(0,B28-'01_Số liệu gốc'!$C$69) -> 818.923 | C74: =C27*MAX(0,C28-'01_Số liệu gốc'!$C$69) -> 711.923 | D74: =D27*MAX(0,D28-'01_Số liệu gốc'!$C$69) -> 711.923 | F74: Không xây thì 31 tỷ dở dang mất trắng (đã là chi phí chìm) | H74: =H27*MAX(0,H28-'01_Số liệu gốc'!$C$69) -> 711.923 | I74: =I27*MAX(0,I28-'01_Số liệu gốc'!$C$69) -> 0 | J74: =J27*MAX(0,J28-'01_Số liệu gốc'!$C$69) -> 711.923 | K74: =K27*MAX(0,K28-'01_Số liệu gốc'!$C$69) -> 711.923 | L74: =L27*MAX(0,L28-'01_Số liệu gốc'!$C$69) -> 711.923 | M74: =M27*MAX(0,M28-'01_Số liệu gốc'!$C$69) -> 711.923 | N74: =N27*MAX(0,N28-'01_Số liệu gốc'!$C$69) -> 711.923 | O74: =O27*MAX(0,O28-'01_Số liệu gốc'!$C$69) -> 711.923 | ... W74: =W27*MAX(0,W28-'01_Số liệu gốc'!$C$69) -> 711.923
A75: lãi tăng thêm ĐẦY CÔNG SUẤT ÷ vốn | B75: =IF(B27=0,0,B271/B28) -> 0.023529412 | C75: =IF(C27=0,0,C271/C28) -> 0.12113055 | D75: =IF(D27=0,0,D271/D28) -> 0.14804845 | H75: =IF(H27=0,0,H271/H28) -> 0.12113055 | I75: =IF(I27=0,0,I271/I28) -> 0 | J75: =IF(J27=0,0,J271/J28) -> 0.12113055 | K75: =IF(K27=0,0,K271/K28) -> 0.12113055 | L75: =IF(L27=0,0,L271/L28) -> 0.12113055 | M75: =IF(M27=0,0,M271/M28) -> 0.12113055 | N75: =IF(N27=0,0,N271/N28) -> 0.12113055 | O75: =IF(O27=0,0,O271/O28) -> 0.12113055 | ... W75: =IF(W27=0,0,W271/W28) -> 0.12113055
A76: Hệ số dòng tiền đều 20 năm sau 2031 ở lợi suất dự án | B76: =(1-(1+B45)^-20)/B45 -> 7.2770559 | C76: =(1-(1+C45)^-20)/C45 -> 7.2770559 | D76: =(1-(1+D45)^-20)/D45 -> 7.2770559 | H76: =(1-(1+H45)^-20)/H45 -> 7.2770559 | I76: =(1-(1+I45)^-20)/I45 -> 7.2770559 | J76: =(1-(1+J45)^-20)/J45 -> 7.2770559 | K76: =(1-(1+K45)^-20)/K45 -> 7.2770559 | L76: =(1-(1+L45)^-20)/L45 -> 7.2770559 | M76: =(1-(1+M45)^-20)/M45 -> 6.9827442 | N76: =(1-(1+N45)^-20)/N45 -> 7.2770559 | O76: =(1-(1+O45)^-20)/O45 -> 7.2770559 | ... W76: =(1-(1+W45)^-20)/W45 -> 7.2770559
A78: D. DÒNG TIỀN 2027–2031 — lõi (phương pháp 2), hai dự án (B2), tiền ròng và cổ tức (phương pháp 3)
A79: Năm 1 — 2027 · lõi: 12 tháng 07/2026–06/2027, chiết khấu t = 0,5 · dự án: năm dương lịch 2027, t = 1
A80: B | B80: =B6*(1+B11)^0 -> 2200 | C80: =C6*(1+C11)^0 -> 2450 | D80: =D6*(1+D11)^0 -> 2700 | H80: =H6*(1+H11)^0 -> 2450 | I80: =I6*(1+I11)^0 -> 2450 | J80: =J6*(1+J11)^0 -> 2450 | K80: =K6*(1+K11)^0 -> 2450 | L80: =L6*(1+L11)^0 -> 2450 | M80: =M6*(1+M11)^0 -> 2450 | N80: =N6*(1+N11)^0 -> 2450 | O80: =O6*(1+O11)^0 -> 2450 | ... W80: =W6*(1+W11)^0 -> 2450
A81: EBIT lõi | B81: =B40*B7+(B53-B9)*B80-B42*(1+B35)^0 -> 146.41915 | C81: =C40*C7+(C53-C9)*C80-C42*(1+C35)^0 -> 214.78496 | D81: =D40*D7+(D53-D9)*D80-D42*(1+D35)^0 -> 284.15078 | H81: =H40*H7+(H53-H9)*H80-H42*(1+H35)^0 -> 214.78496 | I81: =I40*I7+(I53-I9)*I80-I42*(1+I35)^0 -> 214.78496 | J81: =J40*J7+(J53-J9)*J80-J42*(1+J35)^0 -> 214.78496 | K81: =K40*K7+(K53-K9)*K80-K42*(1+K35)^0 -> 214.78496 | L81: =L40*L7+(L53-L9)*L80-L42*(1+L35)^0 -> 214.78496 | M81: =M40*M7+(M53-M9)*M80-M42*(1+M35)^0 -> 214.78496 | N81: =N40*N7+(N53-N9)*N80-N42*(1+N35)^0 -> 214.78496 | O81: =O40*O7+(O53-O9)*O80-O42*(1+O35)^0 -> 214.78496 | ... W81: =W40*W7+(W53-W9)*W80-W42*(1+W35)^0 -> 216.72582
A82: lợi nhuận lõi sau thuế | B82: =B81*(1-B10) -> 133.24143 | C82: =C81*(1-C10) -> 195.45432 | D82: =D81*(1-D10) -> 258.57721 | H82: =H81*(1-H10) -> 195.45432 | I82: =I81*(1-I10) -> 195.45432 | J82: =J81*(1-J10) -> 195.45432 | K82: =K81*(1-K10) -> 195.45432 | L82: =L81*(1-L10) -> 195.45432 | M82: =M81*(1-M10) -> 195.45432 | N82: =N81*(1-N10) -> 195.45432 | O82: =O81*(1-O10) -> 195.45432 | ... W82: =W81*(1-W10) -> 197.22049
A83: tái đầu tư lõi = (chi đầu tư − khấu hao) × doanh thu + vốn lưu động × tăng doanh thu | B83: =(B46-B47)*(B80+B7)+B48*IF((B80+B7-'02_Giả định'!$B$30)<0,B49,1)*(B80+B7-'02_Giả định'!$B$30) -> 0 | C83: =(C46-C47)*(C80+C7)+C48*IF((C80+C7-'02_Giả định'!$B$30)<0,C49,1)*(C80+C7-'02_Giả định'!$B$30) -> 15.38928 | D83: =(D46-D47)*(D80+D7)+D48*IF((D80+D7-'02_Giả định'!$B$30)<0,D49,1)*(D80+D7-'02_Giả định'!$B$30) -> 31.01928 | H83: =(H46-H47)*(H80+H7)+H48*IF((H80+H7-'02_Giả định'!$B$30)<0,H49,1)*(H80+H7-'02_Giả định'!$B$30) -> 15.38928 | I83: =(I46-I47)*(I80+I7)+I48*IF((I80+I7-'02_Giả định'!$B$30)<0,I49,1)*(I80+I7-'02_Giả định'!$B$30) -> 15.38928 | J83: =(J46-J47)*(J80+J7)+J48*IF((J80+J7-'02_Giả định'!$B$30)<0,J49,1)*(J80+J7-'02_Giả định'!$B$30) -> 15.38928 | K83: =(K46-K47)*(K80+K7)+K48*IF((K80+K7-'02_Giả định'!$B$30)<0,K49,1)*(K80+K7-'02_Giả định'!$B$30) -> 15.38928 | L83: =(L46-L47)*(L80+L7)+L48*IF((L80+L7-'02_Giả định'!$B$30)<0,L49,1)*(L80+L7-'02_Giả định'!$B$30) -> 15.38928 | M83: =(M46-M47)*(M80+M7)+M48*IF((M80+M7-'02_Giả định'!$B$30)<0,M49,1)*(M80+M7-'02_Giả định'!$B$30) -> 15.38928 | N83: =(N46-N47)*(N80+N7)+N48*IF((N80+N7-'02_Giả định'!$B$30)<0,N49,1)*(N80+N7-'02_Giả định'!$B$30) -> 15.38928 | O83: =(O46-O47)*(O80+O7)+O48*IF((O80+O7-'02_Giả định'!$B$30)<0,O49,1)*(O80+O7-'02_Giả định'!$B$30) -> 15.38928 | ... W83: =(W46-W47)*(W80+W7)+W48*IF((W80+W7-'02_Giả định'!$B$30)<0,W49,1)*(W80+W7-'02_Giả định'!$B$30) -> 15.38928
A84: dòng tiền tự do phần lõi = lõi × (1 − quỹ) − tái đầu tư | B84: =B82*(1-B36)-B83 -> 119.91728 | C84: =C82*(1-C36)-C83 -> 160.5196 | D84: =D82*(1-D36)-D83 -> 201.70021 | H84: =H82*(1-H36)-H83 -> 160.5196 | I84: =I82*(1-I36)-I83 -> 160.5196 | J84: =J82*(1-J36)-J83 -> 160.5196 | K84: =K82*(1-K36)-K83 -> 160.5196 | L84: =L82*(1-L36)-L83 -> 160.5196 | M84: =M82*(1-M36)-M83 -> 160.5196 | N84: =N82*(1-N36)-N83 -> 160.5196 | O84: =O82*(1-O36)-O83 -> 160.5196 | ... W84: =W82*(1-W36)-W83 -> 162.10916
A85: hiện giá dòng tiền phần lõi ở r (giữa kỳ) | B85: =B84/(1+B44)^0.5 -> 113.70578 | C85: =C84/(1+C44)^0.5 -> 152.20497 | D85: =D84/(1+D44)^0.5 -> 191.25248 | H85: =H84/(1+H44)^0.5 -> 152.20497 | I85: =I84/(1+I44)^0.5 -> 152.20497 | J85: =J84/(1+J44)^0.5 -> 152.20497 | K85: =K84/(1+K44)^0.5 -> 152.20497 | L85: =L84/(1+L44)^0.5 -> 152.20497 | M85: =M84/(1+M44)^0.5 -> 151.81238 | N85: =N84/(1+N44)^0.5 -> 151.39317 | O85: =O84/(1+O44)^0.5 -> 152.20497 | ... W85: =W84/(1+W44)^0.5 -> 153.71219
A86: chi trang trại | B86: =B66 -> 780.679 | C86: =C66 -> 704.679 | D86: =D66 -> 704.679 | H86: =H66 -> 704.679 | I86: =I66 -> 704.679 | J86: =J66 -> 704.679 | K86: =K66 -> 704.679 | L86: =L66 -> 704.679 | M86: =M66 -> 704.679 | N86: =N66 -> 704.679 | O86: =O66 -> 704.679 | ... W86: =W66 -> 704.679
A87: chi nhà máy (50% hai năm trước năm có lãi; có lãi 2028 thì dồn vào 2027) | B87: =B74*(IF(B29-2027=1,0.5,0)+IF(B29-2027=2,0.5,0)+IF(AND(B29=2028,2027=2027),0.5,0)) -> 0 | C87: =C74*(IF(C29-2027=1,0.5,0)+IF(C29-2027=2,0.5,0)+IF(AND(C29=2028,2027=2027),0.5,0)) -> 0 | D87: =D74*(IF(D29-2027=1,0.5,0)+IF(D29-2027=2,0.5,0)+IF(AND(D29=2028,2027=2027),0.5,0)) -> 0 | H87: =H74*(IF(H29-2027=1,0.5,0)+IF(H29-2027=2,0.5,0)+IF(AND(H29=2028,2027=2027),0.5,0)) -> 0 | I87: =I74*(IF(I29-2027=1,0.5,0)+IF(I29-2027=2,0.5,0)+IF(AND(I29=2028,2027=2027),0.5,0)) -> 0 | J87: =J74*(IF(J29-2027=1,0.5,0)+IF(J29-2027=2,0.5,0)+IF(AND(J29=2028,2027=2027),0.5,0)) -> 711.923 | K87: =K74*(IF(K29-2027=1,0.5,0)+IF(K29-2027=2,0.5,0)+IF(AND(K29=2028,2027=2027),0.5,0)) -> 0 | L87: =L74*(IF(L29-2027=1,0.5,0)+IF(L29-2027=2,0.5,0)+IF(AND(L29=2028,2027=2027),0.5,0)) -> 0 | M87: =M74*(IF(M29-2027=1,0.5,0)+IF(M29-2027=2,0.5,0)+IF(AND(M29=2028,2027=2027),0.5,0)) -> 0 | N87: =N74*(IF(N29-2027=1,0.5,0)+IF(N29-2027=2,0.5,0)+IF(AND(N29=2028,2027=2027),0.5,0)) -> 0 | O87: =O74*(IF(O29-2027=1,0.5,0)+IF(O29-2027=2,0.5,0)+IF(AND(O29=2028,2027=2027),0.5,0)) -> 0 | ... W87: =W74*(IF(W29-2027=1,0.5,0)+IF(W29-2027=2,0.5,0)+IF(AND(W29=2028,2027=2027),0.5,0)) -> 0
A88: chi hai dự án | B88: =B86+B87 -> 780.679 | C88: =C86+C87 -> 704.679 | D88: =D86+D87 -> 704.679 | H88: =H86+H87 -> 704.679 | I88: =I86+I87 -> 704.679 | J88: =J86+J87 -> 1416.602 | K88: =K86+K87 -> 704.679 | L88: =L86+L87 -> 704.679 | M88: =M86+M87 -> 704.679 | N88: =N86+N87 -> 704.679 | O88: =O86+O87 -> 704.679 | ... W88: =W86+W87 -> 704.679
A89: lãi kế toán trang trại + du lịch | B89: =B70*B20 -> 4.11 | C89: =C70*C20 -> 27.65 | D89: =D70*D20 -> 45.78 | H89: =H70*H20 -> 27.65 | I89: =I70*I20 -> 27.65 | J89: =J70*J20 -> 27.65 | K89: =K70*K20 -> 11.9 | L89: =L70*L20 -> 17.65 | M89: =M70*M20 -> 27.65 | N89: =N70*N20 -> 27.65 | O89: =O70*O20 -> 27.65 | ... W89: =W70*W20 -> 27.65
A90: lãi tăng thêm nhà máy | B90: =B27*B275 -> 0 | C90: =C27*C275 -> 0 | D90: =D27*D275 -> 0 | H90: =H27*H275 -> 0 | I90: =I27*I275 -> 0 | J90: =J27*J275 -> 0 | K90: =K27*K275 -> 0 | L90: =L27*L275 -> 0 | M90: =M27*M275 -> 0 | N90: =N27*N275 -> 0 | O90: =O27*O275 -> 0 | ... W90: =W27*W275 -> 0
A91: lãi kế toán hai dự án | B91: =B89+B90 -> 4.11 | C91: =C89+C90 -> 27.65 | D91: =D89+D90 -> 45.78 | H91: =H89+H90 -> 27.65 | I91: =I89+I90 -> 27.65 | J91: =J89+J90 -> 27.65 | K91: =K89+K90 -> 11.9 | L91: =L89+L90 -> 17.65 | M91: =M89+M90 -> 27.65 | N91: =N89+N90 -> 27.65 | O91: =O89+O90 -> 27.65 | ... W91: =W89+W90 -> 27.65
A92: dòng tiền trang trại + du lịch = tiền thu − quỹ × lãi dương − chi | B92: =B71*B20-B36*MAX(0,B89)-B86 -> -768.58 | C92: =C71*C20-C36*MAX(0,C89)-C86 -> -667.694 | D92: =D71*D20-D36*MAX(0,D89)-D86 -> -648.957 | H92: =H71*H20-H36*MAX(0,H89)-H86 -> -667.694 | I92: =I71*I20-I36*MAX(0,I89)-I86 -> -667.694 | J92: =J71*J20-J36*MAX(0,J89)-J86 -> -667.694 | K92: =K71*K20-K36*MAX(0,K89)-K86 -> -681.869 | L92: =L71*L20-L36*MAX(0,L89)-L86 -> -676.694 | M92: =M71*M20-M36*MAX(0,M89)-M86 -> -667.694 | N92: =N71*N20-N36*MAX(0,N89)-N86 -> -667.694 | O92: =O71*O20-O36*MAX(0,O89)-O86 -> -667.694 | ... W92: =W71*W20-W36*MAX(0,W89)-W86 -> -667.694
A93: dòng tiền nhà máy = lãi × (1 − quỹ) − chi | B93: =B90*(1-B36)-B87 -> 0 | C93: =C90*(1-C36)-C87 -> 0 | D93: =D90*(1-D36)-D87 -> 0 | H93: =H90*(1-H36)-H87 -> 0 | I93: =I90*(1-I36)-I87 -> 0 | J93: =J90*(1-J36)-J87 -> -711.923 | K93: =K90*(1-K36)-K87 -> 0 | L93: =L90*(1-L36)-L87 -> 0 | M93: =M90*(1-M36)-M87 -> 0 | N93: =N90*(1-N36)-N87 -> 0 | O93: =O90*(1-O36)-O87 -> 0 | ... W93: =W90*(1-W36)-W87 -> 0
A94: hiện giá dòng tiền trang trại ở lợi suất dự án | B94: =B92/(1+B45)^1 -> -683.66839 | C94: =C92/(1+C45)^1 -> -593.92813 | D94: =D92/(1+D45)^1 -> -577.26116 | H94: =H92/(1+H45)^1 -> -593.92813 | I94: =I92/(1+I45)^1 -> -593.92813 | J94: =J92/(1+J45)^1 -> -593.92813 | K94: =K92/(1+K45)^1 -> -606.53709 | L94: =L92/(1+L45)^1 -> -601.93382 | M94: =M92/(1+M45)^1 -> -590.35721 | N94: =N92/(1+N45)^1 -> -593.92813 | O94: =O92/(1+O45)^1 -> -593.92813 | ... W94: =W92/(1+W45)^1 -> -593.92813
A95: hiện giá dòng tiền nhà máy ở lợi suất dự án | B95: =B93/(1+B45)^1 -> 0 | C95: =C93/(1+C45)^1 -> 0 | D95: =D93/(1+D45)^1 -> 0 | H95: =H93/(1+H45)^1 -> 0 | I95: =I93/(1+I45)^1 -> 0 | J95: =J93/(1+J45)^1 -> -633.27077 | K95: =K93/(1+K45)^1 -> 0 | L95: =L93/(1+L45)^1 -> 0 | M95: =M93/(1+M45)^1 -> 0 | N95: =N93/(1+N45)^1 -> 0 | O95: =O93/(1+O45)^1 -> 0 | ... W95: =W93/(1+W45)^1 -> 0
A96: lãi tiền gửi (âm = lãi vay) trên số dư đầu năm | B96: =IF('01_Số liệu gốc'!$C$65>0,B16,B38)*'01_Số liệu gốc'!$C$65 -> 90.904905 | C96: =IF('01_Số liệu gốc'!$C$65>0,C16,C38)*'01_Số liệu gốc'!$C$65 -> 97.89759 | D96: =IF('01_Số liệu gốc'!$C$65>0,D16,D38)*'01_Số liệu gốc'!$C$65 -> 104.89028 | H96: =IF('01_Số liệu gốc'!$C$65>0,H16,H38)*'01_Số liệu gốc'!$C$65 -> 97.89759 | I96: =IF('01_Số liệu gốc'!$C$65>0,I16,I38)*'01_Số liệu gốc'!$C$65 -> 97.89759 | J96: =IF('01_Số liệu gốc'!$C$65>0,J16,J38)*'01_Số liệu gốc'!$C$65 -> 97.89759 | K96: =IF('01_Số liệu gốc'!$C$65>0,K16,K38)*'01_Số liệu gốc'!$C$65 -> 97.89759 | L96: =IF('01_Số liệu gốc'!$C$65>0,L16,L38)*'01_Số liệu gốc'!$C$65 -> 97.89759 | M96: =IF('01_Số liệu gốc'!$C$65>0,M16,M38)*'01_Số liệu gốc'!$C$65 -> 97.89759 | N96: =IF('01_Số liệu gốc'!$C$65>0,N16,N38)*'01_Số liệu gốc'!$C$65 -> 97.89759 | O96: =IF('01_Số liệu gốc'!$C$65>0,O16,O38)*'01_Số liệu gốc'!$C$65 -> 97.89759 | ... W96: =IF('01_Số liệu gốc'!$C$65>0,W16,W38)*'01_Số liệu gốc'!$C$65 -> 97.89759
A97: LNST = lõi + dự án + lãi × (1 − 20%) | B97: =B82+B91+B96*(1-B37) -> 210.07535 | C97: =C82+C91+C96*(1-C37) -> 301.42239 | D97: =D82+D91+D96*(1-D37) -> 388.26943 | H97: =H82+H91+H96*(1-H37) -> 301.42239 | I97: =I82+I91+I96*(1-I37) -> 301.42239 | J97: =J82+J91+J96*(1-J37) -> 301.42239 | K97: =K82+K91+K96*(1-K37) -> 285.67239 | L97: =L82+L91+L96*(1-L37) -> 291.42239 | M97: =M82+M91+M96*(1-M37) -> 301.42239 | N97: =N82+N91+N96*(1-N37) -> 301.42239 | O97: =O82+O91+O96*(1-O37) -> 301.42239 | ... W97: =W82+W91+W96*(1-W37) -> 303.18856
A98: cổ tức tiền mặt | B98: =B15*'01_Số liệu gốc'!$B$8/1000 -> 110 | C98: =C15*'01_Số liệu gốc'!$B$8/1000 -> 165 | D98: =D15*'01_Số liệu gốc'!$B$8/1000 -> 220 | H98: =H15*'01_Số liệu gốc'!$B$8/1000 -> 165 | I98: =I15*'01_Số liệu gốc'!$B$8/1000 -> 165 | J98: =J15*'01_Số liệu gốc'!$B$8/1000 -> 165 | K98: =K15*'01_Số liệu gốc'!$B$8/1000 -> 165 | L98: =L15*'01_Số liệu gốc'!$B$8/1000 -> 165 | M98: =M15*'01_Số liệu gốc'!$B$8/1000 -> 165 | N98: =N15*'01_Số liệu gốc'!$B$8/1000 -> 165 | O98: =O15*'01_Số liệu gốc'!$B$8/1000 -> 110 | ... W98: =W15*'01_Số liệu gốc'!$B$8/1000 -> 165
A99: cộng lại khấu hao trang trại − chi duy trì (không ra tiền) | B99: =(B69-B24)*B20 -> 8.4 | C99: =(C69-C24)*C20 -> 12.1 | D99: =(D69-D24)*D20 -> 14.52 | H99: =(H69-H24)*H20 -> 12.1 | I99: =(I69-I24)*I20 -> 12.1 | J99: =(J69-J24)*J20 -> 12.1 | K99: =(K69-K24)*K20 -> 12.1 | L99: =(L69-L24)*L20 -> 12.1 | M99: =(M69-M24)*M20 -> 12.1 | N99: =(N69-N24)*N20 -> 12.1 | O99: =(O69-O24)*O20 -> 12.1 | ... W99: =(W69-W24)*W20 -> 12.1
A100: TIỀN RÒNG CUỐI NĂM (âm = phải vay) | B100: ='01_Số liệu gốc'!$C$65+B97*(1-B36)-B98-B88-B83+B99 -> 705.32582 | C100: ='01_Số liệu gốc'!$C$65+C97*(1-C36)-C98-C88-C83+C99 -> 796.84887 | D100: ='01_Số liệu gốc'!$C$65+D97*(1-D36)-D98-D88-D83+D99 -> 806.8012 | H100: ='01_Số liệu gốc'!$C$65+H97*(1-H36)-H98-H88-H83+H99 -> 796.84887 | I100: ='01_Số liệu gốc'!$C$65+I97*(1-I36)-I98-I88-I83+I99 -> 796.84887 | J100: ='01_Số liệu gốc'!$C$65+J97*(1-J36)-J98-J88-J83+J99 -> 84.92587 | K100: ='01_Số liệu gốc'!$C$65+K97*(1-K36)-K98-K88-K83+K99 -> 782.67387 | L100: ='01_Số liệu gốc'!$C$65+L97*(1-L36)-L98-L88-L83+L99 -> 787.84887 | M100: ='01_Số liệu gốc'!$C$65+M97*(1-M36)-M98-M88-M83+M99 -> 796.84887 | N100: ='01_Số liệu gốc'!$C$65+N97*(1-N36)-N98-N88-N83+N99 -> 796.84887 | O100: ='01_Số liệu gốc'!$C$65+O97*(1-O36)-O98-O88-O83+O99 -> 851.84887 | ... W100: ='01_Số liệu gốc'!$C$65+W97*(1-W36)-W98-W88-W83+W99 -> 798.43843
A101: vốn chủ cuối năm | B101: ='01_Số liệu gốc'!$C$67+B97*(1-B36)-B98 -> 2400.1568 | C101: ='01_Số liệu gốc'!$C$67+C97*(1-C36)-C98 -> 2427.3691 | D101: ='01_Số liệu gốc'!$C$67+D97*(1-D36)-D98 -> 2450.5315 | H101: ='01_Số liệu gốc'!$C$67+H97*(1-H36)-H98 -> 2427.3691 | I101: ='01_Số liệu gốc'!$C$67+I97*(1-I36)-I98 -> 2427.3691 | J101: ='01_Số liệu gốc'!$C$67+J97*(1-J36)-J98 -> 2427.3691 | K101: ='01_Số liệu gốc'!$C$67+K97*(1-K36)-K98 -> 2413.1941 | L101: ='01_Số liệu gốc'!$C$67+L97*(1-L36)-L98 -> 2418.3691 | M101: ='01_Số liệu gốc'!$C$67+M97*(1-M36)-M98 -> 2427.3691 | N101: ='01_Số liệu gốc'!$C$67+N97*(1-N36)-N98 -> 2427.3691 | O101: ='01_Số liệu gốc'!$C$67+O97*(1-O36)-O98 -> 2482.3691 | ... W101: ='01_Số liệu gốc'!$C$67+W97*(1-W36)-W98 -> 2428.9587
A102: hiện giá cổ tức | B102: =B98/(1+B44)^1 -> 98.899518 | C102: =C98/(1+C44)^1 -> 148.34928 | D102: =D98/(1+D44)^1 -> 197.79904 | H102: =H98/(1+H44)^1 -> 148.34928 | I102: =I98/(1+I44)^1 -> 148.34928 | J102: =J98/(1+J44)^1 -> 148.34928 | K102: =K98/(1+K44)^1 -> 148.34928 | L102: =L98/(1+L44)^1 -> 148.34928 | M102: =M98/(1+M44)^1 -> 147.58497 | N102: =N98/(1+N44)^1 -> 146.77104 | O102: =O98/(1+O44)^1 -> 98.899518 | ... W102: =W98/(1+W44)^1 -> 148.34928
A103: Năm 2 — 2028 · lõi: 12 tháng 07/2027–06/2028, chiết khấu t = 1,5 · dự án: năm dương lịch 2028, t = 2
...

Sheet 04_Độ nhạy
A1: MCM — ĐỘ NHẠY (đồng/cổ phiếu)
A2: Quanh kịch bản CƠ SỞ. Ô nền vàng = cơ sở; nền cam = thấp hơn giá hiện tại (bảng 2: âm). Bảng 1–3 là công thức dạng đóng của riêng một phương pháp; bảng 4 đọc từ các cột phép thử ở 03 — mỗi dòng là một bản tính lại đầy đủ cả năm phương pháp. Bảng 5: tổng giá trị ba kịch bản theo chi phí mỗi lít ở trang trại.
A4: BẢNG 1 — RIÊNG PHƯƠNG PHÁP 1: B, doanh thu phần còn lại (hàng, tỷ) × CHI PHÍ BÁN HÀNG ÷ B (cột) — (tiền − quỹ) × (1 − k) như phương pháp 1
A5: hàng \ cột | B5: ='03_Định giá'!$C$9-0.02 -> 0.25 | C5: ='03_Định giá'!$C$9-0.01 -> 0.26 | D5: ='03_Định giá'!$C$9+0 -> 0.27 | E5: ='03_Định giá'!$C$9+0.01 -> 0.28 | F5: ='03_Định giá'!$C$9+0.02 -> 0.29
A6: ='03_Định giá'!$C$6-300 -> 2150 | B6: =MAX(0,(('03_Định giá'!$C$40*'03_Định giá'!$C$7+('03_Định giá'!$C$53-(B$5))*($A6)-'03_Định giá'!$C$42)*(1-'03_Định giá'!$C$10)*(1-'03_Định giá'!$C$36)*'03_Định giá'!$C$12+('03_Định giá'!$C$214-'03_Định giá'!$C$216)*(1-'02_Giả định'!$B$26)+'03_Định giá'!$C$207)*1000/'01_Số liệu gốc'!$B$8) -> 28719.767 | C6: =MAX(0,(('03_Định giá'!$C$40*'03_Định giá'!$C$7+('03_Định giá'!$C$53-(C$5))*($A6)-'03_Định giá'!$C$42)*(1-'03_Định giá'!$C$10)*(1-'03_Định giá'!$C$36)*'03_Định giá'!$C$12+('03_Định giá'!$C$214-'03_Định giá'!$C$216)*(1-'02_Giả định'!$B$26)+'03_Định giá'!$C$207)*1000/'01_Số liệu gốc'!$B$8) -> 26990.933 | D6: =MAX(0,(('03_Định giá'!$C$40*'03_Định giá'!$C$7+('03_Định giá'!$C$53-(D$5))*($A6)-'03_Định giá'!$C$42)*(1-'03_Định giá'!$C$10)*(1-'03_Định giá'!$C$36)*'03_Định giá'!$C$12+('03_Định giá'!$C$214-'03_Định giá'!$C$216)*(1-'02_Giả định'!$B$26)+'03_Định giá'!$C$207)*1000/'01_Số liệu gốc'!$B$8) -> 25262.098 | E6: =MAX(0,(('03_Định giá'!$C$40*'03_Định giá'!$C$7+('03_Định giá'!$C$53-(E$5))*($A6)-'03_Định giá'!$C$42)*(1-'03_Định giá'!$C$10)*(1-'03_Định giá'!$C$36)*'03_Định giá'!$C$12+('03_Định giá'!$C$214-'03_Định giá'!$C$216)*(1-'02_Giả định'!$B$26)+'03_Định giá'!$C$207)*1000/'01_Số liệu gốc'!$B$8) -> 23533.264 | F6: =MAX(0,(('03_Định giá'!$C$40*'03_Định giá'!$C$7+('03_Định giá'!$C$53-(F$5))*($A6)-'03_Định giá'!$C$42)*(1-'03_Định giá'!$C$10)*(1-'03_Định giá'!$C$36)*'03_Định giá'!$C$12+('03_Định giá'!$C$214-'03_Định giá'!$C$216)*(1-'02_Giả định'!$B$26)+'03_Định giá'!$C$207)*1000/'01_Số liệu gốc'!$B$8) -> 21804.429
A7: ='03_Định giá'!$C$6-150 -> 2300 | B7: =MAX(0,(('03_Định giá'!$C$40*'03_Định giá'!$C$7+('03_Định giá'!$C$53-(B$5))*($A7)-'03_Định giá'!$C$42)*(1-'03_Định giá'!$C$10)*(1-'03_Định giá'!$C$36)*'03_Định giá'!$C$12+('03_Định giá'!$C$214-'03_Định giá'!$C$216)*(1-'02_Giả định'!$B$26)+'03_Định giá'!$C$207)*1000/'01_Số liệu gốc'!$B$8) -> 29895.334 | C7: =MAX(0,(('03_Định giá'!$C$40*'03_Định giá'!$C$7+('03_Định giá'!$C$53-(C$5))*($A7)-'03_Định giá'!$C$42)*(1-'03_Định giá'!$C$10)*(1-'03_Định giá'!$C$36)*'03_Định giá'!$C$12+('03_Định giá'!$C$214-'03_Định giá'!$C$216)*(1-'02_Giả định'!$B$26)+'03_Định giá'!$C$207)*1000/'01_Số liệu gốc'!$B$8) -> 28045.883 | D7: =MAX(0,(('03_Định giá'!$C$40*'03_Định giá'!$C$7+('03_Định giá'!$C$53-(D$5))*($A7)-'03_Định giá'!$C$42)*(1-'03_Định giá'!$C$10)*(1-'03_Định giá'!$C$36)*'03_Định giá'!$C$12+('03_Định giá'!$C$214-'03_Định giá'!$C$216)*(1-'02_Giả định'!$B$26)+'03_Định giá'!$C$207)*1000/'01_Số liệu gốc'!$B$8) -> 26196.432 | E7: =MAX(0,(('03_Định giá'!$C$40*'03_Định giá'!$C$7+('03_Định giá'!$C$53-(E$5))*($A7)-'03_Định giá'!$C$42)*(1-'03_Định giá'!$C$10)*(1-'03_Định giá'!$C$36)*'03_Định giá'!$C$12+('03_Định giá'!$C$214-'03_Định giá'!$C$216)*(1-'02_Giả định'!$B$26)+'03_Định giá'!$C$207)*1000/'01_Số liệu gốc'!$B$8) -> 24346.981 | F7: =MAX(0,(('03_Định giá'!$C$40*'03_Định giá'!$C$7+('03_Định giá'!$C$53-(F$5))*($A7)-'03_Định giá'!$C$42)*(1-'03_Định giá'!$C$10)*(1-'03_Định giá'!$C$36)*'03_Định giá'!$C$12+('03_Định giá'!$C$214-'03_Định giá'!$C$216)*(1-'02_Giả định'!$B$26)+'03_Định giá'!$C$207)*1000/'01_Số liệu gốc'!$B$8) -> 22497.53
A8: ='03_Định giá'!$C$6+0 -> 2450 | B8: =MAX(0,(('03_Định giá'!$C$40*'03_Định giá'!$C$7+('03_Định giá'!$C$53-(B$5))*($A8)-'03_Định giá'!$C$42)*(1-'03_Định giá'!$C$10)*(1-'03_Định giá'!$C$36)*'03_Định giá'!$C$12+('03_Định giá'!$C$214-'03_Định giá'!$C$216)*(1-'02_Giả định'!$B$26)+'03_Định giá'!$C$207)*1000/'01_Số liệu gốc'!$B$8) -> 31070.9 | C8: =MAX(0,(('03_Định giá'!$C$40*'03_Định giá'!$C$7+('03_Định giá'!$C$53-(C$5))*($A8)-'03_Định giá'!$C$42)*(1-'03_Định giá'!$C$10)*(1-'03_Định giá'!$C$36)*'03_Định giá'!$C$12+('03_Định giá'!$C$214-'03_Định giá'!$C$216)*(1-'02_Giả định'!$B$26)+'03_Định giá'!$C$207)*1000/'01_Số liệu gốc'!$B$8) -> 29100.833 | D8: =MAX(0,(('03_Định giá'!$C$40*'03_Định giá'!$C$7+('03_Định giá'!$C$53-(D$5))*($A8)-'03_Định giá'!$C$42)*(1-'03_Định giá'!$C$10)*(1-'03_Định giá'!$C$36)*'03_Định giá'!$C$12+('03_Định giá'!$C$214-'03_Định giá'!$C$216)*(1-'02_Giả định'!$B$26)+'03_Định giá'!$C$207)*1000/'01_Số liệu gốc'!$B$8) -> 27130.765 | E8: =MAX(0,(('03_Định giá'!$C$40*'03_Định giá'!$C$7+('03_Định giá'!$C$53-(E$5))*($A8)-'03_Định giá'!$C$42)*(1-'03_Định giá'!$C$10)*(1-'03_Định giá'!$C$36)*'03_Định giá'!$C$12+('03_Định giá'!$C$214-'03_Định giá'!$C$216)*(1-'02_Giả định'!$B$26)+'03_Định giá'!$C$207)*1000/'01_Số liệu gốc'!$B$8) -> 25160.698 | F8: =MAX(0,(('03_Định giá'!$C$40*'03_Định giá'!$C$7+('03_Định giá'!$C$53-(F$5))*($A8)-'03_Định giá'!$C$42)*(1-'03_Định giá'!$C$10)*(1-'03_Định giá'!$C$36)*'03_Định giá'!$C$12+('03_Định giá'!$C$214-'03_Định giá'!$C$216)*(1-'02_Giả định'!$B$26)+'03_Định giá'!$C$207)*1000/'01_Số liệu gốc'!$B$8) -> 23190.631
A9: ='03_Định giá'!$C$6+150 -> 2600 | B9: =MAX(0,(('03_Định giá'!$C$40*'03_Định giá'!$C$7+('03_Định giá'!$C$53-(B$5))*($A9)-'03_Định giá'!$C$42)*(1-'03_Định giá'!$C$10)*(1-'03_Định giá'!$C$36)*'03_Định giá'!$C$12+('03_Định giá'!$C$214-'03_Định giá'!$C$216)*(1-'02_Giả định'!$B$26)+'03_Định giá'!$C$207)*1000/'01_Số liệu gốc'!$B$8) -> 32246.466 | C9: =MAX(0,(('03_Định giá'!$C$40*'03_Định giá'!$C$7+('03_Định giá'!$C$53-(C$5))*($A9)-'03_Định giá'!$C$42)*(1-'03_Định giá'!$C$10)*(1-'03_Định giá'!$C$36)*'03_Định giá'!$C$12+('03_Định giá'!$C$214-'03_Định giá'!$C$216)*(1-'02_Giả định'!$B$26)+'03_Định giá'!$C$207)*1000/'01_Số liệu gốc'!$B$8) -> 30155.783 | D9: =MAX(0,(('03_Định giá'!$C$40*'03_Định giá'!$C$7+('03_Định giá'!$C$53-(D$5))*($A9)-'03_Định giá'!$C$42)*(1-'03_Định giá'!$C$10)*(1-'03_Định giá'!$C$36)*'03_Định giá'!$C$12+('03_Định giá'!$C$214-'03_Định giá'!$C$216)*(1-'02_Giả định'!$B$26)+'03_Định giá'!$C$207)*1000/'01_Số liệu gốc'!$B$8) -> 28065.099 | E9: =MAX(0,(('03_Định giá'!$C$40*'03_Định giá'!$C$7+('03_Định giá'!$C$53-(E$5))*($A9)-'03_Định giá'!$C$42)*(1-'03_Định giá'!$C$10)*(1-'03_Định giá'!$C$36)*'03_Định giá'!$C$12+('03_Định giá'!$C$214-'03_Định giá'!$C$216)*(1-'02_Giả định'!$B$26)+'03_Định giá'!$C$207)*1000/'01_Số liệu gốc'!$B$8) -> 25974.415 | F9: =MAX(0,(('03_Định giá'!$C$40*'03_Định giá'!$C$7+('03_Định giá'!$C$53-(F$5))*($A9)-'03_Định giá'!$C$42)*(1-'03_Định giá'!$C$10)*(1-'03_Định giá'!$C$36)*'03_Định giá'!$C$12+('03_Định giá'!$C$214-'03_Định giá'!$C$216)*(1-'02_Giả định'!$B$26)+'03_Định giá'!$C$207)*1000/'01_Số liệu gốc'!$B$8) -> 23883.732
A10: ='03_Định giá'!$C$6+300 -> 2750 | B10: =MAX(0,(('03_Định giá'!$C$40*'03_Định giá'!$C$7+('03_Định giá'!$C$53-(B$5))*($A10)-'03_Định giá'!$C$42)*(1-'03_Định giá'!$C$10)*(1-'03_Định giá'!$C$36)*'03_Định giá'!$C$12+('03_Định giá'!$C$214-'03_Định giá'!$C$216)*(1-'02_Giả định'!$B$26)+'03_Định giá'!$C$207)*1000/'01_Số liệu gốc'!$B$8) -> 33422.032 | C10: =MAX(0,(('03_Định giá'!$C$40*'03_Định giá'!$C$7+('03_Định giá'!$C$53-(C$5))*($A10)-'03_Định giá'!$C$42)*(1-'03_Định giá'!$C$10)*(1-'03_Định giá'!$C$36)*'03_Định giá'!$C$12+('03_Định giá'!$C$214-'03_Định giá'!$C$216)*(1-'02_Giả định'!$B$26)+'03_Định giá'!$C$207)*1000/'01_Số liệu gốc'!$B$8) -> 31210.732 | D10: =MAX(0,(('03_Định giá'!$C$40*'03_Định giá'!$C$7+('03_Định giá'!$C$53-(D$5))*($A10)-'03_Định giá'!$C$42)*(1-'03_Định giá'!$C$10)*(1-'03_Định giá'!$C$36)*'03_Định giá'!$C$12+('03_Định giá'!$C$214-'03_Định giá'!$C$216)*(1-'02_Giả định'!$B$26)+'03_Định giá'!$C$207)*1000/'01_Số liệu gốc'!$B$8) -> 28999.432 | E10: =MAX(0,(('03_Định giá'!$C$40*'03_Định giá'!$C$7+('03_Định giá'!$C$53-(E$5))*($A10)-'03_Định giá'!$C$42)*(1-'03_Định giá'!$C$10)*(1-'03_Định giá'!$C$36)*'03_Định giá'!$C$12+('03_Định giá'!$C$214-'03_Định giá'!$C$216)*(1-'02_Giả định'!$B$26)+'03_Định giá'!$C$207)*1000/'01_Số liệu gốc'!$B$8) -> 26788.132 | F10: =MAX(0,(('03_Định giá'!$C$40*'03_Định giá'!$C$7+('03_Định giá'!$C$53-(F$5))*($A10)-'03_Định giá'!$C$42)*(1-'03_Định giá'!$C$10)*(1-'03_Định giá'!$C$36)*'03_Định giá'!$C$12+('03_Định giá'!$C$214-'03_Định giá'!$C$216)*(1-'02_Giả định'!$B$26)+'03_Định giá'!$C$207)*1000/'01_Số liệu gốc'!$B$8) -> 24576.832
A11: Mỗi 1 điểm % chi phí bán hàng trên ~2.450 tỷ doanh thu = ~24,5 tỷ EBIT — gần bằng 150 tỷ doanh thu. Khuyến mãi quyết định lợi nhuận nhiều như doanh thu.
A13: BẢNG 2 — GIÁ TRỊ RÒNG HAI DỰ ÁN (đồng/cp): GIÁ BÁN SỮA TRANG TRẠI (hàng, đ/lít) × CHI PHÍ TIỀN MẶT MỖI LÍT (cột)
A14: hàng \ cột | B14: ='03_Định giá'!$C$22-1000 -> 9500 | C14: ='03_Định giá'!$C$22-500 -> 10000 | D14: ='03_Định giá'!$C$22+0 -> 10500 | E14: ='03_Định giá'!$C$22+500 -> 11000 | F14: ='03_Định giá'!$C$22+1000 -> 11500
A15: ='03_Định giá'!$C$21-2000 -> 12500 | B15: =('03_Định giá'!$C$207+'03_Định giá'!$C$19*((($A15)-'03_Định giá'!$C$21)*(1+'03_Định giá'!$C$23)-((B$14)-'03_Định giá'!$C$22))/1000*'03_Định giá'!$C$209)*1000/'01_Số liệu gốc'!$B$8 -> -2678.2143 | C15: =('03_Định giá'!$C$207+'03_Định giá'!$C$19*((($A15)-'03_Định giá'!$C$21)*(1+'03_Định giá'!$C$23)-((C$14)-'03_Định giá'!$C$22))/1000*'03_Định giá'!$C$209)*1000/'01_Số liệu gốc'!$B$8 -> -3265.2974 | D15: =('03_Định giá'!$C$207+'03_Định giá'!$C$19*((($A15)-'03_Định giá'!$C$21)*(1+'03_Định giá'!$C$23)-((D$14)-'03_Định giá'!$C$22))/1000*'03_Định giá'!$C$209)*1000/'01_Số liệu gốc'!$B$8 -> -3852.3804 | E15: =('03_Định giá'!$C$207+'03_Định giá'!$C$19*((($A15)-'03_Định giá'!$C$21)*(1+'03_Định giá'!$C$23)-((E$14)-'03_Định giá'!$C$22))/1000*'03_Định giá'!$C$209)*1000/'01_Số liệu gốc'!$B$8 -> -4439.4635 | F15: =('03_Định giá'!$C$207+'03_Định giá'!$C$19*((($A15)-'03_Định giá'!$C$21)*(1+'03_Định giá'!$C$23)-((F$14)-'03_Định giá'!$C$22))/1000*'03_Định giá'!$C$209)*1000/'01_Số liệu gốc'!$B$8 -> -5026.5466
A16: ='03_Định giá'!$C$21-1000 -> 13500 | B16: =('03_Định giá'!$C$207+'03_Định giá'!$C$19*((($A16)-'03_Định giá'!$C$21)*(1+'03_Định giá'!$C$23)-((B$14)-'03_Định giá'!$C$22))/1000*'03_Định giá'!$C$209)*1000/'01_Số liệu gốc'!$B$8 -> -1445.3398 | C16: =('03_Định giá'!$C$207+'03_Định giá'!$C$19*((($A16)-'03_Định giá'!$C$21)*(1+'03_Định giá'!$C$23)-((C$14)-'03_Định giá'!$C$22))/1000*'03_Định giá'!$C$209)*1000/'01_Số liệu gốc'!$B$8 -> -2032.4229 | D16: =('03_Định giá'!$C$207+'03_Định giá'!$C$19*((($A16)-'03_Định giá'!$C$21)*(1+'03_Định giá'!$C$23)-((D$14)-'03_Định giá'!$C$22))/1000*'03_Định giá'!$C$209)*1000/'01_Số liệu gốc'!$B$8 -> -2619.506 | E16: =('03_Định giá'!$C$207+'03_Định giá'!$C$19*((($A16)-'03_Định giá'!$C$21)*(1+'03_Định giá'!$C$23)-((E$14)-'03_Định giá'!$C$22))/1000*'03_Định giá'!$C$209)*1000/'01_Số liệu gốc'!$B$8 -> -3206.589 | F16: =('03_Định giá'!$C$207+'03_Định giá'!$C$19*((($A16)-'03_Định giá'!$C$21)*(1+'03_Định giá'!$C$23)-((F$14)-'03_Định giá'!$C$22))/1000*'03_Định giá'!$C$209)*1000/'01_Số liệu gốc'!$B$8 -> -3793.6721
A17: ='03_Định giá'!$C$21+0 -> 14500 | B17: =('03_Định giá'!$C$207+'03_Định giá'!$C$19*((($A17)-'03_Định giá'!$C$21)*(1+'03_Định giá'!$C$23)-((B$14)-'03_Định giá'!$C$22))/1000*'03_Định giá'!$C$209)*1000/'01_Số liệu gốc'!$B$8 -> -212.46541 | C17: =('03_Định giá'!$C$207+'03_Định giá'!$C$19*((($A17)-'03_Định giá'!$C$21)*(1+'03_Định giá'!$C$23)-((C$14)-'03_Định giá'!$C$22))/1000*'03_Định giá'!$C$209)*1000/'01_Số liệu gốc'!$B$8 -> -799.54847 | D17: =('03_Định giá'!$C$207+'03_Định giá'!$C$19*((($A17)-'03_Định giá'!$C$21)*(1+'03_Định giá'!$C$23)-((D$14)-'03_Định giá'!$C$22))/1000*'03_Định giá'!$C$209)*1000/'01_Số liệu gốc'!$B$8 -> -1386.6315 | E17: =('03_Định giá'!$C$207+'03_Định giá'!$C$19*((($A17)-'03_Định giá'!$C$21)*(1+'03_Định giá'!$C$23)-((E$14)-'03_Định giá'!$C$22))/1000*'03_Định giá'!$C$209)*1000/'01_Số liệu gốc'!$B$8 -> -1973.7146 | F17: =('03_Định giá'!$C$207+'03_Định giá'!$C$19*((($A17)-'03_Định giá'!$C$21)*(1+'03_Định giá'!$C$23)-((F$14)-'03_Định giá'!$C$22))/1000*'03_Định giá'!$C$209)*1000/'01_Số liệu gốc'!$B$8 -> -2560.7977
A18: ='03_Định giá'!$C$21+1000 -> 15500 | B18: =('03_Định giá'!$C$207+'03_Định giá'!$C$19*((($A18)-'03_Định giá'!$C$21)*(1+'03_Định giá'!$C$23)-((B$14)-'03_Định giá'!$C$22))/1000*'03_Định giá'!$C$209)*1000/'01_Số liệu gốc'!$B$8 -> 1020.409 | C18: =('03_Định giá'!$C$207+'03_Định giá'!$C$19*((($A18)-'03_Định giá'!$C$21)*(1+'03_Định giá'!$C$23)-((C$14)-'03_Định giá'!$C$22))/1000*'03_Định giá'!$C$209)*1000/'01_Số liệu gốc'!$B$8 -> 433.32597 | D18: =('03_Định giá'!$C$207+'03_Định giá'!$C$19*((($A18)-'03_Định giá'!$C$21)*(1+'03_Định giá'!$C$23)-((D$14)-'03_Định giá'!$C$22))/1000*'03_Định giá'!$C$209)*1000/'01_Số liệu gốc'!$B$8 -> -153.7571 | E18: =('03_Định giá'!$C$207+'03_Định giá'!$C$19*((($A18)-'03_Định giá'!$C$21)*(1+'03_Định giá'!$C$23)-((E$14)-'03_Định giá'!$C$22))/1000*'03_Định giá'!$C$209)*1000/'01_Số liệu gốc'!$B$8 -> -740.84017 | F18: =('03_Định giá'!$C$207+'03_Định giá'!$C$19*((($A18)-'03_Định giá'!$C$21)*(1+'03_Định giá'!$C$23)-((F$14)-'03_Định giá'!$C$22))/1000*'03_Định giá'!$C$209)*1000/'01_Số liệu gốc'!$B$8 -> -1327.9232
A19: ='03_Định giá'!$C$21+2000 -> 16500 | B19: =('03_Định giá'!$C$207+'03_Định giá'!$C$19*((($A19)-'03_Định giá'!$C$21)*(1+'03_Định giá'!$C$23)-((B$14)-'03_Định giá'!$C$22))/1000*'03_Định giá'!$C$209)*1000/'01_Số liệu gốc'!$B$8 -> 2253.2835 | C19: =('03_Định giá'!$C$207+'03_Định giá'!$C$19*((($A19)-'03_Định giá'!$C$21)*(1+'03_Định giá'!$C$23)-((C$14)-'03_Định giá'!$C$22))/1000*'03_Định giá'!$C$209)*1000/'01_Số liệu gốc'!$B$8 -> 1666.2004 | D19: =('03_Định giá'!$C$207+'03_Định giá'!$C$19*((($A19)-'03_Định giá'!$C$21)*(1+'03_Định giá'!$C$23)-((D$14)-'03_Định giá'!$C$22))/1000*'03_Định giá'!$C$209)*1000/'01_Số liệu gốc'!$B$8 -> 1079.1173 | E19: =('03_Định giá'!$C$207+'03_Định giá'!$C$19*((($A19)-'03_Định giá'!$C$21)*(1+'03_Định giá'!$C$23)-((E$14)-'03_Định giá'!$C$22))/1000*'03_Định giá'!$C$209)*1000/'01_Số liệu gốc'!$B$8 -> 492.03428 | F19: =('03_Định giá'!$C$207+'03_Định giá'!$C$19*((($A19)-'03_Định giá'!$C$21)*(1+'03_Định giá'!$C$23)-((F$14)-'03_Định giá'!$C$22))/1000*'03_Định giá'!$C$209)*1000/'01_Số liệu gốc'!$B$8 -> -95.048792
A20: Nhà máy giữ nguyên cơ sở. Mỗi 1.000 đ/lít ≈ 20 tỷ lãi trước khấu hao/năm. Cộng thẳng vào cả năm phương pháp (trừ P/B theo ROE). Mức hòa vốn từng kịch bản ở 06 mục C.
A22: BẢNG 3 — RIÊNG PHƯƠNG PHÁP 4: ROE CHU KỲ (hàng) × LỢI SUẤT YÊU CẦU r (cột)
A23: hàng \ cột | B23: ='03_Định giá'!$C$44-0.02 -> 0.09224 | C23: ='03_Định giá'!$C$44-0.01 -> 0.10224 | D23: ='03_Định giá'!$C$44+0 -> 0.11224 | E23: ='03_Định giá'!$C$44+0.01 -> 0.12224 | F23: ='03_Định giá'!$C$44+0.02 -> 0.13224
A24: ='03_Định giá'!$C$14-0.03 -> 0.085 | B24: =MAX(0,(($A24)*(1-'03_Định giá'!$C$36)-'03_Định giá'!$C$35)/((B$23)-'03_Định giá'!$C$35)*'01_Số liệu gốc'!$C$74) -> 15764.583 | C24: =MAX(0,(($A24)*(1-'03_Định giá'!$C$36)-'03_Định giá'!$C$35)/((C$23)-'03_Định giá'!$C$35)*'01_Số liệu gốc'!$C$74) -> 13582.331 | D24: =MAX(0,(($A24)*(1-'03_Định giá'!$C$36)-'03_Định giá'!$C$35)/((D$23)-'03_Định giá'!$C$35)*'01_Số liệu gốc'!$C$74) -> 11930.783 | E24: =MAX(0,(($A24)*(1-'03_Định giá'!$C$36)-'03_Định giá'!$C$35)/((E$23)-'03_Định giá'!$C$35)*'01_Số liệu gốc'!$C$74) -> 10637.333 | F24: =MAX(0,(($A24)*(1-'03_Định giá'!$C$36)-'03_Định giá'!$C$35)/((F$23)-'03_Định giá'!$C$35)*'01_Số liệu gốc'!$C$74) -> 9596.9055
A25: ='03_Định giá'!$C$14-0.015 -> 0.1 | B25: =MAX(0,(($A25)*(1-'03_Định giá'!$C$36)-'03_Định giá'!$C$35)/((B$23)-'03_Định giá'!$C$35)*'01_Số liệu gốc'!$C$74) -> 20341.397 | C25: =MAX(0,(($A25)*(1-'03_Định giá'!$C$36)-'03_Định giá'!$C$35)/((C$23)-'03_Định giá'!$C$35)*'01_Số liệu gốc'!$C$74) -> 17525.589 | D25: =MAX(0,(($A25)*(1-'03_Định giá'!$C$36)-'03_Định giá'!$C$35)/((D$23)-'03_Định giá'!$C$35)*'01_Số liệu gốc'!$C$74) -> 15394.559 | E25: =MAX(0,(($A25)*(1-'03_Định giá'!$C$36)-'03_Định giá'!$C$35)/((E$23)-'03_Định giá'!$C$35)*'01_Số liệu gốc'!$C$74) -> 13725.591 | F25: =MAX(0,(($A25)*(1-'03_Định giá'!$C$36)-'03_Định giá'!$C$35)/((F$23)-'03_Định giá'!$C$35)*'01_Số liệu gốc'!$C$74) -> 12383.104
A26: ='03_Định giá'!$C$14+0 -> 0.115 | B26: =MAX(0,(($A26)*(1-'03_Định giá'!$C$36)-'03_Định giá'!$C$35)/((B$23)-'03_Định giá'!$C$35)*'01_Số liệu gốc'!$C$74) -> 24918.211 | C26: =MAX(0,(($A26)*(1-'03_Định giá'!$C$36)-'03_Định giá'!$C$35)/((C$23)-'03_Định giá'!$C$35)*'01_Số liệu gốc'!$C$74) -> 21468.846 | D26: =MAX(0,(($A26)*(1-'03_Định giá'!$C$36)-'03_Định giá'!$C$35)/((D$23)-'03_Định giá'!$C$35)*'01_Số liệu gốc'!$C$74) -> 18858.335 | E26: =MAX(0,(($A26)*(1-'03_Định giá'!$C$36)-'03_Định giá'!$C$35)/((E$23)-'03_Định giá'!$C$35)*'01_Số liệu gốc'!$C$74) -> 16813.849 | F26: =MAX(0,(($A26)*(1-'03_Định giá'!$C$36)-'03_Định giá'!$C$35)/((F$23)-'03_Định giá'!$C$35)*'01_Số liệu gốc'!$C$74) -> 15169.302
A27: ='03_Định giá'!$C$14+0.015 -> 0.13 | B27: =MAX(0,(($A27)*(1-'03_Định giá'!$C$36)-'03_Định giá'!$C$35)/((B$23)-'03_Định giá'!$C$35)*'01_Số liệu gốc'!$C$74) -> 29495.026 | C27: =MAX(0,(($A27)*(1-'03_Định giá'!$C$36)-'03_Định giá'!$C$35)/((C$23)-'03_Định giá'!$C$35)*'01_Số liệu gốc'!$C$74) -> 25412.104 | D27: =MAX(0,(($A27)*(1-'03_Định giá'!$C$36)-'03_Định giá'!$C$35)/((D$23)-'03_Định giá'!$C$35)*'01_Số liệu gốc'!$C$74) -> 22322.111 | E27: =MAX(0,(($A27)*(1-'03_Định giá'!$C$36)-'03_Định giá'!$C$35)/((E$23)-'03_Định giá'!$C$35)*'01_Số liệu gốc'!$C$74) -> 19902.107 | F27: =MAX(0,(($A27)*(1-'03_Định giá'!$C$36)-'03_Định giá'!$C$35)/((F$23)-'03_Định giá'!$C$35)*'01_Số liệu gốc'!$C$74) -> 17955.501
A28: ='03_Định giá'!$C$14+0.03 -> 0.145 | B28: =MAX(0,(($A28)*(1-'03_Định giá'!$C$36)-'03_Định giá'!$C$35)/((B$23)-'03_Định giá'!$C$35)*'01_Số liệu gốc'!$C$74) -> 34071.84 | C28: =MAX(0,(($A28)*(1-'03_Định giá'!$C$36)-'03_Định giá'!$C$35)/((C$23)-'03_Định giá'!$C$35)*'01_Số liệu gốc'!$C$74) -> 29355.361 | D28: =MAX(0,(($A28)*(1-'03_Định giá'!$C$36)-'03_Định giá'!$C$35)/((D$23)-'03_Định giá'!$C$35)*'01_Số liệu gốc'!$C$74) -> 25785.887 | E28: =MAX(0,(($A28)*(1-'03_Định giá'!$C$36)-'03_Định giá'!$C$35)/((E$23)-'03_Định giá'!$C$35)*'01_Số liệu gốc'!$C$74) -> 22990.365 | F28: =MAX(0,(($A28)*(1-'03_Định giá'!$C$36)-'03_Định giá'!$C$35)/((F$23)-'03_Định giá'!$C$35)*'01_Số liệu gốc'!$C$74) -> 20741.699
A29: r ± 1 điểm ≈ β ± 0,11 ở ERP 9,2%. Phép thử β 0,65 / 0,85 và ERP 10% tính đủ cả năm phương pháp ở bảng 4 (T5, T6, T14).
A31: BẢNG 4 — PHÉP THỬ MỘT BIẾN trên GIÁ TRỊ CƠ SỞ = DCF + (tiền − quỹ) × (1 − k) + dự án (tính lại đầy đủ ở 03 cột H–W)
A32: Phép thử | B32: Giá trị thử | C32: Giá trị cơ sở | D32: Chênh (đồng) | E32: Chênh % | F32: Cột ở 03 | G32: Đọc thế nào
A33: T0 · Đối chứng: không đổi gì (phải ra đúng cơ sở) | C33: ='03_Định giá'!$H$256 -> 26693.757 | D33: =C33-'03_Định giá'!$C$256 -> 0 | E33: =C33/'03_Định giá'!$C$256-1 -> 0 | F33: H | G33: Phải bằng 0 — kiểm đường ống phép thử
A34: T1 · Không xây nhà máy trong 5 năm — MỨC TRẦN (coi nhà máy cũ chạy mãi không tốn thêm) | B34: ='03_Định giá'!$I$27 -> 0 | C34: ='03_Định giá'!$I$256 -> 27647.686 | D34: =C34-'03_Định giá'!$C$256 -> 953.92891 | E34: =C34/'03_Định giá'!$C$256-1 -> 0.035736031 | F34: I | G34: MỨC TRẦN: không tính chi phí giữ nhà máy cũ (hết đất, xuống cấp) hay Creamery bị chặn công suất
A35: T2 · Nhà máy chạy từ 2028 (lịch công ty: xong Q4/2027) | B35: ='03_Định giá'!$J$29 -> 2028 | C35: ='03_Định giá'!$J$256 -> 26513.158 | D35: =C35-'03_Định giá'!$C$256 -> -180.59873 | E35: =C35/'03_Định giá'!$C$256-1 -> -0.0067655793 | F35: J | G35: Chi sớm hơn nhưng có lãi sớm hơn
A36: T3 · Sữa trang trại bán thô 13.000 đ/lít | B36: ='03_Định giá'!$K$21 -> 13000 | C36: ='03_Định giá'!$K$256 -> 24844.445 | D36: =C36-'03_Định giá'!$C$256 -> -1849.3117 | E36: =C36/'03_Định giá'!$C$256-1 -> -0.069278809 | F36: K | G36: Creamery không hút được sữa trại mới — bán thô cho Vinamilk
A37: T4 · Chi phí nuôi 11.500 đ/lít | B37: ='03_Định giá'!$L$22 -> 11500 | C37: ='03_Định giá'!$L$256 -> 25519.591 | D37: =C37-'03_Định giá'!$C$256 -> -1174.1661 | E37: =C37/'03_Định giá'!$C$256-1 -> -0.043986545 | F37: L
A38: T5 · ERP 10% (VDSC, cận trên) | B38: ='03_Định giá'!$M$32 -> 0.1 | C38: ='03_Định giá'!$M$256 -> 25186.558 | D38: =C38-'03_Định giá'!$C$256 -> -1507.1982 | E38: =C38/'03_Định giá'!$C$256-1 -> -0.056462575 | F38: M | G38: Mức VDSC dùng cho doanh nghiệp chu kỳ
A39: T6 · β phần kinh doanh 0,85 (bằng dự án) | B39: ='03_Định giá'!$N$33 -> 0.85 | C39: ='03_Định giá'!$N$256 -> 24720.972 | D39: =C39-'03_Định giá'!$C$256 -> -1972.7848 | E39: =C39/'03_Định giá'!$C$256-1 -> -0.073904353 | F39: N | G39: Coi kinh doanh hiện tại rủi ro như dự án
A40: T7 · Cổ tức 1.000đ/cp (tối thiểu 50% LNST) | B40: ='03_Định giá'!$O$15 -> 1000 | C40: ='03_Định giá'!$O$256 -> 26693.757 | D40: =C40-'03_Định giá'!$C$256 -> 0 | E40: =C40/'03_Định giá'!$C$256-1 -> 0 | F40: O | G40: Ít tiền về cổ đông sớm, ít phải vay · Từ 13/10/2026 chênh 0: chỉ đổi phương pháp đối chiếu
A41: T8 · B về mức 2025 (Creamery không cất cánh) | B41: ='03_Định giá'!$P$6 -> 2166.786 | C41: ='03_Định giá'!$P$256 -> 25015.838 | D41: =C41-'03_Định giá'!$C$256 -> -1677.9188 | E41: =C41/'03_Định giá'!$C$256-1 -> -0.0628581 | F41: P | G41: Creamery không bù được sữa thương hiệu đang giảm
A42: T9 · B về mức 2023 | B42: ='03_Định giá'!$Q$6 -> 2710.123 | C42: ='03_Định giá'!$Q$256 -> 28234.871 | D42: =C42-'03_Định giá'!$C$256 -> 1541.1148 | E42: =C42/'03_Định giá'!$C$256-1 -> 0.057733154 | F42: Q | G42: Hàng thương hiệu trở lại thời trước 2024
A43: T10 · Chi phí bán hàng ÷ B = mức 12 tháng | B43: ='03_Định giá'!$R$9 -> 0.27366486 | C43: ='03_Định giá'!$R$256 -> 25950.278 | D43: =C43-'03_Định giá'!$C$256 -> -743.47888 | E43: =C43/'03_Định giá'!$C$256-1 -> -0.027852163 | F43: R
A44: T11 · P/E lõi 10x (như bản 09/10) | B44: ='03_Định giá'!$S$12 -> 10 | C44: ='03_Định giá'!$S$256 -> 26693.757 | D44: =C44-'03_Định giá'!$C$256 -> 0 | E44: =C44/'03_Định giá'!$C$256-1 -> 0 | F44: S | G44: Bội số bản 09/10 (khi r = 14%) · Từ 13/10/2026 chênh 0: chỉ đổi phương pháp đối chiếu
A45: T12 · P/E lõi = P/E trung vị lịch sử MCM | B45: ='03_Định giá'!$T$12 -> 13.89 | C45: ='03_Định giá'!$T$256 -> 26693.757 | D45: =C45-'03_Định giá'!$C$256 -> 0 | E45: =C45/'03_Định giá'!$C$256-1 -> 0 | F45: T | G45: Bội số thị trường từng trả cho CẢ công ty (gồm lãi tiền gửi) — quá rộng tay cho phần lõi · Từ 13/10/2026 chênh 0: chỉ đổi phương pháp đối chiếu
A46: T13 · Biên gộp B giữ mức 6T/2026 | B46: ='03_Định giá'!$U$8 -> 0.0063439955 | C46: ='03_Định giá'!$U$256 -> 27980.744 | D46: =C46-'03_Định giá'!$C$256 -> 1286.9873 | E46: =C46/'03_Định giá'!$C$256-1 -> 0.048213044 | F46: U | G46: Biên gộp nửa đầu 2026 là mức bền
A47: T14 · β phần kinh doanh 0,65 | B47: ='03_Định giá'!$V$33 -> 0.65 | C47: ='03_Định giá'!$V$256 -> 28011.324 | D47: =C47-'03_Định giá'!$C$256 -> 1317.5676 | E47: =C47/'03_Định giá'!$C$256-1 -> 0.049358643 | F47: V | G47: Đầu dưới dải β (MCM tự tính 0,70)
A48: T15 · Biên gộp bán cho Vinamilk 5% | B48: ='03_Định giá'!$W$40 -> 0.05 | C48: ='03_Định giá'!$W$256 -> 27092.246 | D48: =C48-'03_Định giá'!$C$256 -> 398.48936 | E48: =C48/'03_Định giá'!$C$256-1 -> 0.014928186 | F48: W | G48: Cơ sở dùng 10% (ước của người viết 12/10/2026)
A49: Trọng số bằng nhau (20% mỗi phương pháp) | C49: =AVERAGE('03_Định giá'!$C$221,'03_Định giá'!$C$239,'03_Định giá'!$C$248,'03_Định giá'!$C$230,'03_Định giá'!$C$226) -> 24436.079 | D49: =C49-'03_Định giá'!$C$256 -> -2257.6779 | E49: =C49/'03_Định giá'!$C$256-1 -> -0.084577
A50: Chỉ phương pháp 1 (P/E lõi + tiền + dự án) | C50: ='03_Định giá'!$C$221 -> 27130.765 | D50: =C50-'03_Định giá'!$C$256 -> 437.00862 | E50: =C50/'03_Định giá'!$C$256-1 -> 0.016371192 | G50: Cách thị trường hay nhìn MCM
A51: Chỉ phương pháp 3 (cổ tức) | C51: ='03_Định giá'!$C$248 -> 22496.248 | D51: =C51-'03_Định giá'!$C$256 -> -4197.5085 | E51: =C51/'03_Định giá'!$C$256-1 -> -0.15724682 | G51: Góc nhìn của cổ đông thiểu số
A52: Cách tính trước 13/10: bình quân năm phương pháp 30/25/20/15/10, tiền tính đủ | C52: =0.3*'03_Định giá'!$C$221+0.25*'03_Định giá'!$C$239+0.2*'03_Định giá'!$C$248+0.15*'03_Định giá'!$C$230+0.1*'03_Định giá'!$C$226+(0.3+0.25+0.1)*'02_Giả định'!$B$26*'03_Định giá'!$C$215 -> 25667.206 | D52: =C52-'03_Định giá'!$C$256 -> -1026.5509 | E52: =C52/'03_Định giá'!$C$256-1 -> -0.038456592 | G52: Trọng số năm phương pháp trước 13/10, áp lên mô hình hiện tại
A53: k = 0% ((tiền ròng − quỹ) tính đủ mệnh giá) | C53: ='03_Định giá'!$C$239+'02_Giả định'!$B$26*('03_Định giá'!$C$214-'03_Định giá'!$C$216)*1000/'01_Số liệu gốc'!$B$8 -> 27943.35 | D53: =C53-'03_Định giá'!$C$256 -> 1249.5936 | E53: =C53/'03_Định giá'!$C$256-1 -> 0.046812206 | G53: Mỗi 10 điểm k ≈ 1.250 đ/cp (tiền trừ quỹ)
A54: k = 20% | C54: ='03_Định giá'!$C$239-(0.2-'02_Giả định'!$B$26)*('03_Định giá'!$C$214-'03_Định giá'!$C$216)*1000/'01_Số liệu gốc'!$B$8 -> 25444.163 | D54: =C54-'03_Định giá'!$C$256 -> -1249.5936 | E54: =C54/'03_Định giá'!$C$256-1 -> -0.046812206 | G54: Vinamilk giữ tiền lâu hoặc dồn vào dự án mới
A56: BẢNG 5 — TỔNG GIÁ TRỊ (đồng/cp) THEO CHI PHÍ TIỀN MẶT MỖI LÍT Ở TRANG TRẠI (hàng, đ/lít) × BA KỊCH BẢN (cột) — giá bán sữa giữ theo từng kịch bản
A57: chi phí \ kịch bản | B57: Xấu | C57: Cơ sở | D57: Tốt
A58: ='03_Định giá'!$C$22+0 -> 10500 | B58: ='03_Định giá'!$B$256-($A58-'03_Định giá'!$B$22)*'03_Định giá'!$B$19/1000*'03_Định giá'!$B$209*('02_Giả định'!$B$19+'02_Giả định'!$B$20+'02_Giả định'!$B$23)*1000/'01_Số liệu gốc'!$B$8 -> 14575.268 | C58: ='03_Định giá'!$C$256-($A58-'03_Định giá'!$C$22)*'03_Định giá'!$C$19/1000*'03_Định giá'!$C$209*('02_Giả định'!$B$19+'02_Giả định'!$B$20+'02_Giả định'!$B$23)*1000/'01_Số liệu gốc'!$B$8 -> 26693.757 | D58: ='03_Định giá'!$D$256-($A58-'03_Định giá'!$D$22)*'03_Định giá'!$D$19/1000*'03_Định giá'!$D$209*('02_Giả định'!$B$19+'02_Giả định'!$B$20+'02_Giả định'!$B$23)*1000/'01_Số liệu gốc'!$B$8 -> 36657.749
A59: ='03_Định giá'!$C$22+100 -> 10600 | B59: ='03_Định giá'!$B$256-($A59-'03_Định giá'!$B$22)*'03_Định giá'!$B$19/1000*'03_Định giá'!$B$209*('02_Giả định'!$B$19+'02_Giả định'!$B$20+'02_Giả định'!$B$23)*1000/'01_Số liệu gốc'!$B$8 -> 14472.213 | C59: ='03_Định giá'!$C$256-($A59-'03_Định giá'!$C$22)*'03_Định giá'!$C$19/1000*'03_Định giá'!$C$209*('02_Giả định'!$B$19+'02_Giả định'!$B$20+'02_Giả định'!$B$23)*1000/'01_Số liệu gốc'!$B$8 -> 26576.34 | D59: ='03_Định giá'!$D$256-($A59-'03_Định giá'!$D$22)*'03_Định giá'!$D$19/1000*'03_Định giá'!$D$209*('02_Giả định'!$B$19+'02_Giả định'!$B$20+'02_Giả định'!$B$23)*1000/'01_Số liệu gốc'!$B$8 -> 36526.99
A60: ='03_Định giá'!$C$22+200 -> 10700 | B60: ='03_Định giá'!$B$256-($A60-'03_Định giá'!$B$22)*'03_Định giá'!$B$19/1000*'03_Định giá'!$B$209*('02_Giả định'!$B$19+'02_Giả định'!$B$20+'02_Giả định'!$B$23)*1000/'01_Số liệu gốc'!$B$8 -> 14369.158 | C60: ='03_Định giá'!$C$256-($A60-'03_Định giá'!$C$22)*'03_Định giá'!$C$19/1000*'03_Định giá'!$C$209*('02_Giả định'!$B$19+'02_Giả định'!$B$20+'02_Giả định'!$B$23)*1000/'01_Số liệu gốc'!$B$8 -> 26458.923 | D60: ='03_Định giá'!$D$256-($A60-'03_Định giá'!$D$22)*'03_Định giá'!$D$19/1000*'03_Định giá'!$D$209*('02_Giả định'!$B$19+'02_Giả định'!$B$20+'02_Giả định'!$B$23)*1000/'01_Số liệu gốc'!$B$8 -> 36396.23
A61: ='03_Định giá'!$C$22+300 -> 10800 | B61: ='03_Định giá'!$B$256-($A61-'03_Định giá'!$B$22)*'03_Định giá'!$B$19/1000*'03_Định giá'!$B$209*('02_Giả định'!$B$19+'02_Giả định'!$B$20+'02_Giả định'!$B$23)*1000/'01_Số liệu gốc'!$B$8 -> 14266.104 | C61: ='03_Định giá'!$C$256-($A61-'03_Định giá'!$C$22)*'03_Định giá'!$C$19/1000*'03_Định giá'!$C$209*('02_Giả định'!$B$19+'02_Giả định'!$B$20+'02_Giả định'!$B$23)*1000/'01_Số liệu gốc'!$B$8 -> 26341.507 | D61: ='03_Định giá'!$D$256-($A61-'03_Định giá'!$D$22)*'03_Định giá'!$D$19/1000*'03_Định giá'!$D$209*('02_Giả định'!$B$19+'02_Giả định'!$B$20+'02_Giả định'!$B$23)*1000/'01_Số liệu gốc'!$B$8 -> 36265.471
A62: ='03_Định giá'!$C$22+400 -> 10900 | B62: ='03_Định giá'!$B$256-($A62-'03_Định giá'!$B$22)*'03_Định giá'!$B$19/1000*'03_Định giá'!$B$209*('02_Giả định'!$B$19+'02_Giả định'!$B$20+'02_Giả định'!$B$23)*1000/'01_Số liệu gốc'!$B$8 -> 14163.049 | C62: ='03_Định giá'!$C$256-($A62-'03_Định giá'!$C$22)*'03_Định giá'!$C$19/1000*'03_Định giá'!$C$209*('02_Giả định'!$B$19+'02_Giả định'!$B$20+'02_Giả định'!$B$23)*1000/'01_Số liệu gốc'!$B$8 -> 26224.09 | D62: ='03_Định giá'!$D$256-($A62-'03_Định giá'!$D$22)*'03_Định giá'!$D$19/1000*'03_Định giá'!$D$209*('02_Giả định'!$B$19+'02_Giả định'!$B$20+'02_Giả định'!$B$23)*1000/'01_Số liệu gốc'!$B$8 -> 36134.711
A63: ='03_Định giá'!$C$22+500 -> 11000 | B63: ='03_Định giá'!$B$256-($A63-'03_Định giá'!$B$22)*'03_Định giá'!$B$19/1000*'03_Định giá'!$B$209*('02_Giả định'!$B$19+'02_Giả định'!$B$20+'02_Giả định'!$B$23)*1000/'01_Số liệu gốc'!$B$8 -> 14059.994 | C63: ='03_Định giá'!$C$256-($A63-'03_Định giá'!$C$22)*'03_Định giá'!$C$19/1000*'03_Định giá'!$C$209*('02_Giả định'!$B$19+'02_Giả định'!$B$20+'02_Giả định'!$B$23)*1000/'01_Số liệu gốc'!$B$8 -> 26106.674 | D63: ='03_Định giá'!$D$256-($A63-'03_Định giá'!$D$22)*'03_Định giá'!$D$19/1000*'03_Định giá'!$D$209*('02_Giả định'!$B$19+'02_Giả định'!$B$20+'02_Giả định'!$B$23)*1000/'01_Số liệu gốc'!$B$8 -> 36003.952
A64: Mỗi +100 đ/lít | B64: =B59-B58 -> -103.05491 | C64: =C59-C58 -> -117.41661 | D64: =D59-D58 -> -130.75941
A65: Kiểm: lãi trang trại ở chi phí cao nhất vẫn dương (bảng tuyến tính đúng) | B65: =IF(AND('03_Định giá'!$B$70-'03_Định giá'!$B$19*($A$63-'03_Định giá'!$B$22)/1000>0,'03_Định giá'!$C$70-'03_Định giá'!$C$19*($A$63-'03_Định giá'!$C$22)/1000>0,'03_Định giá'!$D$70-'03_Định giá'!$D$19*($A$63-'03_Định giá'!$D$22)/1000>0),"ĐẠT","SAI — lãi trang trại âm ở dòng cuối: quỹ không trích trên lãi âm, bảng tính dư") -> ĐẠT
A66: Chỉ trang trại đổi; lõi, tiền, nhà máy giữ nguyên. Dòng 10.500 = giả định cả ba kịch bản. Mỗi +100 đ/lít ≈ −2 tỷ lãi trước khấu hao/năm. Nền cam = thấp hơn giá hiện tại.

Sheet 05_Đối chiếu
A1: MCM — ĐỐI CHIẾU CHÉO
A3: A. BỘI SỐ TẠI GIÁ THỊ TRƯỜNG VÀ TẠI GIÁ TRỊ CƠ SỞ
A4: Chỉ tiêu | B4: Tại giá thị trường | D4: Tại giá trị cơ sở | F4: Ghi chú
A5: Vốn hoá (tỷ đồng) | B5: ='01_Số liệu gốc'!$B$11*'01_Số liệu gốc'!$B$8/1000 -> 2926 | D5: ='03_Định giá'!$C$256*'01_Số liệu gốc'!$B$8/1000 -> 2936.3132
A6: Giá trị phần lõi + dự án = vốn hoá − tiền ròng (tỷ đồng) | B6: =B5-'01_Số liệu gốc'!$C$65 -> 1527.463 | D6: =D5-'01_Số liệu gốc'!$C$65 -> 1537.7762 | F6: Thị trường trả cho kinh doanh lõi CỘNG hai dự án bao nhiêu sau khi trừ tiền
A7: P/E 12 tháng (cả lãi tiền gửi) | B7: =B5/'01_Số liệu gốc'!$H$51 -> 11.218035 | D7: =D5/'01_Số liệu gốc'!$H$51 -> 11.257575 | F7: Cách thị trường và Vietcap đọc
A8: P/E lõi 12 tháng = (vốn hoá − tiền) ÷ lợi nhuận lõi sau thuế, sau quỹ | B8: =B6/('02_Giả định'!$B$35*(1-'02_Giả định'!$B$48)*(1-'02_Giả định'!$B$13)) -> 9.3651204 | D8: =D6/('02_Giả định'!$B$35*(1-'02_Giả định'!$B$48)*(1-'02_Giả định'!$B$13)) -> 9.4283526 | F8: Coi dự án hòa vốn
A9: P/E lõi chuẩn hoá cơ sở | B9: =B6/'03_Định giá'!$C$58 -> 8.6832624 | D9: =D6/'03_Định giá'!$C$58 -> 8.7418907 | F9: So P/E đặt ở 02 (10,8x) — chưa trừ giá trị ròng dự án
A10: P/B (sổ sách 30/06/2026) | B10: ='01_Số liệu gốc'!$B$11/'01_Số liệu gốc'!$C$74 -> 1.2606152 | D10: ='03_Định giá'!$C$256/'01_Số liệu gốc'!$C$74 -> 1.2650584
A11: EV/EBITDA lõi 12 tháng (EV = vốn hoá − tiền) | B11: =B6/('02_Giả định'!$B$35+'01_Số liệu gốc'!$H$52) -> 5.7472035 | D11: =D6/('02_Giả định'!$B$35+'01_Số liệu gốc'!$H$52) -> 5.7860079
A12: Tỷ suất cổ tức (2.000đ/cp như 2022–2025) | B12: ='01_Số liệu gốc'!$B$135/'01_Số liệu gốc'!$B$11 -> 0.07518797 | D12: ='01_Số liệu gốc'!$B$135/'03_Định giá'!$C$256 -> 0.074923887 | F12: Cổ tức 2025 cao hơn LNST sau quỹ — chính sách 2026 hạ về tối thiểu 50% LNST
A13: P/E lõi cơ bản = (1 − quỹ − g ÷ ROIC) ÷ ((1 − quỹ) × (r − g)), ROIC trạng thái dừng (02 mục B) | B13: =(1-'02_Giả định'!$B$13-'02_Giả định'!$B$12/'02_Giả định'!$B$54)/((1-'02_Giả định'!$B$13)*('02_Giả định'!$B$10-'02_Giả định'!$B$12)) -> 9.7892537 | F13: Bội số mà ROIC lõi và r (02 mục A) biện minh được. Đặt ở 02: 10,8x
A14: EV/EBITDA lõi cơ bản = (1 − thuế)(1 − quỹ − g ÷ ROIC) × EBIT/EBITDA ÷ (r − g), ROIC trạng thái dừng (02 mục B) | B14: =(1-'02_Giả định'!$B$48)*(1-'02_Giả định'!$B$13-'02_Giả định'!$B$12/'02_Giả định'!$B$54)*('02_Giả định'!$B$35/('02_Giả định'!$B$35+'01_Số liệu gốc'!$H$52))/('02_Giả định'!$B$10-'02_Giả định'!$B$12) -> 6.0074863 | F14: Đặt ở 02: 6,6x
A16: B. GIÁ ĐANG NGẦM ĐỊNH ĐIỀU GÌ — giải ngược dạng đóng
A17: (a) ROE thuộc cổ đông ngầm định (công thức phương pháp 4) | B17: ='02_Giả định'!$B$12+'01_Số liệu gốc'!$B$11/'01_Số liệu gốc'!$C$74*('02_Giả định'!$B$10-'02_Giả định'!$B$12) -> 0.13367299
A18: quy về ROE trước trích quỹ | B18: =B17/(1-'02_Giả định'!$B$13) -> 0.14852555 | F18: So ROE 2022–2025 bình quân và 12 tháng (01 mục F)
A19: (b) P/E lõi ngầm định nếu hai dự án hòa vốn | B19: =(('01_Số liệu gốc'!$B$11*'01_Số liệu gốc'!$B$8/1000)-'01_Số liệu gốc'!$C$65)/'03_Định giá'!$C$58 -> 8.6832624 | F19: Trên lợi nhuận lõi chuẩn hoá cơ sở
A20: (c) P/E lõi ngầm định với giá trị ròng dự án cơ sở | B20: =(('01_Số liệu gốc'!$B$11*'01_Số liệu gốc'!$B$8/1000)-'01_Số liệu gốc'!$C$65-'03_Định giá'!$C$207)/'03_Định giá'!$C$58 -> 9.550356 | F20: Cao hơn P/E đặt ở 02 nghĩa là giá đang trả trước cho dự án tốt hơn cơ sở
A21: (d) B (doanh thu phần còn lại) ngầm định ở P/E đặt ở 02 và dự án cơ sở (tỷ) | B21: =((('01_Số liệu gốc'!$B$11*'01_Số liệu gốc'!$B$8/1000)-'01_Số liệu gốc'!$C$65-'03_Định giá'!$C$207)/'03_Định giá'!$C$12/((1-'03_Định giá'!$C$10)*(1-'03_Định giá'!$C$36))+'03_Định giá'!$C$42-'03_Định giá'!$C$40*'03_Định giá'!$C$7)/('03_Định giá'!$C$53-'03_Định giá'!$C$9) -> 2129.1731 | F21: So B cơ sở 2.450; 12 tháng 2.302; đỉnh 2023 2.710
A22: (e) Giá trị ròng dự án ngầm định ở P/E đặt ở 02 và lõi cơ sở (tỷ) | B22: =('01_Số liệu gốc'!$B$11*'01_Số liệu gốc'!$B$8/1000)-'01_Số liệu gốc'!$C$65-'03_Định giá'!$C$219 -> -372.35296 | F22: So giá trị ròng dự án cơ sở ở 06 mục C
A23: (f) LỢI SUẤT YÊU CẦU PHẦN KINH DOANH NGẦM ĐỊNH Ở GIÁ HIỆN TẠI | B23: ='02_Giả định'!$B$12+'03_Định giá'!$C$58*(1-'02_Giả định'!$B$12/'02_Giả định'!$B$54)/(('01_Số liệu gốc'!$B$11*'01_Số liệu gốc'!$B$8/1000)-'01_Số liệu gốc'!$C$65-'03_Định giá'!$C$207) -> 0.11633829 | F23: Bằng g + lợi nhuận lõi × (1 − g ÷ ROIC) ÷ (vốn hoá − tiền − dự án). So r ở 02 mục A: thấp hơn r = giá đắt
A24: (g) LỢI SUẤT KỲ VỌNG CẢ CỔ PHIẾU NẾU MUA Ở GIÁ HIỆN TẠI | B24: =((('01_Số liệu gốc'!$B$11*'01_Số liệu gốc'!$B$8/1000)-'01_Số liệu gốc'!$C$65)*B23+'01_Số liệu gốc'!$C$65*'03_Định giá'!$C$16*(1-'02_Giả định'!$B$14)*(1-'02_Giả định'!$B$13))/('01_Số liệu gốc'!$B$11*'01_Số liệu gốc'!$B$8/1000) -> 0.084821838 | F24: Bình quân: phần kinh doanh ở (f), phần tiền gửi ở lãi tiền gửi sau thuế, sau quỹ — tiền là ~nửa giá trị
A25: (h) Chênh so lãi tiền gửi tham chiếu của nhà đầu tư (điểm %) | B25: =(B24-'02_Giả định'!$B$17)*100 -> -0.51781619 | F25: Âm = thấp hơn lãi gửi tham chiếu (02 mục A)
A26: Tự kiểm: thế (a) ngược vào công thức phương pháp 4 ra đúng giá thị trường | B26: =(B17-'02_Giả định'!$B$12)/('02_Giả định'!$B$10-'02_Giả định'!$B$12)*'01_Số liệu gốc'!$C$74 -> 26600 | C26: =IF(ABS(B26-'01_Số liệu gốc'!$B$11)<0.01,"KHỚP","LỆCH") -> KHỚP
A27: Tự kiểm: thế (d) vào phương pháp 1 cơ sở ra đúng giá thị trường | B27: =(('03_Định giá'!$C$40*'03_Định giá'!$C$7+('03_Định giá'!$C$53-'03_Định giá'!$C$9)*B21-'03_Định giá'!$C$42)*(1-'03_Định giá'!$C$10)*(1-'03_Định giá'!$C$36)*'03_Định giá'!$C$12+'01_Số liệu gốc'!$C$65+'03_Định giá'!$C$207)*1000/'01_Số liệu gốc'!$B$8 -> 26600 | C27: =IF(ABS(B27-'01_Số liệu gốc'!$B$11)<0.01,"KHỚP","LỆCH") -> KHỚP
A29: C. HAI ĐƯỜNG TỚI ROE — lịch sử (phương pháp 4) và động cơ lõi + lãi tiền gửi
A30: Chỉ tiêu | B30: Xấu | C30: Cơ sở | D30: Tốt | F30: Đọc thế nào
A31: ROE chu kỳ lịch sử đặt ở 02 (trước trích quỹ) | B31: ='02_Giả định'!B75 -> 0.095 | C31: ='02_Giả định'!C75 -> 0.115 | D31: ='02_Giả định'!D75 -> 0.14
A32: ROE theo động cơ = (lợi nhuận lõi + lãi tiền gửi × 80%) ÷ vốn chủ 30/06/2026, trước dự án | B32: =('03_Định giá'!B57+'03_Định giá'!B16*'03_Định giá'!B214*(1-'03_Định giá'!B37))/'01_Số liệu gốc'!$C$67 -> 0.088736516 | C32: =('03_Định giá'!C57+'03_Định giá'!C16*'03_Định giá'!C214*(1-'03_Định giá'!C37))/'01_Số liệu gốc'!$C$67 -> 0.11794997 | D32: =('03_Định giá'!D57+'03_Định giá'!D16*'03_Định giá'!D214*(1-'03_Định giá'!D37))/'01_Số liệu gốc'!$C$67 -> 0.14755549
A33: Chênh (điểm %) | B33: =(B32-B31)*100 -> -0.62634841 | C33: =(C32-C31)*100 -> 0.29499746 | D33: =(D32-D31)*100 -> 0.75554905 | F33: Gần 0 = hai cách độc lập kể cùng câu chuyện. Khi tiền gửi đổ vào dự án ROIC thấp, ROE không tăng dù tiền nhàn rỗi giảm
A35: D. NHÓM SO SÁNH (số cứng — cập nhật tay)
A36: Mã | B36: P/E | C36: P/B | D36: EV/EBITDA 12 tháng | F36: Ghi chú
A37: VNM | B37: 11.06 | C37: 3.8 | D37: 9.29 | F37: Vinamilk — công ty mẹ cấp cao nhất của MCM
A38: IDP | B38: 27.55 | C38: 5.36 | D38: 17.76 | F38: Sữa Quốc tế (Kun) — tăng trưởng, ít tiền gửi
A39: QNS | B39: 9.97 | C39: 1.81 | D39: 8.66 | F39: Đường Quảng Ngãi — Vinasoy (sữa đậu nành) + đường
A40: SAB | B40: 11.51 | C40: 2.81 | D40: 10.38 | F40: Bia — hàng tiêu dùng, nhiều tiền gửi như MCM
A41: MCM | B41: 11.18 | C41: 1.26 | D41: 10.82 | F41: Hệ thống (Vietcap) — để so. EV KHÔNG trừ tiền gửi có kỳ hạn → không so thẳng với mục A
A42: Trung vị VNM, IDP, QNS, SAB | B42: =MEDIAN(B37:B40) -> 11.285 | C42: =MEDIAN(C37:C40) -> 3.305 | D42: =MEDIAN(D37:D40) -> 9.835
A43: P/E, P/B: daily_valuation phiên 07/10/2026. EV/EBITDA: gen_ratios_vietcap RATIO_TTM Q2/2026. Không mã nào cùng mô hình nửa trại sữa nửa thương hiệu, lại bị công ty mẹ mua sữa — chỉ để định vị.
A45: E. ĐỐI CHIẾU VỚI FILE QNS — nếu định giá phần lõi như Vinasoy (9 lần EBIT, dùng chung)
A46: Chỉ tiêu | B46: Xấu | C46: Cơ sở | D46: Tốt | F46: Ghi chú
A47: Bội số Vinasoy trong file QNS (lần EBIT) | B47: 9 | F47: QNS_SOTP_2026-09-30.xlsx, 02_Giả định dòng 25 — đọc trên bản sao 09/10/2026
A48: Giá trị = (EBIT lõi × 9 + tiền ròng + giá trị ròng dự án) ÷ cổ phiếu (đồng) | B48: =MAX(0,('03_Định giá'!B56*$B$47+'03_Định giá'!B214+'03_Định giá'!B207)*1000/'01_Số liệu gốc'!$B$8) -> 17276.511 | C48: =MAX(0,('03_Định giá'!C56*$B$47+'03_Định giá'!C214+'03_Định giá'!C207)*1000/'01_Số liệu gốc'!$B$8) -> 28900.656 | D48: =MAX(0,('03_Định giá'!D56*$B$47+'03_Định giá'!D214+'03_Định giá'!D207)*1000/'01_Số liệu gốc'!$B$8) -> 37802.084 | F48: Không trừ quỹ khen thưởng phúc lợi, không trừ thuế — cách đọc của file QNS. Dùng để thấy chênh giữa hai file, không đưa vào bình quân
A50: F. MỐC KIỂM QUÝ 3/2026 — đà cải thiện lợi nhuận lõi 6 tháng có giữ được không
A51: Chỉ tiêu | B51: Dự báo (giữ đà) | C51: Cận dưới | D51: Cận trên | E51: Thực tế | F51: Trạng thái
A52: LNST Q3/2026 (tỷ đồng) | B52: ='02_Giả định'!$B$56 -> 48.16472 | C52: ='02_Giả định'!$C$56 -> 38.11436 | D52: ='02_Giả định'!$D$56 -> 58.21508 | F52: =IF(E52="","CHỜ BCTC Q3 (cuối tháng 10/2026) — nhập LNST vào cột E",IF(E52<C52,"DƯỚI DẢI — đà 6 tháng không giữ được: xem lại B và chi phí bán hàng ở 02",IF(E52>D52,"TRÊN DẢI — xem có khoản bất thường không","TRONG DẢI"))) -> CHỜ BCTC Q3 (cuối tháng 10/2026) — nhập LNST vào cột E
A53: Cận dưới/trên = còn một nửa / mạnh gấp rưỡi mức EBIT lõi tăng thêm mỗi quý của 6T/2026. Kèm theo: xây dựng dở dang nhà máy có nhích khỏi 31 tỷ không (san lấp Q3/2026 theo kế hoạch).
A55: G. GIỚI HẠN MÔ HÌNH
A56: 1. Biên gộp của phần bán cho Vinamilk (mV) 10% là ước của người viết (12/10/2026), không có nguồn công bố (bản trước dùng 5%; hồi quy 3 năm cho số âm). Đổi mV chỉ dịch biên của B; EBIT 12 tháng vẫn khớp. mV 5%: 04 bảng 4 dòng T15.
A57: 2. Phương pháp 1, 2, 3, 5 cùng đi từ một con số lợi nhuận lõi chuẩn hoá — B và chi phí bán hàng sai thì bốn phương pháp sai cùng chiều. Chỉ phương pháp 4 (ROE lịch sử) độc lập.
A58: 3. Giá bán, chi phí mỗi lít của trang trại và lãi du lịch, lãi tăng thêm của nhà máy là TỰ ĐẶT: công ty không công bố (06 mục F). Trang trại chi nốt dồn vào 2027; sau 2031 trang trại thêm 20 năm dòng tiền đều rồi dừng; nhà máy lãi tăng dần tới năm đầy công suất rồi vĩnh viễn (06 dòng 22–25).
A59: 4. Lợi nhuận lõi coi nhà máy cũ chạy mãi; phần nhà máy mới thay nhà máy cũ nằm trong lãi tăng thêm (năm đầu thấp, tăng dần khi lấp công suất), không mô hình riêng chi phí sửa chữa nhà máy cũ. Sữa trại mới có giành chỗ sữa nông hộ (đang dư) hay không — không mô hình; nguồn sữa nông hộ đi ngang (01 dòng 125–129), giới hạn là sức bán.
A60: 5. Lợi suất yêu cầu theo cách rút gọn của công ty chứng khoán (Rf + β × ERP); cách Damodaran đầy đủ (cộng riêng rủi ro quốc gia, Rf quy từ USD) cho MCM ~13,3%. Thuế: lãi tiền gửi chịu đủ 20%, phần miễn thuế dồn hết vào lợi nhuận lõi.
A61: 6. Phần lõi tính 12 tháng một kỳ từ 01/07/2026, chiết khấu giữa kỳ (từ 14/10/2026 không còn bỏ nửa cuối 2026). Phương pháp 3 (cổ tức) vẫn bắt đầu 2027: tạm ứng đợt 1/2026 coi như chi từ lợi nhuận nửa cuối 2026.
A62: 7. Thanh khoản rất thấp (~0,4 tỷ/phiên): giá thị trường có thể lệch xa giá trị lâu; Vinamilk có thể mua nốt hoặc không bao giờ — không mô hình.

Sheet 06_Dự án
A1: MCM — HAI DỰ ÁN MỚI: TRANG TRẠI 4.000 CON (CÓ DU LỊCH) VÀ NHÀ MÁY SỮA (bản 15/10/2026)
A2: Dữ kiện dự án ở 01 mục G. Sheet này: giả định theo ba kịch bản (nền xanh lá), kết quả đọc từ 03 (tính lại đủ ở mọi cột phép thử), mức hòa vốn, việc theo dõi mỗi quý và những gì phải hỏi công ty. Giá trị dự án = dòng tiền 2027–2031 + đuôi sau 2031 (trang trại 20 năm đều; nhà máy tăng dần tới năm đầy công suất rồi vĩnh viễn, 03 mục B3), chiết khấu ở lợi suất dự án (02 mục A). Phần đã chi là chi phí chìm.
A4: A. TRANG TRẠI 4.000 CON — tách phần bò sữa (lít × giá − chi phí) và phần du lịch
A5: Tham số | B5: Xấu | C5: Cơ sở | D5: Tốt | E5: Mốc / nguồn số | F5: Căn cứ
A6: Vốn phần trang trại bò sữa (tỷ) | B6: 860 | C6: 784 | D6: 784 | E6: ='01_Số liệu gốc'!$B$110*'01_Số liệu gốc'!$B$111/('01_Số liệu gốc'!$B$111+'01_Số liệu gốc'!$B$112) -> 784 | F6: Mốc = 1.120 × 70% (tỷ lệ 700/1.000 lúc khởi công). Xấu: vượt dự toán ~10% — đang lắp máy, nhập gian vắt sữa. Vinamilk Quảng Ngãi 4.000 con: 700 tỷ
A7: Vốn phần du lịch, cảnh quan thực làm (tỷ) | B7: 336 | C7: 336 | D7: 336 | E7: ='01_Số liệu gốc'!$B$110*(1-'01_Số liệu gốc'!$B$111/('01_Số liệu gốc'!$B$111+'01_Số liệu gốc'!$B$112)) -> 336 | F7: Chốt 13/10/2026: giữ 336 tỷ cả ba kịch bản = 1.120 × 30% như phương án 2022 — chưa có nghị quyết thu nhỏ du lịch. Bản trước: cơ sở 150, tốt 100 (tự đặt theo lời chủ tịch ĐHĐCĐ 20/04/2026). Lãi du lịch B15:D15 giữ nguyên.
A8: Sản lượng khi đủ đàn (triệu lít/năm) | B8: 18 | C8: 20 | D8: 22 | E8: ='01_Số liệu gốc'!$B$113 -> 20 | F8: Thiết kế 20; trại 2.000 con hiện có làm ra 11 triệu lít → 4.000 con ≈ 22. Năng suất đàn MCM 26 lít/con/ngày (BCTN 2025), KBSV kỳ vọng trại mới 30–32
A9: Sản lượng năm 2027 so với khi đủ đàn | B9: 0.3 | C9: 0.5 | D9: 0.6 | F9: Chính thức Q2/2027, đủ đàn 2028 (KBSV). Xấu: lên đàn chậm (nguồn bò chưa công bố)
A10: Giá bán sữa của trang trại (đồng/lít) | B10: 13000 | C10: 14500 | D10: 15000 | F10: Giá tại trại cả nước 13.000–14.500 đ/kg (2024), 14.000–15.000 (2025) — Người Chăn Nuôi 17/03/2026; Ba Vì 12.000–14.000 (09/2025). MCM: giá mua, giá bán cho Vinamilk 2026 "giữ nguyên 2025", không công bố số. Tốt = 15.000, đỉnh dải giá tại trại 2025 (14/10/2026, theo quy trình; bản 12/10: 16.000 giá nội bộ cho Creamery). Bán nội bộ giá cao chỉ chuyển tiền giữa hai túi — phần bù hàng cao cấp đã nằm ở biên gộp B
A11: Chi phí tiền mặt mỗi lít: thức ăn, nhân công, thú y (đồng/lít) | B11: 10500 | C11: 10500 | D11: 10500 | F11: Chốt 14/10/2026: 10.500 cả ba kịch bản — giá sữa và chi phí thức ăn thường đi cùng chiều (2024 thức ăn tăng thì giá thu mua sữa tăng 7–8%), nên không cộng dồn giá thấp + chi phí cao (bản 12/10: 11.500 / 10.500 / 9.500). Rủi ro chi phí: 04 bảng 5. TỰ ĐẶT — công ty không công bố. Mốc duy nhất: chi phí sản xuất sữa Việt Nam 9.500–10.000 đ/lít (IPSARD 2019, cũ). Ngô, khô đậu +21–25% so cùng kỳ (09/2026)
A12: Thu thêm từ bê đực, bò loại (% doanh thu sữa) | B12: 0.05 | C12: 0.05 | D12: 0.05 | F12: TỰ ĐẶT
A13: Chi duy trì chuồng trại, thiết bị (tỷ/năm) | B13: 15 | C13: 15 | D13: 15 | F13: TỰ ĐẶT
A14: Khấu hao phần bò sữa (năm) | B14: 20 | C14: 20 | D14: 20 | F14: Nhà cửa 5–33 năm, máy móc 5–24 năm (chính sách kế toán BCTC 2025)
A15: Du lịch: lãi trước thuế mỗi năm từ 2028 (tỷ) | B15: 0 | C15: 10 | D15: 25 | F15: TỰ ĐẶT — không có số khách, giá vé. Mộc Châu 2,5 triệu lượt khách (2023), quy hoạch 5 triệu (2030); bán sữa tại chỗ chỉ tiêu được vài % sản lượng. Thuế 20% (không phải thu nhập chăn nuôi)
A17: B. NHÀ MÁY SỮA MỚI — giai đoạn 1 (giai đoạn 2 1.257 tỷ ngoài 5 năm, không tính)
A18: Tham số | B18: Xấu | C18: Cơ sở | D18: Tốt | E18: Mốc / nguồn số | F18: Căn cứ
A19: Có xây trong 5 năm (1 = có, 0 = không) | B19: 1 | C19: 1 | D19: 1 | F19: Xấu (Chốt 13/10/2026): VẪN XÂY nhưng muộn — mặt bằng kẹt thêm (82%, hộ nhà kiên cố chưa chịu đền bù), chạy 2032, vốn vượt 850 tỷ, lãi thêm 20 tỷ/năm. Không xây mà nhà máy cũ chạy mãi là tự mâu thuẫn (hết đất, xuống cấp) — giờ chỉ còn ở phép thử T1
A20: Vốn giai đoạn 1 (tỷ) | B20: 850 | C20: 743 | D20: 743 | E20: ='01_Số liệu gốc'!$B$117 -> 743 | F20: Báo Sơn La 09/09/2025. QĐ 2932/QĐ-UBND 19/11/2025 điều chỉnh chủ trương — chưa có toàn văn. Xấu: vượt dự toán ~15%
A21: Năm bắt đầu có lãi (chi 50%/50% trong hai năm trước đó) | B21: 2032 | C21: 2030 | D21: 2030 | F21: Chốt 12/10/2026: cơ sở chạy đầu 2030 — theo lời chủ tịch ĐHĐCĐ 20/04/2026 ("2,3 năm tới vẫn đáp ứng") và tiến độ thực (tiền chi cho nhà máy 6 tháng chỉ +0,5 tỷ). Xấu: 2032. Tốt: 2030 (Chốt 15/10/2026, thay Q4/2027 cũ — Tốt khác cơ sở ở mức lãi và tốc độ lấp đầy, không ở tiến độ). | G21: =IF(AND(MIN(B21:D21)>=2028,MAX(B21:D21)<=2032),"ĐẠT — năm có lãi trong 2028–2032","SAI — năm có lãi phải trong 2028–2032: năm khác làm 03 dòng 82 tính sai vốn nhà máy") -> ĐẠT — năm có lãi trong 2028–2032
A22: Lãi tăng thêm sau thuế NĂM ĐẦU chạy (tỷ) | B22: 20 | C22: 45 | D22: 45 | F22: TỰ ĐẶT (Chốt 15/10/2026: lãi TĂNG DẦN, không đứng yên mãi). Năm đầu thấp vì nhà máy mới (~500 tấn/ngày GĐ1) dư công suất so với nhà máy cũ 200 tấn/ngày; phần lớn là THAY nhà máy cũ (hết đất, xuống cấp) + chi phí sửa chữa tránh được. Tốt hạ 75 → 45 năm đầu (tăng nhờ dòng 23).
A23: Lãi tăng thêm sau thuế khi chạy ĐẦY CÔNG SUẤT (tỷ) | B23: 20 | C23: 90 | D23: 110 | F23: TỰ ĐẶT (Chốt 15/10/2026). Cơ sở 90 ≈ 10,9% vốn sau quỹ (dưới lợi suất 12,4% — dự án thay thế bắt buộc); Tốt 110 ≈ 13,3% (dưới ROIC lõi 17,1%); Xấu 20 đứng yên. NGUỒN LÃI: sữa đầu vào đi ngang (đàn ~26 nghìn con 2019–2025, 01 dòng 126–129), nên lãi tăng thêm KHÔNG đến từ sữa mới mà từ (1) chuyển dần ~120 tấn/ngày sữa đang bán thô cho Vinamilk sang tự chế biến Creamery, (2) tiết kiệm chi phí so nhà máy cũ xuống cấp. Creamery không cạnh tranh VNM: kỳ vọng 50–60% doanh thu, được đưa vào cửa hàng Vinamilk (VietnamBiz 20/04/2026).
A24: Năm chạy đầy công suất (lãi tăng đều từ năm có lãi đến năm này) | B24: 2032 | C24: 2038 | D24: 2035 | F24: TỰ ĐẶT (Chốt 15/10/2026). Thời gian chuyển sữa bán thô sang Creamery + đạt hiệu suất nhà máy mới: ~8 năm → cơ sở 2038; Tốt 2035 (TGĐ: tăng 5–7%/năm phù hợp sản lượng hiện có). 'Đầy công suất' = LÃI đạt mức ổn định, không phải chạy đủ 500 tấn/ngày (nguồn sữa ~240–300 tấn/ngày). Xấu = năm có lãi (không có lộ trình).
A25: Tăng trưởng lãi mỗi năm sau năm đầy công suất | B25: 0 | C25: ='02_Giả định'!$B$12 -> 0.03 | D25: ='02_Giả định'!$B$12 -> 0.03 | F25: Cơ sở/Tốt: theo g dài hạn ở 02 (lãi danh nghĩa tăng theo lạm phát, lợi suất 12,4% đã gồm lạm phát). Xấu: 0% (đứng yên như bản trước). Mô hình chạy năm 2027–2060 rồi vĩnh viễn với tỷ lệ này (03 mục B3).
A27: C. KẾT QUẢ BA KỊCH BẢN (đọc từ 03 — đổi giả định ở trên là chạy lại)
A28: Chỉ tiêu | B28: Xấu | C28: Cơ sở | D28: Tốt | F28: Đọc thế nào
A29: Trang trại: tổng vốn theo kịch bản (bò sữa + du lịch, tỷ) | B29: ='03_Định giá'!$B$65 -> 1196 | C29: ='03_Định giá'!$C$65 -> 1120 | D29: ='03_Định giá'!$D$65 -> 1120
A30: còn phải chi sau 30/06/2026 (tỷ) | B30: ='03_Định giá'!$B$66 -> 780.679 | C30: ='03_Định giá'!$C$66 -> 704.679 | D30: ='03_Định giá'!$D$66 -> 704.679 | F30: Đã ghi sổ 415,3 tỷ (01 mục D) là chi phí chìm
A31: Trang trại: doanh thu khi đủ đàn (tỷ/năm) | B31: ='03_Định giá'!$B$67 -> 245.7 | C31: ='03_Định giá'!$C$67 -> 304.5 | D31: ='03_Định giá'!$D$67 -> 346.5 | F31: lít × giá × (1 + thu thêm)
A32: lãi trước khấu hao (tỷ/năm) | B32: ='03_Định giá'!$B$68 -> 56.7 | C32: ='03_Định giá'!$C$68 -> 94.5 | D32: ='03_Định giá'!$D$68 -> 115.5 | F32: Mỗi 1.000 đ/lít giá hoặc chi phí ≈ 20 tỷ/năm
A33: lãi sau khấu hao, miễn thuế (tỷ/năm) | B33: ='03_Định giá'!$B$70 -> 13.7 | C33: ='03_Định giá'!$C$70 -> 55.3 | D33: ='03_Định giá'!$D$70 -> 76.3
A34: LÃI TRÊN VỐN PHẦN BÒ SỮA | B34: ='03_Định giá'!$B$72 -> 0.015930233 | C34: ='03_Định giá'!$C$72 -> 0.070535714 | D34: ='03_Định giá'!$D$72 -> 0.097321429 | F34: So lợi suất dự án 12,4% và lãi gửi ngân hàng
A35: Du lịch: lãi sau thuế (tỷ/năm) | B35: ='03_Định giá'!$B$73 -> 0 | C35: ='03_Định giá'!$C$73 -> 8 | D35: ='03_Định giá'!$D$73 -> 20 | F35: Cần ~20 tỷ/năm mới bằng gửi tiết kiệm trên 150–336 tỷ vốn
A36: Nhà máy: vốn còn phải chi (tỷ) | B36: ='03_Định giá'!$B$74 -> 818.923 | C36: ='03_Định giá'!$C$74 -> 711.923 | D36: ='03_Định giá'!$D$74 -> 711.923
A37: lãi khi đầy công suất ÷ vốn | B37: ='03_Định giá'!$B$75 -> 0.023529412 | C37: ='03_Định giá'!$C$75 -> 0.12113055 | D37: ='03_Định giá'!$D$75 -> 0.14804845
A38: GIÁ TRỊ RÒNG TRANG TRẠI, gồm du lịch (tỷ) | B38: ='03_Định giá'!$B$205 -> -412.2193 | C38: ='03_Định giá'!$C$205 -> -47.597289 | D38: ='03_Định giá'!$D$205 -> 168.97143 | F38: Âm = phần còn phải chi sinh lời dưới 12,4%
A39: GIÁ TRỊ RÒNG NHÀ MÁY (tỷ) | B39: ='03_Định giá'!$B$206 -> -403.67382 | C39: ='03_Định giá'!$C$206 -> -104.93218 | D39: ='03_Định giá'!$D$206 -> 33.363775
A40: GIÁ TRỊ RÒNG HAI DỰ ÁN (tỷ) | B40: ='03_Định giá'!$B$207 -> -815.89312 | C40: ='03_Định giá'!$C$207 -> -152.52947 | D40: ='03_Định giá'!$D$207 -> 202.33521 | F40: Cộng vào cả năm phương pháp (PP4 qua ROE lịch sử)
A41: quy ra đồng/cổ phiếu | B41: ='03_Định giá'!$B$208 -> -7417.2102 | C41: ='03_Định giá'!$C$208 -> -1386.6315 | D41: ='03_Định giá'!$D$208 -> 1839.411
A42: HÒA VỐN: giá bán sữa trang trại để giá trị ròng trang trại = 0 (đ/lít) | B42: ='03_Định giá'!$B$210 -> 16463.201 | C42: ='03_Định giá'!$C$210 -> 14850.971 | D42: ='03_Định giá'!$D$210 -> 13881.185 | F42: Giữ chi phí ở kịch bản đó
A43: HÒA VỐN: lãi KHI ĐẦY CÔNG SUẤT của nhà máy để giá trị ròng nhà máy = 0 (tỷ/năm) | B43: ='03_Định giá'!$B$212 -> 120.02938 | C43: ='03_Định giá'!$C$212 -> 117.92425 | D43: ='03_Định giá'!$D$212 -> 102.65709
A44: tương ứng lãi trên vốn nhà máy | B44: ='03_Định giá'!$B$213 -> 0.14121104 | C44: ='03_Định giá'!$C$213 -> 0.15871366 | D44: ='03_Định giá'!$D$213 -> 0.13816567
A46: D. DÒNG TIỀN HAI DỰ ÁN, KỊCH BẢN CƠ SỞ (tỷ đồng, 03 mục D)
A47: Khoản | B47: 2027 | C47: 2028 | D47: 2029 | E47: 2030 | F47: 2031
A48: Chi trang trại | B48: ='03_Định giá'!$C$86 -> 704.679 | C48: ='03_Định giá'!$C$110 -> 0 | D48: ='03_Định giá'!$C$134 -> 0 | E48: ='03_Định giá'!$C$158 -> 0 | F48: ='03_Định giá'!$C$182 -> 0
A49: Chi nhà máy | B49: ='03_Định giá'!$C$87 -> 0 | C49: ='03_Định giá'!$C$111 -> 355.9615 | D49: ='03_Định giá'!$C$135 -> 355.9615 | E49: ='03_Định giá'!$C$159 -> 0 | F49: ='03_Định giá'!$C$183 -> 0
A50: Lãi kế toán hai dự án | B50: ='03_Định giá'!$C$91 -> 27.65 | C50: ='03_Định giá'!$C$115 -> 63.3 | D50: ='03_Định giá'!$C$139 -> 63.3 | E50: ='03_Định giá'!$C$163 -> 108.3 | F50: ='03_Định giá'!$C$187 -> 113.925
A51: Dòng tiền trang trại + du lịch sau quỹ | B51: ='03_Định giá'!$C$92 -> -667.694 | C51: ='03_Định giá'!$C$116 -> 81.17 | D51: ='03_Định giá'!$C$140 -> 81.17 | E51: ='03_Định giá'!$C$164 -> 81.17 | F51: ='03_Định giá'!$C$188 -> 81.17
A52: Dòng tiền nhà máy sau quỹ | B52: ='03_Định giá'!$C$93 -> 0 | C52: ='03_Định giá'!$C$117 -> -355.9615 | D52: ='03_Định giá'!$C$141 -> -355.9615 | E52: ='03_Định giá'!$C$165 -> 40.5 | F52: ='03_Định giá'!$C$189 -> 45.5625
A53: Sau 2031: trang trại dòng tiền đều thêm 20 năm; nhà máy tăng dần tới năm đầy công suất (dòng 23–24) rồi tăng theo dòng 25 vĩnh viễn — 03 mục B2, B3
A55: E. THEO DÕI MỖI QUÝ — dự án đi đúng hay lệch
A56: Chỉ tiêu | B56: Xem ở đâu | E56: Tốt | F56: Xấu
A57: Xây dựng dở dang trang trại | B57: Thuyết minh xây dựng dở dang | E57: Chuyển sang tài sản cố định ~Q2/2027 | F57: Kéo dài, hoặc tổng vốn vượt 1.120 tỷ
A58: Tiền phát hành chi cho nhà máy | B58: Báo cáo sử dụng vốn (6 tháng/lần) | E58: Tăng — đã san lấp, xây hàng rào | F58: Đứng ở ~32 tỷ
A59: Tiền ròng | B59: Bảng cân đối | E59: Giảm đúng nhịp chi dự án | F59: Giảm nhanh hơn, hoặc bắt đầu vay
A60: Cổ tức | B60: Nghị quyết HĐQT, ĐHĐCĐ | E60: ≥ 50% LNST mà không phải vay | F60: Vay để trả cổ tức
A61: Bán cho Vinamilk | B61: Thuyết minh bên liên quan | E61: Ổn định | F61: Tiếp tục giảm (6T/2026 −8,6%)
A62: Đàn bò | B62: Thuyết minh tài sản sinh học | E62: Tăng mạnh 2026–2027 | F62: Đứng yên
A63: Biên lãi gộp | B63: Kết quả kinh doanh | E63: Tăng khi sữa trại mới vào Creamery (2027–2028) | F63: Sản lượng tăng mà biên không tăng
A64: Tiền thuê đất | B64: Thuyết minh thuế, phải nộp | E64: Rõ phần của dự án | F64: Tiếp tục tăng mạnh (6T/2026: 19,1 tỷ)
A65: Doanh thu du lịch hoặc "khác" | B65: Thuyết minh doanh thu | E65: Xuất hiện từ 2027 | F65: Không có
A67: F. CÒN THIẾU — chỉ công ty trả lời được
A68: 1. Giá MCM bán sữa tươi nguyên liệu cho Vinamilk và giá thu mua của nông hộ (đ/kg) — ĐHĐCĐ 2026 hỏi thẳng, công ty không nêu số.
A69: 2. Chi phí ra 1 lít sữa ở trại tập trung 2.000 con hiện có.
A70: 3. Toàn văn QĐ 2932/QĐ-UBND ngày 19/11/2025: vốn, giai đoạn, tiến độ nhà máy sau điều chỉnh.
A71: 4. 1.120 tỷ hiện gồm những gì; phần du lịch còn bao nhiêu; đã gồm tiền mua bò chưa.
A72: 5. Bò cho trại mới lấy từ đâu; 40,9 tỷ mua của Lao-Jagro là tài sản gì.
A73: 6. Sản lượng sữa nguyên liệu từng năm, chia trại tự có / nông hộ, bán Vinamilk / chế biến.
A74: 7. Tiền thuê 138 ha (QĐ 2126/QĐ-UBND 19/10/2023): đơn giá, trả hằng năm hay một lần.
